Workbook

Sheet Cover
B3: FINANCIAL FEASIBILITY & PROJECTION MODEL
B5: Small-Scale Food & Agro-Processing Unit — Gujarat
B7: 5-Year Monthly Model — fully formula-linked, ready for data entry
B10: BLANK, FULLY-LINKED TEMPLATE — ENTER YOUR DATA IN THE YELLOW CELLS
B13: Applicant / Enterprise | C13: 〈Enterprise name〉 (edit on Assumptions)
B14: Proposed location | C14: 〈Taluka / District〉, Gujarat
B15: Enterprise class (MSME) | C15: Small Enterprise (P&M ≤ ₹25 cr; turnover ≤ ₹100 cr)
B16: Constitution | C16: Private Limited Company (assumed)
B17: Projection horizon | C17: 60 months (5 financial years), monthly granularity
B18: Currency / units | C18: All financial lines in ₹ lakh unless stated (1 lakh = ₹100,000)
B19: Base / model date | C19: FY-1 = first year of commercial operation
B22: WORKBOOK CONTENTS
B24: 01 | C24: Assumptions | D24: Every driver – blue = editable input, with live source links
B25: 02 | C25: Capex & Financing | D25: Project cost, means of finance, subsidy build-up
B26: 03 | C26: Loan Schedule | D26: Monthly term-loan amortisation (moratorium + repayment)
B27: 04 | C27: Depreciation | D27: Block-wise SLM depreciation schedule
B28: 05 | C28: Payroll | D28: Monthly headcount & wage bill (feeds employment impact)
B29: 06 | C29: Monthly Model | D29: THE ENGINE – 60-month P&L from production to net cash
B30: 07 | C30: Annual P&L | D30: Year 1-5 profit & loss summary
B31: 08 | C31: Cash Flow | D31: Annual cash-flow statement
B32: 09 | C32: Balance Sheet | D32: Annual balance sheet (self-balancing)
B33: 10 | C33: Returns & Ratios | D33: IRR, NPV, DSCR, break-even, margins
B34: 11 | C34: Socio-Economic Impact | D34: Jobs, wages, farmer linkage, taxes, local multiplier
B35: 12 | C35: Sustainability (ESG) | D35: Energy, water, waste, solar, emissions
... B38: 15 | C38: Sources | D38: Consolidated, clickable source bibliography
B40: Disclaimer: This is a projection model built on stated assumptions and publicly sourced parameters (see hyperlinks). It is not audited advice. Figures must be validated by the promoter, a chartered accountant and the appraising bank before submission. Tax, subsidy and scheme parameters change — verify each source link at time of use.

Sheet Assumptions
B1: ASSUMPTIONS — single source of truth for the model
B2: Blue = editable input • Yellow = key driver • Black = derived • Green links (col E) open the live source. Change any blue cell and the whole model updates.
B4: Parameter | C4: Value | D4: Unit | E4: Source / basis (click)
B5: A. Macro-economic & tax parameters
B6: Effective corporate tax rate (s.115BAA, incl. surcharge+cess) | D6: % | E6: s.115BAA 22% (eff. 25.17%); s.115BAB 15% (eff. 17.16%, sunset 31-Mar-2024) – ClearTax
B7: └ Alternative if s.115BAB eligible (new mfg, if applicable) | D7: % | E7: Corporate tax – Income Tax Dept (domestic company rates, AY 2025-26)
B8: Annual escalation – selling price / realisation | D8: % p.a. | E8: Analyst estimate aligned to RBI CPI target band (4% ±2%)
B9: Annual escalation – raw material & consumables | D9: % p.a. | E9: Analyst estimate aligned to RBI CPI target band (4% ±2%)
B10: Annual escalation – wages & salaries | D10: % p.a. | E10: Analyst estimate aligned to RBI CPI target band (4% ±2%)
B11: Annual escalation – other operating expenses | D11: % p.a. | E11: Analyst estimate aligned to RBI CPI target band (4% ±2%)
B12: Working days per month | D12: days | E12: Management / DPR estimate (to be validated by promoter & appraising bank)
B13: B. Project cost (capex, ₹ lakh)
B14: Land & site development | D14: ₹ lakh | E14: Management / DPR estimate (to be validated by promoter & appraising bank)
B15: Factory building & civil works | D15: ₹ lakh | E15: Management / DPR estimate (to be validated by promoter & appraising bank)
B16: Plant & machinery (processing + packaging line) | D16: ₹ lakh | E16: Management / DPR estimate (to be validated by promoter & appraising bank)
B17: Utilities – power, water, cold storage, DG, solar | D17: ₹ lakh | E17: Management / DPR estimate (to be validated by promoter & appraising bank)
B18: Misc. fixed assets (furniture, IT, lab, ETP) | D18: ₹ lakh | E18: Management / DPR estimate (to be validated by promoter & appraising bank)
B19: Preliminary & pre-operative expenses | D19: ₹ lakh | E19: Management / DPR estimate (to be validated by promoter & appraising bank)
B20: Contingency (~2% of capital cost) | D20: ₹ lakh | E20: Management / DPR estimate (to be validated by promoter & appraising bank)
B21: Margin money for working capital | D21: ₹ lakh | E21: Management / DPR estimate (to be validated by promoter & appraising bank)
B22: C. Means of finance
B23: Promoter contribution (equity) | D23: % of project | E23: CGTMSE collateral-free credit guarantee up to ₹5 cr (raised to ₹10 cr, Budget 2025) – MoMSME/SIDBI
B24: Term-loan interest rate (p.a.) | D24: % p.a. | E24: MSME term-loan / working-capital rates & RBI repo (~6.5% early-2026; term loans ~9-11%) – 2026 survey
B25: Term-loan tenure (incl. moratorium) | D25: months | E25: MSME term-loan / working-capital rates & RBI repo (~6.5% early-2026; term loans ~9-11%) – 2026 survey
B26: Moratorium on principal (interest serviced) | D26: months | E26: MSME term-loan / working-capital rates & RBI repo (~6.5% early-2026; term loans ~9-11%) – 2026 survey
B27: Working-capital finance rate (p.a.) | D27: % p.a. | E27: MSME term-loan / working-capital rates & RBI repo (~6.5% early-2026; term loans ~9-11%) – 2026 survey
B28: Working capital funded by bank | D28: % of WC gap | E28: CGTMSE collateral-free credit guarantee up to ₹5 cr (raised to ₹10 cr, Budget 2025) – MoMSME/SIDBI
B29: D. Production & capacity
B30: Installed capacity at 100% (finished product) | D30: tonnes/mo | E30: Management / DPR estimate (to be validated by promoter & appraising bank)
B31: Capacity utilisation – Year 1 | D31: % | E31: Management / DPR estimate (to be validated by promoter & appraising bank)
B32: Capacity utilisation – Year 2 | D32: % | E32: Management / DPR estimate (to be validated by promoter & appraising bank)
B33: Capacity utilisation – Year 3 | D33: % | E33: Management / DPR estimate (to be validated by promoter & appraising bank)
B34: Capacity utilisation – Year 4 | D34: % | E34: Management / DPR estimate (to be validated by promoter & appraising bank)
B35: Capacity utilisation – Year 5 | D35: % | E35: Management / DPR estimate (to be validated by promoter & appraising bank)
B36: E. Pricing & unit economics (Year 1 base, ₹ per tonne)
B37: Average net realisation (ex-GST) | D37: ₹/tonne | E37: Management / DPR estimate (to be validated by promoter & appraising bank)
B38: Raw material (farm produce incl. wastage) | D38: ₹/tonne | E38: Management / DPR estimate (to be validated by promoter & appraising bank)
B39: Packaging & consumables | D39: ₹/tonne | E39: Management / DPR estimate (to be validated by promoter & appraising bank)
B40: Direct utilities per tonne (power/steam/water) | D40: ₹/tonne | E40: Management / DPR estimate (to be validated by promoter & appraising bank)
B41: Other direct / QC / logistics inward | D41: ₹/tonne | E41: Management / DPR estimate (to be validated by promoter & appraising bank)
B42: F. Operating expenses (fixed, ₹ lakh per month – Year 1 base)
B43: Fixed power, fuel & DG (plant overhead) | D43: ₹ lakh/mo | E43: Management / DPR estimate (to be validated by promoter & appraising bank)
B44: Repairs & maintenance | D44: ₹ lakh/mo | E44: Management / DPR estimate (to be validated by promoter & appraising bank)
B45: Administrative & general overhead | D45: ₹ lakh/mo | E45: Management / DPR estimate (to be validated by promoter & appraising bank)
B46: Selling, distribution & branding | D46: % of revenue | E46: Management / DPR estimate (to be validated by promoter & appraising bank)
B47: Insurance (assets + stock) | D47: ₹ lakh/mo | E47: Management / DPR estimate (to be validated by promoter & appraising bank)
B48: G. Manpower (headcount & average wage)
B49: Total headcount – Year 1 | D49: persons | E49: Management / DPR estimate (to be validated by promoter & appraising bank)
B50: Total headcount – Year 2 | D50: persons | E50: Management / DPR estimate (to be validated by promoter & appraising bank)
B51: Total headcount – Year 3 | D51: persons | E51: Management / DPR estimate (to be validated by promoter & appraising bank)
B52: Total headcount – Year 4 | D52: persons | E52: Management / DPR estimate (to be validated by promoter & appraising bank)
B53: Total headcount – Year 5 | D53: persons | E53: Management / DPR estimate (to be validated by promoter & appraising bank)
B54: Average monthly wage (blended) | D54: ₹/person/mo | E54: Management / DPR estimate (to be validated by promoter & appraising bank)
B55: Share of women in workforce | D55: % | E55: Management / DPR estimate (to be validated by promoter & appraising bank)
B56: H. Working-capital cycle
B57: Debtor / receivable days | D57: days | E57: Management / DPR estimate (to be validated by promoter & appraising bank)
B58: Inventory holding days | D58: days | E58: Management / DPR estimate (to be validated by promoter & appraising bank)
B59: Creditor / payable days | D59: days | E59: Management / DPR estimate (to be validated by promoter & appraising bank)
B60: I. Depreciation (SLM book rates)
B61: Building depreciation rate | D61: % p.a. | E61: Management / DPR estimate (to be validated by promoter & appraising bank)
B62: Plant & machinery depreciation rate | D62: % p.a. | E62: Management / DPR estimate (to be validated by promoter & appraising bank)
B63: Utilities & misc depreciation rate | D63: % p.a. | E63: Management / DPR estimate (to be validated by promoter & appraising bank)
B64: J. Government scheme parameters (benefit rates)
B65: State capital investment subsidy (Aatmanirbhar Gujarat) | D65: % of eFCI | E65: Aatmanirbhar Gujarat Scheme for MSMEs 2022-27 (capital + interest subsidy) – myScheme (GoI)
B66: └ Cap on capital subsidy | D66: ₹ lakh | E66: Aatmanirbhar Gujarat incentives: capital + 7% interest subsidy, net-SGST & EPF reimbursement – EY / IPF
B67: Interest subsidy on term loan (Aatmanirbhar Gujarat) | D67: % p.a. | E67: Aatmanirbhar Gujarat incentives: capital + 7% interest subsidy, net-SGST & EPF reimbursement – EY / IPF
B68: └ Interest-subsidy cap per year | D68: ₹ lakh/yr | E68: Aatmanirbhar Gujarat incentives: capital + 7% interest subsidy, net-SGST & EPF reimbursement – EY / IPF
B69: PMFME credit-linked subsidy (if micro food unit) | D69: % of proj cost | E69: PMFME – 35% credit-linked capital subsidy up to ₹10 lakh (micro food units) – MoFPI / myScheme
B70: └ PMFME cap per unit | D70: ₹ lakh | E70: PMFME – 35% credit-linked capital subsidy up to ₹10 lakh (micro food units) – MoFPI / myScheme
B71: Net SGST reimbursement (indicative, on intra-state sales) | D71: % of net SGST | E71: Aatmanirbhar Gujarat incentives: capital + 7% interest subsidy, net-SGST & EPF reimbursement – EY / IPF
B72: K. Discounting
B73: Discount rate / WACC for NPV | D73: % p.a. | E73: Analyst estimate aligned to RBI CPI target band (4% ±2%)
B74: L. Derived totals (formulas)
B75: Total project cost | C75: =SUM($C$14,$C$15,$C$16,$C$17,$C$18,$C$19,$C$20,$C$21) -> 0 | D75: ₹ lakh
B76: Eligible fixed capital investment (land+bldg+P&M+util+misc) | C76: =SUM($C$14,$C$15,$C$16,$C$17,$C$18) -> 0 | D76: ₹ lakh
B77: Promoter equity | C77: =$C$75*$C$23 -> 0 | D77: ₹ lakh
B78: Term loan (balance of project cost) | C78: =$C$75-$C$77 -> 0 | D78: ₹ lakh
B79: Capital investment subsidy (state) | C79: =MIN($C$76*$C$65,$C$66) -> 0 | D79: ₹ lakh

Sheet Capex & Financing
B1: PROJECT COST & MEANS OF FINANCE (₹ lakh)
B3: A. Project cost
B4: Land & site development | C4: =IFERROR(Assumptions!$C$14,0) -> 0 | D4: ₹ lakh
B5: Factory building & civil | C5: =IFERROR(Assumptions!$C$15,0) -> 0 | D5: ₹ lakh
B6: Plant & machinery | C6: =IFERROR(Assumptions!$C$16,0) -> 0 | D6: ₹ lakh
B7: Utilities (power/water/cold-chain/solar) | C7: =IFERROR(Assumptions!$C$17,0) -> 0 | D7: ₹ lakh
B8: Misc. fixed assets (furniture, IT, lab, ETP) | C8: =IFERROR(Assumptions!$C$18,0) -> 0 | D8: ₹ lakh
B9: Preliminary & pre-operative | C9: =IFERROR(Assumptions!$C$19,0) -> 0 | D9: ₹ lakh
B10: Contingency | C10: =IFERROR(Assumptions!$C$20,0) -> 0 | D10: ₹ lakh
B11: Margin money for working capital | C11: =IFERROR(Assumptions!$C$21,0) -> 0 | D11: ₹ lakh
B12: Total project cost | C12: =IFERROR(Assumptions!$C$75,0) -> 0 | D12: ₹ lakh
B14: B. Means of finance
B15: Promoter equity | C15: =IFERROR(Assumptions!$C$77,0) -> 0 | D15: ₹ lakh | E15: Own contribution
B16: Term loan | C16: =IFERROR(Assumptions!$C$78,0) -> 0 | D16: ₹ lakh | E16: CGTMSE-eligible bank term loan
B17: Total means of finance | C17: =IFERROR(C15+C16,0) -> 0 | D17: ₹ lakh
B18: Debt : Equity ratio | C18: =IFERROR(C16/C15,"")
B19: Promoter contribution (%) | C19: =IFERROR(C15/C12,"")
B21: C. Government support build-up (indicative)
B22: State capital investment subsidy | C22: =IFERROR(Assumptions!$C$79,0) -> 0 | D22: ₹ lakh | E22: Aatmanirbhar Gujarat (post-COD claim)
B23: Interest subsidy (5-yr, term loan) | C23: =IFERROR(SUM('Loan Schedule'!C12:BJ12),0) -> 0 | D23: ₹ lakh | E23: Reduces effective interest cost
B24: PMFME subsidy (only if micro unit) | C24: =IFERROR(MIN(Assumptions!$C$75*Assumptions!$C$69,Assumptions!$C$70),0) -> 0 | D24: ₹ lakh | E24: Conditional – P&M ≤ ₹2.5 cr
B25: Total indicative support | C25: =IFERROR(Assumptions!$C$79+C23,0) -> 0 | D25: ₹ lakh
B27: Note: subsidies are reimbursed after commencement of commercial operation and are shown as inflows in the Cash Flow / Balance Sheet, not netted against project cost here. Enabler schemes (CGTMSE guarantee, concessional tax) reduce risk and outflows but are not cash grants.

Sheet Loan Schedule
A1: TERM-LOAN AMORTISATION (₹ lakh, monthly)
A2: Equal-principal repayment after moratorium; interest on reducing balance. Interest-subsidy row feeds the P&L.
A3: Month # | C3: 1 | D3: 2 | E3: 3 | F3: 4 | G3: 5 | H3: 6 | I3: 7 | J3: 8 | K3: 9 | L3: 10 | M3: 11 | N3: 12 | O3: 13 | P3: 14 | Q3: 15 | R3: 16 | S3: 17 | T3: 18 | U3: 19 | V3: 20 | W3: 21 | X3: 22 | Y3: 23 | Z3: 24 | AA3: 25 | AB3: 26 | AC3: 27 | AD3: 28 | AE3: 29 | AF3: 30 | AG3: 31 | AH3: 32 | AI3: 33 | AJ3: 34 | AK3: 35 | AL3: 36 | AM3: 37 | AN3: 38 | AO3: 39 | AP3: 40 | AQ3: 41 | AR3: 42 | AS3: 43 | AT3: 44 | AU3: 45 | AV3: 46 | AW3: 47 | AX3: 48 | AY3: 49 | AZ3: 50 | BA3: 51 | BB3: 52 | BC3: 53 | BD3: 54 | BE3: 55 | BF3: 56 | BG3: 57 | BH3: 58 | BI3: 59 | BJ3: 60
A4: Financial Year | C4: Y1 | D4: Y1 | E4: Y1 | F4: Y1 | G4: Y1 | H4: Y1 | I4: Y1 | J4: Y1 | K4: Y1 | L4: Y1 | M4: Y1 | N4: Y1 | O4: Y2 | P4: Y2 | Q4: Y2 | R4: Y2 | S4: Y2 | T4: Y2 | U4: Y2 | V4: Y2 | W4: Y2 | X4: Y2 | Y4: Y2 | Z4: Y2 | AA4: Y3 | AB4: Y3 | AC4: Y3 | AD4: Y3 | AE4: Y3 | AF4: Y3 | AG4: Y3 | AH4: Y3 | AI4: Y3 | AJ4: Y3 | AK4: Y3 | AL4: Y3 | AM4: Y4 | AN4: Y4 | AO4: Y4 | AP4: Y4 | AQ4: Y4 | AR4: Y4 | AS4: Y4 | AT4: Y4 | AU4: Y4 | AV4: Y4 | AW4: Y4 | AX4: Y4 | AY4: Y5 | AZ4: Y5 | BA4: Y5 | BB4: Y5 | BC4: Y5 | BD4: Y5 | BE4: Y5 | BF4: Y5 | BG4: Y5 | BH4: Y5 | BI4: Y5 | BJ4: Y5
A6: Opening balance | B6: ₹ lakh | C6: =IFERROR(Assumptions!$C$78,0) -> 0 | D6: =IFERROR(C10,0) -> 0 | E6: =IFERROR(D10,0) -> 0 | F6: =IFERROR(E10,0) -> 0 | G6: =IFERROR(F10,0) -> 0 | H6: =IFERROR(G10,0) -> 0 | I6: =IFERROR(H10,0) -> 0 | J6: =IFERROR(I10,0) -> 0 | K6: =IFERROR(J10,0) -> 0 | ... BJ6: =IFERROR(BI10,0) -> 0
A7: Interest for month | B7: ₹ lakh | C7: =IFERROR(C6*Assumptions!$C$24/12,0) -> 0 | D7: =IFERROR(D6*Assumptions!$C$24/12,0) -> 0 | E7: =IFERROR(E6*Assumptions!$C$24/12,0) -> 0 | F7: =IFERROR(F6*Assumptions!$C$24/12,0) -> 0 | G7: =IFERROR(G6*Assumptions!$C$24/12,0) -> 0 | H7: =IFERROR(H6*Assumptions!$C$24/12,0) -> 0 | I7: =IFERROR(I6*Assumptions!$C$24/12,0) -> 0 | J7: =IFERROR(J6*Assumptions!$C$24/12,0) -> 0 | ... BJ7: =IFERROR(BJ6*Assumptions!$C$24/12,0) -> 0
A8: Principal repayment | B8: ₹ lakh | C8: =IFERROR(IF(1<=Assumptions!$C$26,0,Assumptions!$C$78/(Assumptions!$C$25-Assumptions!$C$26)),0) -> 0 | D8: =IFERROR(IF(2<=Assumptions!$C$26,0,Assumptions!$C$78/(Assumptions!$C$25-Assumptions!$C$26)),0) -> 0 | E8: =IFERROR(IF(3<=Assumptions!$C$26,0,Assumptions!$C$78/(Assumptions!$C$25-Assumptions!$C$26)),0) -> 0 | F8: =IFERROR(IF(4<=Assumptions!$C$26,0,Assumptions!$C$78/(Assumptions!$C$25-Assumptions!$C$26)),0) -> 0 | G8: =IFERROR(IF(5<=Assumptions!$C$26,0,Assumptions!$C$78/(Assumptions!$C$25-Assumptions!$C$26)),0) -> 0 | H8: =IFERROR(IF(6<=Assumptions!$C$26,0,Assumptions!$C$78/(Assumptions!$C$25-Assumptions!$C$26)),0) -> 0 | I8: =IFERROR(IF(7<=Assumptions!$C$26,0,Assumptions!$C$78/(Assumptions!$C$25-Assumptions!$C$26)),0) -> 0 | J8: =IFERROR(IF(8<=Assumptions!$C$26,0,Assumptions!$C$78/(Assumptions!$C$25-Assumptions!$C$26)),0) -> 0 | K8: =IFERROR(IF(9<=Assumptions!$C$26,0,Assumptions!$C$78/(Assumptions!$C$25-Assumptions!$C$26)),0) -> 0 | L8: =IFERROR(IF(10<=Assumptions!$C$26,0,Assumptions!$C$78/(Assumptions!$C$25-Assumptions!$C$26)),0) -> 0 | M8: =IFERROR(IF(11<=Assumptions!$C$26,0,Assumptions!$C$78/(Assumptions!$C$25-Assumptions!$C$26)),0) -> 0 | N8: =IFERROR(IF(12<=Assumptions!$C$26,0,Assumptions!$C$78/(Assumptions!$C$25-Assumptions!$C$26)),0) -> 0 | O8: =IFERROR(IF(13<=Assumptions!$C$26,0,Assumptions!$C$78/(Assumptions!$C$25-Assumptions!$C$26)),0) -> 0 | P8: =IFERROR(IF(14<=Assumptions!$C$26,0,Assumptions!$C$78/(Assumptions!$C$25-Assumptions!$C$26)),0) -> 0 | Q8: =IFERROR(IF(15<=Assumptions!$C$26,0,Assumptions!$C$78/(Assumptions!$C$25-Assumptions!$C$26)),0) -> 0 | R8: =IFERROR(IF(16<=Assumptions!$C$26,0,Assumptions!$C$78/(Assumptions!$C$25-Assumptions!$C$26)),0) -> 0 | S8: =IFERROR(IF(17<=Assumptions!$C$26,0,Assumptions!$C$78/(Assumptions!$C$25-Assumptions!$C$26)),0) -> 0 | T8: =IFERROR(IF(18<=Assumptions!$C$26,0,Assumptions!$C$78/(Assumptions!$C$25-Assumptions!$C$26)),0) -> 0 | U8: =IFERROR(IF(19<=Assumptions!$C$26,0,Assumptions!$C$78/(Assumptions!$C$25-Assumptions!$C$26)),0) -> 0 | V8: =IFERROR(IF(20<=Assumptions!$C$26,0,Assumptions!$C$78/(Assumptions!$C$25-Assumptions!$C$26)),0) -> 0 | W8: =IFERROR(IF(21<=Assumptions!$C$26,0,Assumptions!$C$78/(Assumptions!$C$25-Assumptions!$C$26)),0) -> 0 | X8: =IFERROR(IF(22<=Assumptions!$C$26,0,Assumptions!$C$78/(Assumptions!$C$25-Assumptions!$C$26)),0) -> 0 | Y8: =IFERROR(IF(23<=Assumptions!$C$26,0,Assumptions!$C$78/(Assumptions!$C$25-Assumptions!$C$26)),0) -> 0 | Z8: =IFERROR(IF(24<=Assumptions!$C$26,0,Assumptions!$C$78/(Assumptions!$C$25-Assumptions!$C$26)),0) -> 0 | AA8: =IFERROR(IF(25<=Assumptions!$C$26,0,Assumptions!$C$78/(Assumptions!$C$25-Assumptions!$C$26)),0) -> 0 | AB8: =IFERROR(IF(26<=Assumptions!$C$26,0,Assumptions!$C$78/(Assumptions!$C$25-Assumptions!$C$26)),0) -> 0 | AC8: =IFERROR(IF(27<=Assumptions!$C$26,0,Assumptions!$C$78/(Assumptions!$C$25-Assumptions!$C$26)),0) -> 0 | AD8: =IFERROR(IF(28<=Assumptions!$C$26,0,Assumptions!$C$78/(Assumptions!$C$25-Assumptions!$C$26)),0) -> 0 | AE8: =IFERROR(IF(29<=Assumptions!$C$26,0,Assumptions!$C$78/(Assumptions!$C$25-Assumptions!$C$26)),0) -> 0 | AF8: =IFERROR(IF(30<=Assumptions!$C$26,0,Assumptions!$C$78/(Assumptions!$C$25-Assumptions!$C$26)),0) -> 0 | AG8: =IFERROR(IF(31<=Assumptions!$C$26,0,Assumptions!$C$78/(Assumptions!$C$25-Assumptions!$C$26)),0) -> 0 | AH8: =IFERROR(IF(32<=Assumptions!$C$26,0,Assumptions!$C$78/(Assumptions!$C$25-Assumptions!$C$26)),0) -> 0 | AI8: =IFERROR(IF(33<=Assumptions!$C$26,0,Assumptions!$C$78/(Assumptions!$C$25-Assumptions!$C$26)),0) -> 0 | AJ8: =IFERROR(IF(34<=Assumptions!$C$26,0,Assumptions!$C$78/(Assumptions!$C$25-Assumptions!$C$26)),0) -> 0 | AK8: =IFERROR(IF(35<=Assumptions!$C$26,0,Assumptions!$C$78/(Assumptions!$C$25-Assumptions!$C$26)),0) -> 0 | AL8: =IFERROR(IF(36<=Assumptions!$C$26,0,Assumptions!$C$78/(Assumptions!$C$25-Assumptions!$C$26)),0) -> 0 | AM8: =IFERROR(IF(37<=Assumptions!$C$26,0,Assumptions!$C$78/(Assumptions!$C$25-Assumptions!$C$26)),0) -> 0 | AN8: =IFERROR(IF(38<=Assumptions!$C$26,0,Assumptions!$C$78/(Assumptions!$C$25-Assumptions!$C$26)),0) -> 0 | AO8: =IFERROR(IF(39<=Assumptions!$C$26,0,Assumptions!$C$78/(Assumptions!$C$25-Assumptions!$C$26)),0) -> 0 | AP8: =IFERROR(IF(40<=Assumptions!$C$26,0,Assumptions!$C$78/(Assumptions!$C$25-Assumptions!$C$26)),0) -> 0 | AQ8: =IFERROR(IF(41<=Assumptions!$C$26,0,Assumptions!$C$78/(Assumptions!$C$25-Assumptions!$C$26)),0) -> 0 | AR8: =IFERROR(IF(42<=Assumptions!$C$26,0,Assumptions!$C$78/(Assumptions!$C$25-Assumptions!$C$26)),0) -> 0 | AS8: =IFERROR(IF(43<=Assumptions!$C$26,0,Assumptions!$C$78/(Assumptions!$C$25-Assumptions!$C$26)),0) -> 0 | AT8: =IFERROR(IF(44<=Assumptions!$C$26,0,Assumptions!$C$78/(Assumptions!$C$25-Assumptions!$C$26)),0) -> 0 | AU8: =IFERROR(IF(45<=Assumptions!$C$26,0,Assumptions!$C$78/(Assumptions!$C$25-Assumptions!$C$26)),0) -> 0 | AV8: =IFERROR(IF(46<=Assumptions!$C$26,0,Assumptions!$C$78/(Assumptions!$C$25-Assumptions!$C$26)),0) -> 0 | AW8: =IFERROR(IF(47<=Assumptions!$C$26,0,Assumptions!$C$78/(Assumptions!$C$25-Assumptions!$C$26)),0) -> 0 | AX8: =IFERROR(IF(48<=Assumptions!$C$26,0,Assumptions!$C$78/(Assumptions!$C$25-Assumptions!$C$26)),0) -> 0 | AY8: =IFERROR(IF(49<=Assumptions!$C$26,0,Assumptions!$C$78/(Assumptions!$C$25-Assumptions!$C$26)),0) -> 0 | AZ8: =IFERROR(IF(50<=Assumptions!$C$26,0,Assumptions!$C$78/(Assumptions!$C$25-Assumptions!$C$26)),0) -> 0 | BA8: =IFERROR(IF(51<=Assumptions!$C$26,0,Assumptions!$C$78/(Assumptions!$C$25-Assumptions!$C$26)),0) -> 0 | BB8: =IFERROR(IF(52<=Assumptions!$C$26,0,Assumptions!$C$78/(Assumptions!$C$25-Assumptions!$C$26)),0) -> 0 | BC8: =IFERROR(IF(53<=Assumptions!$C$26,0,Assumptions!$C$78/(Assumptions!$C$25-Assumptions!$C$26)),0) -> 0 | BD8: =IFERROR(IF(54<=Assumptions!$C$26,0,Assumptions!$C$78/(Assumptions!$C$25-Assumptions!$C$26)),0) -> 0 | BE8: =IFERROR(IF(55<=Assumptions!$C$26,0,Assumptions!$C$78/(Assumptions!$C$25-Assumptions!$C$26)),0) -> 0 | BF8: =IFERROR(IF(56<=Assumptions!$C$26,0,Assumptions!$C$78/(Assumptions!$C$25-Assumptions!$C$26)),0) -> 0 | BG8: =IFERROR(IF(57<=Assumptions!$C$26,0,Assumptions!$C$78/(Assumptions!$C$25-Assumptions!$C$26)),0) -> 0 | BH8: =IFERROR(IF(58<=Assumptions!$C$26,0,Assumptions!$C$78/(Assumptions!$C$25-Assumptions!$C$26)),0) -> 0 | BI8: =IFERROR(IF(59<=Assumptions!$C$26,0,Assumptions!$C$78/(Assumptions!$C$25-Assumptions!$C$26)),0) -> 0 | BJ8: =IFERROR(IF(60<=Assumptions!$C$26,0,Assumptions!$C$78/(Assumptions!$C$25-Assumptions!$C$26)),0) -> 0
A9: Total debt service (interest+principal) | B9: ₹ lakh | C9: =IFERROR(C7+C8,0) -> 0 | D9: =IFERROR(D7+D8,0) -> 0 | E9: =IFERROR(E7+E8,0) -> 0 | F9: =IFERROR(F7+F8,0) -> 0 | G9: =IFERROR(G7+G8,0) -> 0 | H9: =IFERROR(H7+H8,0) -> 0 | I9: =IFERROR(I7+I8,0) -> 0 | J9: =IFERROR(J7+J8,0) -> 0 | ... BJ9: =IFERROR(BJ7+BJ8,0) -> 0
A10: Closing balance | B10: ₹ lakh | C10: =IFERROR(C6-C8,0) -> 0 | D10: =IFERROR(D6-D8,0) -> 0 | E10: =IFERROR(E6-E8,0) -> 0 | F10: =IFERROR(F6-F8,0) -> 0 | G10: =IFERROR(G6-G8,0) -> 0 | H10: =IFERROR(H6-H8,0) -> 0 | I10: =IFERROR(I6-I8,0) -> 0 | J10: =IFERROR(J6-J8,0) -> 0 | ... BJ10: =IFERROR(BJ6-BJ8,0) -> 0
A12: Less: interest subsidy (Aatmanirbhar Gujarat) | B12: ₹ lakh | C12: =IFERROR(MIN(C6*Assumptions!$C$67/12,Assumptions!$C$68/12),0) -> 0 | D12: =IFERROR(MIN(D6*Assumptions!$C$67/12,Assumptions!$C$68/12),0) -> 0 | E12: =IFERROR(MIN(E6*Assumptions!$C$67/12,Assumptions!$C$68/12),0) -> 0 | F12: =IFERROR(MIN(F6*Assumptions!$C$67/12,Assumptions!$C$68/12),0) -> 0 | G12: =IFERROR(MIN(G6*Assumptions!$C$67/12,Assumptions!$C$68/12),0) -> 0 | H12: =IFERROR(MIN(H6*Assumptions!$C$67/12,Assumptions!$C$68/12),0) -> 0 | I12: =IFERROR(MIN(I6*Assumptions!$C$67/12,Assumptions!$C$68/12),0) -> 0 | J12: =IFERROR(MIN(J6*Assumptions!$C$67/12,Assumptions!$C$68/12),0) -> 0 | ... BJ12: =IFERROR(MIN(BJ6*Assumptions!$C$67/12,Assumptions!$C$68/12),0) -> 0
A13: Net interest cost to enterprise | B13: ₹ lakh | C13: =IFERROR(C7-C12,0) -> 0 | D13: =IFERROR(D7-D12,0) -> 0 | E13: =IFERROR(E7-E12,0) -> 0 | F13: =IFERROR(F7-F12,0) -> 0 | G13: =IFERROR(G7-G12,0) -> 0 | H13: =IFERROR(H7-H12,0) -> 0 | I13: =IFERROR(I7-I12,0) -> 0 | J13: =IFERROR(J7-J12,0) -> 0 | ... BJ13: =IFERROR(BJ7-BJ12,0) -> 0

Sheet Depreciation
A1: DEPRECIATION SCHEDULE (₹ lakh, monthly, SLM)
A2: Straight-line book depreciation by asset block; constant per month over the horizon.
A3: Month # | C3: 1 | D3: 2 | E3: 3 | F3: 4 | G3: 5 | H3: 6 | I3: 7 | J3: 8 | K3: 9 | L3: 10 | M3: 11 | N3: 12 | O3: 13 | P3: 14 | Q3: 15 | R3: 16 | S3: 17 | T3: 18 | U3: 19 | V3: 20 | W3: 21 | X3: 22 | Y3: 23 | Z3: 24 | AA3: 25 | AB3: 26 | AC3: 27 | AD3: 28 | AE3: 29 | AF3: 30 | AG3: 31 | AH3: 32 | AI3: 33 | AJ3: 34 | AK3: 35 | AL3: 36 | AM3: 37 | AN3: 38 | AO3: 39 | AP3: 40 | AQ3: 41 | AR3: 42 | AS3: 43 | AT3: 44 | AU3: 45 | AV3: 46 | AW3: 47 | AX3: 48 | AY3: 49 | AZ3: 50 | BA3: 51 | BB3: 52 | BC3: 53 | BD3: 54 | BE3: 55 | BF3: 56 | BG3: 57 | BH3: 58 | BI3: 59 | BJ3: 60
A4: Financial Year | C4: Y1 | D4: Y1 | E4: Y1 | F4: Y1 | G4: Y1 | H4: Y1 | I4: Y1 | J4: Y1 | K4: Y1 | L4: Y1 | M4: Y1 | N4: Y1 | O4: Y2 | P4: Y2 | Q4: Y2 | R4: Y2 | S4: Y2 | T4: Y2 | U4: Y2 | V4: Y2 | W4: Y2 | X4: Y2 | Y4: Y2 | Z4: Y2 | AA4: Y3 | AB4: Y3 | AC4: Y3 | AD4: Y3 | AE4: Y3 | AF4: Y3 | AG4: Y3 | AH4: Y3 | AI4: Y3 | AJ4: Y3 | AK4: Y3 | AL4: Y3 | AM4: Y4 | AN4: Y4 | AO4: Y4 | AP4: Y4 | AQ4: Y4 | AR4: Y4 | AS4: Y4 | AT4: Y4 | AU4: Y4 | AV4: Y4 | AW4: Y4 | AX4: Y4 | AY4: Y5 | AZ4: Y5 | BA4: Y5 | BB4: Y5 | BC4: Y5 | BD4: Y5 | BE4: Y5 | BF4: Y5 | BG4: Y5 | BH4: Y5 | BI4: Y5 | BJ4: Y5
A6: Building & civil | B6: ₹ lakh | C6: =IFERROR(Assumptions!$C$15*Assumptions!$C$61/12,0) -> 0 | D6: =IFERROR(Assumptions!$C$15*Assumptions!$C$61/12,0) -> 0 | E6: =IFERROR(Assumptions!$C$15*Assumptions!$C$61/12,0) -> 0 | F6: =IFERROR(Assumptions!$C$15*Assumptions!$C$61/12,0) -> 0 | G6: =IFERROR(Assumptions!$C$15*Assumptions!$C$61/12,0) -> 0 | H6: =IFERROR(Assumptions!$C$15*Assumptions!$C$61/12,0) -> 0 | I6: =IFERROR(Assumptions!$C$15*Assumptions!$C$61/12,0) -> 0 | J6: =IFERROR(Assumptions!$C$15*Assumptions!$C$61/12,0) -> 0 | ... BJ6: =IFERROR(Assumptions!$C$15*Assumptions!$C$61/12,0) -> 0
A7: Plant & machinery | B7: ₹ lakh | C7: =IFERROR(Assumptions!$C$16*Assumptions!$C$62/12,0) -> 0 | D7: =IFERROR(Assumptions!$C$16*Assumptions!$C$62/12,0) -> 0 | E7: =IFERROR(Assumptions!$C$16*Assumptions!$C$62/12,0) -> 0 | F7: =IFERROR(Assumptions!$C$16*Assumptions!$C$62/12,0) -> 0 | G7: =IFERROR(Assumptions!$C$16*Assumptions!$C$62/12,0) -> 0 | H7: =IFERROR(Assumptions!$C$16*Assumptions!$C$62/12,0) -> 0 | I7: =IFERROR(Assumptions!$C$16*Assumptions!$C$62/12,0) -> 0 | J7: =IFERROR(Assumptions!$C$16*Assumptions!$C$62/12,0) -> 0 | ... BJ7: =IFERROR(Assumptions!$C$16*Assumptions!$C$62/12,0) -> 0
A8: Utilities & misc assets | B8: ₹ lakh | C8: =IFERROR((Assumptions!$C$17+Assumptions!$C$18)*Assumptions!$C$63/12,0) -> 0 | D8: =IFERROR((Assumptions!$C$17+Assumptions!$C$18)*Assumptions!$C$63/12,0) -> 0 | E8: =IFERROR((Assumptions!$C$17+Assumptions!$C$18)*Assumptions!$C$63/12,0) -> 0 | F8: =IFERROR((Assumptions!$C$17+Assumptions!$C$18)*Assumptions!$C$63/12,0) -> 0 | G8: =IFERROR((Assumptions!$C$17+Assumptions!$C$18)*Assumptions!$C$63/12,0) -> 0 | H8: =IFERROR((Assumptions!$C$17+Assumptions!$C$18)*Assumptions!$C$63/12,0) -> 0 | I8: =IFERROR((Assumptions!$C$17+Assumptions!$C$18)*Assumptions!$C$63/12,0) -> 0 | J8: =IFERROR((Assumptions!$C$17+Assumptions!$C$18)*Assumptions!$C$63/12,0) -> 0 | ... BJ8: =IFERROR((Assumptions!$C$17+Assumptions!$C$18)*Assumptions!$C$63/12,0) -> 0
A9: Total depreciation | B9: ₹ lakh | C9: =IFERROR(SUM(C6:C8),0) -> 0 | D9: =IFERROR(SUM(D6:D8),0) -> 0 | E9: =IFERROR(SUM(E6:E8),0) -> 0 | F9: =IFERROR(SUM(F6:F8),0) -> 0 | G9: =IFERROR(SUM(G6:G8),0) -> 0 | H9: =IFERROR(SUM(H6:H8),0) -> 0 | I9: =IFERROR(SUM(I6:I8),0) -> 0 | J9: =IFERROR(SUM(J6:J8),0) -> 0 | ... BJ9: =IFERROR(SUM(BJ6:BJ8),0) -> 0

Sheet Payroll
A1: MANPOWER & PAYROLL (monthly)
A2: Headcount steps up by year; average wage escalates. Feeds both the P&L and the Socio-Economic Impact sheet.
A3: Month # | C3: 1 | D3: 2 | E3: 3 | F3: 4 | G3: 5 | H3: 6 | I3: 7 | J3: 8 | K3: 9 | L3: 10 | M3: 11 | N3: 12 | O3: 13 | P3: 14 | Q3: 15 | R3: 16 | S3: 17 | T3: 18 | U3: 19 | V3: 20 | W3: 21 | X3: 22 | Y3: 23 | Z3: 24 | AA3: 25 | AB3: 26 | AC3: 27 | AD3: 28 | AE3: 29 | AF3: 30 | AG3: 31 | AH3: 32 | AI3: 33 | AJ3: 34 | AK3: 35 | AL3: 36 | AM3: 37 | AN3: 38 | AO3: 39 | AP3: 40 | AQ3: 41 | AR3: 42 | AS3: 43 | AT3: 44 | AU3: 45 | AV3: 46 | AW3: 47 | AX3: 48 | AY3: 49 | AZ3: 50 | BA3: 51 | BB3: 52 | BC3: 53 | BD3: 54 | BE3: 55 | BF3: 56 | BG3: 57 | BH3: 58 | BI3: 59 | BJ3: 60
A4: Financial Year | C4: Y1 | D4: Y1 | E4: Y1 | F4: Y1 | G4: Y1 | H4: Y1 | I4: Y1 | J4: Y1 | K4: Y1 | L4: Y1 | M4: Y1 | N4: Y1 | O4: Y2 | P4: Y2 | Q4: Y2 | R4: Y2 | S4: Y2 | T4: Y2 | U4: Y2 | V4: Y2 | W4: Y2 | X4: Y2 | Y4: Y2 | Z4: Y2 | AA4: Y3 | AB4: Y3 | AC4: Y3 | AD4: Y3 | AE4: Y3 | AF4: Y3 | AG4: Y3 | AH4: Y3 | AI4: Y3 | AJ4: Y3 | AK4: Y3 | AL4: Y3 | AM4: Y4 | AN4: Y4 | AO4: Y4 | AP4: Y4 | AQ4: Y4 | AR4: Y4 | AS4: Y4 | AT4: Y4 | AU4: Y4 | AV4: Y4 | AW4: Y4 | AX4: Y4 | AY4: Y5 | AZ4: Y5 | BA4: Y5 | BB4: Y5 | BC4: Y5 | BD4: Y5 | BE4: Y5 | BF4: Y5 | BG4: Y5 | BH4: Y5 | BI4: Y5 | BJ4: Y5
A6: Total headcount | B6: persons | C6: =IFERROR(Assumptions!$C$49,0) -> 0 | D6: =IFERROR(Assumptions!$C$49,0) -> 0 | E6: =IFERROR(Assumptions!$C$49,0) -> 0 | F6: =IFERROR(Assumptions!$C$49,0) -> 0 | G6: =IFERROR(Assumptions!$C$49,0) -> 0 | H6: =IFERROR(Assumptions!$C$49,0) -> 0 | I6: =IFERROR(Assumptions!$C$49,0) -> 0 | J6: =IFERROR(Assumptions!$C$49,0) -> 0 | ... N6: =IFERROR(Assumptions!$C$49,0) -> 0 | O6: =IFERROR(Assumptions!$C$50,0) -> 0 | P6: =IFERROR(Assumptions!$C$50,0) -> 0 | Q6: =IFERROR(Assumptions!$C$50,0) -> 0 | R6: =IFERROR(Assumptions!$C$50,0) -> 0 | S6: =IFERROR(Assumptions!$C$50,0) -> 0 | T6: =IFERROR(Assumptions!$C$50,0) -> 0 | U6: =IFERROR(Assumptions!$C$50,0) -> 0 | V6: =IFERROR(Assumptions!$C$50,0) -> 0 | ... Z6: =IFERROR(Assumptions!$C$50,0) -> 0 | AA6: =IFERROR(Assumptions!$C$51,0) -> 0 | AB6: =IFERROR(Assumptions!$C$51,0) -> 0 | AC6: =IFERROR(Assumptions!$C$51,0) -> 0 | AD6: =IFERROR(Assumptions!$C$51,0) -> 0 | AE6: =IFERROR(Assumptions!$C$51,0) -> 0 | AF6: =IFERROR(Assumptions!$C$51,0) -> 0 | AG6: =IFERROR(Assumptions!$C$51,0) -> 0 | AH6: =IFERROR(Assumptions!$C$51,0) -> 0 | ... AL6: =IFERROR(Assumptions!$C$51,0) -> 0 | AM6: =IFERROR(Assumptions!$C$52,0) -> 0 | AN6: =IFERROR(Assumptions!$C$52,0) -> 0 | AO6: =IFERROR(Assumptions!$C$52,0) -> 0 | AP6: =IFERROR(Assumptions!$C$52,0) -> 0 | AQ6: =IFERROR(Assumptions!$C$52,0) -> 0 | AR6: =IFERROR(Assumptions!$C$52,0) -> 0 | AS6: =IFERROR(Assumptions!$C$52,0) -> 0 | AT6: =IFERROR(Assumptions!$C$52,0) -> 0 | ... AX6: =IFERROR(Assumptions!$C$52,0) -> 0 | AY6: =IFERROR(Assumptions!$C$53,0) -> 0 | AZ6: =IFERROR(Assumptions!$C$53,0) -> 0 | BA6: =IFERROR(Assumptions!$C$53,0) -> 0 | BB6: =IFERROR(Assumptions!$C$53,0) -> 0 | BC6: =IFERROR(Assumptions!$C$53,0) -> 0 | BD6: =IFERROR(Assumptions!$C$53,0) -> 0 | BE6: =IFERROR(Assumptions!$C$53,0) -> 0 | BF6: =IFERROR(Assumptions!$C$53,0) -> 0 | ... BJ6: =IFERROR(Assumptions!$C$53,0) -> 0
A7: of which women | B7: persons | C7: =IFERROR(C6*Assumptions!$C$55,0) -> 0 | D7: =IFERROR(D6*Assumptions!$C$55,0) -> 0 | E7: =IFERROR(E6*Assumptions!$C$55,0) -> 0 | F7: =IFERROR(F6*Assumptions!$C$55,0) -> 0 | G7: =IFERROR(G6*Assumptions!$C$55,0) -> 0 | H7: =IFERROR(H6*Assumptions!$C$55,0) -> 0 | I7: =IFERROR(I6*Assumptions!$C$55,0) -> 0 | J7: =IFERROR(J6*Assumptions!$C$55,0) -> 0 | ... BJ7: =IFERROR(BJ6*Assumptions!$C$55,0) -> 0
A8: Average monthly wage | B8: ₹ | C8: =IFERROR(Assumptions!$C$54*(1+Assumptions!$C$10)^(1-1),0) -> 0 | D8: =IFERROR(Assumptions!$C$54*(1+Assumptions!$C$10)^(1-1),0) -> 0 | E8: =IFERROR(Assumptions!$C$54*(1+Assumptions!$C$10)^(1-1),0) -> 0 | F8: =IFERROR(Assumptions!$C$54*(1+Assumptions!$C$10)^(1-1),0) -> 0 | G8: =IFERROR(Assumptions!$C$54*(1+Assumptions!$C$10)^(1-1),0) -> 0 | H8: =IFERROR(Assumptions!$C$54*(1+Assumptions!$C$10)^(1-1),0) -> 0 | I8: =IFERROR(Assumptions!$C$54*(1+Assumptions!$C$10)^(1-1),0) -> 0 | J8: =IFERROR(Assumptions!$C$54*(1+Assumptions!$C$10)^(1-1),0) -> 0 | ... N8: =IFERROR(Assumptions!$C$54*(1+Assumptions!$C$10)^(1-1),0) -> 0 | O8: =IFERROR(Assumptions!$C$54*(1+Assumptions!$C$10)^(2-1),0) -> 0 | P8: =IFERROR(Assumptions!$C$54*(1+Assumptions!$C$10)^(2-1),0) -> 0 | Q8: =IFERROR(Assumptions!$C$54*(1+Assumptions!$C$10)^(2-1),0) -> 0 | R8: =IFERROR(Assumptions!$C$54*(1+Assumptions!$C$10)^(2-1),0) -> 0 | S8: =IFERROR(Assumptions!$C$54*(1+Assumptions!$C$10)^(2-1),0) -> 0 | T8: =IFERROR(Assumptions!$C$54*(1+Assumptions!$C$10)^(2-1),0) -> 0 | U8: =IFERROR(Assumptions!$C$54*(1+Assumptions!$C$10)^(2-1),0) -> 0 | V8: =IFERROR(Assumptions!$C$54*(1+Assumptions!$C$10)^(2-1),0) -> 0 | ... Z8: =IFERROR(Assumptions!$C$54*(1+Assumptions!$C$10)^(2-1),0) -> 0 | AA8: =IFERROR(Assumptions!$C$54*(1+Assumptions!$C$10)^(3-1),0) -> 0 | AB8: =IFERROR(Assumptions!$C$54*(1+Assumptions!$C$10)^(3-1),0) -> 0 | AC8: =IFERROR(Assumptions!$C$54*(1+Assumptions!$C$10)^(3-1),0) -> 0 | AD8: =IFERROR(Assumptions!$C$54*(1+Assumptions!$C$10)^(3-1),0) -> 0 | AE8: =IFERROR(Assumptions!$C$54*(1+Assumptions!$C$10)^(3-1),0) -> 0 | AF8: =IFERROR(Assumptions!$C$54*(1+Assumptions!$C$10)^(3-1),0) -> 0 | AG8: =IFERROR(Assumptions!$C$54*(1+Assumptions!$C$10)^(3-1),0) -> 0 | AH8: =IFERROR(Assumptions!$C$54*(1+Assumptions!$C$10)^(3-1),0) -> 0 | ... AL8: =IFERROR(Assumptions!$C$54*(1+Assumptions!$C$10)^(3-1),0) -> 0 | AM8: =IFERROR(Assumptions!$C$54*(1+Assumptions!$C$10)^(4-1),0) -> 0 | AN8: =IFERROR(Assumptions!$C$54*(1+Assumptions!$C$10)^(4-1),0) -> 0 | AO8: =IFERROR(Assumptions!$C$54*(1+Assumptions!$C$10)^(4-1),0) -> 0 | AP8: =IFERROR(Assumptions!$C$54*(1+Assumptions!$C$10)^(4-1),0) -> 0 | AQ8: =IFERROR(Assumptions!$C$54*(1+Assumptions!$C$10)^(4-1),0) -> 0 | AR8: =IFERROR(Assumptions!$C$54*(1+Assumptions!$C$10)^(4-1),0) -> 0 | AS8: =IFERROR(Assumptions!$C$54*(1+Assumptions!$C$10)^(4-1),0) -> 0 | AT8: =IFERROR(Assumptions!$C$54*(1+Assumptions!$C$10)^(4-1),0) -> 0 | ... AX8: =IFERROR(Assumptions!$C$54*(1+Assumptions!$C$10)^(4-1),0) -> 0 | AY8: =IFERROR(Assumptions!$C$54*(1+Assumptions!$C$10)^(5-1),0) -> 0 | AZ8: =IFERROR(Assumptions!$C$54*(1+Assumptions!$C$10)^(5-1),0) -> 0 | BA8: =IFERROR(Assumptions!$C$54*(1+Assumptions!$C$10)^(5-1),0) -> 0 | BB8: =IFERROR(Assumptions!$C$54*(1+Assumptions!$C$10)^(5-1),0) -> 0 | BC8: =IFERROR(Assumptions!$C$54*(1+Assumptions!$C$10)^(5-1),0) -> 0 | BD8: =IFERROR(Assumptions!$C$54*(1+Assumptions!$C$10)^(5-1),0) -> 0 | BE8: =IFERROR(Assumptions!$C$54*(1+Assumptions!$C$10)^(5-1),0) -> 0 | BF8: =IFERROR(Assumptions!$C$54*(1+Assumptions!$C$10)^(5-1),0) -> 0 | ... BJ8: =IFERROR(Assumptions!$C$54*(1+Assumptions!$C$10)^(5-1),0) -> 0
A9: Monthly wage & salary bill | B9: ₹ lakh | C9: =IFERROR(C6*C8/100000,0) -> 0 | D9: =IFERROR(D6*D8/100000,0) -> 0 | E9: =IFERROR(E6*E8/100000,0) -> 0 | F9: =IFERROR(F6*F8/100000,0) -> 0 | G9: =IFERROR(G6*G8/100000,0) -> 0 | H9: =IFERROR(H6*H8/100000,0) -> 0 | I9: =IFERROR(I6*I8/100000,0) -> 0 | J9: =IFERROR(J6*J8/100000,0) -> 0 | ... BJ9: =IFERROR(BJ6*BJ8/100000,0) -> 0

Sheet Monthly Model
A1: MONTHLY MODEL — integrated P&L, working capital & cash flow (₹ lakh)
A2: Fully formula-driven from Assumptions. Escalation, ramp-up, financing, tax loss carry-forward all automated.
A3: Month # | C3: 1 | D3: 2 | E3: 3 | F3: 4 | G3: 5 | H3: 6 | I3: 7 | J3: 8 | K3: 9 | L3: 10 | M3: 11 | N3: 12 | O3: 13 | P3: 14 | Q3: 15 | R3: 16 | S3: 17 | T3: 18 | U3: 19 | V3: 20 | W3: 21 | X3: 22 | Y3: 23 | Z3: 24 | AA3: 25 | AB3: 26 | AC3: 27 | AD3: 28 | AE3: 29 | AF3: 30 | AG3: 31 | AH3: 32 | AI3: 33 | AJ3: 34 | AK3: 35 | AL3: 36 | AM3: 37 | AN3: 38 | AO3: 39 | AP3: 40 | AQ3: 41 | AR3: 42 | AS3: 43 | AT3: 44 | AU3: 45 | AV3: 46 | AW3: 47 | AX3: 48 | AY3: 49 | AZ3: 50 | BA3: 51 | BB3: 52 | BC3: 53 | BD3: 54 | BE3: 55 | BF3: 56 | BG3: 57 | BH3: 58 | BI3: 59 | BJ3: 60
A4: Financial Year | C4: Y1 | D4: Y1 | E4: Y1 | F4: Y1 | G4: Y1 | H4: Y1 | I4: Y1 | J4: Y1 | K4: Y1 | L4: Y1 | M4: Y1 | N4: Y1 | O4: Y2 | P4: Y2 | Q4: Y2 | R4: Y2 | S4: Y2 | T4: Y2 | U4: Y2 | V4: Y2 | W4: Y2 | X4: Y2 | Y4: Y2 | Z4: Y2 | AA4: Y3 | AB4: Y3 | AC4: Y3 | AD4: Y3 | AE4: Y3 | AF4: Y3 | AG4: Y3 | AH4: Y3 | AI4: Y3 | AJ4: Y3 | AK4: Y3 | AL4: Y3 | AM4: Y4 | AN4: Y4 | AO4: Y4 | AP4: Y4 | AQ4: Y4 | AR4: Y4 | AS4: Y4 | AT4: Y4 | AU4: Y4 | AV4: Y4 | AW4: Y4 | AX4: Y4 | AY4: Y5 | AZ4: Y5 | BA4: Y5 | BB4: Y5 | BC4: Y5 | BD4: Y5 | BE4: Y5 | BF4: Y5 | BG4: Y5 | BH4: Y5 | BI4: Y5 | BJ4: Y5
A6: PRODUCTION
A7: Installed capacity (100%) | B7: tonnes | C7: =IFERROR(Assumptions!$C$30,0) -> 0 | D7: =IFERROR(Assumptions!$C$30,0) -> 0 | E7: =IFERROR(Assumptions!$C$30,0) -> 0 | F7: =IFERROR(Assumptions!$C$30,0) -> 0 | G7: =IFERROR(Assumptions!$C$30,0) -> 0 | H7: =IFERROR(Assumptions!$C$30,0) -> 0 | I7: =IFERROR(Assumptions!$C$30,0) -> 0 | J7: =IFERROR(Assumptions!$C$30,0) -> 0 | ... BJ7: =IFERROR(Assumptions!$C$30,0) -> 0
A8: Capacity utilisation | B8: % | C8: =IFERROR(Assumptions!$C$31,0) -> 0 | D8: =IFERROR(Assumptions!$C$31,0) -> 0 | E8: =IFERROR(Assumptions!$C$31,0) -> 0 | F8: =IFERROR(Assumptions!$C$31,0) -> 0 | G8: =IFERROR(Assumptions!$C$31,0) -> 0 | H8: =IFERROR(Assumptions!$C$31,0) -> 0 | I8: =IFERROR(Assumptions!$C$31,0) -> 0 | J8: =IFERROR(Assumptions!$C$31,0) -> 0 | ... N8: =IFERROR(Assumptions!$C$31,0) -> 0 | O8: =IFERROR(Assumptions!$C$32,0) -> 0 | P8: =IFERROR(Assumptions!$C$32,0) -> 0 | Q8: =IFERROR(Assumptions!$C$32,0) -> 0 | R8: =IFERROR(Assumptions!$C$32,0) -> 0 | S8: =IFERROR(Assumptions!$C$32,0) -> 0 | T8: =IFERROR(Assumptions!$C$32,0) -> 0 | U8: =IFERROR(Assumptions!$C$32,0) -> 0 | V8: =IFERROR(Assumptions!$C$32,0) -> 0 | ... Z8: =IFERROR(Assumptions!$C$32,0) -> 0 | AA8: =IFERROR(Assumptions!$C$33,0) -> 0 | AB8: =IFERROR(Assumptions!$C$33,0) -> 0 | AC8: =IFERROR(Assumptions!$C$33,0) -> 0 | AD8: =IFERROR(Assumptions!$C$33,0) -> 0 | AE8: =IFERROR(Assumptions!$C$33,0) -> 0 | AF8: =IFERROR(Assumptions!$C$33,0) -> 0 | AG8: =IFERROR(Assumptions!$C$33,0) -> 0 | AH8: =IFERROR(Assumptions!$C$33,0) -> 0 | ... AL8: =IFERROR(Assumptions!$C$33,0) -> 0 | AM8: =IFERROR(Assumptions!$C$34,0) -> 0 | AN8: =IFERROR(Assumptions!$C$34,0) -> 0 | AO8: =IFERROR(Assumptions!$C$34,0) -> 0 | AP8: =IFERROR(Assumptions!$C$34,0) -> 0 | AQ8: =IFERROR(Assumptions!$C$34,0) -> 0 | AR8: =IFERROR(Assumptions!$C$34,0) -> 0 | AS8: =IFERROR(Assumptions!$C$34,0) -> 0 | AT8: =IFERROR(Assumptions!$C$34,0) -> 0 | ... AX8: =IFERROR(Assumptions!$C$34,0) -> 0 | AY8: =IFERROR(Assumptions!$C$35,0) -> 0 | AZ8: =IFERROR(Assumptions!$C$35,0) -> 0 | BA8: =IFERROR(Assumptions!$C$35,0) -> 0 | BB8: =IFERROR(Assumptions!$C$35,0) -> 0 | BC8: =IFERROR(Assumptions!$C$35,0) -> 0 | BD8: =IFERROR(Assumptions!$C$35,0) -> 0 | BE8: =IFERROR(Assumptions!$C$35,0) -> 0 | BF8: =IFERROR(Assumptions!$C$35,0) -> 0 | ... BJ8: =IFERROR(Assumptions!$C$35,0) -> 0
A9: Production | B9: tonnes | C9: =IFERROR(C7*C8,0) -> 0 | D9: =IFERROR(D7*D8,0) -> 0 | E9: =IFERROR(E7*E8,0) -> 0 | F9: =IFERROR(F7*F8,0) -> 0 | G9: =IFERROR(G7*G8,0) -> 0 | H9: =IFERROR(H7*H8,0) -> 0 | I9: =IFERROR(I7*I8,0) -> 0 | J9: =IFERROR(J7*J8,0) -> 0 | ... BJ9: =IFERROR(BJ7*BJ8,0) -> 0
A10: Sales volume | B10: tonnes | C10: =IFERROR(C9,0) -> 0 | D10: =IFERROR(D9,0) -> 0 | E10: =IFERROR(E9,0) -> 0 | F10: =IFERROR(F9,0) -> 0 | G10: =IFERROR(G9,0) -> 0 | H10: =IFERROR(H9,0) -> 0 | I10: =IFERROR(I9,0) -> 0 | J10: =IFERROR(J9,0) -> 0 | ... BJ10: =IFERROR(BJ9,0) -> 0
A11: REVENUE
A12: Net realisation | B12: ₹/tonne | C12: =IFERROR(Assumptions!$C$37*(1+Assumptions!$C$8)^(1-1),0) -> 0 | D12: =IFERROR(Assumptions!$C$37*(1+Assumptions!$C$8)^(1-1),0) -> 0 | E12: =IFERROR(Assumptions!$C$37*(1+Assumptions!$C$8)^(1-1),0) -> 0 | F12: =IFERROR(Assumptions!$C$37*(1+Assumptions!$C$8)^(1-1),0) -> 0 | G12: =IFERROR(Assumptions!$C$37*(1+Assumptions!$C$8)^(1-1),0) -> 0 | H12: =IFERROR(Assumptions!$C$37*(1+Assumptions!$C$8)^(1-1),0) -> 0 | I12: =IFERROR(Assumptions!$C$37*(1+Assumptions!$C$8)^(1-1),0) -> 0 | J12: =IFERROR(Assumptions!$C$37*(1+Assumptions!$C$8)^(1-1),0) -> 0 | ... N12: =IFERROR(Assumptions!$C$37*(1+Assumptions!$C$8)^(1-1),0) -> 0 | O12: =IFERROR(Assumptions!$C$37*(1+Assumptions!$C$8)^(2-1),0) -> 0 | P12: =IFERROR(Assumptions!$C$37*(1+Assumptions!$C$8)^(2-1),0) -> 0 | Q12: =IFERROR(Assumptions!$C$37*(1+Assumptions!$C$8)^(2-1),0) -> 0 | R12: =IFERROR(Assumptions!$C$37*(1+Assumptions!$C$8)^(2-1),0) -> 0 | S12: =IFERROR(Assumptions!$C$37*(1+Assumptions!$C$8)^(2-1),0) -> 0 | T12: =IFERROR(Assumptions!$C$37*(1+Assumptions!$C$8)^(2-1),0) -> 0 | U12: =IFERROR(Assumptions!$C$37*(1+Assumptions!$C$8)^(2-1),0) -> 0 | V12: =IFERROR(Assumptions!$C$37*(1+Assumptions!$C$8)^(2-1),0) -> 0 | ... Z12: =IFERROR(Assumptions!$C$37*(1+Assumptions!$C$8)^(2-1),0) -> 0 | AA12: =IFERROR(Assumptions!$C$37*(1+Assumptions!$C$8)^(3-1),0) -> 0 | AB12: =IFERROR(Assumptions!$C$37*(1+Assumptions!$C$8)^(3-1),0) -> 0 | AC12: =IFERROR(Assumptions!$C$37*(1+Assumptions!$C$8)^(3-1),0) -> 0 | AD12: =IFERROR(Assumptions!$C$37*(1+Assumptions!$C$8)^(3-1),0) -> 0 | AE12: =IFERROR(Assumptions!$C$37*(1+Assumptions!$C$8)^(3-1),0) -> 0 | AF12: =IFERROR(Assumptions!$C$37*(1+Assumptions!$C$8)^(3-1),0) -> 0 | AG12: =IFERROR(Assumptions!$C$37*(1+Assumptions!$C$8)^(3-1),0) -> 0 | AH12: =IFERROR(Assumptions!$C$37*(1+Assumptions!$C$8)^(3-1),0) -> 0 | ... AL12: =IFERROR(Assumptions!$C$37*(1+Assumptions!$C$8)^(3-1),0) -> 0 | AM12: =IFERROR(Assumptions!$C$37*(1+Assumptions!$C$8)^(4-1),0) -> 0 | AN12: =IFERROR(Assumptions!$C$37*(1+Assumptions!$C$8)^(4-1),0) -> 0 | AO12: =IFERROR(Assumptions!$C$37*(1+Assumptions!$C$8)^(4-1),0) -> 0 | AP12: =IFERROR(Assumptions!$C$37*(1+Assumptions!$C$8)^(4-1),0) -> 0 | AQ12: =IFERROR(Assumptions!$C$37*(1+Assumptions!$C$8)^(4-1),0) -> 0 | AR12: =IFERROR(Assumptions!$C$37*(1+Assumptions!$C$8)^(4-1),0) -> 0 | AS12: =IFERROR(Assumptions!$C$37*(1+Assumptions!$C$8)^(4-1),0) -> 0 | AT12: =IFERROR(Assumptions!$C$37*(1+Assumptions!$C$8)^(4-1),0) -> 0 | ... AX12: =IFERROR(Assumptions!$C$37*(1+Assumptions!$C$8)^(4-1),0) -> 0 | AY12: =IFERROR(Assumptions!$C$37*(1+Assumptions!$C$8)^(5-1),0) -> 0 | AZ12: =IFERROR(Assumptions!$C$37*(1+Assumptions!$C$8)^(5-1),0) -> 0 | BA12: =IFERROR(Assumptions!$C$37*(1+Assumptions!$C$8)^(5-1),0) -> 0 | BB12: =IFERROR(Assumptions!$C$37*(1+Assumptions!$C$8)^(5-1),0) -> 0 | BC12: =IFERROR(Assumptions!$C$37*(1+Assumptions!$C$8)^(5-1),0) -> 0 | BD12: =IFERROR(Assumptions!$C$37*(1+Assumptions!$C$8)^(5-1),0) -> 0 | BE12: =IFERROR(Assumptions!$C$37*(1+Assumptions!$C$8)^(5-1),0) -> 0 | BF12: =IFERROR(Assumptions!$C$37*(1+Assumptions!$C$8)^(5-1),0) -> 0 | ... BJ12: =IFERROR(Assumptions!$C$37*(1+Assumptions!$C$8)^(5-1),0) -> 0
A13: Gross revenue (net of GST) | B13: ₹ lakh | C13: =IFERROR(C10*C12/100000,0) -> 0 | D13: =IFERROR(D10*D12/100000,0) -> 0 | E13: =IFERROR(E10*E12/100000,0) -> 0 | F13: =IFERROR(F10*F12/100000,0) -> 0 | G13: =IFERROR(G10*G12/100000,0) -> 0 | H13: =IFERROR(H10*H12/100000,0) -> 0 | I13: =IFERROR(I10*I12/100000,0) -> 0 | J13: =IFERROR(J10*J12/100000,0) -> 0 | ... BJ13: =IFERROR(BJ10*BJ12/100000,0) -> 0
A14: DIRECT COST OF GOODS SOLD
A15: Raw material | B15: ₹ lakh | C15: =IFERROR(C10*Assumptions!$C$38*(1+Assumptions!$C$9)^(1-1)/100000,0) -> 0 | D15: =IFERROR(D10*Assumptions!$C$38*(1+Assumptions!$C$9)^(1-1)/100000,0) -> 0 | E15: =IFERROR(E10*Assumptions!$C$38*(1+Assumptions!$C$9)^(1-1)/100000,0) -> 0 | F15: =IFERROR(F10*Assumptions!$C$38*(1+Assumptions!$C$9)^(1-1)/100000,0) -> 0 | G15: =IFERROR(G10*Assumptions!$C$38*(1+Assumptions!$C$9)^(1-1)/100000,0) -> 0 | H15: =IFERROR(H10*Assumptions!$C$38*(1+Assumptions!$C$9)^(1-1)/100000,0) -> 0 | I15: =IFERROR(I10*Assumptions!$C$38*(1+Assumptions!$C$9)^(1-1)/100000,0) -> 0 | J15: =IFERROR(J10*Assumptions!$C$38*(1+Assumptions!$C$9)^(1-1)/100000,0) -> 0 | ... N15: =IFERROR(N10*Assumptions!$C$38*(1+Assumptions!$C$9)^(1-1)/100000,0) -> 0 | O15: =IFERROR(O10*Assumptions!$C$38*(1+Assumptions!$C$9)^(2-1)/100000,0) -> 0 | P15: =IFERROR(P10*Assumptions!$C$38*(1+Assumptions!$C$9)^(2-1)/100000,0) -> 0 | Q15: =IFERROR(Q10*Assumptions!$C$38*(1+Assumptions!$C$9)^(2-1)/100000,0) -> 0 | R15: =IFERROR(R10*Assumptions!$C$38*(1+Assumptions!$C$9)^(2-1)/100000,0) -> 0 | S15: =IFERROR(S10*Assumptions!$C$38*(1+Assumptions!$C$9)^(2-1)/100000,0) -> 0 | T15: =IFERROR(T10*Assumptions!$C$38*(1+Assumptions!$C$9)^(2-1)/100000,0) -> 0 | U15: =IFERROR(U10*Assumptions!$C$38*(1+Assumptions!$C$9)^(2-1)/100000,0) -> 0 | V15: =IFERROR(V10*Assumptions!$C$38*(1+Assumptions!$C$9)^(2-1)/100000,0) -> 0 | ... Z15: =IFERROR(Z10*Assumptions!$C$38*(1+Assumptions!$C$9)^(2-1)/100000,0) -> 0 | AA15: =IFERROR(AA10*Assumptions!$C$38*(1+Assumptions!$C$9)^(3-1)/100000,0) -> 0 | AB15: =IFERROR(AB10*Assumptions!$C$38*(1+Assumptions!$C$9)^(3-1)/100000,0) -> 0 | AC15: =IFERROR(AC10*Assumptions!$C$38*(1+Assumptions!$C$9)^(3-1)/100000,0) -> 0 | AD15: =IFERROR(AD10*Assumptions!$C$38*(1+Assumptions!$C$9)^(3-1)/100000,0) -> 0 | AE15: =IFERROR(AE10*Assumptions!$C$38*(1+Assumptions!$C$9)^(3-1)/100000,0) -> 0 | AF15: =IFERROR(AF10*Assumptions!$C$38*(1+Assumptions!$C$9)^(3-1)/100000,0) -> 0 | AG15: =IFERROR(AG10*Assumptions!$C$38*(1+Assumptions!$C$9)^(3-1)/100000,0) -> 0 | AH15: =IFERROR(AH10*Assumptions!$C$38*(1+Assumptions!$C$9)^(3-1)/100000,0) -> 0 | ... AL15: =IFERROR(AL10*Assumptions!$C$38*(1+Assumptions!$C$9)^(3-1)/100000,0) -> 0 | AM15: =IFERROR(AM10*Assumptions!$C$38*(1+Assumptions!$C$9)^(4-1)/100000,0) -> 0 | AN15: =IFERROR(AN10*Assumptions!$C$38*(1+Assumptions!$C$9)^(4-1)/100000,0) -> 0 | AO15: =IFERROR(AO10*Assumptions!$C$38*(1+Assumptions!$C$9)^(4-1)/100000,0) -> 0 | AP15: =IFERROR(AP10*Assumptions!$C$38*(1+Assumptions!$C$9)^(4-1)/100000,0) -> 0 | AQ15: =IFERROR(AQ10*Assumptions!$C$38*(1+Assumptions!$C$9)^(4-1)/100000,0) -> 0 | AR15: =IFERROR(AR10*Assumptions!$C$38*(1+Assumptions!$C$9)^(4-1)/100000,0) -> 0 | AS15: =IFERROR(AS10*Assumptions!$C$38*(1+Assumptions!$C$9)^(4-1)/100000,0) -> 0 | AT15: =IFERROR(AT10*Assumptions!$C$38*(1+Assumptions!$C$9)^(4-1)/100000,0) -> 0 | ... AX15: =IFERROR(AX10*Assumptions!$C$38*(1+Assumptions!$C$9)^(4-1)/100000,0) -> 0 | AY15: =IFERROR(AY10*Assumptions!$C$38*(1+Assumptions!$C$9)^(5-1)/100000,0) -> 0 | AZ15: =IFERROR(AZ10*Assumptions!$C$38*(1+Assumptions!$C$9)^(5-1)/100000,0) -> 0 | BA15: =IFERROR(BA10*Assumptions!$C$38*(1+Assumptions!$C$9)^(5-1)/100000,0) -> 0 | BB15: =IFERROR(BB10*Assumptions!$C$38*(1+Assumptions!$C$9)^(5-1)/100000,0) -> 0 | BC15: =IFERROR(BC10*Assumptions!$C$38*(1+Assumptions!$C$9)^(5-1)/100000,0) -> 0 | BD15: =IFERROR(BD10*Assumptions!$C$38*(1+Assumptions!$C$9)^(5-1)/100000,0) -> 0 | BE15: =IFERROR(BE10*Assumptions!$C$38*(1+Assumptions!$C$9)^(5-1)/100000,0) -> 0 | BF15: =IFERROR(BF10*Assumptions!$C$38*(1+Assumptions!$C$9)^(5-1)/100000,0) -> 0 | ... BJ15: =IFERROR(BJ10*Assumptions!$C$38*(1+Assumptions!$C$9)^(5-1)/100000,0) -> 0
A16: Packaging & consumables | B16: ₹ lakh | C16: =IFERROR(C10*Assumptions!$C$39*(1+Assumptions!$C$9)^(1-1)/100000,0) -> 0 | D16: =IFERROR(D10*Assumptions!$C$39*(1+Assumptions!$C$9)^(1-1)/100000,0) -> 0 | E16: =IFERROR(E10*Assumptions!$C$39*(1+Assumptions!$C$9)^(1-1)/100000,0) -> 0 | F16: =IFERROR(F10*Assumptions!$C$39*(1+Assumptions!$C$9)^(1-1)/100000,0) -> 0 | G16: =IFERROR(G10*Assumptions!$C$39*(1+Assumptions!$C$9)^(1-1)/100000,0) -> 0 | H16: =IFERROR(H10*Assumptions!$C$39*(1+Assumptions!$C$9)^(1-1)/100000,0) -> 0 | I16: =IFERROR(I10*Assumptions!$C$39*(1+Assumptions!$C$9)^(1-1)/100000,0) -> 0 | J16: =IFERROR(J10*Assumptions!$C$39*(1+Assumptions!$C$9)^(1-1)/100000,0) -> 0 | ... N16: =IFERROR(N10*Assumptions!$C$39*(1+Assumptions!$C$9)^(1-1)/100000,0) -> 0 | O16: =IFERROR(O10*Assumptions!$C$39*(1+Assumptions!$C$9)^(2-1)/100000,0) -> 0 | P16: =IFERROR(P10*Assumptions!$C$39*(1+Assumptions!$C$9)^(2-1)/100000,0) -> 0 | Q16: =IFERROR(Q10*Assumptions!$C$39*(1+Assumptions!$C$9)^(2-1)/100000,0) -> 0 | R16: =IFERROR(R10*Assumptions!$C$39*(1+Assumptions!$C$9)^(2-1)/100000,0) -> 0 | S16: =IFERROR(S10*Assumptions!$C$39*(1+Assumptions!$C$9)^(2-1)/100000,0) -> 0 | T16: =IFERROR(T10*Assumptions!$C$39*(1+Assumptions!$C$9)^(2-1)/100000,0) -> 0 | U16: =IFERROR(U10*Assumptions!$C$39*(1+Assumptions!$C$9)^(2-1)/100000,0) -> 0 | V16: =IFERROR(V10*Assumptions!$C$39*(1+Assumptions!$C$9)^(2-1)/100000,0) -> 0 | ... Z16: =IFERROR(Z10*Assumptions!$C$39*(1+Assumptions!$C$9)^(2-1)/100000,0) -> 0 | AA16: =IFERROR(AA10*Assumptions!$C$39*(1+Assumptions!$C$9)^(3-1)/100000,0) -> 0 | AB16: =IFERROR(AB10*Assumptions!$C$39*(1+Assumptions!$C$9)^(3-1)/100000,0) -> 0 | AC16: =IFERROR(AC10*Assumptions!$C$39*(1+Assumptions!$C$9)^(3-1)/100000,0) -> 0 | AD16: =IFERROR(AD10*Assumptions!$C$39*(1+Assumptions!$C$9)^(3-1)/100000,0) -> 0 | AE16: =IFERROR(AE10*Assumptions!$C$39*(1+Assumptions!$C$9)^(3-1)/100000,0) -> 0 | AF16: =IFERROR(AF10*Assumptions!$C$39*(1+Assumptions!$C$9)^(3-1)/100000,0) -> 0 | AG16: =IFERROR(AG10*Assumptions!$C$39*(1+Assumptions!$C$9)^(3-1)/100000,0) -> 0 | AH16: =IFERROR(AH10*Assumptions!$C$39*(1+Assumptions!$C$9)^(3-1)/100000,0) -> 0 | ... AL16: =IFERROR(AL10*Assumptions!$C$39*(1+Assumptions!$C$9)^(3-1)/100000,0) -> 0 | AM16: =IFERROR(AM10*Assumptions!$C$39*(1+Assumptions!$C$9)^(4-1)/100000,0) -> 0 | AN16: =IFERROR(AN10*Assumptions!$C$39*(1+Assumptions!$C$9)^(4-1)/100000,0) -> 0 | AO16: =IFERROR(AO10*Assumptions!$C$39*(1+Assumptions!$C$9)^(4-1)/100000,0) -> 0 | AP16: =IFERROR(AP10*Assumptions!$C$39*(1+Assumptions!$C$9)^(4-1)/100000,0) -> 0 | AQ16: =IFERROR(AQ10*Assumptions!$C$39*(1+Assumptions!$C$9)^(4-1)/100000,0) -> 0 | AR16: =IFERROR(AR10*Assumptions!$C$39*(1+Assumptions!$C$9)^(4-1)/100000,0) -> 0 | AS16: =IFERROR(AS10*Assumptions!$C$39*(1+Assumptions!$C$9)^(4-1)/100000,0) -> 0 | AT16: =IFERROR(AT10*Assumptions!$C$39*(1+Assumptions!$C$9)^(4-1)/100000,0) -> 0 | ... AX16: =IFERROR(AX10*Assumptions!$C$39*(1+Assumptions!$C$9)^(4-1)/100000,0) -> 0 | AY16: =IFERROR(AY10*Assumptions!$C$39*(1+Assumptions!$C$9)^(5-1)/100000,0) -> 0 | AZ16: =IFERROR(AZ10*Assumptions!$C$39*(1+Assumptions!$C$9)^(5-1)/100000,0) -> 0 | BA16: =IFERROR(BA10*Assumptions!$C$39*(1+Assumptions!$C$9)^(5-1)/100000,0) -> 0 | BB16: =IFERROR(BB10*Assumptions!$C$39*(1+Assumptions!$C$9)^(5-1)/100000,0) -> 0 | BC16: =IFERROR(BC10*Assumptions!$C$39*(1+Assumptions!$C$9)^(5-1)/100000,0) -> 0 | BD16: =IFERROR(BD10*Assumptions!$C$39*(1+Assumptions!$C$9)^(5-1)/100000,0) -> 0 | BE16: =IFERROR(BE10*Assumptions!$C$39*(1+Assumptions!$C$9)^(5-1)/100000,0) -> 0 | BF16: =IFERROR(BF10*Assumptions!$C$39*(1+Assumptions!$C$9)^(5-1)/100000,0) -> 0 | ... BJ16: =IFERROR(BJ10*Assumptions!$C$39*(1+Assumptions!$C$9)^(5-1)/100000,0) -> 0
A17: Direct utilities | B17: ₹ lakh | C17: =IFERROR(C10*Assumptions!$C$40*(1+Assumptions!$C$11)^(1-1)/100000,0) -> 0 | D17: =IFERROR(D10*Assumptions!$C$40*(1+Assumptions!$C$11)^(1-1)/100000,0) -> 0 | E17: =IFERROR(E10*Assumptions!$C$40*(1+Assumptions!$C$11)^(1-1)/100000,0) -> 0 | F17: =IFERROR(F10*Assumptions!$C$40*(1+Assumptions!$C$11)^(1-1)/100000,0) -> 0 | G17: =IFERROR(G10*Assumptions!$C$40*(1+Assumptions!$C$11)^(1-1)/100000,0) -> 0 | H17: =IFERROR(H10*Assumptions!$C$40*(1+Assumptions!$C$11)^(1-1)/100000,0) -> 0 | I17: =IFERROR(I10*Assumptions!$C$40*(1+Assumptions!$C$11)^(1-1)/100000,0) -> 0 | J17: =IFERROR(J10*Assumptions!$C$40*(1+Assumptions!$C$11)^(1-1)/100000,0) -> 0 | ... N17: =IFERROR(N10*Assumptions!$C$40*(1+Assumptions!$C$11)^(1-1)/100000,0) -> 0 | O17: =IFERROR(O10*Assumptions!$C$40*(1+Assumptions!$C$11)^(2-1)/100000,0) -> 0 | P17: =IFERROR(P10*Assumptions!$C$40*(1+Assumptions!$C$11)^(2-1)/100000,0) -> 0 | Q17: =IFERROR(Q10*Assumptions!$C$40*(1+Assumptions!$C$11)^(2-1)/100000,0) -> 0 | R17: =IFERROR(R10*Assumptions!$C$40*(1+Assumptions!$C$11)^(2-1)/100000,0) -> 0 | S17: =IFERROR(S10*Assumptions!$C$40*(1+Assumptions!$C$11)^(2-1)/100000,0) -> 0 | T17: =IFERROR(T10*Assumptions!$C$40*(1+Assumptions!$C$11)^(2-1)/100000,0) -> 0 | U17: =IFERROR(U10*Assumptions!$C$40*(1+Assumptions!$C$11)^(2-1)/100000,0) -> 0 | V17: =IFERROR(V10*Assumptions!$C$40*(1+Assumptions!$C$11)^(2-1)/100000,0) -> 0 | ... Z17: =IFERROR(Z10*Assumptions!$C$40*(1+Assumptions!$C$11)^(2-1)/100000,0) -> 0 | AA17: =IFERROR(AA10*Assumptions!$C$40*(1+Assumptions!$C$11)^(3-1)/100000,0) -> 0 | AB17: =IFERROR(AB10*Assumptions!$C$40*(1+Assumptions!$C$11)^(3-1)/100000,0) -> 0 | AC17: =IFERROR(AC10*Assumptions!$C$40*(1+Assumptions!$C$11)^(3-1)/100000,0) -> 0 | AD17: =IFERROR(AD10*Assumptions!$C$40*(1+Assumptions!$C$11)^(3-1)/100000,0) -> 0 | AE17: =IFERROR(AE10*Assumptions!$C$40*(1+Assumptions!$C$11)^(3-1)/100000,0) -> 0 | AF17: =IFERROR(AF10*Assumptions!$C$40*(1+Assumptions!$C$11)^(3-1)/100000,0) -> 0 | AG17: =IFERROR(AG10*Assumptions!$C$40*(1+Assumptions!$C$11)^(3-1)/100000,0) -> 0 | AH17: =IFERROR(AH10*Assumptions!$C$40*(1+Assumptions!$C$11)^(3-1)/100000,0) -> 0 | ... AL17: =IFERROR(AL10*Assumptions!$C$40*(1+Assumptions!$C$11)^(3-1)/100000,0) -> 0 | AM17: =IFERROR(AM10*Assumptions!$C$40*(1+Assumptions!$C$11)^(4-1)/100000,0) -> 0 | AN17: =IFERROR(AN10*Assumptions!$C$40*(1+Assumptions!$C$11)^(4-1)/100000,0) -> 0 | AO17: =IFERROR(AO10*Assumptions!$C$40*(1+Assumptions!$C$11)^(4-1)/100000,0) -> 0 | AP17: =IFERROR(AP10*Assumptions!$C$40*(1+Assumptions!$C$11)^(4-1)/100000,0) -> 0 | AQ17: =IFERROR(AQ10*Assumptions!$C$40*(1+Assumptions!$C$11)^(4-1)/100000,0) -> 0 | AR17: =IFERROR(AR10*Assumptions!$C$40*(1+Assumptions!$C$11)^(4-1)/100000,0) -> 0 | AS17: =IFERROR(AS10*Assumptions!$C$40*(1+Assumptions!$C$11)^(4-1)/100000,0) -> 0 | AT17: =IFERROR(AT10*Assumptions!$C$40*(1+Assumptions!$C$11)^(4-1)/100000,0) -> 0 | ... AX17: =IFERROR(AX10*Assumptions!$C$40*(1+Assumptions!$C$11)^(4-1)/100000,0) -> 0 | AY17: =IFERROR(AY10*Assumptions!$C$40*(1+Assumptions!$C$11)^(5-1)/100000,0) -> 0 | AZ17: =IFERROR(AZ10*Assumptions!$C$40*(1+Assumptions!$C$11)^(5-1)/100000,0) -> 0 | BA17: =IFERROR(BA10*Assumptions!$C$40*(1+Assumptions!$C$11)^(5-1)/100000,0) -> 0 | BB17: =IFERROR(BB10*Assumptions!$C$40*(1+Assumptions!$C$11)^(5-1)/100000,0) -> 0 | BC17: =IFERROR(BC10*Assumptions!$C$40*(1+Assumptions!$C$11)^(5-1)/100000,0) -> 0 | BD17: =IFERROR(BD10*Assumptions!$C$40*(1+Assumptions!$C$11)^(5-1)/100000,0) -> 0 | BE17: =IFERROR(BE10*Assumptions!$C$40*(1+Assumptions!$C$11)^(5-1)/100000,0) -> 0 | BF17: =IFERROR(BF10*Assumptions!$C$40*(1+Assumptions!$C$11)^(5-1)/100000,0) -> 0 | ... BJ17: =IFERROR(BJ10*Assumptions!$C$40*(1+Assumptions!$C$11)^(5-1)/100000,0) -> 0
A18: Other direct cost | B18: ₹ lakh | C18: =IFERROR(C10*Assumptions!$C$41*(1+Assumptions!$C$11)^(1-1)/100000,0) -> 0 | D18: =IFERROR(D10*Assumptions!$C$41*(1+Assumptions!$C$11)^(1-1)/100000,0) -> 0 | E18: =IFERROR(E10*Assumptions!$C$41*(1+Assumptions!$C$11)^(1-1)/100000,0) -> 0 | F18: =IFERROR(F10*Assumptions!$C$41*(1+Assumptions!$C$11)^(1-1)/100000,0) -> 0 | G18: =IFERROR(G10*Assumptions!$C$41*(1+Assumptions!$C$11)^(1-1)/100000,0) -> 0 | H18: =IFERROR(H10*Assumptions!$C$41*(1+Assumptions!$C$11)^(1-1)/100000,0) -> 0 | I18: =IFERROR(I10*Assumptions!$C$41*(1+Assumptions!$C$11)^(1-1)/100000,0) -> 0 | J18: =IFERROR(J10*Assumptions!$C$41*(1+Assumptions!$C$11)^(1-1)/100000,0) -> 0 | ... N18: =IFERROR(N10*Assumptions!$C$41*(1+Assumptions!$C$11)^(1-1)/100000,0) -> 0 | O18: =IFERROR(O10*Assumptions!$C$41*(1+Assumptions!$C$11)^(2-1)/100000,0) -> 0 | P18: =IFERROR(P10*Assumptions!$C$41*(1+Assumptions!$C$11)^(2-1)/100000,0) -> 0 | Q18: =IFERROR(Q10*Assumptions!$C$41*(1+Assumptions!$C$11)^(2-1)/100000,0) -> 0 | R18: =IFERROR(R10*Assumptions!$C$41*(1+Assumptions!$C$11)^(2-1)/100000,0) -> 0 | S18: =IFERROR(S10*Assumptions!$C$41*(1+Assumptions!$C$11)^(2-1)/100000,0) -> 0 | T18: =IFERROR(T10*Assumptions!$C$41*(1+Assumptions!$C$11)^(2-1)/100000,0) -> 0 | U18: =IFERROR(U10*Assumptions!$C$41*(1+Assumptions!$C$11)^(2-1)/100000,0) -> 0 | V18: =IFERROR(V10*Assumptions!$C$41*(1+Assumptions!$C$11)^(2-1)/100000,0) -> 0 | ... Z18: =IFERROR(Z10*Assumptions!$C$41*(1+Assumptions!$C$11)^(2-1)/100000,0) -> 0 | AA18: =IFERROR(AA10*Assumptions!$C$41*(1+Assumptions!$C$11)^(3-1)/100000,0) -> 0 | AB18: =IFERROR(AB10*Assumptions!$C$41*(1+Assumptions!$C$11)^(3-1)/100000,0) -> 0 | AC18: =IFERROR(AC10*Assumptions!$C$41*(1+Assumptions!$C$11)^(3-1)/100000,0) -> 0 | AD18: =IFERROR(AD10*Assumptions!$C$41*(1+Assumptions!$C$11)^(3-1)/100000,0) -> 0 | AE18: =IFERROR(AE10*Assumptions!$C$41*(1+Assumptions!$C$11)^(3-1)/100000,0) -> 0 | AF18: =IFERROR(AF10*Assumptions!$C$41*(1+Assumptions!$C$11)^(3-1)/100000,0) -> 0 | AG18: =IFERROR(AG10*Assumptions!$C$41*(1+Assumptions!$C$11)^(3-1)/100000,0) -> 0 | AH18: =IFERROR(AH10*Assumptions!$C$41*(1+Assumptions!$C$11)^(3-1)/100000,0) -> 0 | ... AL18: =IFERROR(AL10*Assumptions!$C$41*(1+Assumptions!$C$11)^(3-1)/100000,0) -> 0 | AM18: =IFERROR(AM10*Assumptions!$C$41*(1+Assumptions!$C$11)^(4-1)/100000,0) -> 0 | AN18: =IFERROR(AN10*Assumptions!$C$41*(1+Assumptions!$C$11)^(4-1)/100000,0) -> 0 | AO18: =IFERROR(AO10*Assumptions!$C$41*(1+Assumptions!$C$11)^(4-1)/100000,0) -> 0 | AP18: =IFERROR(AP10*Assumptions!$C$41*(1+Assumptions!$C$11)^(4-1)/100000,0) -> 0 | AQ18: =IFERROR(AQ10*Assumptions!$C$41*(1+Assumptions!$C$11)^(4-1)/100000,0) -> 0 | AR18: =IFERROR(AR10*Assumptions!$C$41*(1+Assumptions!$C$11)^(4-1)/100000,0) -> 0 | AS18: =IFERROR(AS10*Assumptions!$C$41*(1+Assumptions!$C$11)^(4-1)/100000,0) -> 0 | AT18: =IFERROR(AT10*Assumptions!$C$41*(1+Assumptions!$C$11)^(4-1)/100000,0) -> 0 | ... AX18: =IFERROR(AX10*Assumptions!$C$41*(1+Assumptions!$C$11)^(4-1)/100000,0) -> 0 | AY18: =IFERROR(AY10*Assumptions!$C$41*(1+Assumptions!$C$11)^(5-1)/100000,0) -> 0 | AZ18: =IFERROR(AZ10*Assumptions!$C$41*(1+Assumptions!$C$11)^(5-1)/100000,0) -> 0 | BA18: =IFERROR(BA10*Assumptions!$C$41*(1+Assumptions!$C$11)^(5-1)/100000,0) -> 0 | BB18: =IFERROR(BB10*Assumptions!$C$41*(1+Assumptions!$C$11)^(5-1)/100000,0) -> 0 | BC18: =IFERROR(BC10*Assumptions!$C$41*(1+Assumptions!$C$11)^(5-1)/100000,0) -> 0 | BD18: =IFERROR(BD10*Assumptions!$C$41*(1+Assumptions!$C$11)^(5-1)/100000,0) -> 0 | BE18: =IFERROR(BE10*Assumptions!$C$41*(1+Assumptions!$C$11)^(5-1)/100000,0) -> 0 | BF18: =IFERROR(BF10*Assumptions!$C$41*(1+Assumptions!$C$11)^(5-1)/100000,0) -> 0 | ... BJ18: =IFERROR(BJ10*Assumptions!$C$41*(1+Assumptions!$C$11)^(5-1)/100000,0) -> 0
A19: Total COGS | B19: ₹ lakh | C19: =IFERROR(SUM(C15:C18),0) -> 0 | D19: =IFERROR(SUM(D15:D18),0) -> 0 | E19: =IFERROR(SUM(E15:E18),0) -> 0 | F19: =IFERROR(SUM(F15:F18),0) -> 0 | G19: =IFERROR(SUM(G15:G18),0) -> 0 | H19: =IFERROR(SUM(H15:H18),0) -> 0 | I19: =IFERROR(SUM(I15:I18),0) -> 0 | J19: =IFERROR(SUM(J15:J18),0) -> 0 | ... BJ19: =IFERROR(SUM(BJ15:BJ18),0) -> 0
A20: Gross profit | B20: ₹ lakh | C20: =IFERROR(C13-C19,0) -> 0 | D20: =IFERROR(D13-D19,0) -> 0 | E20: =IFERROR(E13-E19,0) -> 0 | F20: =IFERROR(F13-F19,0) -> 0 | G20: =IFERROR(G13-G19,0) -> 0 | H20: =IFERROR(H13-H19,0) -> 0 | I20: =IFERROR(I13-I19,0) -> 0 | J20: =IFERROR(J13-J19,0) -> 0 | ... BJ20: =IFERROR(BJ13-BJ19,0) -> 0
A21: OPERATING EXPENSES
A22: Salaries & wages | B22: ₹ lakh | C22: =IFERROR(Payroll!C9,0) -> 0 | D22: =IFERROR(Payroll!D9,0) -> 0 | E22: =IFERROR(Payroll!E9,0) -> 0 | F22: =IFERROR(Payroll!F9,0) -> 0 | G22: =IFERROR(Payroll!G9,0) -> 0 | H22: =IFERROR(Payroll!H9,0) -> 0 | I22: =IFERROR(Payroll!I9,0) -> 0 | J22: =IFERROR(Payroll!J9,0) -> 0 | ... BJ22: =IFERROR(Payroll!BJ9,0) -> 0
A23: Fixed power, fuel & DG | B23: ₹ lakh | C23: =IFERROR(Assumptions!$C$43*(1+Assumptions!$C$11)^(1-1),0) -> 0 | D23: =IFERROR(Assumptions!$C$43*(1+Assumptions!$C$11)^(1-1),0) -> 0 | E23: =IFERROR(Assumptions!$C$43*(1+Assumptions!$C$11)^(1-1),0) -> 0 | F23: =IFERROR(Assumptions!$C$43*(1+Assumptions!$C$11)^(1-1),0) -> 0 | G23: =IFERROR(Assumptions!$C$43*(1+Assumptions!$C$11)^(1-1),0) -> 0 | H23: =IFERROR(Assumptions!$C$43*(1+Assumptions!$C$11)^(1-1),0) -> 0 | I23: =IFERROR(Assumptions!$C$43*(1+Assumptions!$C$11)^(1-1),0) -> 0 | J23: =IFERROR(Assumptions!$C$43*(1+Assumptions!$C$11)^(1-1),0) -> 0 | ... N23: =IFERROR(Assumptions!$C$43*(1+Assumptions!$C$11)^(1-1),0) -> 0 | O23: =IFERROR(Assumptions!$C$43*(1+Assumptions!$C$11)^(2-1),0) -> 0 | P23: =IFERROR(Assumptions!$C$43*(1+Assumptions!$C$11)^(2-1),0) -> 0 | Q23: =IFERROR(Assumptions!$C$43*(1+Assumptions!$C$11)^(2-1),0) -> 0 | R23: =IFERROR(Assumptions!$C$43*(1+Assumptions!$C$11)^(2-1),0) -> 0 | S23: =IFERROR(Assumptions!$C$43*(1+Assumptions!$C$11)^(2-1),0) -> 0 | T23: =IFERROR(Assumptions!$C$43*(1+Assumptions!$C$11)^(2-1),0) -> 0 | U23: =IFERROR(Assumptions!$C$43*(1+Assumptions!$C$11)^(2-1),0) -> 0 | V23: =IFERROR(Assumptions!$C$43*(1+Assumptions!$C$11)^(2-1),0) -> 0 | ... Z23: =IFERROR(Assumptions!$C$43*(1+Assumptions!$C$11)^(2-1),0) -> 0 | AA23: =IFERROR(Assumptions!$C$43*(1+Assumptions!$C$11)^(3-1),0) -> 0 | AB23: =IFERROR(Assumptions!$C$43*(1+Assumptions!$C$11)^(3-1),0) -> 0 | AC23: =IFERROR(Assumptions!$C$43*(1+Assumptions!$C$11)^(3-1),0) -> 0 | AD23: =IFERROR(Assumptions!$C$43*(1+Assumptions!$C$11)^(3-1),0) -> 0 | AE23: =IFERROR(Assumptions!$C$43*(1+Assumptions!$C$11)^(3-1),0) -> 0 | AF23: =IFERROR(Assumptions!$C$43*(1+Assumptions!$C$11)^(3-1),0) -> 0 | AG23: =IFERROR(Assumptions!$C$43*(1+Assumptions!$C$11)^(3-1),0) -> 0 | AH23: =IFERROR(Assumptions!$C$43*(1+Assumptions!$C$11)^(3-1),0) -> 0 | ... AL23: =IFERROR(Assumptions!$C$43*(1+Assumptions!$C$11)^(3-1),0) -> 0 | AM23: =IFERROR(Assumptions!$C$43*(1+Assumptions!$C$11)^(4-1),0) -> 0 | AN23: =IFERROR(Assumptions!$C$43*(1+Assumptions!$C$11)^(4-1),0) -> 0 | AO23: =IFERROR(Assumptions!$C$43*(1+Assumptions!$C$11)^(4-1),0) -> 0 | AP23: =IFERROR(Assumptions!$C$43*(1+Assumptions!$C$11)^(4-1),0) -> 0 | AQ23: =IFERROR(Assumptions!$C$43*(1+Assumptions!$C$11)^(4-1),0) -> 0 | AR23: =IFERROR(Assumptions!$C$43*(1+Assumptions!$C$11)^(4-1),0) -> 0 | AS23: =IFERROR(Assumptions!$C$43*(1+Assumptions!$C$11)^(4-1),0) -> 0 | AT23: =IFERROR(Assumptions!$C$43*(1+Assumptions!$C$11)^(4-1),0) -> 0 | ... AX23: =IFERROR(Assumptions!$C$43*(1+Assumptions!$C$11)^(4-1),0) -> 0 | AY23: =IFERROR(Assumptions!$C$43*(1+Assumptions!$C$11)^(5-1),0) -> 0 | AZ23: =IFERROR(Assumptions!$C$43*(1+Assumptions!$C$11)^(5-1),0) -> 0 | BA23: =IFERROR(Assumptions!$C$43*(1+Assumptions!$C$11)^(5-1),0) -> 0 | BB23: =IFERROR(Assumptions!$C$43*(1+Assumptions!$C$11)^(5-1),0) -> 0 | BC23: =IFERROR(Assumptions!$C$43*(1+Assumptions!$C$11)^(5-1),0) -> 0 | BD23: =IFERROR(Assumptions!$C$43*(1+Assumptions!$C$11)^(5-1),0) -> 0 | BE23: =IFERROR(Assumptions!$C$43*(1+Assumptions!$C$11)^(5-1),0) -> 0 | BF23: =IFERROR(Assumptions!$C$43*(1+Assumptions!$C$11)^(5-1),0) -> 0 | ... BJ23: =IFERROR(Assumptions!$C$43*(1+Assumptions!$C$11)^(5-1),0) -> 0
A24: Repairs & maintenance | B24: ₹ lakh | C24: =IFERROR(Assumptions!$C$44*(1+Assumptions!$C$11)^(1-1),0) -> 0 | D24: =IFERROR(Assumptions!$C$44*(1+Assumptions!$C$11)^(1-1),0) -> 0 | E24: =IFERROR(Assumptions!$C$44*(1+Assumptions!$C$11)^(1-1),0) -> 0 | F24: =IFERROR(Assumptions!$C$44*(1+Assumptions!$C$11)^(1-1),0) -> 0 | G24: =IFERROR(Assumptions!$C$44*(1+Assumptions!$C$11)^(1-1),0) -> 0 | H24: =IFERROR(Assumptions!$C$44*(1+Assumptions!$C$11)^(1-1),0) -> 0 | I24: =IFERROR(Assumptions!$C$44*(1+Assumptions!$C$11)^(1-1),0) -> 0 | J24: =IFERROR(Assumptions!$C$44*(1+Assumptions!$C$11)^(1-1),0) -> 0 | ... N24: =IFERROR(Assumptions!$C$44*(1+Assumptions!$C$11)^(1-1),0) -> 0 | O24: =IFERROR(Assumptions!$C$44*(1+Assumptions!$C$11)^(2-1),0) -> 0 | P24: =IFERROR(Assumptions!$C$44*(1+Assumptions!$C$11)^(2-1),0) -> 0 | Q24: =IFERROR(Assumptions!$C$44*(1+Assumptions!$C$11)^(2-1),0) -> 0 | R24: =IFERROR(Assumptions!$C$44*(1+Assumptions!$C$11)^(2-1),0) -> 0 | S24: =IFERROR(Assumptions!$C$44*(1+Assumptions!$C$11)^(2-1),0) -> 0 | T24: =IFERROR(Assumptions!$C$44*(1+Assumptions!$C$11)^(2-1),0) -> 0 | U24: =IFERROR(Assumptions!$C$44*(1+Assumptions!$C$11)^(2-1),0) -> 0 | V24: =IFERROR(Assumptions!$C$44*(1+Assumptions!$C$11)^(2-1),0) -> 0 | ... Z24: =IFERROR(Assumptions!$C$44*(1+Assumptions!$C$11)^(2-1),0) -> 0 | AA24: =IFERROR(Assumptions!$C$44*(1+Assumptions!$C$11)^(3-1),0) -> 0 | AB24: =IFERROR(Assumptions!$C$44*(1+Assumptions!$C$11)^(3-1),0) -> 0 | AC24: =IFERROR(Assumptions!$C$44*(1+Assumptions!$C$11)^(3-1),0) -> 0 | AD24: =IFERROR(Assumptions!$C$44*(1+Assumptions!$C$11)^(3-1),0) -> 0 | AE24: =IFERROR(Assumptions!$C$44*(1+Assumptions!$C$11)^(3-1),0) -> 0 | AF24: =IFERROR(Assumptions!$C$44*(1+Assumptions!$C$11)^(3-1),0) -> 0 | AG24: =IFERROR(Assumptions!$C$44*(1+Assumptions!$C$11)^(3-1),0) -> 0 | AH24: =IFERROR(Assumptions!$C$44*(1+Assumptions!$C$11)^(3-1),0) -> 0 | ... AL24: =IFERROR(Assumptions!$C$44*(1+Assumptions!$C$11)^(3-1),0) -> 0 | AM24: =IFERROR(Assumptions!$C$44*(1+Assumptions!$C$11)^(4-1),0) -> 0 | AN24: =IFERROR(Assumptions!$C$44*(1+Assumptions!$C$11)^(4-1),0) -> 0 | AO24: =IFERROR(Assumptions!$C$44*(1+Assumptions!$C$11)^(4-1),0) -> 0 | AP24: =IFERROR(Assumptions!$C$44*(1+Assumptions!$C$11)^(4-1),0) -> 0 | AQ24: =IFERROR(Assumptions!$C$44*(1+Assumptions!$C$11)^(4-1),0) -> 0 | AR24: =IFERROR(Assumptions!$C$44*(1+Assumptions!$C$11)^(4-1),0) -> 0 | AS24: =IFERROR(Assumptions!$C$44*(1+Assumptions!$C$11)^(4-1),0) -> 0 | AT24: =IFERROR(Assumptions!$C$44*(1+Assumptions!$C$11)^(4-1),0) -> 0 | ... AX24: =IFERROR(Assumptions!$C$44*(1+Assumptions!$C$11)^(4-1),0) -> 0 | AY24: =IFERROR(Assumptions!$C$44*(1+Assumptions!$C$11)^(5-1),0) -> 0 | AZ24: =IFERROR(Assumptions!$C$44*(1+Assumptions!$C$11)^(5-1),0) -> 0 | BA24: =IFERROR(Assumptions!$C$44*(1+Assumptions!$C$11)^(5-1),0) -> 0 | BB24: =IFERROR(Assumptions!$C$44*(1+Assumptions!$C$11)^(5-1),0) -> 0 | BC24: =IFERROR(Assumptions!$C$44*(1+Assumptions!$C$11)^(5-1),0) -> 0 | BD24: =IFERROR(Assumptions!$C$44*(1+Assumptions!$C$11)^(5-1),0) -> 0 | BE24: =IFERROR(Assumptions!$C$44*(1+Assumptions!$C$11)^(5-1),0) -> 0 | BF24: =IFERROR(Assumptions!$C$44*(1+Assumptions!$C$11)^(5-1),0) -> 0 | ... BJ24: =IFERROR(Assumptions!$C$44*(1+Assumptions!$C$11)^(5-1),0) -> 0
A25: Administrative & general | B25: ₹ lakh | C25: =IFERROR(Assumptions!$C$45*(1+Assumptions!$C$11)^(1-1),0) -> 0 | D25: =IFERROR(Assumptions!$C$45*(1+Assumptions!$C$11)^(1-1),0) -> 0 | E25: =IFERROR(Assumptions!$C$45*(1+Assumptions!$C$11)^(1-1),0) -> 0 | F25: =IFERROR(Assumptions!$C$45*(1+Assumptions!$C$11)^(1-1),0) -> 0 | G25: =IFERROR(Assumptions!$C$45*(1+Assumptions!$C$11)^(1-1),0) -> 0 | H25: =IFERROR(Assumptions!$C$45*(1+Assumptions!$C$11)^(1-1),0) -> 0 | I25: =IFERROR(Assumptions!$C$45*(1+Assumptions!$C$11)^(1-1),0) -> 0 | J25: =IFERROR(Assumptions!$C$45*(1+Assumptions!$C$11)^(1-1),0) -> 0 | ... N25: =IFERROR(Assumptions!$C$45*(1+Assumptions!$C$11)^(1-1),0) -> 0 | O25: =IFERROR(Assumptions!$C$45*(1+Assumptions!$C$11)^(2-1),0) -> 0 | P25: =IFERROR(Assumptions!$C$45*(1+Assumptions!$C$11)^(2-1),0) -> 0 | Q25: =IFERROR(Assumptions!$C$45*(1+Assumptions!$C$11)^(2-1),0) -> 0 | R25: =IFERROR(Assumptions!$C$45*(1+Assumptions!$C$11)^(2-1),0) -> 0 | S25: =IFERROR(Assumptions!$C$45*(1+Assumptions!$C$11)^(2-1),0) -> 0 | T25: =IFERROR(Assumptions!$C$45*(1+Assumptions!$C$11)^(2-1),0) -> 0 | U25: =IFERROR(Assumptions!$C$45*(1+Assumptions!$C$11)^(2-1),0) -> 0 | V25: =IFERROR(Assumptions!$C$45*(1+Assumptions!$C$11)^(2-1),0) -> 0 | ... Z25: =IFERROR(Assumptions!$C$45*(1+Assumptions!$C$11)^(2-1),0) -> 0 | AA25: =IFERROR(Assumptions!$C$45*(1+Assumptions!$C$11)^(3-1),0) -> 0 | AB25: =IFERROR(Assumptions!$C$45*(1+Assumptions!$C$11)^(3-1),0) -> 0 | AC25: =IFERROR(Assumptions!$C$45*(1+Assumptions!$C$11)^(3-1),0) -> 0 | AD25: =IFERROR(Assumptions!$C$45*(1+Assumptions!$C$11)^(3-1),0) -> 0 | AE25: =IFERROR(Assumptions!$C$45*(1+Assumptions!$C$11)^(3-1),0) -> 0 | AF25: =IFERROR(Assumptions!$C$45*(1+Assumptions!$C$11)^(3-1),0) -> 0 | AG25: =IFERROR(Assumptions!$C$45*(1+Assumptions!$C$11)^(3-1),0) -> 0 | AH25: =IFERROR(Assumptions!$C$45*(1+Assumptions!$C$11)^(3-1),0) -> 0 | ... AL25: =IFERROR(Assumptions!$C$45*(1+Assumptions!$C$11)^(3-1),0) -> 0 | AM25: =IFERROR(Assumptions!$C$45*(1+Assumptions!$C$11)^(4-1),0) -> 0 | AN25: =IFERROR(Assumptions!$C$45*(1+Assumptions!$C$11)^(4-1),0) -> 0 | AO25: =IFERROR(Assumptions!$C$45*(1+Assumptions!$C$11)^(4-1),0) -> 0 | AP25: =IFERROR(Assumptions!$C$45*(1+Assumptions!$C$11)^(4-1),0) -> 0 | AQ25: =IFERROR(Assumptions!$C$45*(1+Assumptions!$C$11)^(4-1),0) -> 0 | AR25: =IFERROR(Assumptions!$C$45*(1+Assumptions!$C$11)^(4-1),0) -> 0 | AS25: =IFERROR(Assumptions!$C$45*(1+Assumptions!$C$11)^(4-1),0) -> 0 | AT25: =IFERROR(Assumptions!$C$45*(1+Assumptions!$C$11)^(4-1),0) -> 0 | ... AX25: =IFERROR(Assumptions!$C$45*(1+Assumptions!$C$11)^(4-1),0) -> 0 | AY25: =IFERROR(Assumptions!$C$45*(1+Assumptions!$C$11)^(5-1),0) -> 0 | AZ25: =IFERROR(Assumptions!$C$45*(1+Assumptions!$C$11)^(5-1),0) -> 0 | BA25: =IFERROR(Assumptions!$C$45*(1+Assumptions!$C$11)^(5-1),0) -> 0 | BB25: =IFERROR(Assumptions!$C$45*(1+Assumptions!$C$11)^(5-1),0) -> 0 | BC25: =IFERROR(Assumptions!$C$45*(1+Assumptions!$C$11)^(5-1),0) -> 0 | BD25: =IFERROR(Assumptions!$C$45*(1+Assumptions!$C$11)^(5-1),0) -> 0 | BE25: =IFERROR(Assumptions!$C$45*(1+Assumptions!$C$11)^(5-1),0) -> 0 | BF25: =IFERROR(Assumptions!$C$45*(1+Assumptions!$C$11)^(5-1),0) -> 0 | ... BJ25: =IFERROR(Assumptions!$C$45*(1+Assumptions!$C$11)^(5-1),0) -> 0
A26: Selling, distribution & branding | B26: ₹ lakh | C26: =IFERROR(C13*Assumptions!$C$46,0) -> 0 | D26: =IFERROR(D13*Assumptions!$C$46,0) -> 0 | E26: =IFERROR(E13*Assumptions!$C$46,0) -> 0 | F26: =IFERROR(F13*Assumptions!$C$46,0) -> 0 | G26: =IFERROR(G13*Assumptions!$C$46,0) -> 0 | H26: =IFERROR(H13*Assumptions!$C$46,0) -> 0 | I26: =IFERROR(I13*Assumptions!$C$46,0) -> 0 | J26: =IFERROR(J13*Assumptions!$C$46,0) -> 0 | ... BJ26: =IFERROR(BJ13*Assumptions!$C$46,0) -> 0
A27: Insurance | B27: ₹ lakh | C27: =IFERROR(Assumptions!$C$47*(1+Assumptions!$C$11)^(1-1),0) -> 0 | D27: =IFERROR(Assumptions!$C$47*(1+Assumptions!$C$11)^(1-1),0) -> 0 | E27: =IFERROR(Assumptions!$C$47*(1+Assumptions!$C$11)^(1-1),0) -> 0 | F27: =IFERROR(Assumptions!$C$47*(1+Assumptions!$C$11)^(1-1),0) -> 0 | G27: =IFERROR(Assumptions!$C$47*(1+Assumptions!$C$11)^(1-1),0) -> 0 | H27: =IFERROR(Assumptions!$C$47*(1+Assumptions!$C$11)^(1-1),0) -> 0 | I27: =IFERROR(Assumptions!$C$47*(1+Assumptions!$C$11)^(1-1),0) -> 0 | J27: =IFERROR(Assumptions!$C$47*(1+Assumptions!$C$11)^(1-1),0) -> 0 | ... N27: =IFERROR(Assumptions!$C$47*(1+Assumptions!$C$11)^(1-1),0) -> 0 | O27: =IFERROR(Assumptions!$C$47*(1+Assumptions!$C$11)^(2-1),0) -> 0 | P27: =IFERROR(Assumptions!$C$47*(1+Assumptions!$C$11)^(2-1),0) -> 0 | Q27: =IFERROR(Assumptions!$C$47*(1+Assumptions!$C$11)^(2-1),0) -> 0 | R27: =IFERROR(Assumptions!$C$47*(1+Assumptions!$C$11)^(2-1),0) -> 0 | S27: =IFERROR(Assumptions!$C$47*(1+Assumptions!$C$11)^(2-1),0) -> 0 | T27: =IFERROR(Assumptions!$C$47*(1+Assumptions!$C$11)^(2-1),0) -> 0 | U27: =IFERROR(Assumptions!$C$47*(1+Assumptions!$C$11)^(2-1),0) -> 0 | V27: =IFERROR(Assumptions!$C$47*(1+Assumptions!$C$11)^(2-1),0) -> 0 | ... Z27: =IFERROR(Assumptions!$C$47*(1+Assumptions!$C$11)^(2-1),0) -> 0 | AA27: =IFERROR(Assumptions!$C$47*(1+Assumptions!$C$11)^(3-1),0) -> 0 | AB27: =IFERROR(Assumptions!$C$47*(1+Assumptions!$C$11)^(3-1),0) -> 0 | AC27: =IFERROR(Assumptions!$C$47*(1+Assumptions!$C$11)^(3-1),0) -> 0 | AD27: =IFERROR(Assumptions!$C$47*(1+Assumptions!$C$11)^(3-1),0) -> 0 | AE27: =IFERROR(Assumptions!$C$47*(1+Assumptions!$C$11)^(3-1),0) -> 0 | AF27: =IFERROR(Assumptions!$C$47*(1+Assumptions!$C$11)^(3-1),0) -> 0 | AG27: =IFERROR(Assumptions!$C$47*(1+Assumptions!$C$11)^(3-1),0) -> 0 | AH27: =IFERROR(Assumptions!$C$47*(1+Assumptions!$C$11)^(3-1),0) -> 0 | ... AL27: =IFERROR(Assumptions!$C$47*(1+Assumptions!$C$11)^(3-1),0) -> 0 | AM27: =IFERROR(Assumptions!$C$47*(1+Assumptions!$C$11)^(4-1),0) -> 0 | AN27: =IFERROR(Assumptions!$C$47*(1+Assumptions!$C$11)^(4-1),0) -> 0 | AO27: =IFERROR(Assumptions!$C$47*(1+Assumptions!$C$11)^(4-1),0) -> 0 | AP27: =IFERROR(Assumptions!$C$47*(1+Assumptions!$C$11)^(4-1),0) -> 0 | AQ27: =IFERROR(Assumptions!$C$47*(1+Assumptions!$C$11)^(4-1),0) -> 0 | AR27: =IFERROR(Assumptions!$C$47*(1+Assumptions!$C$11)^(4-1),0) -> 0 | AS27: =IFERROR(Assumptions!$C$47*(1+Assumptions!$C$11)^(4-1),0) -> 0 | AT27: =IFERROR(Assumptions!$C$47*(1+Assumptions!$C$11)^(4-1),0) -> 0 | ... AX27: =IFERROR(Assumptions!$C$47*(1+Assumptions!$C$11)^(4-1),0) -> 0 | AY27: =IFERROR(Assumptions!$C$47*(1+Assumptions!$C$11)^(5-1),0) -> 0 | AZ27: =IFERROR(Assumptions!$C$47*(1+Assumptions!$C$11)^(5-1),0) -> 0 | BA27: =IFERROR(Assumptions!$C$47*(1+Assumptions!$C$11)^(5-1),0) -> 0 | BB27: =IFERROR(Assumptions!$C$47*(1+Assumptions!$C$11)^(5-1),0) -> 0 | BC27: =IFERROR(Assumptions!$C$47*(1+Assumptions!$C$11)^(5-1),0) -> 0 | BD27: =IFERROR(Assumptions!$C$47*(1+Assumptions!$C$11)^(5-1),0) -> 0 | BE27: =IFERROR(Assumptions!$C$47*(1+Assumptions!$C$11)^(5-1),0) -> 0 | BF27: =IFERROR(Assumptions!$C$47*(1+Assumptions!$C$11)^(5-1),0) -> 0 | ... BJ27: =IFERROR(Assumptions!$C$47*(1+Assumptions!$C$11)^(5-1),0) -> 0
A28: Total operating expenses | B28: ₹ lakh | C28: =IFERROR(SUM(C22:C27),0) -> 0 | D28: =IFERROR(SUM(D22:D27),0) -> 0 | E28: =IFERROR(SUM(E22:E27),0) -> 0 | F28: =IFERROR(SUM(F22:F27),0) -> 0 | G28: =IFERROR(SUM(G22:G27),0) -> 0 | H28: =IFERROR(SUM(H22:H27),0) -> 0 | I28: =IFERROR(SUM(I22:I27),0) -> 0 | J28: =IFERROR(SUM(J22:J27),0) -> 0 | ... BJ28: =IFERROR(SUM(BJ22:BJ27),0) -> 0
A29: EARNINGS
A30: EBITDA | B30: ₹ lakh | C30: =IFERROR(C20-C28,0) -> 0 | D30: =IFERROR(D20-D28,0) -> 0 | E30: =IFERROR(E20-E28,0) -> 0 | F30: =IFERROR(F20-F28,0) -> 0 | G30: =IFERROR(G20-G28,0) -> 0 | H30: =IFERROR(H20-H28,0) -> 0 | I30: =IFERROR(I20-I28,0) -> 0 | J30: =IFERROR(J20-J28,0) -> 0 | ... BJ30: =IFERROR(BJ20-BJ28,0) -> 0
A31: EBITDA margin | B31: % | C31: =IFERROR(IF(C13=0,0,C30/C13),0) -> 0 | D31: =IFERROR(IF(D13=0,0,D30/D13),0) -> 0 | E31: =IFERROR(IF(E13=0,0,E30/E13),0) -> 0 | F31: =IFERROR(IF(F13=0,0,F30/F13),0) -> 0 | G31: =IFERROR(IF(G13=0,0,G30/G13),0) -> 0 | H31: =IFERROR(IF(H13=0,0,H30/H13),0) -> 0 | I31: =IFERROR(IF(I13=0,0,I30/I13),0) -> 0 | J31: =IFERROR(IF(J13=0,0,J30/J13),0) -> 0 | ... BJ31: =IFERROR(IF(BJ13=0,0,BJ30/BJ13),0) -> 0
A32: Depreciation | B32: ₹ lakh | C32: =IFERROR(Depreciation!C9,0) -> 0 | D32: =IFERROR(Depreciation!D9,0) -> 0 | E32: =IFERROR(Depreciation!E9,0) -> 0 | F32: =IFERROR(Depreciation!F9,0) -> 0 | G32: =IFERROR(Depreciation!G9,0) -> 0 | H32: =IFERROR(Depreciation!H9,0) -> 0 | I32: =IFERROR(Depreciation!I9,0) -> 0 | J32: =IFERROR(Depreciation!J9,0) -> 0 | ... BJ32: =IFERROR(Depreciation!BJ9,0) -> 0
A33: EBIT | B33: ₹ lakh | C33: =IFERROR(C30-C32,0) -> 0 | D33: =IFERROR(D30-D32,0) -> 0 | E33: =IFERROR(E30-E32,0) -> 0 | F33: =IFERROR(F30-F32,0) -> 0 | G33: =IFERROR(G30-G32,0) -> 0 | H33: =IFERROR(H30-H32,0) -> 0 | I33: =IFERROR(I30-I32,0) -> 0 | J33: =IFERROR(J30-J32,0) -> 0 | ... BJ33: =IFERROR(BJ30-BJ32,0) -> 0
A34: WORKING-CAPITAL POSITION
A35: Debtors / receivables | B35: ₹ lakh | C35: =IFERROR(C13*Assumptions!$C$57/30,0) -> 0 | D35: =IFERROR(D13*Assumptions!$C$57/30,0) -> 0 | E35: =IFERROR(E13*Assumptions!$C$57/30,0) -> 0 | F35: =IFERROR(F13*Assumptions!$C$57/30,0) -> 0 | G35: =IFERROR(G13*Assumptions!$C$57/30,0) -> 0 | H35: =IFERROR(H13*Assumptions!$C$57/30,0) -> 0 | I35: =IFERROR(I13*Assumptions!$C$57/30,0) -> 0 | J35: =IFERROR(J13*Assumptions!$C$57/30,0) -> 0 | ... BJ35: =IFERROR(BJ13*Assumptions!$C$57/30,0) -> 0
A36: Inventory | B36: ₹ lakh | C36: =IFERROR(C19*Assumptions!$C$58/30,0) -> 0 | D36: =IFERROR(D19*Assumptions!$C$58/30,0) -> 0 | E36: =IFERROR(E19*Assumptions!$C$58/30,0) -> 0 | F36: =IFERROR(F19*Assumptions!$C$58/30,0) -> 0 | G36: =IFERROR(G19*Assumptions!$C$58/30,0) -> 0 | H36: =IFERROR(H19*Assumptions!$C$58/30,0) -> 0 | I36: =IFERROR(I19*Assumptions!$C$58/30,0) -> 0 | J36: =IFERROR(J19*Assumptions!$C$58/30,0) -> 0 | ... BJ36: =IFERROR(BJ19*Assumptions!$C$58/30,0) -> 0
A37: Creditors / payables | B37: ₹ lakh | C37: =IFERROR((C15+C16)*Assumptions!$C$59/30,0) -> 0 | D37: =IFERROR((D15+D16)*Assumptions!$C$59/30,0) -> 0 | E37: =IFERROR((E15+E16)*Assumptions!$C$59/30,0) -> 0 | F37: =IFERROR((F15+F16)*Assumptions!$C$59/30,0) -> 0 | G37: =IFERROR((G15+G16)*Assumptions!$C$59/30,0) -> 0 | H37: =IFERROR((H15+H16)*Assumptions!$C$59/30,0) -> 0 | I37: =IFERROR((I15+I16)*Assumptions!$C$59/30,0) -> 0 | J37: =IFERROR((J15+J16)*Assumptions!$C$59/30,0) -> 0 | ... BJ37: =IFERROR((BJ15+BJ16)*Assumptions!$C$59/30,0) -> 0
A38: Net working capital | B38: ₹ lakh | C38: =IFERROR(C35+C36-C37,0) -> 0 | D38: =IFERROR(D35+D36-D37,0) -> 0 | E38: =IFERROR(E35+E36-E37,0) -> 0 | F38: =IFERROR(F35+F36-F37,0) -> 0 | G38: =IFERROR(G35+G36-G37,0) -> 0 | H38: =IFERROR(H35+H36-H37,0) -> 0 | I38: =IFERROR(I35+I36-I37,0) -> 0 | J38: =IFERROR(J35+J36-J37,0) -> 0 | ... BJ38: =IFERROR(BJ35+BJ36-BJ37,0) -> 0
A39: Working-capital borrowing | B39: ₹ lakh | C39: =IFERROR(C38*Assumptions!$C$28,0) -> 0 | D39: =IFERROR(D38*Assumptions!$C$28,0) -> 0 | E39: =IFERROR(E38*Assumptions!$C$28,0) -> 0 | F39: =IFERROR(F38*Assumptions!$C$28,0) -> 0 | G39: =IFERROR(G38*Assumptions!$C$28,0) -> 0 | H39: =IFERROR(H38*Assumptions!$C$28,0) -> 0 | I39: =IFERROR(I38*Assumptions!$C$28,0) -> 0 | J39: =IFERROR(J38*Assumptions!$C$28,0) -> 0 | ... BJ39: =IFERROR(BJ38*Assumptions!$C$28,0) -> 0
A40: FINANCE COST, TAX & PROFIT
A41: Interest – term loan (net of subsidy) | B41: ₹ lakh | C41: =IFERROR('Loan Schedule'!C13,0) -> 0 | D41: =IFERROR('Loan Schedule'!D13,0) -> 0 | E41: =IFERROR('Loan Schedule'!E13,0) -> 0 | F41: =IFERROR('Loan Schedule'!F13,0) -> 0 | G41: =IFERROR('Loan Schedule'!G13,0) -> 0 | H41: =IFERROR('Loan Schedule'!H13,0) -> 0 | I41: =IFERROR('Loan Schedule'!I13,0) -> 0 | J41: =IFERROR('Loan Schedule'!J13,0) -> 0 | ... BJ41: =IFERROR('Loan Schedule'!BJ13,0) -> 0
A42: Interest – working capital | B42: ₹ lakh | C42: =IFERROR(C39*Assumptions!$C$27/12,0) -> 0 | D42: =IFERROR(D39*Assumptions!$C$27/12,0) -> 0 | E42: =IFERROR(E39*Assumptions!$C$27/12,0) -> 0 | F42: =IFERROR(F39*Assumptions!$C$27/12,0) -> 0 | G42: =IFERROR(G39*Assumptions!$C$27/12,0) -> 0 | H42: =IFERROR(H39*Assumptions!$C$27/12,0) -> 0 | I42: =IFERROR(I39*Assumptions!$C$27/12,0) -> 0 | J42: =IFERROR(J39*Assumptions!$C$27/12,0) -> 0 | ... BJ42: =IFERROR(BJ39*Assumptions!$C$27/12,0) -> 0
A43: Profit before tax (PBT) | B43: ₹ lakh | C43: =IFERROR(C33-C41-C42,0) -> 0 | D43: =IFERROR(D33-D41-D42,0) -> 0 | E43: =IFERROR(E33-E41-E42,0) -> 0 | F43: =IFERROR(F33-F41-F42,0) -> 0 | G43: =IFERROR(G33-G41-G42,0) -> 0 | H43: =IFERROR(H33-H41-H42,0) -> 0 | I43: =IFERROR(I33-I41-I42,0) -> 0 | J43: =IFERROR(J33-J41-J42,0) -> 0 | ... BJ43: =IFERROR(BJ33-BJ41-BJ42,0) -> 0
A44: Cumulative PBT | B44: ₹ lakh | C44: =IFERROR(C43,0) -> 0 | D44: =C44+D43 -> 0 | E44: =D44+E43 -> 0 | F44: =E44+F43 -> 0 | G44: =F44+G43 -> 0 | H44: =G44+H43 -> 0 | I44: =H44+I43 -> 0 | J44: =I44+J43 -> 0 | K44: =J44+K43 -> 0 | ... BJ44: =BI44+BJ43 -> 0
A45: Cumulative tax provision (with loss c/f) | B45: ₹ lakh | C45: =IFERROR(MAX(0,C44)*Assumptions!$C$6,0) -> 0 | D45: =IFERROR(MAX(0,D44)*Assumptions!$C$6,0) -> 0 | E45: =IFERROR(MAX(0,E44)*Assumptions!$C$6,0) -> 0 | F45: =IFERROR(MAX(0,F44)*Assumptions!$C$6,0) -> 0 | G45: =IFERROR(MAX(0,G44)*Assumptions!$C$6,0) -> 0 | H45: =IFERROR(MAX(0,H44)*Assumptions!$C$6,0) -> 0 | I45: =IFERROR(MAX(0,I44)*Assumptions!$C$6,0) -> 0 | J45: =IFERROR(MAX(0,J44)*Assumptions!$C$6,0) -> 0 | ... BJ45: =IFERROR(MAX(0,BJ44)*Assumptions!$C$6,0) -> 0
A46: Income tax for month | B46: ₹ lakh | C46: =IFERROR(MAX(0,C45),0) -> 0 | D46: =IFERROR(MAX(0,D45-C45),0) -> 0 | E46: =IFERROR(MAX(0,E45-D45),0) -> 0 | F46: =IFERROR(MAX(0,F45-E45),0) -> 0 | G46: =IFERROR(MAX(0,G45-F45),0) -> 0 | H46: =IFERROR(MAX(0,H45-G45),0) -> 0 | I46: =IFERROR(MAX(0,I45-H45),0) -> 0 | J46: =IFERROR(MAX(0,J45-I45),0) -> 0 | K46: =IFERROR(MAX(0,K45-J45),0) -> 0 | ... BJ46: =IFERROR(MAX(0,BJ45-BI45),0) -> 0
A47: PROFIT AFTER TAX (PAT) | B47: ₹ lakh | C47: =IFERROR(C43-C46,0) -> 0 | D47: =IFERROR(D43-D46,0) -> 0 | E47: =IFERROR(E43-E46,0) -> 0 | F47: =IFERROR(F43-F46,0) -> 0 | G47: =IFERROR(G43-G46,0) -> 0 | H47: =IFERROR(H43-H46,0) -> 0 | I47: =IFERROR(I43-I46,0) -> 0 | J47: =IFERROR(J43-J46,0) -> 0 | ... BJ47: =IFERROR(BJ43-BJ46,0) -> 0
A48: PAT margin | B48: % | C48: =IFERROR(IF(C13=0,0,C47/C13),0) -> 0 | D48: =IFERROR(IF(D13=0,0,D47/D13),0) -> 0 | E48: =IFERROR(IF(E13=0,0,E47/E13),0) -> 0 | F48: =IFERROR(IF(F13=0,0,F47/F13),0) -> 0 | G48: =IFERROR(IF(G13=0,0,G47/G13),0) -> 0 | H48: =IFERROR(IF(H13=0,0,H47/H13),0) -> 0 | I48: =IFERROR(IF(I13=0,0,I47/I13),0) -> 0 | J48: =IFERROR(IF(J13=0,0,J47/J13),0) -> 0 | ... BJ48: =IFERROR(IF(BJ13=0,0,BJ47/BJ13),0) -> 0
A49: CASH FLOW
A50: Operating cash flow (PAT + depreciation) | B50: ₹ lakh | C50: =IFERROR(C47+C32,0) -> 0 | D50: =IFERROR(D47+D32,0) -> 0 | E50: =IFERROR(E47+E32,0) -> 0 | F50: =IFERROR(F47+F32,0) -> 0 | G50: =IFERROR(G47+G32,0) -> 0 | H50: =IFERROR(H47+H32,0) -> 0 | I50: =IFERROR(I47+I32,0) -> 0 | J50: =IFERROR(J47+J32,0) -> 0 | ... BJ50: =IFERROR(BJ47+BJ32,0) -> 0
A51: Less: term-loan principal | B51: ₹ lakh | C51: =IFERROR(-'Loan Schedule'!C8,0) -> 0 | D51: =IFERROR(-'Loan Schedule'!D8,0) -> 0 | E51: =IFERROR(-'Loan Schedule'!E8,0) -> 0 | F51: =IFERROR(-'Loan Schedule'!F8,0) -> 0 | G51: =IFERROR(-'Loan Schedule'!G8,0) -> 0 | H51: =IFERROR(-'Loan Schedule'!H8,0) -> 0 | I51: =IFERROR(-'Loan Schedule'!I8,0) -> 0 | J51: =IFERROR(-'Loan Schedule'!J8,0) -> 0 | ... BJ51: =IFERROR(-'Loan Schedule'!BJ8,0) -> 0
A52: Less: increase in working capital | B52: ₹ lakh | C52: =IFERROR(-C38,0) -> 0 | D52: =IFERROR(-(D38-C38),0) -> 0 | E52: =IFERROR(-(E38-D38),0) -> 0 | F52: =IFERROR(-(F38-E38),0) -> 0 | G52: =IFERROR(-(G38-F38),0) -> 0 | H52: =IFERROR(-(H38-G38),0) -> 0 | I52: =IFERROR(-(I38-H38),0) -> 0 | J52: =IFERROR(-(J38-I38),0) -> 0 | K52: =IFERROR(-(K38-J38),0) -> 0 | ... BJ52: =IFERROR(-(BJ38-BI38),0) -> 0
A53: Net cash flow | B53: ₹ lakh | C53: =IFERROR(C50+C51+C52,0) -> 0 | D53: =IFERROR(D50+D51+D52,0) -> 0 | E53: =IFERROR(E50+E51+E52,0) -> 0 | F53: =IFERROR(F50+F51+F52,0) -> 0 | G53: =IFERROR(G50+G51+G52,0) -> 0 | H53: =IFERROR(H50+H51+H52,0) -> 0 | I53: =IFERROR(I50+I51+I52,0) -> 0 | J53: =IFERROR(J50+J51+J52,0) -> 0 | ... BJ53: =IFERROR(BJ50+BJ51+BJ52,0) -> 0
A54: Cumulative cash flow | B54: ₹ lakh | C54: =IFERROR(C53,0) -> 0 | D54: =C54+D53 -> 0 | E54: =D54+E53 -> 0 | F54: =E54+F53 -> 0 | G54: =F54+G53 -> 0 | H54: =G54+H53 -> 0 | I54: =H54+I53 -> 0 | J54: =I54+J53 -> 0 | K54: =J54+K53 -> 0 | ... BJ54: =BI54+BJ53 -> 0

Sheet Annual P&L
A1: ANNUAL PROFIT & LOSS (₹ lakh)
A2: Aggregated from the Monthly Model. Year 1 = first year of commercial operation.
C4: Year 1 | D4: Year 2 | E4: Year 3 | F4: Year 4 | G4: Year 5 | H4: 5-Yr Total
B5: Revenue (net of GST) | C5: =IFERROR(SUM('Monthly Model'!C13:N13),0) -> 0 | D5: =IFERROR(SUM('Monthly Model'!O13:Z13),0) -> 0 | E5: =IFERROR(SUM('Monthly Model'!AA13:AL13),0) -> 0 | F5: =IFERROR(SUM('Monthly Model'!AM13:AX13),0) -> 0 | G5: =IFERROR(SUM('Monthly Model'!AY13:BJ13),0) -> 0 | H5: =IFERROR(SUM(C5:G5),0) -> 0
B6: Cost of goods sold | C6: =IFERROR(SUM('Monthly Model'!C19:N19),0) -> 0 | D6: =IFERROR(SUM('Monthly Model'!O19:Z19),0) -> 0 | E6: =IFERROR(SUM('Monthly Model'!AA19:AL19),0) -> 0 | F6: =IFERROR(SUM('Monthly Model'!AM19:AX19),0) -> 0 | G6: =IFERROR(SUM('Monthly Model'!AY19:BJ19),0) -> 0 | H6: =IFERROR(SUM(C6:G6),0) -> 0
B7: Gross profit | C7: =IFERROR(C5-C6,0) -> 0 | D7: =IFERROR(D5-D6,0) -> 0 | E7: =IFERROR(E5-E6,0) -> 0 | F7: =IFERROR(F5-F6,0) -> 0 | G7: =IFERROR(G5-G6,0) -> 0 | H7: =IFERROR(SUM(C7:G7),0) -> 0
B8: Operating expenses | C8: =IFERROR(SUM('Monthly Model'!C28:N28),0) -> 0 | D8: =IFERROR(SUM('Monthly Model'!O28:Z28),0) -> 0 | E8: =IFERROR(SUM('Monthly Model'!AA28:AL28),0) -> 0 | F8: =IFERROR(SUM('Monthly Model'!AM28:AX28),0) -> 0 | G8: =IFERROR(SUM('Monthly Model'!AY28:BJ28),0) -> 0 | H8: =IFERROR(SUM(C8:G8),0) -> 0
B9: EBITDA | C9: =IFERROR(C7-C8,0) -> 0 | D9: =IFERROR(D7-D8,0) -> 0 | E9: =IFERROR(E7-E8,0) -> 0 | F9: =IFERROR(F7-F8,0) -> 0 | G9: =IFERROR(G7-G8,0) -> 0 | H9: =IFERROR(SUM(C9:G9),0) -> 0
B10: EBITDA margin | C10: =IFERROR(IF(C5=0,0,C9/C5),0) -> 0 | D10: =IFERROR(IF(D5=0,0,D9/D5),0) -> 0 | E10: =IFERROR(IF(E5=0,0,E9/E5),0) -> 0 | F10: =IFERROR(IF(F5=0,0,F9/F5),0) -> 0 | G10: =IFERROR(IF(G5=0,0,G9/G5),0) -> 0 | H10: =IFERROR(AVERAGE(C10:G10),0) -> 0
B11: Depreciation | C11: =IFERROR(SUM('Monthly Model'!C32:N32),0) -> 0 | D11: =IFERROR(SUM('Monthly Model'!O32:Z32),0) -> 0 | E11: =IFERROR(SUM('Monthly Model'!AA32:AL32),0) -> 0 | F11: =IFERROR(SUM('Monthly Model'!AM32:AX32),0) -> 0 | G11: =IFERROR(SUM('Monthly Model'!AY32:BJ32),0) -> 0 | H11: =IFERROR(SUM(C11:G11),0) -> 0
B12: EBIT | C12: =IFERROR(C9-C11,0) -> 0 | D12: =IFERROR(D9-D11,0) -> 0 | E12: =IFERROR(E9-E11,0) -> 0 | F12: =IFERROR(F9-F11,0) -> 0 | G12: =IFERROR(G9-G11,0) -> 0 | H12: =IFERROR(SUM(C12:G12),0) -> 0
B13: Interest & finance cost (net of subsidy) | C13: =IFERROR(SUM('Monthly Model'!C41:N41)+SUM('Monthly Model'!C42:N42),0) -> 0 | D13: =IFERROR(SUM('Monthly Model'!O41:Z41)+SUM('Monthly Model'!O42:Z42),0) -> 0 | E13: =IFERROR(SUM('Monthly Model'!AA41:AL41)+SUM('Monthly Model'!AA42:AL42),0) -> 0 | F13: =IFERROR(SUM('Monthly Model'!AM41:AX41)+SUM('Monthly Model'!AM42:AX42),0) -> 0 | G13: =IFERROR(SUM('Monthly Model'!AY41:BJ41)+SUM('Monthly Model'!AY42:BJ42),0) -> 0 | H13: =IFERROR(SUM(C13:G13),0) -> 0
B14: Profit before tax | C14: =IFERROR(C12-C13,0) -> 0 | D14: =IFERROR(D12-D13,0) -> 0 | E14: =IFERROR(E12-E13,0) -> 0 | F14: =IFERROR(F12-F13,0) -> 0 | G14: =IFERROR(G12-G13,0) -> 0 | H14: =IFERROR(SUM(C14:G14),0) -> 0
B15: Income tax | C15: =IFERROR(SUM('Monthly Model'!C46:N46),0) -> 0 | D15: =IFERROR(SUM('Monthly Model'!O46:Z46),0) -> 0 | E15: =IFERROR(SUM('Monthly Model'!AA46:AL46),0) -> 0 | F15: =IFERROR(SUM('Monthly Model'!AM46:AX46),0) -> 0 | G15: =IFERROR(SUM('Monthly Model'!AY46:BJ46),0) -> 0 | H15: =IFERROR(SUM(C15:G15),0) -> 0
B16: Profit after tax (PAT) | C16: =IFERROR(C14-C15,0) -> 0 | D16: =IFERROR(D14-D15,0) -> 0 | E16: =IFERROR(E14-E15,0) -> 0 | F16: =IFERROR(F14-F15,0) -> 0 | G16: =IFERROR(G14-G15,0) -> 0 | H16: =IFERROR(SUM(C16:G16),0) -> 0
B17: PAT margin | C17: =IFERROR(IF(C5=0,0,C16/C5),0) -> 0 | D17: =IFERROR(IF(D5=0,0,D16/D5),0) -> 0 | E17: =IFERROR(IF(E5=0,0,E16/E5),0) -> 0 | F17: =IFERROR(IF(F5=0,0,F16/F5),0) -> 0 | G17: =IFERROR(IF(G5=0,0,G16/G5),0) -> 0 | H17: =IFERROR(AVERAGE(C17:G17),0) -> 0

Sheet Cash Flow
A1: ANNUAL CASH-FLOW STATEMENT (₹ lakh)
A2: Operating, investing and financing flows. Year-1 includes project outflow & drawdown.
C4: Year 1 | D4: Year 2 | E4: Year 3 | F4: Year 4 | G4: Year 5 | H4: 5-Yr Total
B5: PAT | C5: =IFERROR('Annual P&L'!C16,0) -> 0 | D5: =IFERROR('Annual P&L'!D16,0) -> 0 | E5: =IFERROR('Annual P&L'!E16,0) -> 0 | F5: =IFERROR('Annual P&L'!F16,0) -> 0 | G5: =IFERROR('Annual P&L'!G16,0) -> 0 | H5: =IFERROR(SUM(C5:G5),0) -> 0
B6: Add: depreciation | C6: =IFERROR('Annual P&L'!C11,0) -> 0 | D6: =IFERROR('Annual P&L'!D11,0) -> 0 | E6: =IFERROR('Annual P&L'!E11,0) -> 0 | F6: =IFERROR('Annual P&L'!F11,0) -> 0 | G6: =IFERROR('Annual P&L'!G11,0) -> 0 | H6: =IFERROR(SUM(C6:G6),0) -> 0
B7: Less: increase in working capital | C7: =IFERROR(-('Monthly Model'!N38-0),0) -> 0 | D7: =IFERROR(-('Monthly Model'!Z38-'Monthly Model'!N38),0) -> 0 | E7: =IFERROR(-('Monthly Model'!AL38-'Monthly Model'!Z38),0) -> 0 | F7: =IFERROR(-('Monthly Model'!AX38-'Monthly Model'!AL38),0) -> 0 | G7: =IFERROR(-('Monthly Model'!BJ38-'Monthly Model'!AX38),0) -> 0 | H7: =IFERROR(SUM(C7:G7),0) -> 0
B8: Net cash from operations | C8: =IFERROR(C5+C6+C7,0) -> 0 | D8: =IFERROR(D5+D6+D7,0) -> 0 | E8: =IFERROR(E5+E6+E7,0) -> 0 | F8: =IFERROR(F5+F6+F7,0) -> 0 | G8: =IFERROR(G5+G6+G7,0) -> 0 | H8: =IFERROR(SUM(C8:G8),0) -> 0
B9: Investing: project capex | C9: =IFERROR(-Assumptions!$C$75,0) -> 0 | D9: =IFERROR(0,0) -> 0 | E9: =IFERROR(0,0) -> 0 | F9: =IFERROR(0,0) -> 0 | G9: =IFERROR(0,0) -> 0 | H9: =IFERROR(SUM(C9:G9),0) -> 0
B10: Financing: promoter equity | C10: =IFERROR(Assumptions!$C$77,0) -> 0 | D10: =IFERROR(0,0) -> 0 | E10: =IFERROR(0,0) -> 0 | F10: =IFERROR(0,0) -> 0 | G10: =IFERROR(0,0) -> 0 | H10: =IFERROR(SUM(C10:G10),0) -> 0
B11: Financing: term-loan drawdown | C11: =IFERROR(Assumptions!$C$78,0) -> 0 | D11: =IFERROR(0,0) -> 0 | E11: =IFERROR(0,0) -> 0 | F11: =IFERROR(0,0) -> 0 | G11: =IFERROR(0,0) -> 0 | H11: =IFERROR(SUM(C11:G11),0) -> 0
B12: Financing: term-loan repayment | C12: =IFERROR(-SUM('Loan Schedule'!C8:N8),0) -> 0 | D12: =IFERROR(-SUM('Loan Schedule'!O8:Z8),0) -> 0 | E12: =IFERROR(-SUM('Loan Schedule'!AA8:AL8),0) -> 0 | F12: =IFERROR(-SUM('Loan Schedule'!AM8:AX8),0) -> 0 | G12: =IFERROR(-SUM('Loan Schedule'!AY8:BJ8),0) -> 0 | H12: =IFERROR(SUM(C12:G12),0) -> 0
B13: Financing: capital subsidy received | C13: =IFERROR(0,0) -> 0 | D13: =IFERROR(Assumptions!$C$79,0) -> 0 | E13: =IFERROR(0,0) -> 0 | F13: =IFERROR(0,0) -> 0 | G13: =IFERROR(0,0) -> 0 | H13: =IFERROR(SUM(C13:G13),0) -> 0
B14: Net cash flow for year | C14: =C8+C9+C10+C11+C12+C13 -> 0 | D14: =D8+D9+D10+D11+D12+D13 -> 0 | E14: =E8+E9+E10+E11+E12+E13 -> 0 | F14: =F8+F9+F10+F11+F12+F13 -> 0 | G14: =G8+G9+G10+G11+G12+G13 -> 0 | H14: =IFERROR(SUM(C14:G14),0) -> 0
B15: Opening cash | C15: =IFERROR(0,0) -> 0 | D15: =IFERROR(C16,0) -> 0 | E15: =IFERROR(D16,0) -> 0 | F15: =IFERROR(E16,0) -> 0 | G15: =IFERROR(F16,0) -> 0 | H15: =IFERROR(SUM(C15:G15),0) -> 0
B16: Closing cash | C16: =IFERROR(C15+C14,0) -> 0 | D16: =IFERROR(D15+D14,0) -> 0 | E16: =IFERROR(E15+E14,0) -> 0 | F16: =IFERROR(F15+F14,0) -> 0 | G16: =IFERROR(G15+G14,0) -> 0 | H16: =IFERROR(SUM(C16:G16),0) -> 0

Sheet Balance Sheet
A1: ANNUAL BALANCE SHEET (₹ lakh)
A2: Cash is the balancing item; a check row confirms Assets = Equity + Liabilities.
C4: Year 1 | D4: Year 2 | E4: Year 3 | F4: Year 4 | G4: Year 5 | H4: 5-Yr Total
B5: EQUITY & LIABILITIES
B6: Share capital (promoter equity) | C6: =IFERROR(Assumptions!$C$77,0) -> 0 | D6: =IFERROR(Assumptions!$C$77,0) -> 0 | E6: =IFERROR(Assumptions!$C$77,0) -> 0 | F6: =IFERROR(Assumptions!$C$77,0) -> 0 | G6: =IFERROR(Assumptions!$C$77,0) -> 0 | H6: =IFERROR(G6,0) -> 0
B7: Capital reserve (subsidy) | C7: =IFERROR(0,0) -> 0 | D7: =IFERROR(Assumptions!$C$79,0) -> 0 | E7: =IFERROR(Assumptions!$C$79,0) -> 0 | F7: =IFERROR(Assumptions!$C$79,0) -> 0 | G7: =IFERROR(Assumptions!$C$79,0) -> 0 | H7: =IFERROR(G7,0) -> 0
B8: Retained earnings (cum. PAT) | C8: =IFERROR(SUM('Monthly Model'!C47:N47),0) -> 0 | D8: =IFERROR(SUM('Monthly Model'!C47:Z47),0) -> 0 | E8: =IFERROR(SUM('Monthly Model'!C47:AL47),0) -> 0 | F8: =IFERROR(SUM('Monthly Model'!C47:AX47),0) -> 0 | G8: =IFERROR(SUM('Monthly Model'!C47:BJ47),0) -> 0 | H8: =IFERROR(G8,0) -> 0
B9: Term loan (closing) | C9: =IFERROR('Loan Schedule'!N10,0) -> 0 | D9: =IFERROR('Loan Schedule'!Z10,0) -> 0 | E9: =IFERROR('Loan Schedule'!AL10,0) -> 0 | F9: =IFERROR('Loan Schedule'!AX10,0) -> 0 | G9: =IFERROR('Loan Schedule'!BJ10,0) -> 0 | H9: =IFERROR(G9,0) -> 0
B10: Working-capital borrowing | C10: =IFERROR('Monthly Model'!N39,0) -> 0 | D10: =IFERROR('Monthly Model'!Z39,0) -> 0 | E10: =IFERROR('Monthly Model'!AL39,0) -> 0 | F10: =IFERROR('Monthly Model'!AX39,0) -> 0 | G10: =IFERROR('Monthly Model'!BJ39,0) -> 0 | H10: =IFERROR(G10,0) -> 0
B11: Creditors / payables | C11: =IFERROR('Monthly Model'!N37,0) -> 0 | D11: =IFERROR('Monthly Model'!Z37,0) -> 0 | E11: =IFERROR('Monthly Model'!AL37,0) -> 0 | F11: =IFERROR('Monthly Model'!AX37,0) -> 0 | G11: =IFERROR('Monthly Model'!BJ37,0) -> 0 | H11: =IFERROR(G11,0) -> 0
B12: Total equity & liabilities | C12: =IFERROR(SUM(C6:C11),0) -> 0 | D12: =IFERROR(SUM(D6:D11),0) -> 0 | E12: =IFERROR(SUM(E6:E11),0) -> 0 | F12: =IFERROR(SUM(F6:F11),0) -> 0 | G12: =IFERROR(SUM(G6:G11),0) -> 0 | H12: =IFERROR(G12,0) -> 0
B14: ASSETS
B15: Gross fixed assets | C15: =IFERROR(Assumptions!$C$14+Assumptions!$C$15+Assumptions!$C$16+Assumptions!$C$17+Assumptions!$C$18,0) -> 0 | D15: =IFERROR(Assumptions!$C$14+Assumptions!$C$15+Assumptions!$C$16+Assumptions!$C$17+Assumptions!$C$18,0) -> 0 | E15: =IFERROR(Assumptions!$C$14+Assumptions!$C$15+Assumptions!$C$16+Assumptions!$C$17+Assumptions!$C$18,0) -> 0 | F15: =IFERROR(Assumptions!$C$14+Assumptions!$C$15+Assumptions!$C$16+Assumptions!$C$17+Assumptions!$C$18,0) -> 0 | G15: =IFERROR(Assumptions!$C$14+Assumptions!$C$15+Assumptions!$C$16+Assumptions!$C$17+Assumptions!$C$18,0) -> 0 | H15: =IFERROR(G15,0) -> 0
B16: Less: accumulated depreciation | C16: =IFERROR(-SUM(Depreciation!C9:N9),0) -> 0 | D16: =IFERROR(-SUM(Depreciation!C9:Z9),0) -> 0 | E16: =IFERROR(-SUM(Depreciation!C9:AL9),0) -> 0 | F16: =IFERROR(-SUM(Depreciation!C9:AX9),0) -> 0 | G16: =IFERROR(-SUM(Depreciation!C9:BJ9),0) -> 0 | H16: =IFERROR(G16,0) -> 0
B17: Net fixed assets | C17: =IFERROR(C15+C16,0) -> 0 | D17: =IFERROR(D15+D16,0) -> 0 | E17: =IFERROR(E15+E16,0) -> 0 | F17: =IFERROR(F15+F16,0) -> 0 | G17: =IFERROR(G15+G16,0) -> 0 | H17: =IFERROR(G17,0) -> 0
B18: Inventory | C18: =IFERROR('Monthly Model'!N36,0) -> 0 | D18: =IFERROR('Monthly Model'!Z36,0) -> 0 | E18: =IFERROR('Monthly Model'!AL36,0) -> 0 | F18: =IFERROR('Monthly Model'!AX36,0) -> 0 | G18: =IFERROR('Monthly Model'!BJ36,0) -> 0 | H18: =IFERROR(G18,0) -> 0
B19: Debtors / receivables | C19: =IFERROR('Monthly Model'!N35,0) -> 0 | D19: =IFERROR('Monthly Model'!Z35,0) -> 0 | E19: =IFERROR('Monthly Model'!AL35,0) -> 0 | F19: =IFERROR('Monthly Model'!AX35,0) -> 0 | G19: =IFERROR('Monthly Model'!BJ35,0) -> 0 | H19: =IFERROR(G19,0) -> 0
B20: Cash & bank (balancing) | C20: =IFERROR(C12-C17-C18-C19,0) -> 0 | D20: =IFERROR(D12-D17-D18-D19,0) -> 0 | E20: =IFERROR(E12-E17-E18-E19,0) -> 0 | F20: =IFERROR(F12-F17-F18-F19,0) -> 0 | G20: =IFERROR(G12-G17-G18-G19,0) -> 0 | H20: =IFERROR(G20,0) -> 0
B21: Total assets | C21: =IFERROR(C17+C18+C19+C20,0) -> 0 | D21: =IFERROR(D17+D18+D19+D20,0) -> 0 | E21: =IFERROR(E17+E18+E19+E20,0) -> 0 | F21: =IFERROR(F17+F18+F19+F20,0) -> 0 | G21: =IFERROR(G17+G18+G19+G20,0) -> 0 | H21: =IFERROR(G21,0) -> 0
B22: Check (Assets − E&L, must be 0) | C22: =IFERROR(C21-C12,0) -> 0 | D22: =IFERROR(D21-D12,0) -> 0 | E22: =IFERROR(E21-E12,0) -> 0 | F22: =IFERROR(F21-F12,0) -> 0 | G22: =IFERROR(G21-G12,0) -> 0 | H22: =IFERROR(G22,0) -> 0

Sheet Returns & Ratios
A1: INVESTMENT RETURNS, DEBT SERVICE & BREAK-EVEN (₹ lakh)
B3: A. Project free cash flow (pre-financing)
C4: Year 0 | D4: Year 1 | E4: Year 2 | F4: Year 3 | G4: Year 4 | H4: Year 5
B5: FCFF = EBITDA − tax − ΔNWC (+ terminal) | C5: =-Assumptions!$C$75 -> 0 | D5: ='Annual P&L'!C9-'Annual P&L'!C15-'Monthly Model'!N38 -> 0 | E5: ='Annual P&L'!D9-'Annual P&L'!D15-('Monthly Model'!Z38-'Monthly Model'!N38) -> 0 | F5: ='Annual P&L'!E9-'Annual P&L'!E15-('Monthly Model'!AL38-'Monthly Model'!Z38) -> 0 | G5: ='Annual P&L'!F9-'Annual P&L'!F15-('Monthly Model'!AX38-'Monthly Model'!AL38) -> 0 | H5: ='Annual P&L'!G9-'Annual P&L'!G15-('Monthly Model'!BJ38-'Monthly Model'!AX38)+'Balance Sheet'!G17+'Monthly Model'!BJ38 -> 0
B7: B. Equity cash flow
B8: Equity FCF = net cash flow (+subsidy, +terminal equity) | C8: =-Assumptions!$C$77 -> 0 | D8: =SUM('Monthly Model'!C53:N53) -> 0 | E8: =SUM('Monthly Model'!O53:Z53)+Assumptions!$C$79 -> 0 | F8: =SUM('Monthly Model'!AA53:AL53) -> 0 | G8: =SUM('Monthly Model'!AM53:AX53) -> 0 | H8: =SUM('Monthly Model'!AY53:BJ53)+'Balance Sheet'!G6+'Balance Sheet'!G7+'Balance Sheet'!G8-'Balance Sheet'!G6 -> 0
B10: C. Headline return metrics
B11: Project IRR (pre-financing) | C11: =IFERROR(IRR(C5:H5),"") | D11: Internal rate of return on total project cost
B12: Project NPV @ WACC | C12: =IFERROR(NPV(Assumptions!$C$73,D5:H5)+C5,"") -> 0 | D12: Net present value of FCFF, ₹ lakh
B13: Equity IRR | C13: =IFERROR(IRR(C8:H8),"") | D13: Return to promoter on equity contribution
B14: Equity NPV @ WACC | C14: =IFERROR(NPV(Assumptions!$C$73,D8:H8)+C8,"") -> 0 | D14: ₹ lakh
B16: D. Debt-service coverage (DSCR)
C17: Year 1 | D17: Year 2 | E17: Year 3 | F17: Year 4 | G17: Year 5
B18: DSCR = (PAT + dep + interest) / (interest + principal) | C18: =IF(('Annual P&L'!C13+SUM('Loan Schedule'!C8:N8))=0,"",('Annual P&L'!C16+'Annual P&L'!C11+'Annual P&L'!C13)/('Annual P&L'!C13+SUM('Loan Schedule'!C8:N8))) | D18: =IF(('Annual P&L'!D13+SUM('Loan Schedule'!O8:Z8))=0,"",('Annual P&L'!D16+'Annual P&L'!D11+'Annual P&L'!D13)/('Annual P&L'!D13+SUM('Loan Schedule'!O8:Z8))) | E18: =IF(('Annual P&L'!E13+SUM('Loan Schedule'!AA8:AL8))=0,"",('Annual P&L'!E16+'Annual P&L'!E11+'Annual P&L'!E13)/('Annual P&L'!E13+SUM('Loan Schedule'!AA8:AL8))) | F18: =IF(('Annual P&L'!F13+SUM('Loan Schedule'!AM8:AX8))=0,"",('Annual P&L'!F16+'Annual P&L'!F11+'Annual P&L'!F13)/('Annual P&L'!F13+SUM('Loan Schedule'!AM8:AX8))) | G18: =IF(('Annual P&L'!G13+SUM('Loan Schedule'!AY8:BJ8))=0,"",('Annual P&L'!G16+'Annual P&L'!G11+'Annual P&L'!G13)/('Annual P&L'!G13+SUM('Loan Schedule'!AY8:BJ8)))
B19: Average DSCR | C19: =IFERROR(AVERAGE(C18:G18),"")
B21: E. Break-even capacity utilisation
C22: Year 1 | D22: Year 2 | E22: Year 3 | F22: Year 4 | G22: Year 5
B23: BEP utilisation = fixed cost / contribution ratio / (rev@100%) | C23: =IF('Annual P&L'!C5=0,"",('Annual P&L'!C8+'Annual P&L'!C11+'Annual P&L'!C13)/(('Annual P&L'!C5-'Annual P&L'!C6)/'Annual P&L'!C5)/('Annual P&L'!C5/'Monthly Model'!H8)) | D23: =IF('Annual P&L'!D5=0,"",('Annual P&L'!D8+'Annual P&L'!D11+'Annual P&L'!D13)/(('Annual P&L'!D5-'Annual P&L'!D6)/'Annual P&L'!D5)/('Annual P&L'!D5/'Monthly Model'!T8)) | E23: =IF('Annual P&L'!E5=0,"",('Annual P&L'!E8+'Annual P&L'!E11+'Annual P&L'!E13)/(('Annual P&L'!E5-'Annual P&L'!E6)/'Annual P&L'!E5)/('Annual P&L'!E5/'Monthly Model'!AF8)) | F23: =IF('Annual P&L'!F5=0,"",('Annual P&L'!F8+'Annual P&L'!F11+'Annual P&L'!F13)/(('Annual P&L'!F5-'Annual P&L'!F6)/'Annual P&L'!F5)/('Annual P&L'!F5/'Monthly Model'!AR8)) | G23: =IF('Annual P&L'!G5=0,"",('Annual P&L'!G8+'Annual P&L'!G11+'Annual P&L'!G13)/(('Annual P&L'!G5-'Annual P&L'!G6)/'Annual P&L'!G5)/('Annual P&L'!G5/'Monthly Model'!BD8))
B25: Interpretation: DSCR ≥ 1.5x and break-even below operating utilisation both indicate a bankable, resilient project.

Sheet Socio-Economic Impact
A1: SOCIO-ECONOMIC IMPACT
A2: Quantified development outcomes — the core of a grant case. Blue cells are editable multipliers/norms.
B4: Editable local parameters
B5: Employment multiplier (indirect+induced per direct job) | D5: x | E5: Standard agro-processing multiplier (management estimate)
B6: Average annual procurement per farmer family | D6: ₹ lakh | E6: Value of produce bought per supplier farmer p.a.
B7: Net GST contribution rate (indicative) | D7: % of rev | E7: Net of input-tax credit (management estimate)
B9: Employment
B10: Direct employment at peak (Year 5) | C10: =IFERROR(Payroll!BJ6,"") -> 0 | D10: persons | E10: On-roll + contract at full ramp
B11: Women employed (Year 5) | C11: =IFERROR(Payroll!BJ7,"") -> 0 | D11: persons | E11: Gender inclusion
B12: Cumulative person-months of work (5 yr) | C12: =IFERROR(SUM(Payroll!C6:BJ6),"") -> 0 | D12: p-months | E12: Total employment generated
B13: Indirect & induced jobs (Year 5) | C13: =IFERROR(Payroll!BJ6*$C$5,"") -> 0 | D13: persons | E13: Direct × multiplier
B14: Total wages disbursed (5 yr) | C14: =IFERROR(SUM(Payroll!C9:BJ9),"") -> 0 | D14: ₹ lakh | E14: Household income injected
B16: Farmer & supply-chain linkage
B17: Raw material procured (5 yr) | C17: =IFERROR(SUM('Monthly Model'!C15:BJ15),"") -> 0 | D17: ₹ lakh
B18: Farmer families linked (approx.) | C18: =IFERROR(C17/$C$6,"") | D18: families | E18: Raw-material spend / per-farmer procurement
B19: Local content of inputs (target) | D19: % | E19: Share sourced within Gujarat/region (target)
B21: Contribution to the exchequer & economy
B22: Income tax paid (5 yr) | C22: =IFERROR(SUM('Monthly Model'!C46:BJ46),"") -> 0 | D22: ₹ lakh | E22: Direct corporate tax
B23: Indicative net GST (5 yr) | C23: =IFERROR(SUM('Monthly Model'!C13:BJ13)*$C$7,"") -> 0 | D23: ₹ lakh | E23: Revenue × net GST rate
B24: Local economic value (wages + procurement, 5 yr) | C24: =IFERROR(SUM(Payroll!C9:BJ9)+C17,"") -> 0 | D24: ₹ lakh | E24: Direct money into local economy
B26: Narrative for the application
B27: This enterprise advances inclusive, place-based development. It creates direct wage employment (with strong women's participation) in a semi-urban/rural setting, and catalyses a wider set of indirect and induced livelihoods across procurement, logistics and services. By buying farm produce on assured terms it raises and stabilises farmer incomes, reduces post-harvest loss, and formalises an otherwise unorganised value chain. It broadens the tax base (corporate tax + GST), aligns with 'Vocal for Local' and 'Atmanirbhar' priorities, and channels sustained income into the local economy — the classic multiplier a public grant is designed to unlock.

Sheet Sustainability (ESG)
A1: SUSTAINABILITY & ESG
A2: Environmental design and targets. Blue cells are management ESG targets (to be firmed up in the DPR/EIA).
B4: Editable ESG targets (inputs)
B5: Grid + captive energy use (Year 5) | D5: kWh/yr | E5: Estimated at full ramp
B6: Rooftop solar share of electricity | D6: % | E6: On-site renewable generation target
B7: Grid tariff (avoided cost) | D7: ₹/kWh | E7: Industrial tariff, avoided via solar
B8: Grid emission factor | D8: kg CO₂/kWh | E8: CEA national average (approx.)
B9: Process water recycled (ETP/ZLD) | D9: % | E9: Reuse via effluent treatment
B10: Organic waste valorised (compost/biogas) | D10: % | E10: Diverted from landfill
B11: Post-harvest loss reduced (produce processed) | D11: tonnes/yr | E11: Perishables saved via processing
B13: Computed environmental outcomes
B14: Solar electricity generated (Year 5) | C14: =IFERROR($C$5*$C$6,"") -> 0 | D14: kWh/yr | E14: Energy × solar share
B15: Grid energy avoided cost (Year 5) | C15: =IFERROR(($C$5*$C$6)*$C$7/100000,"") -> 0 | D15: ₹ lakh | E15: Solar generation × tariff
B16: CO₂ emissions avoided (Year 5) | C16: =IFERROR(($C$5*$C$6)*$C$8/1000,"") -> 0 | D16: tonnes/yr | E16: Solar generation × emission factor
B17: Water recycled (Year 5, indicative) | C17: =IFERROR($C$9*15000,"") -> 0 | D17: kL/yr | E17: Recycled share × process water
B19: ESG narrative
B20: Environmental: rooftop solar, energy-efficient refrigeration, an effluent-treatment plant with high water recycling, and valorisation of organic waste into compost/biogas minimise the unit's footprint. By processing perishable farm produce, the plant directly cuts post-harvest food loss — a material climate and food-security benefit. Social: safe, formal jobs with gender inclusion, skilling and assured farmer offtake. Governance: FSSAI compliance, transparent procurement, Udyam/GST formalisation and audited accounts. Together these align the project with SDGs 2, 7, 8, 12 and 13 and with national sustainability and food-processing missions.

Sheet Scheme Alignment
A1: GOVERNMENT-SCHEME ALIGNMENT & INDICATIVE BENEFIT
A2: Recommended stack for a Small (₹1-10 cr) unit: state capital + interest subsidy, CGTMSE-backed credit, concessional tax; PMFME/CLCSS conditional. Benefit figures are indicative and formula-linked to Assumptions.
B4: Scheme | C4: Authority | D4: Benefit basis | E4: Indicative (₹ lakh) | F4: Eligibility fit / notes
B5: Aatmanirbhar Gujarat – Capital Investment Subsidy | C5: Industries & Mines Dept, Gujarat | D5: % of eligible fixed capital investment, capped | E5: =IFERROR(Assumptions!$C$79,"") -> 0 | F5: New/expanding manufacturing MSME with Udyam & COD in policy window
B6: Aatmanirbhar Gujarat – Interest Subsidy | C6: Industries & Mines Dept, Gujarat | D6: Subsidy on term-loan interest (5-yr sum) | E6: =IFERROR(SUM('Loan Schedule'!C12:BJ12),"") -> 0 | F6: Bank/FI-financed term loan; paid post-COD
B7: Aatmanirbhar Gujarat – Net SGST Reimbursement | C7: Industries & Mines Dept, Gujarat | D7: Share of net SGST on intra-state sales (indicative) | E7: =IFERROR(SUM('Monthly Model'!C13:BJ13)*0.03*Assumptions!$C$71,"") -> 0 | F7: Category 1/2/3 talukas; intra-Gujarat sales
B8: CGTMSE Credit Guarantee | C8: MoMSME / SIDBI | D8: Collateral-free guarantee on the term loan | E8: =IFERROR(Assumptions!$C$78,"") -> 0 | F8: Guarantee cover up to ₹5 cr (₹10 cr per Budget 2025); enabler, not cash grant
B9: PMFME (conditional) | C9: MoFPI / State Nodal | D9: 35% credit-linked subsidy up to ₹10 lakh | E9: =IFERROR(MIN(Assumptions!$C$75*Assumptions!$C$69,Assumptions!$C$70),"") -> 0 | F9: ONLY if the unit qualifies as MICRO food-processing (P&M ≤₹2.5 cr)
B10: CLCSS-type Tech Upgradation (indicative) | C10: MoMSME (subsumed) | D10: 15% capital subsidy on eligible P&M | E10: =IFERROR(MIN(Assumptions!$C$16*0.15,15),"") -> 0 | F10: For technology upgradation; verify current window
B11: Concessional Corporate Tax (s.115BAA) | C11: Income Tax Dept | D11: 22% base (eff. 25.17%), no MAT | E11: — | F11: Any domestic company; s.115BAB 15% only if COD was ≤ 31-Mar-2024
B12: EPF Reimbursement | C12: Industries & Mines Dept, Gujarat | D12: Employer PF for new employees (10 yr) | E12: — | F12: New employees without prior UAN; strong for a job-creating unit
D13: Total indicative cash subsidy (excl. enablers) | E13: =E5+E6+E7+E9+E10 -> 0

Sheet Dashboard
B1: DASHBOARD — HEADLINE RESULTS
B2: All ₹ figures in lakh unless a % or count. Cards are live-linked to the model.
B3: Year-5 Revenue | E3: Year-5 PAT
B4: =IFERROR('Annual P&L'!G5,"") -> 0 | E4: =IFERROR('Annual P&L'!G16,"") -> 0
B7: Year-5 EBITDA margin | E7: Project IRR
B8: =IFERROR('Annual P&L'!G10,"") -> 0 | E8: =IFERROR(IRR('Returns & Ratios'!C5:H5),"")
B11: Peak direct jobs | E11: Total cash subsidy
B12: =IFERROR(Payroll!BJ6,"") -> 0 | E12: =IFERROR(Assumptions!$C$79+SUM('Loan Schedule'!C12:BJ12),"") -> 0

Sheet Sources
A1: SOURCES & REFERENCES (click to open)
A2: Live, publicly accessible sources underpinning the Assumptions. Verify each at time of use — tax, subsidy and scheme parameters are revised periodically.
B4: What it supports | C4: Source (click to open)
B5: MSME classification, w.e.f. 01-Apr-2025 (Small = P&M ≤₹25 cr / turnover ≤₹100 cr) | C5: https://www.pib.gov.in/PressReleasePage.aspx?PRID=2098389
B6: Corporate tax | C6: https://incometaxindia.gov.in/Documents/Left%20Menu/TAX%20RATES-domestic.htm
B7: s.115BAA 22% (eff. 25.17%); s.115BAB 15% (eff. 17.16%, sunset 31-Mar-2024) | C7: https://cleartax.in/s/section-115-baa-tax-rate-domestic-companies
B8: MSME term-loan / working-capital rates & RBI repo (~6.5% early-2026; term loans ~9-11%) | C8: https://creditcares.in/cgtmse-loan-interest-rate-2026-bank-wise-rates/
B9: CGTMSE collateral-free credit guarantee up to ₹5 cr (raised to ₹10 cr, Budget 2025) | C9: https://cleartax.in/s/msme-loan-scheme-2020
B10: Aatmanirbhar Gujarat Scheme for MSMEs 2022-27 (capital + interest subsidy) | C10: https://www.myscheme.gov.in/schemes/agmsmecis
B11: Aatmanirbhar Gujarat incentives: capital + 7% interest subsidy, net-SGST & EPF reimbursement | C11: https://ipfonline.com/news/detail/policyregulation/aatmanirbhar-gujarat-2022-boosting-growth-of-msmes/15919
B12: Aatmanirbhar Gujarat Industrial Policy 2022 (full text) | C12: https://cmogujarat.gov.in/wp-content/uploads/2022/10/AatmaNirbhar-Gujarat_Industrial-Policy.pdf
B13: PMFME | C13: https://www.myscheme.gov.in/schemes/pmfmpe
B14: PMFME scheme structure, ODOP & eligibility | C14: https://cleartax.in/s/pmfme-scheme
B15: Operational / management estimate | C15: Management / DPR estimate (to be validated by promoter & appraising bank)
