Workbook

Sheet Cover
B2: CREDIT MONITORING ARRANGEMENT (CMA) REPORT
B3: Projected Financials for Bank Term-Loan & Working-Capital Appraisal
B5: Name of the Unit | C5: =Assumptions!C5 -> SaaS Solutions Pvt Ltd
B6: Constitution | C6: =Assumptions!C6 -> Private Limited
B7: Line of Activity | C7: =Assumptions!C7 -> B2B SaaS subscription product
B8: Term Loan applied for (₹) | C8: =Assumptions!C8 -> 4000000
B9: Promoters' Capital (₹) | C9: =Assumptions!C9 -> 1000000
B10: Projection horizon | C10: 5 years (60 months), monthly
B12: CONTENTS
B13: Assumptions | C13: All input variables — the single control panel for the model
B14: Production | C14: 60-month production plan (capacity × utilisation × phasing)
B15: Sales | C15: 60-month sales quantity, price and revenue
B16: Expenses | C16: 60-month operating expenses, interest and depreciation
B17: Profit | C17: 60-month P&L: EBITDA → EBIT → PBT → PAT
B18: Annual_Summary | C18: Consolidated 5-year figures feeding the CMA forms
B19: Form_II_Operating | C19: Form II — Operating statement (profitability)
B20: Form_III_BalanceSheet | C20: Form III — Projected balance sheet
B21: Form_IV_CA_CL | C21: Form IV — Current assets & current liabilities
B22: Form_V_MPBF | C22: Form V — Maximum permissible bank finance
B23: Form_VI_FundFlow | C23: Form VI — Fund-flow statement
B24: Repayment | C24: Term-loan repayment schedule
... B26: Ratios | C26: Key ratios — financial viability
B28: Enter data only in the blue cells on the Assumptions sheet; all other sheets recalculate automatically.

Sheet Dashboard
B1: CMA DASHBOARD — KEY METRICS AT A GLANCE
B3: Live summary — every figure below recalculates automatically from the Assumptions and calculation sheets.
B5: TERM LOAN AMOUNT | F5: PROMOTERS' CAPITAL | J5: AVERAGE DSCR (5-YR) | N5: TERM LOAN TENURE
B7: =Assumptions!C8 -> 4000000 | F7: =Assumptions!C9 -> 1000000 | J7: =DSCR!H14 -> 15.43369 | N7: =Assumptions!C11 -> 60
B10: YEAR-1 EBITDA MARGIN | F10: YEAR-1 NET PROFIT MARGIN | J10: YEAR-1 BREAK-EVEN (% SALES) | N10: YEAR-1 CURRENT RATIO
B12: =Ratios!C10 -> 0.3015625 | F12: =Ratios!C11 -> 0.21335866 | J12: =Ratios!C16 -> 0.36782619 | N12: =Ratios!C6 -> 5.1478711
B52: SELECT YEAR TO VIEW SNAPSHOT → | D52: 1
B54: REVENUE (SELECTED YEAR) | F54: EBITDA (SELECTED YEAR) | J54: PAT (SELECTED YEAR) | N54: DSCR (SELECTED YEAR)
B56: =INDEX(Annual_Summary!C8:G8,1,$D$52) -> 46080000 | F56: =INDEX(Annual_Summary!C22:G22,1,$D$52) -> 13896000 | J56: =INDEX(Annual_Summary!C26:G26,1,$D$52) -> 9831567.1 | N56: =INDEX(DSCR!C14:G14,1,$D$52) -> 7.9048475
B90: WC Component | C90: Days
B91: Raw Material Holding | C91: =Assumptions!C50 -> 0
B92: Finished Goods Holding | C92: =Assumptions!C51 -> 0
B93: Receivables | C93: =Assumptions!C52 -> 30
B94: Payables | C94: =Assumptions!C53 -> 30
B96: Ratio | C96: Year 1 | D96: Year 5
B97: Current Ratio | C97: =Ratios!C6 -> 5.1478711 | D97: =Ratios!G6 -> 14.987105
B98: Debt-Equity Ratio | C98: =Ratios!C7 -> 0.4966788 | D98: =Ratios!G7 -> 0.04855429
B99: EBITDA Margin | C99: =Ratios!C10 -> 0.3015625 | D99: =Ratios!G10 -> 0.31834236
B100: Net Profit Margin | C100: =Ratios!C11 -> 0.21335866 | D100: =Ratios!G11 -> 0.23312998

Sheet Assumptions
A1: ASSUMPTIONS — KEY INPUTS
A2: Enter values only in the blue/shaded cells. Every other sheet updates automatically.
B4: A. COMPANY & LOAN PARTICULARS | S4: Industry | T4: CapLabel | U4: ProdUnitLabel | V4: Cost1Long | W4: Cost1Short | X4: Cost2Long | Y4: Cost2Short | Z4: Cost3Short
B5: Name of the Unit | C5: SaaS Solutions Pvt Ltd | I5: INDUSTRY / BUSINESS TYPE → | J5: Technology & Software | S5: Agriculture & Farming | T5: Installed Capacity (land / livestock / output) | U5: Production (units) | V5: Raw material / input cost per unit (Year 1) | W5: Raw materials / inputs | X5: Power & fuel cost per unit (Year 1) | Y5: Power & fuel | Z5: Farm overheads
B6: Constitution (Proprietor / Partnership / Pvt Ltd) | C6: Private Limited | S6: Technology & Software | T6: Service Delivery Capacity (billable hours/licenses p.a.) | U6: Service delivery (units) | V6: Direct delivery cost per unit (Year 1) | W6: Direct delivery cost | X6: Infrastructure & hosting cost per unit (Year 1) | Y6: Infrastructure & hosting | Z6: Operating overheads
B7: Line of Activity / Product | C7: B2B SaaS subscription product | S7: Retail & E-Commerce | T7: Annual Purchase Capacity (units for resale) | U7: Purchase (units) | V7: Purchase cost of goods per unit (Year 1) | W7: Purchase cost of goods | X7: Freight & packaging cost per unit (Year 1) | Y7: Freight & packaging | Z7: Store overheads
B8: Term Loan applied for | C8: 4000000 | H8: ₹ | S8: Manufacturing | T8: Installed Capacity | U8: Production (units) | V8: Raw material cost per unit (Year 1) | W8: Raw materials | X8: Power & fuel cost per unit (Year 1) | Y8: Power & fuel | Z8: Factory overheads
B9: Promoters' Capital / Equity brought in | C9: 1000000 | H9: ₹ | S9: Tourism & Hospitality | T9: Room / Cover Capacity (room-nights or covers p.a.) | U9: Rooms sold / covers served (units) | V9: Direct service cost per unit (F&B, housekeeping) (Year 1) | W9: Direct service cost | X9: Power & fuel cost per unit (Year 1) | Y9: Power & fuel | Z9: Property overheads
B10: Interest rate on Term Loan | C10: 0.105 | H10: % p.a. | S10: Renewable Energy | T10: Installed Generation Capacity (units of energy p.a.) | U10: Energy generated (units) | V10: O&M cost per unit generated (Year 1) | W10: O&M cost | X10: Grid / power evacuation cost per unit (Year 1) | Y10: Grid / evacuation cost | Z10: Plant overheads
B11: Term Loan tenure | C11: 60 | H11: years | S11: Healthcare & Pharma | T11: Service / Production Capacity (patients or units p.a.) | U11: Patients served / units produced | V11: Consumables & medicine cost per unit (Year 1) | W11: Consumables & medicine | X11: Power & equipment running cost per unit (Year 1) | Y11: Power & equipment cost | Z11: Facility overheads
B12: Moratorium / holiday period | C12: 6 | H12: months | S12: Education & Training | T12: Service Capacity (student seats / batches p.a.) | U12: Students / batches served | V12: Direct delivery cost per unit (faculty, material) (Year 1) | W12: Direct delivery cost | X12: Infrastructure cost per unit (Year 1) | Y12: Infrastructure cost | Z12: Institute overheads
B13: Interest rate on Working Capital | C13: 0.12 | H13: % p.a. | S13: General Business | T13: Capacity (units / customers / hours p.a.) | U13: Output (units) | V13: Direct cost per unit (Year 1) | W13: Direct cost | X13: Overhead cost per unit (Year 1) | Y13: Overhead cost | Z13: Operating overheads
B14: Income Tax rate | C14: 0.25 | H14: % | S14: Construction & Real Estate | T14: Project Execution Capacity (sq.ft / units p.a.) | U14: Construction / units completed | V14: Construction material cost per unit (Year 1) | W14: Construction materials | X14: Site power & machinery cost per unit (Year 1) | Y14: Site power & machinery | Z14: Project overheads
B15: B. CAPACITY & PRODUCTION | S15: Food & Beverage / Restaurant | T15: Seating / Covers Capacity (covers p.a.) | U15: Covers served (units) | V15: Raw material (food & beverage) cost per unit (Year 1) | W15: Food & beverage cost | X15: Kitchen power & fuel cost per unit (Year 1) | Y15: Kitchen power & fuel | Z15: Restaurant overheads
B16: =IFERROR(VLOOKUP($J$5,$S$5:$Z$21,2,FALSE()),"Installed Capacity") -> Service Delivery Capacity (billable hours/licenses p.a.) | C16: 4800 | H16: units p.a. | S16: Transportation & Logistics | T16: Fleet / Route Capacity (trips or tonnage p.a.) | U16: Trips / tonnage handled (units) | V16: Fuel & running cost per unit (Year 1) | W16: Fuel & running cost | X16: Vehicle maintenance cost per unit (Year 1) | Y16: Vehicle maintenance | Z16: Fleet overheads
B17: Capacity Utilisation | C17: Yr 1 | D17: Yr 2 | E17: Yr 3 | F17: Yr 4 | G17: Yr 5 | S17: Textile & Garments | T17: Installed Capacity (garments/fabric units p.a.) | U17: Production (units) | V17: Raw material (yarn/fabric) cost per unit (Year 1) | W17: Raw materials (yarn/fabric) | X17: Power & fuel cost per unit (Year 1) | Y17: Power & fuel | Z17: Factory overheads
B18: → enter % for Year 1 … 5 | C18: 0.8 | D18: 0.85 | E18: 0.9 | F18: 0.95 | G18: 1 | H18: % | S18: Automobile / Auto Ancillary | T18: Installed Capacity (components/vehicles p.a.) | U18: Production (units) | V18: Raw material / component cost per unit (Year 1) | W18: Raw materials / components | X18: Power & fuel cost per unit (Year 1) | Y18: Power & fuel | Z18: Factory overheads
B19: C. MONTHLY PHASING FACTOR (optional — blank = equal spread) | S19: Import / Export Trading | T19: Annual Trading Capacity (units for import/export) | U19: Trading volume (units) | V19: Purchase / import cost per unit (Year 1) | W19: Purchase / import cost | X19: Freight, customs & logistics cost per unit (Year 1) | Y19: Freight & customs | Z19: Trading overheads
B20: Relative weight per month (M1…M12) | C20: M1 | D20: M2 | E20: M3 | F20: M4 | G20: M5 | H20: M6 | I20: M7 | J20: M8 | K20: M9 | L20: M10 | M20: M11 | N20: M12 | S20: Media & Entertainment | T20: Content / Production Capacity (units/hours p.a.) | U20: Content produced (units) | V20: Production cost per unit (Year 1) | W20: Production cost | X20: Equipment & studio cost per unit (Year 1) | Y20: Equipment & studio cost | Z20: Studio overheads
B21: → weights (e.g. 1.0 each, or seasonal) | C21: 0.083 | D21: 0.083 | E21: 0.083 | F21: 0.083 | G21: 0.083 | H21: 0.083 | I21: 0.083 | J21: 0.083 | K21: 0.083 | L21: 0.083 | M21: 0.083 | N21: 0.083 | S21: Mining & Minerals | T21: Installed Extraction Capacity (tonnes p.a.) | U21: Extraction (units) | V21: Raw material / extraction cost per unit (Year 1) | W21: Extraction cost | X21: Power & fuel cost per unit (Year 1) | Y21: Power & fuel | Z21: Mine overheads
B22: D. PRICE & VARIABLE COSTS (Year-1 base, escalated by the % below)
B23: Selling price per unit (Year 1) | C23: 12000 | H23: ₹/unit
B24: annual price escalation | C24: 0.05 | H24: %
B25: =IFERROR(VLOOKUP($J$5,$S$5:$Z$21,4,FALSE()),"Raw material cost per unit (Year 1)") -> Direct delivery cost per unit (Year 1) | C25: 3000 | H25: ₹/unit
B26: annual RM cost escalation | C26: 0.06 | H26: %
B27: =IFERROR(VLOOKUP($J$5,$S$5:$Z$21,6,FALSE()),"Power & fuel cost per unit (Year 1)") -> Infrastructure & hosting cost per unit (Year 1) | C27: 2000 | H27: ₹/unit
B28: annual power cost escalation | C28: 0.05 | H28: %
B29: Other variable cost per unit (Year 1) | C29: 1000 | H29: ₹/unit
B30: annual other-variable escalation | C30: 0.04 | H30: %
B31: E. FIXED / PERIOD COSTS (per month, Year-1 base, escalated below)
B32: Direct wages & salaries / month (Year 1) | C32: 400000 | H32: ₹/month
B33: annual wages escalation | C33: 0.07 | H33: %
B34: Factory overheads / month (Year 1) | C34: 100000 | H34: ₹/month
B35: annual factory-OH escalation | C35: 0.05 | H35: %
B36: Repairs & maintenance / month (Year 1) | C36: 20000 | H36: ₹/month
B37: annual R&M escalation | C37: 0.04 | H37: %
B38: Administrative expenses / month (Year 1) | C38: 50000 | H38: ₹/month
B39: annual admin escalation | C39: 0.05 | H39: %
B40: Selling & distribution | C40: 0.05 | H40: % of sales
B41: F. FIXED ASSETS & DEPRECIATION (straight-line on cost)
B42: Land (no depreciation) | C42: 0 | H42: ₹
B43: Building — cost | C43: 0 | H43: ₹
B44: Building — depreciation rate | C44: 0.1 | H44: %
B45: Plant & Machinery — cost | C45: 500000 | H45: ₹
B46: Plant & Machinery — depreciation rate | C46: 0.15 | H46: %
B47: Furniture / other — cost | C47: 200000 | H47: ₹
B48: Furniture / other — depreciation rate | C48: 0.1 | H48: %
B49: G. WORKING CAPITAL CYCLE
B50: Raw material holding | C50: 0 | H50: days
B51: Finished goods holding | C51: 0 | H51: days
B52: Receivables / debtors | C52: 30 | H52: days
B53: Creditors / payables | C53: 30 | H53: days
B54: Minimum cash & bank balance | C54: 500000 | H54: ₹
B55: Bank's WC margin (borrower's stake) | C55: 0.25 | H55: % | P55: Tandon Method-II uses 25%

Sheet Production
A1: PRODUCTION PLAN — 60-MONTH PROJECTION
A2: Driven by Installed Capacity × Capacity Utilisation × Monthly phasing (Assumptions).
B3: YEAR 1 | O3: YEAR 2 | AB3: YEAR 3 | AO3: YEAR 4 | BB3: YEAR 5
A4: Particulars | B4: M1 | C4: M2 | D4: M3 | E4: M4 | F4: M5 | G4: M6 | H4: M7 | I4: M8 | J4: M9 | K4: M10 | L4: M11 | M4: M12 | N4: Yr 1 Total | O4: M13 | P4: M14 | Q4: M15 | R4: M16 | S4: M17 | T4: M18 | U4: M19 | V4: M20 | W4: M21 | X4: M22 | Y4: M23 | Z4: M24 | AA4: Yr 2 Total | AB4: M25 | AC4: M26 | AD4: M27 | AE4: M28 | AF4: M29 | AG4: M30 | AH4: M31 | AI4: M32 | AJ4: M33 | AK4: M34 | AL4: M35 | AM4: M36 | AN4: Yr 3 Total | AO4: M37 | AP4: M38 | AQ4: M39 | AR4: M40 | AS4: M41 | AT4: M42 | AU4: M43 | AV4: M44 | AW4: M45 | AX4: M46 | AY4: M47 | AZ4: M48 | BA4: Yr 4 Total | BB4: M49 | BC4: M50 | BD4: M51 | BE4: M52 | BF4: M53 | BG4: M54 | BH4: M55 | BI4: M56 | BJ4: M57 | BK4: M58 | BL4: M59 | BM4: M60 | BN4: Yr 5 Total
A5: Capacity utilisation (%) | B5: =Assumptions!$C$18 -> 0.8 | C5: =Assumptions!$C$18 -> 0.8 | D5: =Assumptions!$C$18 -> 0.8 | E5: =Assumptions!$C$18 -> 0.8 | F5: =Assumptions!$C$18 -> 0.8 | G5: =Assumptions!$C$18 -> 0.8 | H5: =Assumptions!$C$18 -> 0.8 | I5: =Assumptions!$C$18 -> 0.8 | ... N5: =Assumptions!$C$18 -> 0.8 | O5: =Assumptions!$D$18 -> 0.85 | P5: =Assumptions!$D$18 -> 0.85 | Q5: =Assumptions!$D$18 -> 0.85 | R5: =Assumptions!$D$18 -> 0.85 | S5: =Assumptions!$D$18 -> 0.85 | T5: =Assumptions!$D$18 -> 0.85 | U5: =Assumptions!$D$18 -> 0.85 | V5: =Assumptions!$D$18 -> 0.85 | ... AA5: =Assumptions!$D$18 -> 0.85 | AB5: =Assumptions!$E$18 -> 0.9 | AC5: =Assumptions!$E$18 -> 0.9 | AD5: =Assumptions!$E$18 -> 0.9 | AE5: =Assumptions!$E$18 -> 0.9 | AF5: =Assumptions!$E$18 -> 0.9 | AG5: =Assumptions!$E$18 -> 0.9 | AH5: =Assumptions!$E$18 -> 0.9 | AI5: =Assumptions!$E$18 -> 0.9 | ... AN5: =Assumptions!$E$18 -> 0.9 | AO5: =Assumptions!$F$18 -> 0.95 | AP5: =Assumptions!$F$18 -> 0.95 | AQ5: =Assumptions!$F$18 -> 0.95 | AR5: =Assumptions!$F$18 -> 0.95 | AS5: =Assumptions!$F$18 -> 0.95 | AT5: =Assumptions!$F$18 -> 0.95 | AU5: =Assumptions!$F$18 -> 0.95 | AV5: =Assumptions!$F$18 -> 0.95 | ... BA5: =Assumptions!$F$18 -> 0.95 | BB5: =Assumptions!$G$18 -> 1 | BC5: =Assumptions!$G$18 -> 1 | BD5: =Assumptions!$G$18 -> 1 | BE5: =Assumptions!$G$18 -> 1 | BF5: =Assumptions!$G$18 -> 1 | BG5: =Assumptions!$G$18 -> 1 | BH5: =Assumptions!$G$18 -> 1 | BI5: =Assumptions!$G$18 -> 1 | ... BN5: =Assumptions!$G$18 -> 1
A6: =IFERROR(VLOOKUP(Assumptions!$J$5,Assumptions!$S$5:$Z$21,3,FALSE()),"Production (units)") -> Service delivery (units) | B6: =(Assumptions!$C$16*Assumptions!$C$18/12)*IF(SUM(Assumptions!$C$21:$N$21)=0,1,12*Assumptions!$C$21/SUM(Assumptions!$C$21:$N$21)) -> 320 | C6: =(Assumptions!$C$16*Assumptions!$C$18/12)*IF(SUM(Assumptions!$C$21:$N$21)=0,1,12*Assumptions!$D$21/SUM(Assumptions!$C$21:$N$21)) -> 320 | D6: =(Assumptions!$C$16*Assumptions!$C$18/12)*IF(SUM(Assumptions!$C$21:$N$21)=0,1,12*Assumptions!$E$21/SUM(Assumptions!$C$21:$N$21)) -> 320 | E6: =(Assumptions!$C$16*Assumptions!$C$18/12)*IF(SUM(Assumptions!$C$21:$N$21)=0,1,12*Assumptions!$F$21/SUM(Assumptions!$C$21:$N$21)) -> 320 | F6: =(Assumptions!$C$16*Assumptions!$C$18/12)*IF(SUM(Assumptions!$C$21:$N$21)=0,1,12*Assumptions!$G$21/SUM(Assumptions!$C$21:$N$21)) -> 320 | G6: =(Assumptions!$C$16*Assumptions!$C$18/12)*IF(SUM(Assumptions!$C$21:$N$21)=0,1,12*Assumptions!$H$21/SUM(Assumptions!$C$21:$N$21)) -> 320 | H6: =(Assumptions!$C$16*Assumptions!$C$18/12)*IF(SUM(Assumptions!$C$21:$N$21)=0,1,12*Assumptions!$I$21/SUM(Assumptions!$C$21:$N$21)) -> 320 | I6: =(Assumptions!$C$16*Assumptions!$C$18/12)*IF(SUM(Assumptions!$C$21:$N$21)=0,1,12*Assumptions!$J$21/SUM(Assumptions!$C$21:$N$21)) -> 320 | J6: =(Assumptions!$C$16*Assumptions!$C$18/12)*IF(SUM(Assumptions!$C$21:$N$21)=0,1,12*Assumptions!$K$21/SUM(Assumptions!$C$21:$N$21)) -> 320 | K6: =(Assumptions!$C$16*Assumptions!$C$18/12)*IF(SUM(Assumptions!$C$21:$N$21)=0,1,12*Assumptions!$L$21/SUM(Assumptions!$C$21:$N$21)) -> 320 | L6: =(Assumptions!$C$16*Assumptions!$C$18/12)*IF(SUM(Assumptions!$C$21:$N$21)=0,1,12*Assumptions!$M$21/SUM(Assumptions!$C$21:$N$21)) -> 320 | M6: =(Assumptions!$C$16*Assumptions!$C$18/12)*IF(SUM(Assumptions!$C$21:$N$21)=0,1,12*Assumptions!$N$21/SUM(Assumptions!$C$21:$N$21)) -> 320 | N6: =SUM(B6:M6) -> 3840 | O6: =(Assumptions!$C$16*Assumptions!$D$18/12)*IF(SUM(Assumptions!$C$21:$N$21)=0,1,12*Assumptions!$C$21/SUM(Assumptions!$C$21:$N$21)) -> 340 | P6: =(Assumptions!$C$16*Assumptions!$D$18/12)*IF(SUM(Assumptions!$C$21:$N$21)=0,1,12*Assumptions!$D$21/SUM(Assumptions!$C$21:$N$21)) -> 340 | Q6: =(Assumptions!$C$16*Assumptions!$D$18/12)*IF(SUM(Assumptions!$C$21:$N$21)=0,1,12*Assumptions!$E$21/SUM(Assumptions!$C$21:$N$21)) -> 340 | R6: =(Assumptions!$C$16*Assumptions!$D$18/12)*IF(SUM(Assumptions!$C$21:$N$21)=0,1,12*Assumptions!$F$21/SUM(Assumptions!$C$21:$N$21)) -> 340 | S6: =(Assumptions!$C$16*Assumptions!$D$18/12)*IF(SUM(Assumptions!$C$21:$N$21)=0,1,12*Assumptions!$G$21/SUM(Assumptions!$C$21:$N$21)) -> 340 | T6: =(Assumptions!$C$16*Assumptions!$D$18/12)*IF(SUM(Assumptions!$C$21:$N$21)=0,1,12*Assumptions!$H$21/SUM(Assumptions!$C$21:$N$21)) -> 340 | U6: =(Assumptions!$C$16*Assumptions!$D$18/12)*IF(SUM(Assumptions!$C$21:$N$21)=0,1,12*Assumptions!$I$21/SUM(Assumptions!$C$21:$N$21)) -> 340 | V6: =(Assumptions!$C$16*Assumptions!$D$18/12)*IF(SUM(Assumptions!$C$21:$N$21)=0,1,12*Assumptions!$J$21/SUM(Assumptions!$C$21:$N$21)) -> 340 | W6: =(Assumptions!$C$16*Assumptions!$D$18/12)*IF(SUM(Assumptions!$C$21:$N$21)=0,1,12*Assumptions!$K$21/SUM(Assumptions!$C$21:$N$21)) -> 340 | X6: =(Assumptions!$C$16*Assumptions!$D$18/12)*IF(SUM(Assumptions!$C$21:$N$21)=0,1,12*Assumptions!$L$21/SUM(Assumptions!$C$21:$N$21)) -> 340 | Y6: =(Assumptions!$C$16*Assumptions!$D$18/12)*IF(SUM(Assumptions!$C$21:$N$21)=0,1,12*Assumptions!$M$21/SUM(Assumptions!$C$21:$N$21)) -> 340 | Z6: =(Assumptions!$C$16*Assumptions!$D$18/12)*IF(SUM(Assumptions!$C$21:$N$21)=0,1,12*Assumptions!$N$21/SUM(Assumptions!$C$21:$N$21)) -> 340 | AA6: =SUM(O6:Z6) -> 4080 | AB6: =(Assumptions!$C$16*Assumptions!$E$18/12)*IF(SUM(Assumptions!$C$21:$N$21)=0,1,12*Assumptions!$C$21/SUM(Assumptions!$C$21:$N$21)) -> 360 | AC6: =(Assumptions!$C$16*Assumptions!$E$18/12)*IF(SUM(Assumptions!$C$21:$N$21)=0,1,12*Assumptions!$D$21/SUM(Assumptions!$C$21:$N$21)) -> 360 | AD6: =(Assumptions!$C$16*Assumptions!$E$18/12)*IF(SUM(Assumptions!$C$21:$N$21)=0,1,12*Assumptions!$E$21/SUM(Assumptions!$C$21:$N$21)) -> 360 | AE6: =(Assumptions!$C$16*Assumptions!$E$18/12)*IF(SUM(Assumptions!$C$21:$N$21)=0,1,12*Assumptions!$F$21/SUM(Assumptions!$C$21:$N$21)) -> 360 | AF6: =(Assumptions!$C$16*Assumptions!$E$18/12)*IF(SUM(Assumptions!$C$21:$N$21)=0,1,12*Assumptions!$G$21/SUM(Assumptions!$C$21:$N$21)) -> 360 | AG6: =(Assumptions!$C$16*Assumptions!$E$18/12)*IF(SUM(Assumptions!$C$21:$N$21)=0,1,12*Assumptions!$H$21/SUM(Assumptions!$C$21:$N$21)) -> 360 | AH6: =(Assumptions!$C$16*Assumptions!$E$18/12)*IF(SUM(Assumptions!$C$21:$N$21)=0,1,12*Assumptions!$I$21/SUM(Assumptions!$C$21:$N$21)) -> 360 | AI6: =(Assumptions!$C$16*Assumptions!$E$18/12)*IF(SUM(Assumptions!$C$21:$N$21)=0,1,12*Assumptions!$J$21/SUM(Assumptions!$C$21:$N$21)) -> 360 | AJ6: =(Assumptions!$C$16*Assumptions!$E$18/12)*IF(SUM(Assumptions!$C$21:$N$21)=0,1,12*Assumptions!$K$21/SUM(Assumptions!$C$21:$N$21)) -> 360 | AK6: =(Assumptions!$C$16*Assumptions!$E$18/12)*IF(SUM(Assumptions!$C$21:$N$21)=0,1,12*Assumptions!$L$21/SUM(Assumptions!$C$21:$N$21)) -> 360 | AL6: =(Assumptions!$C$16*Assumptions!$E$18/12)*IF(SUM(Assumptions!$C$21:$N$21)=0,1,12*Assumptions!$M$21/SUM(Assumptions!$C$21:$N$21)) -> 360 | AM6: =(Assumptions!$C$16*Assumptions!$E$18/12)*IF(SUM(Assumptions!$C$21:$N$21)=0,1,12*Assumptions!$N$21/SUM(Assumptions!$C$21:$N$21)) -> 360 | AN6: =SUM(AB6:AM6) -> 4320 | AO6: =(Assumptions!$C$16*Assumptions!$F$18/12)*IF(SUM(Assumptions!$C$21:$N$21)=0,1,12*Assumptions!$C$21/SUM(Assumptions!$C$21:$N$21)) -> 380 | AP6: =(Assumptions!$C$16*Assumptions!$F$18/12)*IF(SUM(Assumptions!$C$21:$N$21)=0,1,12*Assumptions!$D$21/SUM(Assumptions!$C$21:$N$21)) -> 380 | AQ6: =(Assumptions!$C$16*Assumptions!$F$18/12)*IF(SUM(Assumptions!$C$21:$N$21)=0,1,12*Assumptions!$E$21/SUM(Assumptions!$C$21:$N$21)) -> 380 | AR6: =(Assumptions!$C$16*Assumptions!$F$18/12)*IF(SUM(Assumptions!$C$21:$N$21)=0,1,12*Assumptions!$F$21/SUM(Assumptions!$C$21:$N$21)) -> 380 | AS6: =(Assumptions!$C$16*Assumptions!$F$18/12)*IF(SUM(Assumptions!$C$21:$N$21)=0,1,12*Assumptions!$G$21/SUM(Assumptions!$C$21:$N$21)) -> 380 | AT6: =(Assumptions!$C$16*Assumptions!$F$18/12)*IF(SUM(Assumptions!$C$21:$N$21)=0,1,12*Assumptions!$H$21/SUM(Assumptions!$C$21:$N$21)) -> 380 | AU6: =(Assumptions!$C$16*Assumptions!$F$18/12)*IF(SUM(Assumptions!$C$21:$N$21)=0,1,12*Assumptions!$I$21/SUM(Assumptions!$C$21:$N$21)) -> 380 | AV6: =(Assumptions!$C$16*Assumptions!$F$18/12)*IF(SUM(Assumptions!$C$21:$N$21)=0,1,12*Assumptions!$J$21/SUM(Assumptions!$C$21:$N$21)) -> 380 | AW6: =(Assumptions!$C$16*Assumptions!$F$18/12)*IF(SUM(Assumptions!$C$21:$N$21)=0,1,12*Assumptions!$K$21/SUM(Assumptions!$C$21:$N$21)) -> 380 | AX6: =(Assumptions!$C$16*Assumptions!$F$18/12)*IF(SUM(Assumptions!$C$21:$N$21)=0,1,12*Assumptions!$L$21/SUM(Assumptions!$C$21:$N$21)) -> 380 | AY6: =(Assumptions!$C$16*Assumptions!$F$18/12)*IF(SUM(Assumptions!$C$21:$N$21)=0,1,12*Assumptions!$M$21/SUM(Assumptions!$C$21:$N$21)) -> 380 | AZ6: =(Assumptions!$C$16*Assumptions!$F$18/12)*IF(SUM(Assumptions!$C$21:$N$21)=0,1,12*Assumptions!$N$21/SUM(Assumptions!$C$21:$N$21)) -> 380 | BA6: =SUM(AO6:AZ6) -> 4560 | BB6: =(Assumptions!$C$16*Assumptions!$G$18/12)*IF(SUM(Assumptions!$C$21:$N$21)=0,1,12*Assumptions!$C$21/SUM(Assumptions!$C$21:$N$21)) -> 400 | BC6: =(Assumptions!$C$16*Assumptions!$G$18/12)*IF(SUM(Assumptions!$C$21:$N$21)=0,1,12*Assumptions!$D$21/SUM(Assumptions!$C$21:$N$21)) -> 400 | BD6: =(Assumptions!$C$16*Assumptions!$G$18/12)*IF(SUM(Assumptions!$C$21:$N$21)=0,1,12*Assumptions!$E$21/SUM(Assumptions!$C$21:$N$21)) -> 400 | BE6: =(Assumptions!$C$16*Assumptions!$G$18/12)*IF(SUM(Assumptions!$C$21:$N$21)=0,1,12*Assumptions!$F$21/SUM(Assumptions!$C$21:$N$21)) -> 400 | BF6: =(Assumptions!$C$16*Assumptions!$G$18/12)*IF(SUM(Assumptions!$C$21:$N$21)=0,1,12*Assumptions!$G$21/SUM(Assumptions!$C$21:$N$21)) -> 400 | BG6: =(Assumptions!$C$16*Assumptions!$G$18/12)*IF(SUM(Assumptions!$C$21:$N$21)=0,1,12*Assumptions!$H$21/SUM(Assumptions!$C$21:$N$21)) -> 400 | BH6: =(Assumptions!$C$16*Assumptions!$G$18/12)*IF(SUM(Assumptions!$C$21:$N$21)=0,1,12*Assumptions!$I$21/SUM(Assumptions!$C$21:$N$21)) -> 400 | BI6: =(Assumptions!$C$16*Assumptions!$G$18/12)*IF(SUM(Assumptions!$C$21:$N$21)=0,1,12*Assumptions!$J$21/SUM(Assumptions!$C$21:$N$21)) -> 400 | BJ6: =(Assumptions!$C$16*Assumptions!$G$18/12)*IF(SUM(Assumptions!$C$21:$N$21)=0,1,12*Assumptions!$K$21/SUM(Assumptions!$C$21:$N$21)) -> 400 | BK6: =(Assumptions!$C$16*Assumptions!$G$18/12)*IF(SUM(Assumptions!$C$21:$N$21)=0,1,12*Assumptions!$L$21/SUM(Assumptions!$C$21:$N$21)) -> 400 | BL6: =(Assumptions!$C$16*Assumptions!$G$18/12)*IF(SUM(Assumptions!$C$21:$N$21)=0,1,12*Assumptions!$M$21/SUM(Assumptions!$C$21:$N$21)) -> 400 | BM6: =(Assumptions!$C$16*Assumptions!$G$18/12)*IF(SUM(Assumptions!$C$21:$N$21)=0,1,12*Assumptions!$N$21/SUM(Assumptions!$C$21:$N$21)) -> 400 | BN6: =SUM(BB6:BM6) -> 4800

Sheet Sales
A1: SALES PLAN — 60-MONTH PROJECTION
A2: Sales quantity = production; revenue = quantity × escalated selling price.
B3: YEAR 1 | O3: YEAR 2 | AB3: YEAR 3 | AO3: YEAR 4 | BB3: YEAR 5
A4: Particulars | B4: M1 | C4: M2 | D4: M3 | E4: M4 | F4: M5 | G4: M6 | H4: M7 | I4: M8 | J4: M9 | K4: M10 | L4: M11 | M4: M12 | N4: Yr 1 Total | O4: M13 | P4: M14 | Q4: M15 | R4: M16 | S4: M17 | T4: M18 | U4: M19 | V4: M20 | W4: M21 | X4: M22 | Y4: M23 | Z4: M24 | AA4: Yr 2 Total | AB4: M25 | AC4: M26 | AD4: M27 | AE4: M28 | AF4: M29 | AG4: M30 | AH4: M31 | AI4: M32 | AJ4: M33 | AK4: M34 | AL4: M35 | AM4: M36 | AN4: Yr 3 Total | AO4: M37 | AP4: M38 | AQ4: M39 | AR4: M40 | AS4: M41 | AT4: M42 | AU4: M43 | AV4: M44 | AW4: M45 | AX4: M46 | AY4: M47 | AZ4: M48 | BA4: Yr 4 Total | BB4: M49 | BC4: M50 | BD4: M51 | BE4: M52 | BF4: M53 | BG4: M54 | BH4: M55 | BI4: M56 | BJ4: M57 | BK4: M58 | BL4: M59 | BM4: M60 | BN4: Yr 5 Total
A5: Sales quantity (units) | B5: =Production!B6 -> 320 | C5: =Production!C6 -> 320 | D5: =Production!D6 -> 320 | E5: =Production!E6 -> 320 | F5: =Production!F6 -> 320 | G5: =Production!G6 -> 320 | H5: =Production!H6 -> 320 | I5: =Production!I6 -> 320 | ... M5: =Production!M6 -> 320 | N5: =SUM(B5:M5) -> 3840 | O5: =Production!O6 -> 340 | P5: =Production!P6 -> 340 | Q5: =Production!Q6 -> 340 | R5: =Production!R6 -> 340 | S5: =Production!S6 -> 340 | T5: =Production!T6 -> 340 | U5: =Production!U6 -> 340 | V5: =Production!V6 -> 340 | ... Z5: =Production!Z6 -> 340 | AA5: =SUM(O5:Z5) -> 4080 | AB5: =Production!AB6 -> 360 | AC5: =Production!AC6 -> 360 | AD5: =Production!AD6 -> 360 | AE5: =Production!AE6 -> 360 | AF5: =Production!AF6 -> 360 | AG5: =Production!AG6 -> 360 | AH5: =Production!AH6 -> 360 | AI5: =Production!AI6 -> 360 | ... AM5: =Production!AM6 -> 360 | AN5: =SUM(AB5:AM5) -> 4320 | AO5: =Production!AO6 -> 380 | AP5: =Production!AP6 -> 380 | AQ5: =Production!AQ6 -> 380 | AR5: =Production!AR6 -> 380 | AS5: =Production!AS6 -> 380 | AT5: =Production!AT6 -> 380 | AU5: =Production!AU6 -> 380 | AV5: =Production!AV6 -> 380 | ... AZ5: =Production!AZ6 -> 380 | BA5: =SUM(AO5:AZ5) -> 4560 | BB5: =Production!BB6 -> 400 | BC5: =Production!BC6 -> 400 | BD5: =Production!BD6 -> 400 | BE5: =Production!BE6 -> 400 | BF5: =Production!BF6 -> 400 | BG5: =Production!BG6 -> 400 | BH5: =Production!BH6 -> 400 | BI5: =Production!BI6 -> 400 | ... BM5: =Production!BM6 -> 400 | BN5: =SUM(BB5:BM5) -> 4800
A6: Selling price (₹ / unit) | B6: =Assumptions!$C$23*(1+Assumptions!$C$24)^0 -> 12000 | C6: =Assumptions!$C$23*(1+Assumptions!$C$24)^0 -> 12000 | D6: =Assumptions!$C$23*(1+Assumptions!$C$24)^0 -> 12000 | E6: =Assumptions!$C$23*(1+Assumptions!$C$24)^0 -> 12000 | F6: =Assumptions!$C$23*(1+Assumptions!$C$24)^0 -> 12000 | G6: =Assumptions!$C$23*(1+Assumptions!$C$24)^0 -> 12000 | H6: =Assumptions!$C$23*(1+Assumptions!$C$24)^0 -> 12000 | I6: =Assumptions!$C$23*(1+Assumptions!$C$24)^0 -> 12000 | ... N6: =Assumptions!$C$23*(1+Assumptions!$C$24)^0 -> 12000 | O6: =Assumptions!$C$23*(1+Assumptions!$C$24)^1 -> 12600 | P6: =Assumptions!$C$23*(1+Assumptions!$C$24)^1 -> 12600 | Q6: =Assumptions!$C$23*(1+Assumptions!$C$24)^1 -> 12600 | R6: =Assumptions!$C$23*(1+Assumptions!$C$24)^1 -> 12600 | S6: =Assumptions!$C$23*(1+Assumptions!$C$24)^1 -> 12600 | T6: =Assumptions!$C$23*(1+Assumptions!$C$24)^1 -> 12600 | U6: =Assumptions!$C$23*(1+Assumptions!$C$24)^1 -> 12600 | V6: =Assumptions!$C$23*(1+Assumptions!$C$24)^1 -> 12600 | ... AA6: =Assumptions!$C$23*(1+Assumptions!$C$24)^1 -> 12600 | AB6: =Assumptions!$C$23*(1+Assumptions!$C$24)^2 -> 13230 | AC6: =Assumptions!$C$23*(1+Assumptions!$C$24)^2 -> 13230 | AD6: =Assumptions!$C$23*(1+Assumptions!$C$24)^2 -> 13230 | AE6: =Assumptions!$C$23*(1+Assumptions!$C$24)^2 -> 13230 | AF6: =Assumptions!$C$23*(1+Assumptions!$C$24)^2 -> 13230 | AG6: =Assumptions!$C$23*(1+Assumptions!$C$24)^2 -> 13230 | AH6: =Assumptions!$C$23*(1+Assumptions!$C$24)^2 -> 13230 | AI6: =Assumptions!$C$23*(1+Assumptions!$C$24)^2 -> 13230 | ... AN6: =Assumptions!$C$23*(1+Assumptions!$C$24)^2 -> 13230 | AO6: =Assumptions!$C$23*(1+Assumptions!$C$24)^3 -> 13891.5 | AP6: =Assumptions!$C$23*(1+Assumptions!$C$24)^3 -> 13891.5 | AQ6: =Assumptions!$C$23*(1+Assumptions!$C$24)^3 -> 13891.5 | AR6: =Assumptions!$C$23*(1+Assumptions!$C$24)^3 -> 13891.5 | AS6: =Assumptions!$C$23*(1+Assumptions!$C$24)^3 -> 13891.5 | AT6: =Assumptions!$C$23*(1+Assumptions!$C$24)^3 -> 13891.5 | AU6: =Assumptions!$C$23*(1+Assumptions!$C$24)^3 -> 13891.5 | AV6: =Assumptions!$C$23*(1+Assumptions!$C$24)^3 -> 13891.5 | ... BA6: =Assumptions!$C$23*(1+Assumptions!$C$24)^3 -> 13891.5 | BB6: =Assumptions!$C$23*(1+Assumptions!$C$24)^4 -> 14586.075 | BC6: =Assumptions!$C$23*(1+Assumptions!$C$24)^4 -> 14586.075 | BD6: =Assumptions!$C$23*(1+Assumptions!$C$24)^4 -> 14586.075 | BE6: =Assumptions!$C$23*(1+Assumptions!$C$24)^4 -> 14586.075 | BF6: =Assumptions!$C$23*(1+Assumptions!$C$24)^4 -> 14586.075 | BG6: =Assumptions!$C$23*(1+Assumptions!$C$24)^4 -> 14586.075 | BH6: =Assumptions!$C$23*(1+Assumptions!$C$24)^4 -> 14586.075 | BI6: =Assumptions!$C$23*(1+Assumptions!$C$24)^4 -> 14586.075 | ... BN6: =Assumptions!$C$23*(1+Assumptions!$C$24)^4 -> 14586.075
A7: Net Sales / Revenue (₹) | B7: =B5*B6 -> 3840000 | C7: =C5*C6 -> 3840000 | D7: =D5*D6 -> 3840000 | E7: =E5*E6 -> 3840000 | F7: =F5*F6 -> 3840000 | G7: =G5*G6 -> 3840000 | H7: =H5*H6 -> 3840000 | I7: =I5*I6 -> 3840000 | ... M7: =M5*M6 -> 3840000 | N7: =SUM(B7:M7) -> 46080000 | O7: =O5*O6 -> 4284000 | P7: =P5*P6 -> 4284000 | Q7: =Q5*Q6 -> 4284000 | R7: =R5*R6 -> 4284000 | S7: =S5*S6 -> 4284000 | T7: =T5*T6 -> 4284000 | U7: =U5*U6 -> 4284000 | V7: =V5*V6 -> 4284000 | ... Z7: =Z5*Z6 -> 4284000 | AA7: =SUM(O7:Z7) -> 51408000 | AB7: =AB5*AB6 -> 4762800 | AC7: =AC5*AC6 -> 4762800 | AD7: =AD5*AD6 -> 4762800 | AE7: =AE5*AE6 -> 4762800 | AF7: =AF5*AF6 -> 4762800 | AG7: =AG5*AG6 -> 4762800 | AH7: =AH5*AH6 -> 4762800 | AI7: =AI5*AI6 -> 4762800 | ... AM7: =AM5*AM6 -> 4762800 | AN7: =SUM(AB7:AM7) -> 57153600 | AO7: =AO5*AO6 -> 5278770 | AP7: =AP5*AP6 -> 5278770 | AQ7: =AQ5*AQ6 -> 5278770 | AR7: =AR5*AR6 -> 5278770 | AS7: =AS5*AS6 -> 5278770 | AT7: =AT5*AT6 -> 5278770 | AU7: =AU5*AU6 -> 5278770 | AV7: =AV5*AV6 -> 5278770 | ... AZ7: =AZ5*AZ6 -> 5278770 | BA7: =SUM(AO7:AZ7) -> 63345240 | BB7: =BB5*BB6 -> 5834430 | BC7: =BC5*BC6 -> 5834430 | BD7: =BD5*BD6 -> 5834430 | BE7: =BE5*BE6 -> 5834430 | BF7: =BF5*BF6 -> 5834430 | BG7: =BG5*BG6 -> 5834430 | BH7: =BH5*BH6 -> 5834430 | BI7: =BI5*BI6 -> 5834430 | ... BM7: =BM5*BM6 -> 5834430 | BN7: =SUM(BB7:BM7) -> 70013160

Sheet Expenses
A1: OPERATING EXPENSES — 60-MONTH PROJECTION
A2: Variable costs scale with production; period costs escalate annually; interest & depreciation linked.
B3: YEAR 1 | O3: YEAR 2 | AB3: YEAR 3 | AO3: YEAR 4 | BB3: YEAR 5
A4: Particulars | B4: M1 | C4: M2 | D4: M3 | E4: M4 | F4: M5 | G4: M6 | H4: M7 | I4: M8 | J4: M9 | K4: M10 | L4: M11 | M4: M12 | N4: Yr 1 Total | O4: M13 | P4: M14 | Q4: M15 | R4: M16 | S4: M17 | T4: M18 | U4: M19 | V4: M20 | W4: M21 | X4: M22 | Y4: M23 | Z4: M24 | AA4: Yr 2 Total | AB4: M25 | AC4: M26 | AD4: M27 | AE4: M28 | AF4: M29 | AG4: M30 | AH4: M31 | AI4: M32 | AJ4: M33 | AK4: M34 | AL4: M35 | AM4: M36 | AN4: Yr 3 Total | AO4: M37 | AP4: M38 | AQ4: M39 | AR4: M40 | AS4: M41 | AT4: M42 | AU4: M43 | AV4: M44 | AW4: M45 | AX4: M46 | AY4: M47 | AZ4: M48 | BA4: Yr 4 Total | BB4: M49 | BC4: M50 | BD4: M51 | BE4: M52 | BF4: M53 | BG4: M54 | BH4: M55 | BI4: M56 | BJ4: M57 | BK4: M58 | BL4: M59 | BM4: M60 | BN4: Yr 5 Total
A5: =IFERROR(VLOOKUP(Assumptions!$J$5,Assumptions!$S$5:$Z$21,5,FALSE()),"Raw materials") -> Direct delivery cost | B5: =Production!B6*(Assumptions!$C$25*(1+Assumptions!$C$26)^0) -> 960000 | C5: =Production!C6*(Assumptions!$C$25*(1+Assumptions!$C$26)^0) -> 960000 | D5: =Production!D6*(Assumptions!$C$25*(1+Assumptions!$C$26)^0) -> 960000 | E5: =Production!E6*(Assumptions!$C$25*(1+Assumptions!$C$26)^0) -> 960000 | F5: =Production!F6*(Assumptions!$C$25*(1+Assumptions!$C$26)^0) -> 960000 | G5: =Production!G6*(Assumptions!$C$25*(1+Assumptions!$C$26)^0) -> 960000 | H5: =Production!H6*(Assumptions!$C$25*(1+Assumptions!$C$26)^0) -> 960000 | I5: =Production!I6*(Assumptions!$C$25*(1+Assumptions!$C$26)^0) -> 960000 | ... M5: =Production!M6*(Assumptions!$C$25*(1+Assumptions!$C$26)^0) -> 960000 | N5: =SUM(B5:M5) -> 11520000 | O5: =Production!O6*(Assumptions!$C$25*(1+Assumptions!$C$26)^1) -> 1081200 | P5: =Production!P6*(Assumptions!$C$25*(1+Assumptions!$C$26)^1) -> 1081200 | Q5: =Production!Q6*(Assumptions!$C$25*(1+Assumptions!$C$26)^1) -> 1081200 | R5: =Production!R6*(Assumptions!$C$25*(1+Assumptions!$C$26)^1) -> 1081200 | S5: =Production!S6*(Assumptions!$C$25*(1+Assumptions!$C$26)^1) -> 1081200 | T5: =Production!T6*(Assumptions!$C$25*(1+Assumptions!$C$26)^1) -> 1081200 | U5: =Production!U6*(Assumptions!$C$25*(1+Assumptions!$C$26)^1) -> 1081200 | V5: =Production!V6*(Assumptions!$C$25*(1+Assumptions!$C$26)^1) -> 1081200 | ... Z5: =Production!Z6*(Assumptions!$C$25*(1+Assumptions!$C$26)^1) -> 1081200 | AA5: =SUM(O5:Z5) -> 12974400 | AB5: =Production!AB6*(Assumptions!$C$25*(1+Assumptions!$C$26)^2) -> 1213488 | AC5: =Production!AC6*(Assumptions!$C$25*(1+Assumptions!$C$26)^2) -> 1213488 | AD5: =Production!AD6*(Assumptions!$C$25*(1+Assumptions!$C$26)^2) -> 1213488 | AE5: =Production!AE6*(Assumptions!$C$25*(1+Assumptions!$C$26)^2) -> 1213488 | AF5: =Production!AF6*(Assumptions!$C$25*(1+Assumptions!$C$26)^2) -> 1213488 | AG5: =Production!AG6*(Assumptions!$C$25*(1+Assumptions!$C$26)^2) -> 1213488 | AH5: =Production!AH6*(Assumptions!$C$25*(1+Assumptions!$C$26)^2) -> 1213488 | AI5: =Production!AI6*(Assumptions!$C$25*(1+Assumptions!$C$26)^2) -> 1213488 | ... AM5: =Production!AM6*(Assumptions!$C$25*(1+Assumptions!$C$26)^2) -> 1213488 | AN5: =SUM(AB5:AM5) -> 14561856 | AO5: =Production!AO6*(Assumptions!$C$25*(1+Assumptions!$C$26)^3) -> 1357758.2 | AP5: =Production!AP6*(Assumptions!$C$25*(1+Assumptions!$C$26)^3) -> 1357758.2 | AQ5: =Production!AQ6*(Assumptions!$C$25*(1+Assumptions!$C$26)^3) -> 1357758.2 | AR5: =Production!AR6*(Assumptions!$C$25*(1+Assumptions!$C$26)^3) -> 1357758.2 | AS5: =Production!AS6*(Assumptions!$C$25*(1+Assumptions!$C$26)^3) -> 1357758.2 | AT5: =Production!AT6*(Assumptions!$C$25*(1+Assumptions!$C$26)^3) -> 1357758.2 | AU5: =Production!AU6*(Assumptions!$C$25*(1+Assumptions!$C$26)^3) -> 1357758.2 | AV5: =Production!AV6*(Assumptions!$C$25*(1+Assumptions!$C$26)^3) -> 1357758.2 | ... AZ5: =Production!AZ6*(Assumptions!$C$25*(1+Assumptions!$C$26)^3) -> 1357758.2 | BA5: =SUM(AO5:AZ5) -> 16293099 | BB5: =Production!BB6*(Assumptions!$C$25*(1+Assumptions!$C$26)^4) -> 1514972.4 | BC5: =Production!BC6*(Assumptions!$C$25*(1+Assumptions!$C$26)^4) -> 1514972.4 | BD5: =Production!BD6*(Assumptions!$C$25*(1+Assumptions!$C$26)^4) -> 1514972.4 | BE5: =Production!BE6*(Assumptions!$C$25*(1+Assumptions!$C$26)^4) -> 1514972.4 | BF5: =Production!BF6*(Assumptions!$C$25*(1+Assumptions!$C$26)^4) -> 1514972.4 | BG5: =Production!BG6*(Assumptions!$C$25*(1+Assumptions!$C$26)^4) -> 1514972.4 | BH5: =Production!BH6*(Assumptions!$C$25*(1+Assumptions!$C$26)^4) -> 1514972.4 | BI5: =Production!BI6*(Assumptions!$C$25*(1+Assumptions!$C$26)^4) -> 1514972.4 | ... BM5: =Production!BM6*(Assumptions!$C$25*(1+Assumptions!$C$26)^4) -> 1514972.4 | BN5: =SUM(BB5:BM5) -> 18179668
A6: =IFERROR(VLOOKUP(Assumptions!$J$5,Assumptions!$S$5:$Z$21,7,FALSE()),"Power & fuel") -> Infrastructure & hosting | B6: =Production!B6*(Assumptions!$C$27*(1+Assumptions!$C$28)^0) -> 640000 | C6: =Production!C6*(Assumptions!$C$27*(1+Assumptions!$C$28)^0) -> 640000 | D6: =Production!D6*(Assumptions!$C$27*(1+Assumptions!$C$28)^0) -> 640000 | E6: =Production!E6*(Assumptions!$C$27*(1+Assumptions!$C$28)^0) -> 640000 | F6: =Production!F6*(Assumptions!$C$27*(1+Assumptions!$C$28)^0) -> 640000 | G6: =Production!G6*(Assumptions!$C$27*(1+Assumptions!$C$28)^0) -> 640000 | H6: =Production!H6*(Assumptions!$C$27*(1+Assumptions!$C$28)^0) -> 640000 | I6: =Production!I6*(Assumptions!$C$27*(1+Assumptions!$C$28)^0) -> 640000 | ... M6: =Production!M6*(Assumptions!$C$27*(1+Assumptions!$C$28)^0) -> 640000 | N6: =SUM(B6:M6) -> 7680000 | O6: =Production!O6*(Assumptions!$C$27*(1+Assumptions!$C$28)^1) -> 714000 | P6: =Production!P6*(Assumptions!$C$27*(1+Assumptions!$C$28)^1) -> 714000 | Q6: =Production!Q6*(Assumptions!$C$27*(1+Assumptions!$C$28)^1) -> 714000 | R6: =Production!R6*(Assumptions!$C$27*(1+Assumptions!$C$28)^1) -> 714000 | S6: =Production!S6*(Assumptions!$C$27*(1+Assumptions!$C$28)^1) -> 714000 | T6: =Production!T6*(Assumptions!$C$27*(1+Assumptions!$C$28)^1) -> 714000 | U6: =Production!U6*(Assumptions!$C$27*(1+Assumptions!$C$28)^1) -> 714000 | V6: =Production!V6*(Assumptions!$C$27*(1+Assumptions!$C$28)^1) -> 714000 | ... Z6: =Production!Z6*(Assumptions!$C$27*(1+Assumptions!$C$28)^1) -> 714000 | AA6: =SUM(O6:Z6) -> 8568000 | AB6: =Production!AB6*(Assumptions!$C$27*(1+Assumptions!$C$28)^2) -> 793800 | AC6: =Production!AC6*(Assumptions!$C$27*(1+Assumptions!$C$28)^2) -> 793800 | AD6: =Production!AD6*(Assumptions!$C$27*(1+Assumptions!$C$28)^2) -> 793800 | AE6: =Production!AE6*(Assumptions!$C$27*(1+Assumptions!$C$28)^2) -> 793800 | AF6: =Production!AF6*(Assumptions!$C$27*(1+Assumptions!$C$28)^2) -> 793800 | AG6: =Production!AG6*(Assumptions!$C$27*(1+Assumptions!$C$28)^2) -> 793800 | AH6: =Production!AH6*(Assumptions!$C$27*(1+Assumptions!$C$28)^2) -> 793800 | AI6: =Production!AI6*(Assumptions!$C$27*(1+Assumptions!$C$28)^2) -> 793800 | ... AM6: =Production!AM6*(Assumptions!$C$27*(1+Assumptions!$C$28)^2) -> 793800 | AN6: =SUM(AB6:AM6) -> 9525600 | AO6: =Production!AO6*(Assumptions!$C$27*(1+Assumptions!$C$28)^3) -> 879795 | AP6: =Production!AP6*(Assumptions!$C$27*(1+Assumptions!$C$28)^3) -> 879795 | AQ6: =Production!AQ6*(Assumptions!$C$27*(1+Assumptions!$C$28)^3) -> 879795 | AR6: =Production!AR6*(Assumptions!$C$27*(1+Assumptions!$C$28)^3) -> 879795 | AS6: =Production!AS6*(Assumptions!$C$27*(1+Assumptions!$C$28)^3) -> 879795 | AT6: =Production!AT6*(Assumptions!$C$27*(1+Assumptions!$C$28)^3) -> 879795 | AU6: =Production!AU6*(Assumptions!$C$27*(1+Assumptions!$C$28)^3) -> 879795 | AV6: =Production!AV6*(Assumptions!$C$27*(1+Assumptions!$C$28)^3) -> 879795 | ... AZ6: =Production!AZ6*(Assumptions!$C$27*(1+Assumptions!$C$28)^3) -> 879795 | BA6: =SUM(AO6:AZ6) -> 10557540 | BB6: =Production!BB6*(Assumptions!$C$27*(1+Assumptions!$C$28)^4) -> 972405 | BC6: =Production!BC6*(Assumptions!$C$27*(1+Assumptions!$C$28)^4) -> 972405 | BD6: =Production!BD6*(Assumptions!$C$27*(1+Assumptions!$C$28)^4) -> 972405 | BE6: =Production!BE6*(Assumptions!$C$27*(1+Assumptions!$C$28)^4) -> 972405 | BF6: =Production!BF6*(Assumptions!$C$27*(1+Assumptions!$C$28)^4) -> 972405 | BG6: =Production!BG6*(Assumptions!$C$27*(1+Assumptions!$C$28)^4) -> 972405 | BH6: =Production!BH6*(Assumptions!$C$27*(1+Assumptions!$C$28)^4) -> 972405 | BI6: =Production!BI6*(Assumptions!$C$27*(1+Assumptions!$C$28)^4) -> 972405 | ... BM6: =Production!BM6*(Assumptions!$C$27*(1+Assumptions!$C$28)^4) -> 972405 | BN6: =SUM(BB6:BM6) -> 11668860
A7: Direct wages & salaries | B7: =Assumptions!$C$32*(1+Assumptions!$C$33)^0 -> 400000 | C7: =Assumptions!$C$32*(1+Assumptions!$C$33)^0 -> 400000 | D7: =Assumptions!$C$32*(1+Assumptions!$C$33)^0 -> 400000 | E7: =Assumptions!$C$32*(1+Assumptions!$C$33)^0 -> 400000 | F7: =Assumptions!$C$32*(1+Assumptions!$C$33)^0 -> 400000 | G7: =Assumptions!$C$32*(1+Assumptions!$C$33)^0 -> 400000 | H7: =Assumptions!$C$32*(1+Assumptions!$C$33)^0 -> 400000 | I7: =Assumptions!$C$32*(1+Assumptions!$C$33)^0 -> 400000 | ... M7: =Assumptions!$C$32*(1+Assumptions!$C$33)^0 -> 400000 | N7: =SUM(B7:M7) -> 4800000 | O7: =Assumptions!$C$32*(1+Assumptions!$C$33)^1 -> 428000 | P7: =Assumptions!$C$32*(1+Assumptions!$C$33)^1 -> 428000 | Q7: =Assumptions!$C$32*(1+Assumptions!$C$33)^1 -> 428000 | R7: =Assumptions!$C$32*(1+Assumptions!$C$33)^1 -> 428000 | S7: =Assumptions!$C$32*(1+Assumptions!$C$33)^1 -> 428000 | T7: =Assumptions!$C$32*(1+Assumptions!$C$33)^1 -> 428000 | U7: =Assumptions!$C$32*(1+Assumptions!$C$33)^1 -> 428000 | V7: =Assumptions!$C$32*(1+Assumptions!$C$33)^1 -> 428000 | ... Z7: =Assumptions!$C$32*(1+Assumptions!$C$33)^1 -> 428000 | AA7: =SUM(O7:Z7) -> 5136000 | AB7: =Assumptions!$C$32*(1+Assumptions!$C$33)^2 -> 457960 | AC7: =Assumptions!$C$32*(1+Assumptions!$C$33)^2 -> 457960 | AD7: =Assumptions!$C$32*(1+Assumptions!$C$33)^2 -> 457960 | AE7: =Assumptions!$C$32*(1+Assumptions!$C$33)^2 -> 457960 | AF7: =Assumptions!$C$32*(1+Assumptions!$C$33)^2 -> 457960 | AG7: =Assumptions!$C$32*(1+Assumptions!$C$33)^2 -> 457960 | AH7: =Assumptions!$C$32*(1+Assumptions!$C$33)^2 -> 457960 | AI7: =Assumptions!$C$32*(1+Assumptions!$C$33)^2 -> 457960 | ... AM7: =Assumptions!$C$32*(1+Assumptions!$C$33)^2 -> 457960 | AN7: =SUM(AB7:AM7) -> 5495520 | AO7: =Assumptions!$C$32*(1+Assumptions!$C$33)^3 -> 490017.2 | AP7: =Assumptions!$C$32*(1+Assumptions!$C$33)^3 -> 490017.2 | AQ7: =Assumptions!$C$32*(1+Assumptions!$C$33)^3 -> 490017.2 | AR7: =Assumptions!$C$32*(1+Assumptions!$C$33)^3 -> 490017.2 | AS7: =Assumptions!$C$32*(1+Assumptions!$C$33)^3 -> 490017.2 | AT7: =Assumptions!$C$32*(1+Assumptions!$C$33)^3 -> 490017.2 | AU7: =Assumptions!$C$32*(1+Assumptions!$C$33)^3 -> 490017.2 | AV7: =Assumptions!$C$32*(1+Assumptions!$C$33)^3 -> 490017.2 | ... AZ7: =Assumptions!$C$32*(1+Assumptions!$C$33)^3 -> 490017.2 | BA7: =SUM(AO7:AZ7) -> 5880206.4 | BB7: =Assumptions!$C$32*(1+Assumptions!$C$33)^4 -> 524318.4 | BC7: =Assumptions!$C$32*(1+Assumptions!$C$33)^4 -> 524318.4 | BD7: =Assumptions!$C$32*(1+Assumptions!$C$33)^4 -> 524318.4 | BE7: =Assumptions!$C$32*(1+Assumptions!$C$33)^4 -> 524318.4 | BF7: =Assumptions!$C$32*(1+Assumptions!$C$33)^4 -> 524318.4 | BG7: =Assumptions!$C$32*(1+Assumptions!$C$33)^4 -> 524318.4 | BH7: =Assumptions!$C$32*(1+Assumptions!$C$33)^4 -> 524318.4 | BI7: =Assumptions!$C$32*(1+Assumptions!$C$33)^4 -> 524318.4 | ... BM7: =Assumptions!$C$32*(1+Assumptions!$C$33)^4 -> 524318.4 | BN7: =SUM(BB7:BM7) -> 6291820.8
A8: Other variable cost | B8: =Production!B6*(Assumptions!$C$29*(1+Assumptions!$C$30)^0) -> 320000 | C8: =Production!C6*(Assumptions!$C$29*(1+Assumptions!$C$30)^0) -> 320000 | D8: =Production!D6*(Assumptions!$C$29*(1+Assumptions!$C$30)^0) -> 320000 | E8: =Production!E6*(Assumptions!$C$29*(1+Assumptions!$C$30)^0) -> 320000 | F8: =Production!F6*(Assumptions!$C$29*(1+Assumptions!$C$30)^0) -> 320000 | G8: =Production!G6*(Assumptions!$C$29*(1+Assumptions!$C$30)^0) -> 320000 | H8: =Production!H6*(Assumptions!$C$29*(1+Assumptions!$C$30)^0) -> 320000 | I8: =Production!I6*(Assumptions!$C$29*(1+Assumptions!$C$30)^0) -> 320000 | ... M8: =Production!M6*(Assumptions!$C$29*(1+Assumptions!$C$30)^0) -> 320000 | N8: =SUM(B8:M8) -> 3840000 | O8: =Production!O6*(Assumptions!$C$29*(1+Assumptions!$C$30)^1) -> 353600 | P8: =Production!P6*(Assumptions!$C$29*(1+Assumptions!$C$30)^1) -> 353600 | Q8: =Production!Q6*(Assumptions!$C$29*(1+Assumptions!$C$30)^1) -> 353600 | R8: =Production!R6*(Assumptions!$C$29*(1+Assumptions!$C$30)^1) -> 353600 | S8: =Production!S6*(Assumptions!$C$29*(1+Assumptions!$C$30)^1) -> 353600 | T8: =Production!T6*(Assumptions!$C$29*(1+Assumptions!$C$30)^1) -> 353600 | U8: =Production!U6*(Assumptions!$C$29*(1+Assumptions!$C$30)^1) -> 353600 | V8: =Production!V6*(Assumptions!$C$29*(1+Assumptions!$C$30)^1) -> 353600 | ... Z8: =Production!Z6*(Assumptions!$C$29*(1+Assumptions!$C$30)^1) -> 353600 | AA8: =SUM(O8:Z8) -> 4243200 | AB8: =Production!AB6*(Assumptions!$C$29*(1+Assumptions!$C$30)^2) -> 389376 | AC8: =Production!AC6*(Assumptions!$C$29*(1+Assumptions!$C$30)^2) -> 389376 | AD8: =Production!AD6*(Assumptions!$C$29*(1+Assumptions!$C$30)^2) -> 389376 | AE8: =Production!AE6*(Assumptions!$C$29*(1+Assumptions!$C$30)^2) -> 389376 | AF8: =Production!AF6*(Assumptions!$C$29*(1+Assumptions!$C$30)^2) -> 389376 | AG8: =Production!AG6*(Assumptions!$C$29*(1+Assumptions!$C$30)^2) -> 389376 | AH8: =Production!AH6*(Assumptions!$C$29*(1+Assumptions!$C$30)^2) -> 389376 | AI8: =Production!AI6*(Assumptions!$C$29*(1+Assumptions!$C$30)^2) -> 389376 | ... AM8: =Production!AM6*(Assumptions!$C$29*(1+Assumptions!$C$30)^2) -> 389376 | AN8: =SUM(AB8:AM8) -> 4672512 | AO8: =Production!AO6*(Assumptions!$C$29*(1+Assumptions!$C$30)^3) -> 427448.32 | AP8: =Production!AP6*(Assumptions!$C$29*(1+Assumptions!$C$30)^3) -> 427448.32 | AQ8: =Production!AQ6*(Assumptions!$C$29*(1+Assumptions!$C$30)^3) -> 427448.32 | AR8: =Production!AR6*(Assumptions!$C$29*(1+Assumptions!$C$30)^3) -> 427448.32 | AS8: =Production!AS6*(Assumptions!$C$29*(1+Assumptions!$C$30)^3) -> 427448.32 | AT8: =Production!AT6*(Assumptions!$C$29*(1+Assumptions!$C$30)^3) -> 427448.32 | AU8: =Production!AU6*(Assumptions!$C$29*(1+Assumptions!$C$30)^3) -> 427448.32 | AV8: =Production!AV6*(Assumptions!$C$29*(1+Assumptions!$C$30)^3) -> 427448.32 | ... AZ8: =Production!AZ6*(Assumptions!$C$29*(1+Assumptions!$C$30)^3) -> 427448.32 | BA8: =SUM(AO8:AZ8) -> 5129379.8 | BB8: =Production!BB6*(Assumptions!$C$29*(1+Assumptions!$C$30)^4) -> 467943.42 | BC8: =Production!BC6*(Assumptions!$C$29*(1+Assumptions!$C$30)^4) -> 467943.42 | BD8: =Production!BD6*(Assumptions!$C$29*(1+Assumptions!$C$30)^4) -> 467943.42 | BE8: =Production!BE6*(Assumptions!$C$29*(1+Assumptions!$C$30)^4) -> 467943.42 | BF8: =Production!BF6*(Assumptions!$C$29*(1+Assumptions!$C$30)^4) -> 467943.42 | BG8: =Production!BG6*(Assumptions!$C$29*(1+Assumptions!$C$30)^4) -> 467943.42 | BH8: =Production!BH6*(Assumptions!$C$29*(1+Assumptions!$C$30)^4) -> 467943.42 | BI8: =Production!BI6*(Assumptions!$C$29*(1+Assumptions!$C$30)^4) -> 467943.42 | ... BM8: =Production!BM6*(Assumptions!$C$29*(1+Assumptions!$C$30)^4) -> 467943.42 | BN8: =SUM(BB8:BM8) -> 5615321.1
A9: =IFERROR(VLOOKUP(Assumptions!$J$5,Assumptions!$S$5:$Z$21,8,FALSE()),"Factory overheads") -> Operating overheads | B9: =Assumptions!$C$34*(1+Assumptions!$C$35)^0 -> 100000 | C9: =Assumptions!$C$34*(1+Assumptions!$C$35)^0 -> 100000 | D9: =Assumptions!$C$34*(1+Assumptions!$C$35)^0 -> 100000 | E9: =Assumptions!$C$34*(1+Assumptions!$C$35)^0 -> 100000 | F9: =Assumptions!$C$34*(1+Assumptions!$C$35)^0 -> 100000 | G9: =Assumptions!$C$34*(1+Assumptions!$C$35)^0 -> 100000 | H9: =Assumptions!$C$34*(1+Assumptions!$C$35)^0 -> 100000 | I9: =Assumptions!$C$34*(1+Assumptions!$C$35)^0 -> 100000 | ... M9: =Assumptions!$C$34*(1+Assumptions!$C$35)^0 -> 100000 | N9: =SUM(B9:M9) -> 1200000 | O9: =Assumptions!$C$34*(1+Assumptions!$C$35)^1 -> 105000 | P9: =Assumptions!$C$34*(1+Assumptions!$C$35)^1 -> 105000 | Q9: =Assumptions!$C$34*(1+Assumptions!$C$35)^1 -> 105000 | R9: =Assumptions!$C$34*(1+Assumptions!$C$35)^1 -> 105000 | S9: =Assumptions!$C$34*(1+Assumptions!$C$35)^1 -> 105000 | T9: =Assumptions!$C$34*(1+Assumptions!$C$35)^1 -> 105000 | U9: =Assumptions!$C$34*(1+Assumptions!$C$35)^1 -> 105000 | V9: =Assumptions!$C$34*(1+Assumptions!$C$35)^1 -> 105000 | ... Z9: =Assumptions!$C$34*(1+Assumptions!$C$35)^1 -> 105000 | AA9: =SUM(O9:Z9) -> 1260000 | AB9: =Assumptions!$C$34*(1+Assumptions!$C$35)^2 -> 110250 | AC9: =Assumptions!$C$34*(1+Assumptions!$C$35)^2 -> 110250 | AD9: =Assumptions!$C$34*(1+Assumptions!$C$35)^2 -> 110250 | AE9: =Assumptions!$C$34*(1+Assumptions!$C$35)^2 -> 110250 | AF9: =Assumptions!$C$34*(1+Assumptions!$C$35)^2 -> 110250 | AG9: =Assumptions!$C$34*(1+Assumptions!$C$35)^2 -> 110250 | AH9: =Assumptions!$C$34*(1+Assumptions!$C$35)^2 -> 110250 | AI9: =Assumptions!$C$34*(1+Assumptions!$C$35)^2 -> 110250 | ... AM9: =Assumptions!$C$34*(1+Assumptions!$C$35)^2 -> 110250 | AN9: =SUM(AB9:AM9) -> 1323000 | AO9: =Assumptions!$C$34*(1+Assumptions!$C$35)^3 -> 115762.5 | AP9: =Assumptions!$C$34*(1+Assumptions!$C$35)^3 -> 115762.5 | AQ9: =Assumptions!$C$34*(1+Assumptions!$C$35)^3 -> 115762.5 | AR9: =Assumptions!$C$34*(1+Assumptions!$C$35)^3 -> 115762.5 | AS9: =Assumptions!$C$34*(1+Assumptions!$C$35)^3 -> 115762.5 | AT9: =Assumptions!$C$34*(1+Assumptions!$C$35)^3 -> 115762.5 | AU9: =Assumptions!$C$34*(1+Assumptions!$C$35)^3 -> 115762.5 | AV9: =Assumptions!$C$34*(1+Assumptions!$C$35)^3 -> 115762.5 | ... AZ9: =Assumptions!$C$34*(1+Assumptions!$C$35)^3 -> 115762.5 | BA9: =SUM(AO9:AZ9) -> 1389150 | BB9: =Assumptions!$C$34*(1+Assumptions!$C$35)^4 -> 121550.62 | BC9: =Assumptions!$C$34*(1+Assumptions!$C$35)^4 -> 121550.62 | BD9: =Assumptions!$C$34*(1+Assumptions!$C$35)^4 -> 121550.62 | BE9: =Assumptions!$C$34*(1+Assumptions!$C$35)^4 -> 121550.62 | BF9: =Assumptions!$C$34*(1+Assumptions!$C$35)^4 -> 121550.62 | BG9: =Assumptions!$C$34*(1+Assumptions!$C$35)^4 -> 121550.62 | BH9: =Assumptions!$C$34*(1+Assumptions!$C$35)^4 -> 121550.62 | BI9: =Assumptions!$C$34*(1+Assumptions!$C$35)^4 -> 121550.62 | ... BM9: =Assumptions!$C$34*(1+Assumptions!$C$35)^4 -> 121550.62 | BN9: =SUM(BB9:BM9) -> 1458607.5
A10: Repairs & maintenance | B10: =Assumptions!$C$36*(1+Assumptions!$C$37)^0 -> 20000 | C10: =Assumptions!$C$36*(1+Assumptions!$C$37)^0 -> 20000 | D10: =Assumptions!$C$36*(1+Assumptions!$C$37)^0 -> 20000 | E10: =Assumptions!$C$36*(1+Assumptions!$C$37)^0 -> 20000 | F10: =Assumptions!$C$36*(1+Assumptions!$C$37)^0 -> 20000 | G10: =Assumptions!$C$36*(1+Assumptions!$C$37)^0 -> 20000 | H10: =Assumptions!$C$36*(1+Assumptions!$C$37)^0 -> 20000 | I10: =Assumptions!$C$36*(1+Assumptions!$C$37)^0 -> 20000 | ... M10: =Assumptions!$C$36*(1+Assumptions!$C$37)^0 -> 20000 | N10: =SUM(B10:M10) -> 240000 | O10: =Assumptions!$C$36*(1+Assumptions!$C$37)^1 -> 20800 | P10: =Assumptions!$C$36*(1+Assumptions!$C$37)^1 -> 20800 | Q10: =Assumptions!$C$36*(1+Assumptions!$C$37)^1 -> 20800 | R10: =Assumptions!$C$36*(1+Assumptions!$C$37)^1 -> 20800 | S10: =Assumptions!$C$36*(1+Assumptions!$C$37)^1 -> 20800 | T10: =Assumptions!$C$36*(1+Assumptions!$C$37)^1 -> 20800 | U10: =Assumptions!$C$36*(1+Assumptions!$C$37)^1 -> 20800 | V10: =Assumptions!$C$36*(1+Assumptions!$C$37)^1 -> 20800 | ... Z10: =Assumptions!$C$36*(1+Assumptions!$C$37)^1 -> 20800 | AA10: =SUM(O10:Z10) -> 249600 | AB10: =Assumptions!$C$36*(1+Assumptions!$C$37)^2 -> 21632 | AC10: =Assumptions!$C$36*(1+Assumptions!$C$37)^2 -> 21632 | AD10: =Assumptions!$C$36*(1+Assumptions!$C$37)^2 -> 21632 | AE10: =Assumptions!$C$36*(1+Assumptions!$C$37)^2 -> 21632 | AF10: =Assumptions!$C$36*(1+Assumptions!$C$37)^2 -> 21632 | AG10: =Assumptions!$C$36*(1+Assumptions!$C$37)^2 -> 21632 | AH10: =Assumptions!$C$36*(1+Assumptions!$C$37)^2 -> 21632 | AI10: =Assumptions!$C$36*(1+Assumptions!$C$37)^2 -> 21632 | ... AM10: =Assumptions!$C$36*(1+Assumptions!$C$37)^2 -> 21632 | AN10: =SUM(AB10:AM10) -> 259584 | AO10: =Assumptions!$C$36*(1+Assumptions!$C$37)^3 -> 22497.28 | AP10: =Assumptions!$C$36*(1+Assumptions!$C$37)^3 -> 22497.28 | AQ10: =Assumptions!$C$36*(1+Assumptions!$C$37)^3 -> 22497.28 | AR10: =Assumptions!$C$36*(1+Assumptions!$C$37)^3 -> 22497.28 | AS10: =Assumptions!$C$36*(1+Assumptions!$C$37)^3 -> 22497.28 | AT10: =Assumptions!$C$36*(1+Assumptions!$C$37)^3 -> 22497.28 | AU10: =Assumptions!$C$36*(1+Assumptions!$C$37)^3 -> 22497.28 | AV10: =Assumptions!$C$36*(1+Assumptions!$C$37)^3 -> 22497.28 | ... AZ10: =Assumptions!$C$36*(1+Assumptions!$C$37)^3 -> 22497.28 | BA10: =SUM(AO10:AZ10) -> 269967.36 | BB10: =Assumptions!$C$36*(1+Assumptions!$C$37)^4 -> 23397.171 | BC10: =Assumptions!$C$36*(1+Assumptions!$C$37)^4 -> 23397.171 | BD10: =Assumptions!$C$36*(1+Assumptions!$C$37)^4 -> 23397.171 | BE10: =Assumptions!$C$36*(1+Assumptions!$C$37)^4 -> 23397.171 | BF10: =Assumptions!$C$36*(1+Assumptions!$C$37)^4 -> 23397.171 | BG10: =Assumptions!$C$36*(1+Assumptions!$C$37)^4 -> 23397.171 | BH10: =Assumptions!$C$36*(1+Assumptions!$C$37)^4 -> 23397.171 | BI10: =Assumptions!$C$36*(1+Assumptions!$C$37)^4 -> 23397.171 | ... BM10: =Assumptions!$C$36*(1+Assumptions!$C$37)^4 -> 23397.171 | BN10: =SUM(BB10:BM10) -> 280766.05
A11: Administrative expenses | B11: =Assumptions!$C$38*(1+Assumptions!$C$39)^0 -> 50000 | C11: =Assumptions!$C$38*(1+Assumptions!$C$39)^0 -> 50000 | D11: =Assumptions!$C$38*(1+Assumptions!$C$39)^0 -> 50000 | E11: =Assumptions!$C$38*(1+Assumptions!$C$39)^0 -> 50000 | F11: =Assumptions!$C$38*(1+Assumptions!$C$39)^0 -> 50000 | G11: =Assumptions!$C$38*(1+Assumptions!$C$39)^0 -> 50000 | H11: =Assumptions!$C$38*(1+Assumptions!$C$39)^0 -> 50000 | I11: =Assumptions!$C$38*(1+Assumptions!$C$39)^0 -> 50000 | ... M11: =Assumptions!$C$38*(1+Assumptions!$C$39)^0 -> 50000 | N11: =SUM(B11:M11) -> 600000 | O11: =Assumptions!$C$38*(1+Assumptions!$C$39)^1 -> 52500 | P11: =Assumptions!$C$38*(1+Assumptions!$C$39)^1 -> 52500 | Q11: =Assumptions!$C$38*(1+Assumptions!$C$39)^1 -> 52500 | R11: =Assumptions!$C$38*(1+Assumptions!$C$39)^1 -> 52500 | S11: =Assumptions!$C$38*(1+Assumptions!$C$39)^1 -> 52500 | T11: =Assumptions!$C$38*(1+Assumptions!$C$39)^1 -> 52500 | U11: =Assumptions!$C$38*(1+Assumptions!$C$39)^1 -> 52500 | V11: =Assumptions!$C$38*(1+Assumptions!$C$39)^1 -> 52500 | ... Z11: =Assumptions!$C$38*(1+Assumptions!$C$39)^1 -> 52500 | AA11: =SUM(O11:Z11) -> 630000 | AB11: =Assumptions!$C$38*(1+Assumptions!$C$39)^2 -> 55125 | AC11: =Assumptions!$C$38*(1+Assumptions!$C$39)^2 -> 55125 | AD11: =Assumptions!$C$38*(1+Assumptions!$C$39)^2 -> 55125 | AE11: =Assumptions!$C$38*(1+Assumptions!$C$39)^2 -> 55125 | AF11: =Assumptions!$C$38*(1+Assumptions!$C$39)^2 -> 55125 | AG11: =Assumptions!$C$38*(1+Assumptions!$C$39)^2 -> 55125 | AH11: =Assumptions!$C$38*(1+Assumptions!$C$39)^2 -> 55125 | AI11: =Assumptions!$C$38*(1+Assumptions!$C$39)^2 -> 55125 | ... AM11: =Assumptions!$C$38*(1+Assumptions!$C$39)^2 -> 55125 | AN11: =SUM(AB11:AM11) -> 661500 | AO11: =Assumptions!$C$38*(1+Assumptions!$C$39)^3 -> 57881.25 | AP11: =Assumptions!$C$38*(1+Assumptions!$C$39)^3 -> 57881.25 | AQ11: =Assumptions!$C$38*(1+Assumptions!$C$39)^3 -> 57881.25 | AR11: =Assumptions!$C$38*(1+Assumptions!$C$39)^3 -> 57881.25 | AS11: =Assumptions!$C$38*(1+Assumptions!$C$39)^3 -> 57881.25 | AT11: =Assumptions!$C$38*(1+Assumptions!$C$39)^3 -> 57881.25 | AU11: =Assumptions!$C$38*(1+Assumptions!$C$39)^3 -> 57881.25 | AV11: =Assumptions!$C$38*(1+Assumptions!$C$39)^3 -> 57881.25 | ... AZ11: =Assumptions!$C$38*(1+Assumptions!$C$39)^3 -> 57881.25 | BA11: =SUM(AO11:AZ11) -> 694575 | BB11: =Assumptions!$C$38*(1+Assumptions!$C$39)^4 -> 60775.312 | BC11: =Assumptions!$C$38*(1+Assumptions!$C$39)^4 -> 60775.312 | BD11: =Assumptions!$C$38*(1+Assumptions!$C$39)^4 -> 60775.312 | BE11: =Assumptions!$C$38*(1+Assumptions!$C$39)^4 -> 60775.312 | BF11: =Assumptions!$C$38*(1+Assumptions!$C$39)^4 -> 60775.312 | BG11: =Assumptions!$C$38*(1+Assumptions!$C$39)^4 -> 60775.312 | BH11: =Assumptions!$C$38*(1+Assumptions!$C$39)^4 -> 60775.312 | BI11: =Assumptions!$C$38*(1+Assumptions!$C$39)^4 -> 60775.312 | ... BM11: =Assumptions!$C$38*(1+Assumptions!$C$39)^4 -> 60775.312 | BN11: =SUM(BB11:BM11) -> 729303.75
A12: Selling & distribution | B12: =Sales!B7*Assumptions!$C$40 -> 192000 | C12: =Sales!C7*Assumptions!$C$40 -> 192000 | D12: =Sales!D7*Assumptions!$C$40 -> 192000 | E12: =Sales!E7*Assumptions!$C$40 -> 192000 | F12: =Sales!F7*Assumptions!$C$40 -> 192000 | G12: =Sales!G7*Assumptions!$C$40 -> 192000 | H12: =Sales!H7*Assumptions!$C$40 -> 192000 | I12: =Sales!I7*Assumptions!$C$40 -> 192000 | ... M12: =Sales!M7*Assumptions!$C$40 -> 192000 | N12: =SUM(B12:M12) -> 2304000 | O12: =Sales!O7*Assumptions!$C$40 -> 214200 | P12: =Sales!P7*Assumptions!$C$40 -> 214200 | Q12: =Sales!Q7*Assumptions!$C$40 -> 214200 | R12: =Sales!R7*Assumptions!$C$40 -> 214200 | S12: =Sales!S7*Assumptions!$C$40 -> 214200 | T12: =Sales!T7*Assumptions!$C$40 -> 214200 | U12: =Sales!U7*Assumptions!$C$40 -> 214200 | V12: =Sales!V7*Assumptions!$C$40 -> 214200 | ... Z12: =Sales!Z7*Assumptions!$C$40 -> 214200 | AA12: =SUM(O12:Z12) -> 2570400 | AB12: =Sales!AB7*Assumptions!$C$40 -> 238140 | AC12: =Sales!AC7*Assumptions!$C$40 -> 238140 | AD12: =Sales!AD7*Assumptions!$C$40 -> 238140 | AE12: =Sales!AE7*Assumptions!$C$40 -> 238140 | AF12: =Sales!AF7*Assumptions!$C$40 -> 238140 | AG12: =Sales!AG7*Assumptions!$C$40 -> 238140 | AH12: =Sales!AH7*Assumptions!$C$40 -> 238140 | AI12: =Sales!AI7*Assumptions!$C$40 -> 238140 | ... AM12: =Sales!AM7*Assumptions!$C$40 -> 238140 | AN12: =SUM(AB12:AM12) -> 2857680 | AO12: =Sales!AO7*Assumptions!$C$40 -> 263938.5 | AP12: =Sales!AP7*Assumptions!$C$40 -> 263938.5 | AQ12: =Sales!AQ7*Assumptions!$C$40 -> 263938.5 | AR12: =Sales!AR7*Assumptions!$C$40 -> 263938.5 | AS12: =Sales!AS7*Assumptions!$C$40 -> 263938.5 | AT12: =Sales!AT7*Assumptions!$C$40 -> 263938.5 | AU12: =Sales!AU7*Assumptions!$C$40 -> 263938.5 | AV12: =Sales!AV7*Assumptions!$C$40 -> 263938.5 | ... AZ12: =Sales!AZ7*Assumptions!$C$40 -> 263938.5 | BA12: =SUM(AO12:AZ12) -> 3167262 | BB12: =Sales!BB7*Assumptions!$C$40 -> 291721.5 | BC12: =Sales!BC7*Assumptions!$C$40 -> 291721.5 | BD12: =Sales!BD7*Assumptions!$C$40 -> 291721.5 | BE12: =Sales!BE7*Assumptions!$C$40 -> 291721.5 | BF12: =Sales!BF7*Assumptions!$C$40 -> 291721.5 | BG12: =Sales!BG7*Assumptions!$C$40 -> 291721.5 | BH12: =Sales!BH7*Assumptions!$C$40 -> 291721.5 | BI12: =Sales!BI7*Assumptions!$C$40 -> 291721.5 | ... BM12: =Sales!BM7*Assumptions!$C$40 -> 291721.5 | BN12: =SUM(BB12:BM12) -> 3500658
A13: Depreciation | B13: =(Assumptions!$C$43*Assumptions!$C$44+Assumptions!$C$45*Assumptions!$C$46+Assumptions!$C$47*Assumptions!$C$48)/12 -> 7916.6667 | C13: =(Assumptions!$C$43*Assumptions!$C$44+Assumptions!$C$45*Assumptions!$C$46+Assumptions!$C$47*Assumptions!$C$48)/12 -> 7916.6667 | D13: =(Assumptions!$C$43*Assumptions!$C$44+Assumptions!$C$45*Assumptions!$C$46+Assumptions!$C$47*Assumptions!$C$48)/12 -> 7916.6667 | E13: =(Assumptions!$C$43*Assumptions!$C$44+Assumptions!$C$45*Assumptions!$C$46+Assumptions!$C$47*Assumptions!$C$48)/12 -> 7916.6667 | F13: =(Assumptions!$C$43*Assumptions!$C$44+Assumptions!$C$45*Assumptions!$C$46+Assumptions!$C$47*Assumptions!$C$48)/12 -> 7916.6667 | G13: =(Assumptions!$C$43*Assumptions!$C$44+Assumptions!$C$45*Assumptions!$C$46+Assumptions!$C$47*Assumptions!$C$48)/12 -> 7916.6667 | H13: =(Assumptions!$C$43*Assumptions!$C$44+Assumptions!$C$45*Assumptions!$C$46+Assumptions!$C$47*Assumptions!$C$48)/12 -> 7916.6667 | I13: =(Assumptions!$C$43*Assumptions!$C$44+Assumptions!$C$45*Assumptions!$C$46+Assumptions!$C$47*Assumptions!$C$48)/12 -> 7916.6667 | ... M13: =(Assumptions!$C$43*Assumptions!$C$44+Assumptions!$C$45*Assumptions!$C$46+Assumptions!$C$47*Assumptions!$C$48)/12 -> 7916.6667 | N13: =SUM(B13:M13) -> 95000 | O13: =(Assumptions!$C$43*Assumptions!$C$44+Assumptions!$C$45*Assumptions!$C$46+Assumptions!$C$47*Assumptions!$C$48)/12 -> 7916.6667 | P13: =(Assumptions!$C$43*Assumptions!$C$44+Assumptions!$C$45*Assumptions!$C$46+Assumptions!$C$47*Assumptions!$C$48)/12 -> 7916.6667 | Q13: =(Assumptions!$C$43*Assumptions!$C$44+Assumptions!$C$45*Assumptions!$C$46+Assumptions!$C$47*Assumptions!$C$48)/12 -> 7916.6667 | R13: =(Assumptions!$C$43*Assumptions!$C$44+Assumptions!$C$45*Assumptions!$C$46+Assumptions!$C$47*Assumptions!$C$48)/12 -> 7916.6667 | S13: =(Assumptions!$C$43*Assumptions!$C$44+Assumptions!$C$45*Assumptions!$C$46+Assumptions!$C$47*Assumptions!$C$48)/12 -> 7916.6667 | T13: =(Assumptions!$C$43*Assumptions!$C$44+Assumptions!$C$45*Assumptions!$C$46+Assumptions!$C$47*Assumptions!$C$48)/12 -> 7916.6667 | U13: =(Assumptions!$C$43*Assumptions!$C$44+Assumptions!$C$45*Assumptions!$C$46+Assumptions!$C$47*Assumptions!$C$48)/12 -> 7916.6667 | V13: =(Assumptions!$C$43*Assumptions!$C$44+Assumptions!$C$45*Assumptions!$C$46+Assumptions!$C$47*Assumptions!$C$48)/12 -> 7916.6667 | ... Z13: =(Assumptions!$C$43*Assumptions!$C$44+Assumptions!$C$45*Assumptions!$C$46+Assumptions!$C$47*Assumptions!$C$48)/12 -> 7916.6667 | AA13: =SUM(O13:Z13) -> 95000 | AB13: =(Assumptions!$C$43*Assumptions!$C$44+Assumptions!$C$45*Assumptions!$C$46+Assumptions!$C$47*Assumptions!$C$48)/12 -> 7916.6667 | AC13: =(Assumptions!$C$43*Assumptions!$C$44+Assumptions!$C$45*Assumptions!$C$46+Assumptions!$C$47*Assumptions!$C$48)/12 -> 7916.6667 | AD13: =(Assumptions!$C$43*Assumptions!$C$44+Assumptions!$C$45*Assumptions!$C$46+Assumptions!$C$47*Assumptions!$C$48)/12 -> 7916.6667 | AE13: =(Assumptions!$C$43*Assumptions!$C$44+Assumptions!$C$45*Assumptions!$C$46+Assumptions!$C$47*Assumptions!$C$48)/12 -> 7916.6667 | AF13: =(Assumptions!$C$43*Assumptions!$C$44+Assumptions!$C$45*Assumptions!$C$46+Assumptions!$C$47*Assumptions!$C$48)/12 -> 7916.6667 | AG13: =(Assumptions!$C$43*Assumptions!$C$44+Assumptions!$C$45*Assumptions!$C$46+Assumptions!$C$47*Assumptions!$C$48)/12 -> 7916.6667 | AH13: =(Assumptions!$C$43*Assumptions!$C$44+Assumptions!$C$45*Assumptions!$C$46+Assumptions!$C$47*Assumptions!$C$48)/12 -> 7916.6667 | AI13: =(Assumptions!$C$43*Assumptions!$C$44+Assumptions!$C$45*Assumptions!$C$46+Assumptions!$C$47*Assumptions!$C$48)/12 -> 7916.6667 | ... AM13: =(Assumptions!$C$43*Assumptions!$C$44+Assumptions!$C$45*Assumptions!$C$46+Assumptions!$C$47*Assumptions!$C$48)/12 -> 7916.6667 | AN13: =SUM(AB13:AM13) -> 95000 | AO13: =(Assumptions!$C$43*Assumptions!$C$44+Assumptions!$C$45*Assumptions!$C$46+Assumptions!$C$47*Assumptions!$C$48)/12 -> 7916.6667 | AP13: =(Assumptions!$C$43*Assumptions!$C$44+Assumptions!$C$45*Assumptions!$C$46+Assumptions!$C$47*Assumptions!$C$48)/12 -> 7916.6667 | AQ13: =(Assumptions!$C$43*Assumptions!$C$44+Assumptions!$C$45*Assumptions!$C$46+Assumptions!$C$47*Assumptions!$C$48)/12 -> 7916.6667 | AR13: =(Assumptions!$C$43*Assumptions!$C$44+Assumptions!$C$45*Assumptions!$C$46+Assumptions!$C$47*Assumptions!$C$48)/12 -> 7916.6667 | AS13: =(Assumptions!$C$43*Assumptions!$C$44+Assumptions!$C$45*Assumptions!$C$46+Assumptions!$C$47*Assumptions!$C$48)/12 -> 7916.6667 | AT13: =(Assumptions!$C$43*Assumptions!$C$44+Assumptions!$C$45*Assumptions!$C$46+Assumptions!$C$47*Assumptions!$C$48)/12 -> 7916.6667 | AU13: =(Assumptions!$C$43*Assumptions!$C$44+Assumptions!$C$45*Assumptions!$C$46+Assumptions!$C$47*Assumptions!$C$48)/12 -> 7916.6667 | AV13: =(Assumptions!$C$43*Assumptions!$C$44+Assumptions!$C$45*Assumptions!$C$46+Assumptions!$C$47*Assumptions!$C$48)/12 -> 7916.6667 | ... AZ13: =(Assumptions!$C$43*Assumptions!$C$44+Assumptions!$C$45*Assumptions!$C$46+Assumptions!$C$47*Assumptions!$C$48)/12 -> 7916.6667 | BA13: =SUM(AO13:AZ13) -> 95000 | BB13: =(Assumptions!$C$43*Assumptions!$C$44+Assumptions!$C$45*Assumptions!$C$46+Assumptions!$C$47*Assumptions!$C$48)/12 -> 7916.6667 | BC13: =(Assumptions!$C$43*Assumptions!$C$44+Assumptions!$C$45*Assumptions!$C$46+Assumptions!$C$47*Assumptions!$C$48)/12 -> 7916.6667 | BD13: =(Assumptions!$C$43*Assumptions!$C$44+Assumptions!$C$45*Assumptions!$C$46+Assumptions!$C$47*Assumptions!$C$48)/12 -> 7916.6667 | BE13: =(Assumptions!$C$43*Assumptions!$C$44+Assumptions!$C$45*Assumptions!$C$46+Assumptions!$C$47*Assumptions!$C$48)/12 -> 7916.6667 | BF13: =(Assumptions!$C$43*Assumptions!$C$44+Assumptions!$C$45*Assumptions!$C$46+Assumptions!$C$47*Assumptions!$C$48)/12 -> 7916.6667 | BG13: =(Assumptions!$C$43*Assumptions!$C$44+Assumptions!$C$45*Assumptions!$C$46+Assumptions!$C$47*Assumptions!$C$48)/12 -> 7916.6667 | BH13: =(Assumptions!$C$43*Assumptions!$C$44+Assumptions!$C$45*Assumptions!$C$46+Assumptions!$C$47*Assumptions!$C$48)/12 -> 7916.6667 | BI13: =(Assumptions!$C$43*Assumptions!$C$44+Assumptions!$C$45*Assumptions!$C$46+Assumptions!$C$47*Assumptions!$C$48)/12 -> 7916.6667 | ... BM13: =(Assumptions!$C$43*Assumptions!$C$44+Assumptions!$C$45*Assumptions!$C$46+Assumptions!$C$47*Assumptions!$C$48)/12 -> 7916.6667 | BN13: =SUM(BB13:BM13) -> 95000
A14: Interest — Term Loan | B14: =Repayment!C6/12 -> 35000 | C14: =Repayment!C6/12 -> 35000 | D14: =Repayment!C6/12 -> 35000 | E14: =Repayment!C6/12 -> 35000 | F14: =Repayment!C6/12 -> 35000 | G14: =Repayment!C6/12 -> 35000 | H14: =Repayment!C6/12 -> 35000 | I14: =Repayment!C6/12 -> 35000 | J14: =Repayment!C6/12 -> 35000 | K14: =Repayment!C6/12 -> 35000 | L14: =Repayment!C6/12 -> 35000 | M14: =Repayment!C6/12 -> 35000 | N14: =SUM(B14:M14) -> 420000 | O14: =Repayment!D6/12 -> 27222.222 | P14: =Repayment!D6/12 -> 27222.222 | Q14: =Repayment!D6/12 -> 27222.222 | R14: =Repayment!D6/12 -> 27222.222 | S14: =Repayment!D6/12 -> 27222.222 | T14: =Repayment!D6/12 -> 27222.222 | U14: =Repayment!D6/12 -> 27222.222 | V14: =Repayment!D6/12 -> 27222.222 | W14: =Repayment!D6/12 -> 27222.222 | X14: =Repayment!D6/12 -> 27222.222 | Y14: =Repayment!D6/12 -> 27222.222 | Z14: =Repayment!D6/12 -> 27222.222 | AA14: =SUM(O14:Z14) -> 326666.67 | AB14: =Repayment!E6/12 -> 19444.444 | AC14: =Repayment!E6/12 -> 19444.444 | AD14: =Repayment!E6/12 -> 19444.444 | AE14: =Repayment!E6/12 -> 19444.444 | AF14: =Repayment!E6/12 -> 19444.444 | AG14: =Repayment!E6/12 -> 19444.444 | AH14: =Repayment!E6/12 -> 19444.444 | AI14: =Repayment!E6/12 -> 19444.444 | AJ14: =Repayment!E6/12 -> 19444.444 | AK14: =Repayment!E6/12 -> 19444.444 | AL14: =Repayment!E6/12 -> 19444.444 | AM14: =Repayment!E6/12 -> 19444.444 | AN14: =SUM(AB14:AM14) -> 233333.33 | AO14: =Repayment!F6/12 -> 11666.667 | AP14: =Repayment!F6/12 -> 11666.667 | AQ14: =Repayment!F6/12 -> 11666.667 | AR14: =Repayment!F6/12 -> 11666.667 | AS14: =Repayment!F6/12 -> 11666.667 | AT14: =Repayment!F6/12 -> 11666.667 | AU14: =Repayment!F6/12 -> 11666.667 | AV14: =Repayment!F6/12 -> 11666.667 | AW14: =Repayment!F6/12 -> 11666.667 | AX14: =Repayment!F6/12 -> 11666.667 | AY14: =Repayment!F6/12 -> 11666.667 | AZ14: =Repayment!F6/12 -> 11666.667 | BA14: =SUM(AO14:AZ14) -> 140000 | BB14: =Repayment!G6/12 -> 3888.8889 | BC14: =Repayment!G6/12 -> 3888.8889 | BD14: =Repayment!G6/12 -> 3888.8889 | BE14: =Repayment!G6/12 -> 3888.8889 | BF14: =Repayment!G6/12 -> 3888.8889 | BG14: =Repayment!G6/12 -> 3888.8889 | BH14: =Repayment!G6/12 -> 3888.8889 | BI14: =Repayment!G6/12 -> 3888.8889 | BJ14: =Repayment!G6/12 -> 3888.8889 | BK14: =Repayment!G6/12 -> 3888.8889 | BL14: =Repayment!G6/12 -> 3888.8889 | BM14: =Repayment!G6/12 -> 3888.8889 | BN14: =SUM(BB14:BM14) -> 46666.667
A15: Interest — Working Capital | B15: =Form_V_MPBF!C11*Assumptions!$C$13/12 -> 22686.986 | C15: =Form_V_MPBF!C11*Assumptions!$C$13/12 -> 22686.986 | D15: =Form_V_MPBF!C11*Assumptions!$C$13/12 -> 22686.986 | E15: =Form_V_MPBF!C11*Assumptions!$C$13/12 -> 22686.986 | F15: =Form_V_MPBF!C11*Assumptions!$C$13/12 -> 22686.986 | G15: =Form_V_MPBF!C11*Assumptions!$C$13/12 -> 22686.986 | H15: =Form_V_MPBF!C11*Assumptions!$C$13/12 -> 22686.986 | I15: =Form_V_MPBF!C11*Assumptions!$C$13/12 -> 22686.986 | J15: =Form_V_MPBF!C11*Assumptions!$C$13/12 -> 22686.986 | K15: =Form_V_MPBF!C11*Assumptions!$C$13/12 -> 22686.986 | L15: =Form_V_MPBF!C11*Assumptions!$C$13/12 -> 22686.986 | M15: =Form_V_MPBF!C11*Assumptions!$C$13/12 -> 22686.986 | N15: =SUM(B15:M15) -> 272243.84 | O15: =Form_V_MPBF!D11*Assumptions!$C$13/12 -> 24775.973 | P15: =Form_V_MPBF!D11*Assumptions!$C$13/12 -> 24775.973 | Q15: =Form_V_MPBF!D11*Assumptions!$C$13/12 -> 24775.973 | R15: =Form_V_MPBF!D11*Assumptions!$C$13/12 -> 24775.973 | S15: =Form_V_MPBF!D11*Assumptions!$C$13/12 -> 24775.973 | T15: =Form_V_MPBF!D11*Assumptions!$C$13/12 -> 24775.973 | U15: =Form_V_MPBF!D11*Assumptions!$C$13/12 -> 24775.973 | V15: =Form_V_MPBF!D11*Assumptions!$C$13/12 -> 24775.973 | W15: =Form_V_MPBF!D11*Assumptions!$C$13/12 -> 24775.973 | X15: =Form_V_MPBF!D11*Assumptions!$C$13/12 -> 24775.973 | Y15: =Form_V_MPBF!D11*Assumptions!$C$13/12 -> 24775.973 | Z15: =Form_V_MPBF!D11*Assumptions!$C$13/12 -> 24775.973 | AA15: =SUM(O15:Z15) -> 297311.67 | AB15: =Form_V_MPBF!E11*Assumptions!$C$13/12 -> 27013.022 | AC15: =Form_V_MPBF!E11*Assumptions!$C$13/12 -> 27013.022 | AD15: =Form_V_MPBF!E11*Assumptions!$C$13/12 -> 27013.022 | AE15: =Form_V_MPBF!E11*Assumptions!$C$13/12 -> 27013.022 | AF15: =Form_V_MPBF!E11*Assumptions!$C$13/12 -> 27013.022 | AG15: =Form_V_MPBF!E11*Assumptions!$C$13/12 -> 27013.022 | AH15: =Form_V_MPBF!E11*Assumptions!$C$13/12 -> 27013.022 | AI15: =Form_V_MPBF!E11*Assumptions!$C$13/12 -> 27013.022 | AJ15: =Form_V_MPBF!E11*Assumptions!$C$13/12 -> 27013.022 | AK15: =Form_V_MPBF!E11*Assumptions!$C$13/12 -> 27013.022 | AL15: =Form_V_MPBF!E11*Assumptions!$C$13/12 -> 27013.022 | AM15: =Form_V_MPBF!E11*Assumptions!$C$13/12 -> 27013.022 | AN15: =SUM(AB15:AM15) -> 324156.27 | AO15: =Form_V_MPBF!F11*Assumptions!$C$13/12 -> 29406.847 | AP15: =Form_V_MPBF!F11*Assumptions!$C$13/12 -> 29406.847 | AQ15: =Form_V_MPBF!F11*Assumptions!$C$13/12 -> 29406.847 | AR15: =Form_V_MPBF!F11*Assumptions!$C$13/12 -> 29406.847 | AS15: =Form_V_MPBF!F11*Assumptions!$C$13/12 -> 29406.847 | AT15: =Form_V_MPBF!F11*Assumptions!$C$13/12 -> 29406.847 | AU15: =Form_V_MPBF!F11*Assumptions!$C$13/12 -> 29406.847 | AV15: =Form_V_MPBF!F11*Assumptions!$C$13/12 -> 29406.847 | AW15: =Form_V_MPBF!F11*Assumptions!$C$13/12 -> 29406.847 | AX15: =Form_V_MPBF!F11*Assumptions!$C$13/12 -> 29406.847 | AY15: =Form_V_MPBF!F11*Assumptions!$C$13/12 -> 29406.847 | AZ15: =Form_V_MPBF!F11*Assumptions!$C$13/12 -> 29406.847 | BA15: =SUM(AO15:AZ15) -> 352882.17 | BB15: =Form_V_MPBF!G11*Assumptions!$C$13/12 -> 31966.604 | BC15: =Form_V_MPBF!G11*Assumptions!$C$13/12 -> 31966.604 | BD15: =Form_V_MPBF!G11*Assumptions!$C$13/12 -> 31966.604 | BE15: =Form_V_MPBF!G11*Assumptions!$C$13/12 -> 31966.604 | BF15: =Form_V_MPBF!G11*Assumptions!$C$13/12 -> 31966.604 | BG15: =Form_V_MPBF!G11*Assumptions!$C$13/12 -> 31966.604 | BH15: =Form_V_MPBF!G11*Assumptions!$C$13/12 -> 31966.604 | BI15: =Form_V_MPBF!G11*Assumptions!$C$13/12 -> 31966.604 | BJ15: =Form_V_MPBF!G11*Assumptions!$C$13/12 -> 31966.604 | BK15: =Form_V_MPBF!G11*Assumptions!$C$13/12 -> 31966.604 | BL15: =Form_V_MPBF!G11*Assumptions!$C$13/12 -> 31966.604 | BM15: =Form_V_MPBF!G11*Assumptions!$C$13/12 -> 31966.604 | BN15: =SUM(BB15:BM15) -> 383599.25
A16: Total Operating Expenses | B16: =SUM(B5:B15) -> 2747603.7 | C16: =SUM(C5:C15) -> 2747603.7 | D16: =SUM(D5:D15) -> 2747603.7 | E16: =SUM(E5:E15) -> 2747603.7 | F16: =SUM(F5:F15) -> 2747603.7 | G16: =SUM(G5:G15) -> 2747603.7 | H16: =SUM(H5:H15) -> 2747603.7 | I16: =SUM(I5:I15) -> 2747603.7 | ... M16: =SUM(M5:M15) -> 2747603.7 | N16: =SUM(B16:M16) -> 32971244 | O16: =SUM(O5:O15) -> 3029214.9 | P16: =SUM(P5:P15) -> 3029214.9 | Q16: =SUM(Q5:Q15) -> 3029214.9 | R16: =SUM(R5:R15) -> 3029214.9 | S16: =SUM(S5:S15) -> 3029214.9 | T16: =SUM(T5:T15) -> 3029214.9 | U16: =SUM(U5:U15) -> 3029214.9 | V16: =SUM(V5:V15) -> 3029214.9 | ... Z16: =SUM(Z5:Z15) -> 3029214.9 | AA16: =SUM(O16:Z16) -> 36350578 | AB16: =SUM(AB5:AB15) -> 3334145.1 | AC16: =SUM(AC5:AC15) -> 3334145.1 | AD16: =SUM(AD5:AD15) -> 3334145.1 | AE16: =SUM(AE5:AE15) -> 3334145.1 | AF16: =SUM(AF5:AF15) -> 3334145.1 | AG16: =SUM(AG5:AG15) -> 3334145.1 | AH16: =SUM(AH5:AH15) -> 3334145.1 | AI16: =SUM(AI5:AI15) -> 3334145.1 | ... AM16: =SUM(AM5:AM15) -> 3334145.1 | AN16: =SUM(AB16:AM16) -> 40009742 | AO16: =SUM(AO5:AO15) -> 3664088.5 | AP16: =SUM(AP5:AP15) -> 3664088.5 | AQ16: =SUM(AQ5:AQ15) -> 3664088.5 | AR16: =SUM(AR5:AR15) -> 3664088.5 | AS16: =SUM(AS5:AS15) -> 3664088.5 | AT16: =SUM(AT5:AT15) -> 3664088.5 | AU16: =SUM(AU5:AU15) -> 3664088.5 | AV16: =SUM(AV5:AV15) -> 3664088.5 | ... AZ16: =SUM(AZ5:AZ15) -> 3664088.5 | BA16: =SUM(AO16:AZ16) -> 43969062 | BB16: =SUM(BB5:BB15) -> 4020855.9 | BC16: =SUM(BC5:BC15) -> 4020855.9 | BD16: =SUM(BD5:BD15) -> 4020855.9 | BE16: =SUM(BE5:BE15) -> 4020855.9 | BF16: =SUM(BF5:BF15) -> 4020855.9 | BG16: =SUM(BG5:BG15) -> 4020855.9 | BH16: =SUM(BH5:BH15) -> 4020855.9 | BI16: =SUM(BI5:BI15) -> 4020855.9 | ... BM16: =SUM(BM5:BM15) -> 4020855.9 | BN16: =SUM(BB16:BM16) -> 48250271

Sheet Profit
A1: PROFITABILITY (P&L) — 60-MONTH PROJECTION
A2: EBITDA → EBIT → PBT → PAT, fully linked to Sales and Expenses.
B3: YEAR 1 | O3: YEAR 2 | AB3: YEAR 3 | AO3: YEAR 4 | BB3: YEAR 5
A4: Particulars | B4: M1 | C4: M2 | D4: M3 | E4: M4 | F4: M5 | G4: M6 | H4: M7 | I4: M8 | J4: M9 | K4: M10 | L4: M11 | M4: M12 | N4: Yr 1 Total | O4: M13 | P4: M14 | Q4: M15 | R4: M16 | S4: M17 | T4: M18 | U4: M19 | V4: M20 | W4: M21 | X4: M22 | Y4: M23 | Z4: M24 | AA4: Yr 2 Total | AB4: M25 | AC4: M26 | AD4: M27 | AE4: M28 | AF4: M29 | AG4: M30 | AH4: M31 | AI4: M32 | AJ4: M33 | AK4: M34 | AL4: M35 | AM4: M36 | AN4: Yr 3 Total | AO4: M37 | AP4: M38 | AQ4: M39 | AR4: M40 | AS4: M41 | AT4: M42 | AU4: M43 | AV4: M44 | AW4: M45 | AX4: M46 | AY4: M47 | AZ4: M48 | BA4: Yr 4 Total | BB4: M49 | BC4: M50 | BD4: M51 | BE4: M52 | BF4: M53 | BG4: M54 | BH4: M55 | BI4: M56 | BJ4: M57 | BK4: M58 | BL4: M59 | BM4: M60 | BN4: Yr 5 Total
A5: Net Sales | B5: =Sales!B7 -> 3840000 | C5: =Sales!C7 -> 3840000 | D5: =Sales!D7 -> 3840000 | E5: =Sales!E7 -> 3840000 | F5: =Sales!F7 -> 3840000 | G5: =Sales!G7 -> 3840000 | H5: =Sales!H7 -> 3840000 | I5: =Sales!I7 -> 3840000 | ... M5: =Sales!M7 -> 3840000 | N5: =SUM(B5:M5) -> 46080000 | O5: =Sales!O7 -> 4284000 | P5: =Sales!P7 -> 4284000 | Q5: =Sales!Q7 -> 4284000 | R5: =Sales!R7 -> 4284000 | S5: =Sales!S7 -> 4284000 | T5: =Sales!T7 -> 4284000 | U5: =Sales!U7 -> 4284000 | V5: =Sales!V7 -> 4284000 | ... Z5: =Sales!Z7 -> 4284000 | AA5: =SUM(O5:Z5) -> 51408000 | AB5: =Sales!AB7 -> 4762800 | AC5: =Sales!AC7 -> 4762800 | AD5: =Sales!AD7 -> 4762800 | AE5: =Sales!AE7 -> 4762800 | AF5: =Sales!AF7 -> 4762800 | AG5: =Sales!AG7 -> 4762800 | AH5: =Sales!AH7 -> 4762800 | AI5: =Sales!AI7 -> 4762800 | ... AM5: =Sales!AM7 -> 4762800 | AN5: =SUM(AB5:AM5) -> 57153600 | AO5: =Sales!AO7 -> 5278770 | AP5: =Sales!AP7 -> 5278770 | AQ5: =Sales!AQ7 -> 5278770 | AR5: =Sales!AR7 -> 5278770 | AS5: =Sales!AS7 -> 5278770 | AT5: =Sales!AT7 -> 5278770 | AU5: =Sales!AU7 -> 5278770 | AV5: =Sales!AV7 -> 5278770 | ... AZ5: =Sales!AZ7 -> 5278770 | BA5: =SUM(AO5:AZ5) -> 63345240 | BB5: =Sales!BB7 -> 5834430 | BC5: =Sales!BC7 -> 5834430 | BD5: =Sales!BD7 -> 5834430 | BE5: =Sales!BE7 -> 5834430 | BF5: =Sales!BF7 -> 5834430 | BG5: =Sales!BG7 -> 5834430 | BH5: =Sales!BH7 -> 5834430 | BI5: =Sales!BI7 -> 5834430 | ... BM5: =Sales!BM7 -> 5834430 | BN5: =SUM(BB5:BM5) -> 70013160
A6: =IFERROR("(-) "&VLOOKUP(Assumptions!$J$5,Assumptions!$S$5:$Z$21,5,FALSE()),"(-) Raw materials") -> (-) Direct delivery cost | B6: =Expenses!B5 -> 960000 | C6: =Expenses!C5 -> 960000 | D6: =Expenses!D5 -> 960000 | E6: =Expenses!E5 -> 960000 | F6: =Expenses!F5 -> 960000 | G6: =Expenses!G5 -> 960000 | H6: =Expenses!H5 -> 960000 | I6: =Expenses!I5 -> 960000 | ... M6: =Expenses!M5 -> 960000 | N6: =SUM(B6:M6) -> 11520000 | O6: =Expenses!O5 -> 1081200 | P6: =Expenses!P5 -> 1081200 | Q6: =Expenses!Q5 -> 1081200 | R6: =Expenses!R5 -> 1081200 | S6: =Expenses!S5 -> 1081200 | T6: =Expenses!T5 -> 1081200 | U6: =Expenses!U5 -> 1081200 | V6: =Expenses!V5 -> 1081200 | ... Z6: =Expenses!Z5 -> 1081200 | AA6: =SUM(O6:Z6) -> 12974400 | AB6: =Expenses!AB5 -> 1213488 | AC6: =Expenses!AC5 -> 1213488 | AD6: =Expenses!AD5 -> 1213488 | AE6: =Expenses!AE5 -> 1213488 | AF6: =Expenses!AF5 -> 1213488 | AG6: =Expenses!AG5 -> 1213488 | AH6: =Expenses!AH5 -> 1213488 | AI6: =Expenses!AI5 -> 1213488 | ... AM6: =Expenses!AM5 -> 1213488 | AN6: =SUM(AB6:AM6) -> 14561856 | AO6: =Expenses!AO5 -> 1357758.2 | AP6: =Expenses!AP5 -> 1357758.2 | AQ6: =Expenses!AQ5 -> 1357758.2 | AR6: =Expenses!AR5 -> 1357758.2 | AS6: =Expenses!AS5 -> 1357758.2 | AT6: =Expenses!AT5 -> 1357758.2 | AU6: =Expenses!AU5 -> 1357758.2 | AV6: =Expenses!AV5 -> 1357758.2 | ... AZ6: =Expenses!AZ5 -> 1357758.2 | BA6: =SUM(AO6:AZ6) -> 16293099 | BB6: =Expenses!BB5 -> 1514972.4 | BC6: =Expenses!BC5 -> 1514972.4 | BD6: =Expenses!BD5 -> 1514972.4 | BE6: =Expenses!BE5 -> 1514972.4 | BF6: =Expenses!BF5 -> 1514972.4 | BG6: =Expenses!BG5 -> 1514972.4 | BH6: =Expenses!BH5 -> 1514972.4 | BI6: =Expenses!BI5 -> 1514972.4 | ... BM6: =Expenses!BM5 -> 1514972.4 | BN6: =SUM(BB6:BM6) -> 18179668
A7: =IFERROR("(-) "&VLOOKUP(Assumptions!$J$5,Assumptions!$S$5:$Z$21,7,FALSE()),"(-) Power & fuel") -> (-) Infrastructure & hosting | B7: =Expenses!B6 -> 640000 | C7: =Expenses!C6 -> 640000 | D7: =Expenses!D6 -> 640000 | E7: =Expenses!E6 -> 640000 | F7: =Expenses!F6 -> 640000 | G7: =Expenses!G6 -> 640000 | H7: =Expenses!H6 -> 640000 | I7: =Expenses!I6 -> 640000 | ... M7: =Expenses!M6 -> 640000 | N7: =SUM(B7:M7) -> 7680000 | O7: =Expenses!O6 -> 714000 | P7: =Expenses!P6 -> 714000 | Q7: =Expenses!Q6 -> 714000 | R7: =Expenses!R6 -> 714000 | S7: =Expenses!S6 -> 714000 | T7: =Expenses!T6 -> 714000 | U7: =Expenses!U6 -> 714000 | V7: =Expenses!V6 -> 714000 | ... Z7: =Expenses!Z6 -> 714000 | AA7: =SUM(O7:Z7) -> 8568000 | AB7: =Expenses!AB6 -> 793800 | AC7: =Expenses!AC6 -> 793800 | AD7: =Expenses!AD6 -> 793800 | AE7: =Expenses!AE6 -> 793800 | AF7: =Expenses!AF6 -> 793800 | AG7: =Expenses!AG6 -> 793800 | AH7: =Expenses!AH6 -> 793800 | AI7: =Expenses!AI6 -> 793800 | ... AM7: =Expenses!AM6 -> 793800 | AN7: =SUM(AB7:AM7) -> 9525600 | AO7: =Expenses!AO6 -> 879795 | AP7: =Expenses!AP6 -> 879795 | AQ7: =Expenses!AQ6 -> 879795 | AR7: =Expenses!AR6 -> 879795 | AS7: =Expenses!AS6 -> 879795 | AT7: =Expenses!AT6 -> 879795 | AU7: =Expenses!AU6 -> 879795 | AV7: =Expenses!AV6 -> 879795 | ... AZ7: =Expenses!AZ6 -> 879795 | BA7: =SUM(AO7:AZ7) -> 10557540 | BB7: =Expenses!BB6 -> 972405 | BC7: =Expenses!BC6 -> 972405 | BD7: =Expenses!BD6 -> 972405 | BE7: =Expenses!BE6 -> 972405 | BF7: =Expenses!BF6 -> 972405 | BG7: =Expenses!BG6 -> 972405 | BH7: =Expenses!BH6 -> 972405 | BI7: =Expenses!BI6 -> 972405 | ... BM7: =Expenses!BM6 -> 972405 | BN7: =SUM(BB7:BM7) -> 11668860
A8: (-) Direct wages & salaries | B8: =Expenses!B7 -> 400000 | C8: =Expenses!C7 -> 400000 | D8: =Expenses!D7 -> 400000 | E8: =Expenses!E7 -> 400000 | F8: =Expenses!F7 -> 400000 | G8: =Expenses!G7 -> 400000 | H8: =Expenses!H7 -> 400000 | I8: =Expenses!I7 -> 400000 | ... M8: =Expenses!M7 -> 400000 | N8: =SUM(B8:M8) -> 4800000 | O8: =Expenses!O7 -> 428000 | P8: =Expenses!P7 -> 428000 | Q8: =Expenses!Q7 -> 428000 | R8: =Expenses!R7 -> 428000 | S8: =Expenses!S7 -> 428000 | T8: =Expenses!T7 -> 428000 | U8: =Expenses!U7 -> 428000 | V8: =Expenses!V7 -> 428000 | ... Z8: =Expenses!Z7 -> 428000 | AA8: =SUM(O8:Z8) -> 5136000 | AB8: =Expenses!AB7 -> 457960 | AC8: =Expenses!AC7 -> 457960 | AD8: =Expenses!AD7 -> 457960 | AE8: =Expenses!AE7 -> 457960 | AF8: =Expenses!AF7 -> 457960 | AG8: =Expenses!AG7 -> 457960 | AH8: =Expenses!AH7 -> 457960 | AI8: =Expenses!AI7 -> 457960 | ... AM8: =Expenses!AM7 -> 457960 | AN8: =SUM(AB8:AM8) -> 5495520 | AO8: =Expenses!AO7 -> 490017.2 | AP8: =Expenses!AP7 -> 490017.2 | AQ8: =Expenses!AQ7 -> 490017.2 | AR8: =Expenses!AR7 -> 490017.2 | AS8: =Expenses!AS7 -> 490017.2 | AT8: =Expenses!AT7 -> 490017.2 | AU8: =Expenses!AU7 -> 490017.2 | AV8: =Expenses!AV7 -> 490017.2 | ... AZ8: =Expenses!AZ7 -> 490017.2 | BA8: =SUM(AO8:AZ8) -> 5880206.4 | BB8: =Expenses!BB7 -> 524318.4 | BC8: =Expenses!BC7 -> 524318.4 | BD8: =Expenses!BD7 -> 524318.4 | BE8: =Expenses!BE7 -> 524318.4 | BF8: =Expenses!BF7 -> 524318.4 | BG8: =Expenses!BG7 -> 524318.4 | BH8: =Expenses!BH7 -> 524318.4 | BI8: =Expenses!BI7 -> 524318.4 | ... BM8: =Expenses!BM7 -> 524318.4 | BN8: =SUM(BB8:BM8) -> 6291820.8
A9: (-) Other variable cost | B9: =Expenses!B8 -> 320000 | C9: =Expenses!C8 -> 320000 | D9: =Expenses!D8 -> 320000 | E9: =Expenses!E8 -> 320000 | F9: =Expenses!F8 -> 320000 | G9: =Expenses!G8 -> 320000 | H9: =Expenses!H8 -> 320000 | I9: =Expenses!I8 -> 320000 | ... M9: =Expenses!M8 -> 320000 | N9: =SUM(B9:M9) -> 3840000 | O9: =Expenses!O8 -> 353600 | P9: =Expenses!P8 -> 353600 | Q9: =Expenses!Q8 -> 353600 | R9: =Expenses!R8 -> 353600 | S9: =Expenses!S8 -> 353600 | T9: =Expenses!T8 -> 353600 | U9: =Expenses!U8 -> 353600 | V9: =Expenses!V8 -> 353600 | ... Z9: =Expenses!Z8 -> 353600 | AA9: =SUM(O9:Z9) -> 4243200 | AB9: =Expenses!AB8 -> 389376 | AC9: =Expenses!AC8 -> 389376 | AD9: =Expenses!AD8 -> 389376 | AE9: =Expenses!AE8 -> 389376 | AF9: =Expenses!AF8 -> 389376 | AG9: =Expenses!AG8 -> 389376 | AH9: =Expenses!AH8 -> 389376 | AI9: =Expenses!AI8 -> 389376 | ... AM9: =Expenses!AM8 -> 389376 | AN9: =SUM(AB9:AM9) -> 4672512 | AO9: =Expenses!AO8 -> 427448.32 | AP9: =Expenses!AP8 -> 427448.32 | AQ9: =Expenses!AQ8 -> 427448.32 | AR9: =Expenses!AR8 -> 427448.32 | AS9: =Expenses!AS8 -> 427448.32 | AT9: =Expenses!AT8 -> 427448.32 | AU9: =Expenses!AU8 -> 427448.32 | AV9: =Expenses!AV8 -> 427448.32 | ... AZ9: =Expenses!AZ8 -> 427448.32 | BA9: =SUM(AO9:AZ9) -> 5129379.8 | BB9: =Expenses!BB8 -> 467943.42 | BC9: =Expenses!BC8 -> 467943.42 | BD9: =Expenses!BD8 -> 467943.42 | BE9: =Expenses!BE8 -> 467943.42 | BF9: =Expenses!BF8 -> 467943.42 | BG9: =Expenses!BG8 -> 467943.42 | BH9: =Expenses!BH8 -> 467943.42 | BI9: =Expenses!BI8 -> 467943.42 | ... BM9: =Expenses!BM8 -> 467943.42 | BN9: =SUM(BB9:BM9) -> 5615321.1
A10: =IFERROR("(-) "&VLOOKUP(Assumptions!$J$5,Assumptions!$S$5:$Z$21,8,FALSE()),"(-) Factory overheads") -> (-) Operating overheads | B10: =Expenses!B9 -> 100000 | C10: =Expenses!C9 -> 100000 | D10: =Expenses!D9 -> 100000 | E10: =Expenses!E9 -> 100000 | F10: =Expenses!F9 -> 100000 | G10: =Expenses!G9 -> 100000 | H10: =Expenses!H9 -> 100000 | I10: =Expenses!I9 -> 100000 | ... M10: =Expenses!M9 -> 100000 | N10: =SUM(B10:M10) -> 1200000 | O10: =Expenses!O9 -> 105000 | P10: =Expenses!P9 -> 105000 | Q10: =Expenses!Q9 -> 105000 | R10: =Expenses!R9 -> 105000 | S10: =Expenses!S9 -> 105000 | T10: =Expenses!T9 -> 105000 | U10: =Expenses!U9 -> 105000 | V10: =Expenses!V9 -> 105000 | ... Z10: =Expenses!Z9 -> 105000 | AA10: =SUM(O10:Z10) -> 1260000 | AB10: =Expenses!AB9 -> 110250 | AC10: =Expenses!AC9 -> 110250 | AD10: =Expenses!AD9 -> 110250 | AE10: =Expenses!AE9 -> 110250 | AF10: =Expenses!AF9 -> 110250 | AG10: =Expenses!AG9 -> 110250 | AH10: =Expenses!AH9 -> 110250 | AI10: =Expenses!AI9 -> 110250 | ... AM10: =Expenses!AM9 -> 110250 | AN10: =SUM(AB10:AM10) -> 1323000 | AO10: =Expenses!AO9 -> 115762.5 | AP10: =Expenses!AP9 -> 115762.5 | AQ10: =Expenses!AQ9 -> 115762.5 | AR10: =Expenses!AR9 -> 115762.5 | AS10: =Expenses!AS9 -> 115762.5 | AT10: =Expenses!AT9 -> 115762.5 | AU10: =Expenses!AU9 -> 115762.5 | AV10: =Expenses!AV9 -> 115762.5 | ... AZ10: =Expenses!AZ9 -> 115762.5 | BA10: =SUM(AO10:AZ10) -> 1389150 | BB10: =Expenses!BB9 -> 121550.62 | BC10: =Expenses!BC9 -> 121550.62 | BD10: =Expenses!BD9 -> 121550.62 | BE10: =Expenses!BE9 -> 121550.62 | BF10: =Expenses!BF9 -> 121550.62 | BG10: =Expenses!BG9 -> 121550.62 | BH10: =Expenses!BH9 -> 121550.62 | BI10: =Expenses!BI9 -> 121550.62 | ... BM10: =Expenses!BM9 -> 121550.62 | BN10: =SUM(BB10:BM10) -> 1458607.5
A11: (-) Repairs & maintenance | B11: =Expenses!B10 -> 20000 | C11: =Expenses!C10 -> 20000 | D11: =Expenses!D10 -> 20000 | E11: =Expenses!E10 -> 20000 | F11: =Expenses!F10 -> 20000 | G11: =Expenses!G10 -> 20000 | H11: =Expenses!H10 -> 20000 | I11: =Expenses!I10 -> 20000 | ... M11: =Expenses!M10 -> 20000 | N11: =SUM(B11:M11) -> 240000 | O11: =Expenses!O10 -> 20800 | P11: =Expenses!P10 -> 20800 | Q11: =Expenses!Q10 -> 20800 | R11: =Expenses!R10 -> 20800 | S11: =Expenses!S10 -> 20800 | T11: =Expenses!T10 -> 20800 | U11: =Expenses!U10 -> 20800 | V11: =Expenses!V10 -> 20800 | ... Z11: =Expenses!Z10 -> 20800 | AA11: =SUM(O11:Z11) -> 249600 | AB11: =Expenses!AB10 -> 21632 | AC11: =Expenses!AC10 -> 21632 | AD11: =Expenses!AD10 -> 21632 | AE11: =Expenses!AE10 -> 21632 | AF11: =Expenses!AF10 -> 21632 | AG11: =Expenses!AG10 -> 21632 | AH11: =Expenses!AH10 -> 21632 | AI11: =Expenses!AI10 -> 21632 | ... AM11: =Expenses!AM10 -> 21632 | AN11: =SUM(AB11:AM11) -> 259584 | AO11: =Expenses!AO10 -> 22497.28 | AP11: =Expenses!AP10 -> 22497.28 | AQ11: =Expenses!AQ10 -> 22497.28 | AR11: =Expenses!AR10 -> 22497.28 | AS11: =Expenses!AS10 -> 22497.28 | AT11: =Expenses!AT10 -> 22497.28 | AU11: =Expenses!AU10 -> 22497.28 | AV11: =Expenses!AV10 -> 22497.28 | ... AZ11: =Expenses!AZ10 -> 22497.28 | BA11: =SUM(AO11:AZ11) -> 269967.36 | BB11: =Expenses!BB10 -> 23397.171 | BC11: =Expenses!BC10 -> 23397.171 | BD11: =Expenses!BD10 -> 23397.171 | BE11: =Expenses!BE10 -> 23397.171 | BF11: =Expenses!BF10 -> 23397.171 | BG11: =Expenses!BG10 -> 23397.171 | BH11: =Expenses!BH10 -> 23397.171 | BI11: =Expenses!BI10 -> 23397.171 | ... BM11: =Expenses!BM10 -> 23397.171 | BN11: =SUM(BB11:BM11) -> 280766.05
A12: (-) Administrative expenses | B12: =Expenses!B11 -> 50000 | C12: =Expenses!C11 -> 50000 | D12: =Expenses!D11 -> 50000 | E12: =Expenses!E11 -> 50000 | F12: =Expenses!F11 -> 50000 | G12: =Expenses!G11 -> 50000 | H12: =Expenses!H11 -> 50000 | I12: =Expenses!I11 -> 50000 | ... M12: =Expenses!M11 -> 50000 | N12: =SUM(B12:M12) -> 600000 | O12: =Expenses!O11 -> 52500 | P12: =Expenses!P11 -> 52500 | Q12: =Expenses!Q11 -> 52500 | R12: =Expenses!R11 -> 52500 | S12: =Expenses!S11 -> 52500 | T12: =Expenses!T11 -> 52500 | U12: =Expenses!U11 -> 52500 | V12: =Expenses!V11 -> 52500 | ... Z12: =Expenses!Z11 -> 52500 | AA12: =SUM(O12:Z12) -> 630000 | AB12: =Expenses!AB11 -> 55125 | AC12: =Expenses!AC11 -> 55125 | AD12: =Expenses!AD11 -> 55125 | AE12: =Expenses!AE11 -> 55125 | AF12: =Expenses!AF11 -> 55125 | AG12: =Expenses!AG11 -> 55125 | AH12: =Expenses!AH11 -> 55125 | AI12: =Expenses!AI11 -> 55125 | ... AM12: =Expenses!AM11 -> 55125 | AN12: =SUM(AB12:AM12) -> 661500 | AO12: =Expenses!AO11 -> 57881.25 | AP12: =Expenses!AP11 -> 57881.25 | AQ12: =Expenses!AQ11 -> 57881.25 | AR12: =Expenses!AR11 -> 57881.25 | AS12: =Expenses!AS11 -> 57881.25 | AT12: =Expenses!AT11 -> 57881.25 | AU12: =Expenses!AU11 -> 57881.25 | AV12: =Expenses!AV11 -> 57881.25 | ... AZ12: =Expenses!AZ11 -> 57881.25 | BA12: =SUM(AO12:AZ12) -> 694575 | BB12: =Expenses!BB11 -> 60775.312 | BC12: =Expenses!BC11 -> 60775.312 | BD12: =Expenses!BD11 -> 60775.312 | BE12: =Expenses!BE11 -> 60775.312 | BF12: =Expenses!BF11 -> 60775.312 | BG12: =Expenses!BG11 -> 60775.312 | BH12: =Expenses!BH11 -> 60775.312 | BI12: =Expenses!BI11 -> 60775.312 | ... BM12: =Expenses!BM11 -> 60775.312 | BN12: =SUM(BB12:BM12) -> 729303.75
A13: (-) Selling & distribution | B13: =Expenses!B12 -> 192000 | C13: =Expenses!C12 -> 192000 | D13: =Expenses!D12 -> 192000 | E13: =Expenses!E12 -> 192000 | F13: =Expenses!F12 -> 192000 | G13: =Expenses!G12 -> 192000 | H13: =Expenses!H12 -> 192000 | I13: =Expenses!I12 -> 192000 | ... M13: =Expenses!M12 -> 192000 | N13: =SUM(B13:M13) -> 2304000 | O13: =Expenses!O12 -> 214200 | P13: =Expenses!P12 -> 214200 | Q13: =Expenses!Q12 -> 214200 | R13: =Expenses!R12 -> 214200 | S13: =Expenses!S12 -> 214200 | T13: =Expenses!T12 -> 214200 | U13: =Expenses!U12 -> 214200 | V13: =Expenses!V12 -> 214200 | ... Z13: =Expenses!Z12 -> 214200 | AA13: =SUM(O13:Z13) -> 2570400 | AB13: =Expenses!AB12 -> 238140 | AC13: =Expenses!AC12 -> 238140 | AD13: =Expenses!AD12 -> 238140 | AE13: =Expenses!AE12 -> 238140 | AF13: =Expenses!AF12 -> 238140 | AG13: =Expenses!AG12 -> 238140 | AH13: =Expenses!AH12 -> 238140 | AI13: =Expenses!AI12 -> 238140 | ... AM13: =Expenses!AM12 -> 238140 | AN13: =SUM(AB13:AM13) -> 2857680 | AO13: =Expenses!AO12 -> 263938.5 | AP13: =Expenses!AP12 -> 263938.5 | AQ13: =Expenses!AQ12 -> 263938.5 | AR13: =Expenses!AR12 -> 263938.5 | AS13: =Expenses!AS12 -> 263938.5 | AT13: =Expenses!AT12 -> 263938.5 | AU13: =Expenses!AU12 -> 263938.5 | AV13: =Expenses!AV12 -> 263938.5 | ... AZ13: =Expenses!AZ12 -> 263938.5 | BA13: =SUM(AO13:AZ13) -> 3167262 | BB13: =Expenses!BB12 -> 291721.5 | BC13: =Expenses!BC12 -> 291721.5 | BD13: =Expenses!BD12 -> 291721.5 | BE13: =Expenses!BE12 -> 291721.5 | BF13: =Expenses!BF12 -> 291721.5 | BG13: =Expenses!BG12 -> 291721.5 | BH13: =Expenses!BH12 -> 291721.5 | BI13: =Expenses!BI12 -> 291721.5 | ... BM13: =Expenses!BM12 -> 291721.5 | BN13: =SUM(BB13:BM13) -> 3500658
A14: EBITDA | B14: =B5-SUM(B6:B13) -> 1158000 | C14: =C5-SUM(C6:C13) -> 1158000 | D14: =D5-SUM(D6:D13) -> 1158000 | E14: =E5-SUM(E6:E13) -> 1158000 | F14: =F5-SUM(F6:F13) -> 1158000 | G14: =G5-SUM(G6:G13) -> 1158000 | H14: =H5-SUM(H6:H13) -> 1158000 | I14: =I5-SUM(I6:I13) -> 1158000 | ... M14: =M5-SUM(M6:M13) -> 1158000 | N14: =SUM(B14:M14) -> 13896000 | O14: =O5-SUM(O6:O13) -> 1314700 | P14: =P5-SUM(P6:P13) -> 1314700 | Q14: =Q5-SUM(Q6:Q13) -> 1314700 | R14: =R5-SUM(R6:R13) -> 1314700 | S14: =S5-SUM(S6:S13) -> 1314700 | T14: =T5-SUM(T6:T13) -> 1314700 | U14: =U5-SUM(U6:U13) -> 1314700 | V14: =V5-SUM(V6:V13) -> 1314700 | ... Z14: =Z5-SUM(Z6:Z13) -> 1314700 | AA14: =SUM(O14:Z14) -> 15776400 | AB14: =AB5-SUM(AB6:AB13) -> 1483029 | AC14: =AC5-SUM(AC6:AC13) -> 1483029 | AD14: =AD5-SUM(AD6:AD13) -> 1483029 | AE14: =AE5-SUM(AE6:AE13) -> 1483029 | AF14: =AF5-SUM(AF6:AF13) -> 1483029 | AG14: =AG5-SUM(AG6:AG13) -> 1483029 | AH14: =AH5-SUM(AH6:AH13) -> 1483029 | AI14: =AI5-SUM(AI6:AI13) -> 1483029 | ... AM14: =AM5-SUM(AM6:AM13) -> 1483029 | AN14: =SUM(AB14:AM14) -> 17796348 | AO14: =AO5-SUM(AO6:AO13) -> 1663671.7 | AP14: =AP5-SUM(AP6:AP13) -> 1663671.7 | AQ14: =AQ5-SUM(AQ6:AQ13) -> 1663671.7 | AR14: =AR5-SUM(AR6:AR13) -> 1663671.7 | AS14: =AS5-SUM(AS6:AS13) -> 1663671.7 | AT14: =AT5-SUM(AT6:AT13) -> 1663671.7 | AU14: =AU5-SUM(AU6:AU13) -> 1663671.7 | AV14: =AV5-SUM(AV6:AV13) -> 1663671.7 | ... AZ14: =AZ5-SUM(AZ6:AZ13) -> 1663671.7 | BA14: =SUM(AO14:AZ14) -> 19964061 | BB14: =BB5-SUM(BB6:BB13) -> 1857346.2 | BC14: =BC5-SUM(BC6:BC13) -> 1857346.2 | BD14: =BD5-SUM(BD6:BD13) -> 1857346.2 | BE14: =BE5-SUM(BE6:BE13) -> 1857346.2 | BF14: =BF5-SUM(BF6:BF13) -> 1857346.2 | BG14: =BG5-SUM(BG6:BG13) -> 1857346.2 | BH14: =BH5-SUM(BH6:BH13) -> 1857346.2 | BI14: =BI5-SUM(BI6:BI13) -> 1857346.2 | ... BM14: =BM5-SUM(BM6:BM13) -> 1857346.2 | BN14: =SUM(BB14:BM14) -> 22288155
A15: (-) Depreciation | B15: =Expenses!B13 -> 7916.6667 | C15: =Expenses!C13 -> 7916.6667 | D15: =Expenses!D13 -> 7916.6667 | E15: =Expenses!E13 -> 7916.6667 | F15: =Expenses!F13 -> 7916.6667 | G15: =Expenses!G13 -> 7916.6667 | H15: =Expenses!H13 -> 7916.6667 | I15: =Expenses!I13 -> 7916.6667 | ... M15: =Expenses!M13 -> 7916.6667 | N15: =SUM(B15:M15) -> 95000 | O15: =Expenses!O13 -> 7916.6667 | P15: =Expenses!P13 -> 7916.6667 | Q15: =Expenses!Q13 -> 7916.6667 | R15: =Expenses!R13 -> 7916.6667 | S15: =Expenses!S13 -> 7916.6667 | T15: =Expenses!T13 -> 7916.6667 | U15: =Expenses!U13 -> 7916.6667 | V15: =Expenses!V13 -> 7916.6667 | ... Z15: =Expenses!Z13 -> 7916.6667 | AA15: =SUM(O15:Z15) -> 95000 | AB15: =Expenses!AB13 -> 7916.6667 | AC15: =Expenses!AC13 -> 7916.6667 | AD15: =Expenses!AD13 -> 7916.6667 | AE15: =Expenses!AE13 -> 7916.6667 | AF15: =Expenses!AF13 -> 7916.6667 | AG15: =Expenses!AG13 -> 7916.6667 | AH15: =Expenses!AH13 -> 7916.6667 | AI15: =Expenses!AI13 -> 7916.6667 | ... AM15: =Expenses!AM13 -> 7916.6667 | AN15: =SUM(AB15:AM15) -> 95000 | AO15: =Expenses!AO13 -> 7916.6667 | AP15: =Expenses!AP13 -> 7916.6667 | AQ15: =Expenses!AQ13 -> 7916.6667 | AR15: =Expenses!AR13 -> 7916.6667 | AS15: =Expenses!AS13 -> 7916.6667 | AT15: =Expenses!AT13 -> 7916.6667 | AU15: =Expenses!AU13 -> 7916.6667 | AV15: =Expenses!AV13 -> 7916.6667 | ... AZ15: =Expenses!AZ13 -> 7916.6667 | BA15: =SUM(AO15:AZ15) -> 95000 | BB15: =Expenses!BB13 -> 7916.6667 | BC15: =Expenses!BC13 -> 7916.6667 | BD15: =Expenses!BD13 -> 7916.6667 | BE15: =Expenses!BE13 -> 7916.6667 | BF15: =Expenses!BF13 -> 7916.6667 | BG15: =Expenses!BG13 -> 7916.6667 | BH15: =Expenses!BH13 -> 7916.6667 | BI15: =Expenses!BI13 -> 7916.6667 | ... BM15: =Expenses!BM13 -> 7916.6667 | BN15: =SUM(BB15:BM15) -> 95000
A16: EBIT (Operating Profit) | B16: =B14-B15 -> 1150083.3 | C16: =C14-C15 -> 1150083.3 | D16: =D14-D15 -> 1150083.3 | E16: =E14-E15 -> 1150083.3 | F16: =F14-F15 -> 1150083.3 | G16: =G14-G15 -> 1150083.3 | H16: =H14-H15 -> 1150083.3 | I16: =I14-I15 -> 1150083.3 | ... M16: =M14-M15 -> 1150083.3 | N16: =SUM(B16:M16) -> 13801000 | O16: =O14-O15 -> 1306783.3 | P16: =P14-P15 -> 1306783.3 | Q16: =Q14-Q15 -> 1306783.3 | R16: =R14-R15 -> 1306783.3 | S16: =S14-S15 -> 1306783.3 | T16: =T14-T15 -> 1306783.3 | U16: =U14-U15 -> 1306783.3 | V16: =V14-V15 -> 1306783.3 | ... Z16: =Z14-Z15 -> 1306783.3 | AA16: =SUM(O16:Z16) -> 15681400 | AB16: =AB14-AB15 -> 1475112.3 | AC16: =AC14-AC15 -> 1475112.3 | AD16: =AD14-AD15 -> 1475112.3 | AE16: =AE14-AE15 -> 1475112.3 | AF16: =AF14-AF15 -> 1475112.3 | AG16: =AG14-AG15 -> 1475112.3 | AH16: =AH14-AH15 -> 1475112.3 | AI16: =AI14-AI15 -> 1475112.3 | ... AM16: =AM14-AM15 -> 1475112.3 | AN16: =SUM(AB16:AM16) -> 17701348 | AO16: =AO14-AO15 -> 1655755 | AP16: =AP14-AP15 -> 1655755 | AQ16: =AQ14-AQ15 -> 1655755 | AR16: =AR14-AR15 -> 1655755 | AS16: =AS14-AS15 -> 1655755 | AT16: =AT14-AT15 -> 1655755 | AU16: =AU14-AU15 -> 1655755 | AV16: =AV14-AV15 -> 1655755 | ... AZ16: =AZ14-AZ15 -> 1655755 | BA16: =SUM(AO16:AZ16) -> 19869061 | BB16: =BB14-BB15 -> 1849429.5 | BC16: =BC14-BC15 -> 1849429.5 | BD16: =BD14-BD15 -> 1849429.5 | BE16: =BE14-BE15 -> 1849429.5 | BF16: =BF14-BF15 -> 1849429.5 | BG16: =BG14-BG15 -> 1849429.5 | BH16: =BH14-BH15 -> 1849429.5 | BI16: =BI14-BI15 -> 1849429.5 | ... BM16: =BM14-BM15 -> 1849429.5 | BN16: =SUM(BB16:BM16) -> 22193155
A17: (-) Interest — Term Loan | B17: =Expenses!B14 -> 35000 | C17: =Expenses!C14 -> 35000 | D17: =Expenses!D14 -> 35000 | E17: =Expenses!E14 -> 35000 | F17: =Expenses!F14 -> 35000 | G17: =Expenses!G14 -> 35000 | H17: =Expenses!H14 -> 35000 | I17: =Expenses!I14 -> 35000 | ... M17: =Expenses!M14 -> 35000 | N17: =SUM(B17:M17) -> 420000 | O17: =Expenses!O14 -> 27222.222 | P17: =Expenses!P14 -> 27222.222 | Q17: =Expenses!Q14 -> 27222.222 | R17: =Expenses!R14 -> 27222.222 | S17: =Expenses!S14 -> 27222.222 | T17: =Expenses!T14 -> 27222.222 | U17: =Expenses!U14 -> 27222.222 | V17: =Expenses!V14 -> 27222.222 | ... Z17: =Expenses!Z14 -> 27222.222 | AA17: =SUM(O17:Z17) -> 326666.67 | AB17: =Expenses!AB14 -> 19444.444 | AC17: =Expenses!AC14 -> 19444.444 | AD17: =Expenses!AD14 -> 19444.444 | AE17: =Expenses!AE14 -> 19444.444 | AF17: =Expenses!AF14 -> 19444.444 | AG17: =Expenses!AG14 -> 19444.444 | AH17: =Expenses!AH14 -> 19444.444 | AI17: =Expenses!AI14 -> 19444.444 | ... AM17: =Expenses!AM14 -> 19444.444 | AN17: =SUM(AB17:AM17) -> 233333.33 | AO17: =Expenses!AO14 -> 11666.667 | AP17: =Expenses!AP14 -> 11666.667 | AQ17: =Expenses!AQ14 -> 11666.667 | AR17: =Expenses!AR14 -> 11666.667 | AS17: =Expenses!AS14 -> 11666.667 | AT17: =Expenses!AT14 -> 11666.667 | AU17: =Expenses!AU14 -> 11666.667 | AV17: =Expenses!AV14 -> 11666.667 | ... AZ17: =Expenses!AZ14 -> 11666.667 | BA17: =SUM(AO17:AZ17) -> 140000 | BB17: =Expenses!BB14 -> 3888.8889 | BC17: =Expenses!BC14 -> 3888.8889 | BD17: =Expenses!BD14 -> 3888.8889 | BE17: =Expenses!BE14 -> 3888.8889 | BF17: =Expenses!BF14 -> 3888.8889 | BG17: =Expenses!BG14 -> 3888.8889 | BH17: =Expenses!BH14 -> 3888.8889 | BI17: =Expenses!BI14 -> 3888.8889 | ... BM17: =Expenses!BM14 -> 3888.8889 | BN17: =SUM(BB17:BM17) -> 46666.667
A18: (-) Interest — Working Capital | B18: =Expenses!B15 -> 22686.986 | C18: =Expenses!C15 -> 22686.986 | D18: =Expenses!D15 -> 22686.986 | E18: =Expenses!E15 -> 22686.986 | F18: =Expenses!F15 -> 22686.986 | G18: =Expenses!G15 -> 22686.986 | H18: =Expenses!H15 -> 22686.986 | I18: =Expenses!I15 -> 22686.986 | ... M18: =Expenses!M15 -> 22686.986 | N18: =SUM(B18:M18) -> 272243.84 | O18: =Expenses!O15 -> 24775.973 | P18: =Expenses!P15 -> 24775.973 | Q18: =Expenses!Q15 -> 24775.973 | R18: =Expenses!R15 -> 24775.973 | S18: =Expenses!S15 -> 24775.973 | T18: =Expenses!T15 -> 24775.973 | U18: =Expenses!U15 -> 24775.973 | V18: =Expenses!V15 -> 24775.973 | ... Z18: =Expenses!Z15 -> 24775.973 | AA18: =SUM(O18:Z18) -> 297311.67 | AB18: =Expenses!AB15 -> 27013.022 | AC18: =Expenses!AC15 -> 27013.022 | AD18: =Expenses!AD15 -> 27013.022 | AE18: =Expenses!AE15 -> 27013.022 | AF18: =Expenses!AF15 -> 27013.022 | AG18: =Expenses!AG15 -> 27013.022 | AH18: =Expenses!AH15 -> 27013.022 | AI18: =Expenses!AI15 -> 27013.022 | ... AM18: =Expenses!AM15 -> 27013.022 | AN18: =SUM(AB18:AM18) -> 324156.27 | AO18: =Expenses!AO15 -> 29406.847 | AP18: =Expenses!AP15 -> 29406.847 | AQ18: =Expenses!AQ15 -> 29406.847 | AR18: =Expenses!AR15 -> 29406.847 | AS18: =Expenses!AS15 -> 29406.847 | AT18: =Expenses!AT15 -> 29406.847 | AU18: =Expenses!AU15 -> 29406.847 | AV18: =Expenses!AV15 -> 29406.847 | ... AZ18: =Expenses!AZ15 -> 29406.847 | BA18: =SUM(AO18:AZ18) -> 352882.17 | BB18: =Expenses!BB15 -> 31966.604 | BC18: =Expenses!BC15 -> 31966.604 | BD18: =Expenses!BD15 -> 31966.604 | BE18: =Expenses!BE15 -> 31966.604 | BF18: =Expenses!BF15 -> 31966.604 | BG18: =Expenses!BG15 -> 31966.604 | BH18: =Expenses!BH15 -> 31966.604 | BI18: =Expenses!BI15 -> 31966.604 | ... BM18: =Expenses!BM15 -> 31966.604 | BN18: =SUM(BB18:BM18) -> 383599.25
A19: Profit Before Tax (PBT) | B19: =B16-B17-B18 -> 1092396.3 | C19: =C16-C17-C18 -> 1092396.3 | D19: =D16-D17-D18 -> 1092396.3 | E19: =E16-E17-E18 -> 1092396.3 | F19: =F16-F17-F18 -> 1092396.3 | G19: =G16-G17-G18 -> 1092396.3 | H19: =H16-H17-H18 -> 1092396.3 | I19: =I16-I17-I18 -> 1092396.3 | ... M19: =M16-M17-M18 -> 1092396.3 | N19: =SUM(B19:M19) -> 13108756 | O19: =O16-O17-O18 -> 1254785.1 | P19: =P16-P17-P18 -> 1254785.1 | Q19: =Q16-Q17-Q18 -> 1254785.1 | R19: =R16-R17-R18 -> 1254785.1 | S19: =S16-S17-S18 -> 1254785.1 | T19: =T16-T17-T18 -> 1254785.1 | U19: =U16-U17-U18 -> 1254785.1 | V19: =V16-V17-V18 -> 1254785.1 | ... Z19: =Z16-Z17-Z18 -> 1254785.1 | AA19: =SUM(O19:Z19) -> 15057422 | AB19: =AB16-AB17-AB18 -> 1428654.9 | AC19: =AC16-AC17-AC18 -> 1428654.9 | AD19: =AD16-AD17-AD18 -> 1428654.9 | AE19: =AE16-AE17-AE18 -> 1428654.9 | AF19: =AF16-AF17-AF18 -> 1428654.9 | AG19: =AG16-AG17-AG18 -> 1428654.9 | AH19: =AH16-AH17-AH18 -> 1428654.9 | AI19: =AI16-AI17-AI18 -> 1428654.9 | ... AM19: =AM16-AM17-AM18 -> 1428654.9 | AN19: =SUM(AB19:AM19) -> 17143858 | AO19: =AO16-AO17-AO18 -> 1614681.5 | AP19: =AP16-AP17-AP18 -> 1614681.5 | AQ19: =AQ16-AQ17-AQ18 -> 1614681.5 | AR19: =AR16-AR17-AR18 -> 1614681.5 | AS19: =AS16-AS17-AS18 -> 1614681.5 | AT19: =AT16-AT17-AT18 -> 1614681.5 | AU19: =AU16-AU17-AU18 -> 1614681.5 | AV19: =AV16-AV17-AV18 -> 1614681.5 | ... AZ19: =AZ16-AZ17-AZ18 -> 1614681.5 | BA19: =SUM(AO19:AZ19) -> 19376178 | BB19: =BB16-BB17-BB18 -> 1813574.1 | BC19: =BC16-BC17-BC18 -> 1813574.1 | BD19: =BD16-BD17-BD18 -> 1813574.1 | BE19: =BE16-BE17-BE18 -> 1813574.1 | BF19: =BF16-BF17-BF18 -> 1813574.1 | BG19: =BG16-BG17-BG18 -> 1813574.1 | BH19: =BH16-BH17-BH18 -> 1813574.1 | BI19: =BI16-BI17-BI18 -> 1813574.1 | ... BM19: =BM16-BM17-BM18 -> 1813574.1 | BN19: =SUM(BB19:BM19) -> 21762889
A20: (-) Income Tax | B20: =IF(B19>0,B19*Assumptions!$C$14,0) -> 273099.09 | C20: =IF(C19>0,C19*Assumptions!$C$14,0) -> 273099.09 | D20: =IF(D19>0,D19*Assumptions!$C$14,0) -> 273099.09 | E20: =IF(E19>0,E19*Assumptions!$C$14,0) -> 273099.09 | F20: =IF(F19>0,F19*Assumptions!$C$14,0) -> 273099.09 | G20: =IF(G19>0,G19*Assumptions!$C$14,0) -> 273099.09 | H20: =IF(H19>0,H19*Assumptions!$C$14,0) -> 273099.09 | I20: =IF(I19>0,I19*Assumptions!$C$14,0) -> 273099.09 | ... BN20: =IF(BN19>0,BN19*Assumptions!$C$14,0) -> 5440722.2
A21: Profit After Tax (PAT) | B21: =B19-B20 -> 819297.26 | C21: =C19-C20 -> 819297.26 | D21: =D19-D20 -> 819297.26 | E21: =E19-E20 -> 819297.26 | F21: =F19-F20 -> 819297.26 | G21: =G19-G20 -> 819297.26 | H21: =H19-H20 -> 819297.26 | I21: =I19-I20 -> 819297.26 | ... BN21: =BN19-BN20 -> 16322166
A22: Cash Accrual (PAT + Depreciation) | B22: =B21+B15 -> 827213.93 | C22: =C21+C15 -> 827213.93 | D22: =D21+D15 -> 827213.93 | E22: =E21+E15 -> 827213.93 | F22: =F21+F15 -> 827213.93 | G22: =G21+G15 -> 827213.93 | H22: =H21+H15 -> 827213.93 | I22: =I21+I15 -> 827213.93 | ... BN22: =BN21+BN15 -> 16417166

Sheet Annual_Summary
A1: ANNUAL SUMMARY — CONSOLIDATED 5-YEAR VIEW
A2: Roll-up of the 60-month projections. Feeds every CMA form below.
B4: Particulars | C4: Year 1 | D4: Year 2 | E4: Year 3 | F4: Year 4 | G4: Year 5
B5: PRODUCTION & SALES
B6: =IFERROR(VLOOKUP(Assumptions!$J$5,Assumptions!$S$5:$Z$21,3,FALSE()),"Production (units)") -> Service delivery (units) | C6: =Production!N6 -> 3840 | D6: =Production!AA6 -> 4080 | E6: =Production!AN6 -> 4320 | F6: =Production!BA6 -> 4560 | G6: =Production!BN6 -> 4800
B7: Capacity utilisation (%) | C7: =Assumptions!$C$18 -> 0.8 | D7: =Assumptions!$D$18 -> 0.85 | E7: =Assumptions!$E$18 -> 0.9 | F7: =Assumptions!$F$18 -> 0.95 | G7: =Assumptions!$G$18 -> 1
B8: Net Sales / Revenue (₹) | C8: =Sales!N7 -> 46080000 | D8: =Sales!AA7 -> 51408000 | E8: =Sales!AN7 -> 57153600 | F8: =Sales!BA7 -> 63345240 | G8: =Sales!BN7 -> 70013160
B9: COST STRUCTURE (₹)
B10: =IFERROR(VLOOKUP(Assumptions!$J$5,Assumptions!$S$5:$Z$21,5,FALSE()),"Raw materials") -> Direct delivery cost | C10: =Expenses!N5 -> 11520000 | D10: =Expenses!AA5 -> 12974400 | E10: =Expenses!AN5 -> 14561856 | F10: =Expenses!BA5 -> 16293099 | G10: =Expenses!BN5 -> 18179668
B11: =IFERROR(VLOOKUP(Assumptions!$J$5,Assumptions!$S$5:$Z$21,7,FALSE()),"Power & fuel") -> Infrastructure & hosting | C11: =Expenses!N6 -> 7680000 | D11: =Expenses!AA6 -> 8568000 | E11: =Expenses!AN6 -> 9525600 | F11: =Expenses!BA6 -> 10557540 | G11: =Expenses!BN6 -> 11668860
B12: Direct wages & salaries | C12: =Expenses!N7 -> 4800000 | D12: =Expenses!AA7 -> 5136000 | E12: =Expenses!AN7 -> 5495520 | F12: =Expenses!BA7 -> 5880206.4 | G12: =Expenses!BN7 -> 6291820.8
B13: Other variable cost | C13: =Expenses!N8 -> 3840000 | D13: =Expenses!AA8 -> 4243200 | E13: =Expenses!AN8 -> 4672512 | F13: =Expenses!BA8 -> 5129379.8 | G13: =Expenses!BN8 -> 5615321.1
B14: =IFERROR(VLOOKUP(Assumptions!$J$5,Assumptions!$S$5:$Z$21,8,FALSE()),"Factory overheads") -> Operating overheads | C14: =Expenses!N9 -> 1200000 | D14: =Expenses!AA9 -> 1260000 | E14: =Expenses!AN9 -> 1323000 | F14: =Expenses!BA9 -> 1389150 | G14: =Expenses!BN9 -> 1458607.5
B15: Repairs & maintenance | C15: =Expenses!N10 -> 240000 | D15: =Expenses!AA10 -> 249600 | E15: =Expenses!AN10 -> 259584 | F15: =Expenses!BA10 -> 269967.36 | G15: =Expenses!BN10 -> 280766.05
B16: Administrative expenses | C16: =Expenses!N11 -> 600000 | D16: =Expenses!AA11 -> 630000 | E16: =Expenses!AN11 -> 661500 | F16: =Expenses!BA11 -> 694575 | G16: =Expenses!BN11 -> 729303.75
B17: Selling & distribution | C17: =Expenses!N12 -> 2304000 | D17: =Expenses!AA12 -> 2570400 | E17: =Expenses!AN12 -> 2857680 | F17: =Expenses!BA12 -> 3167262 | G17: =Expenses!BN12 -> 3500658
B18: Depreciation | C18: =Expenses!N13 -> 95000 | D18: =Expenses!AA13 -> 95000 | E18: =Expenses!AN13 -> 95000 | F18: =Expenses!BA13 -> 95000 | G18: =Expenses!BN13 -> 95000
B19: Interest — Term Loan | C19: =Expenses!N14 -> 420000 | D19: =Expenses!AA14 -> 326666.67 | E19: =Expenses!AN14 -> 233333.33 | F19: =Expenses!BA14 -> 140000 | G19: =Expenses!BN14 -> 46666.667
B20: Interest — Working Capital | C20: =Expenses!N15 -> 272243.84 | D20: =Expenses!AA15 -> 297311.67 | E20: =Expenses!AN15 -> 324156.27 | F20: =Expenses!BA15 -> 352882.17 | G20: =Expenses!BN15 -> 383599.25
B21: PROFITABILITY (₹)
B22: EBITDA | C22: =Profit!N14 -> 13896000 | D22: =Profit!AA14 -> 15776400 | E22: =Profit!AN14 -> 17796348 | F22: =Profit!BA14 -> 19964061 | G22: =Profit!BN14 -> 22288155
B23: EBIT (Operating Profit) | C23: =Profit!N16 -> 13801000 | D23: =Profit!AA16 -> 15681400 | E23: =Profit!AN16 -> 17701348 | F23: =Profit!BA16 -> 19869061 | G23: =Profit!BN16 -> 22193155
B24: Profit Before Tax | C24: =Profit!N19 -> 13108756 | D24: =Profit!AA19 -> 15057422 | E24: =Profit!AN19 -> 17143858 | F24: =Profit!BA19 -> 19376178 | G24: =Profit!BN19 -> 21762889
B25: Income Tax | C25: =Profit!N20 -> 3277189 | D25: =Profit!AA20 -> 3764355.4 | E25: =Profit!AN20 -> 4285964.6 | F25: =Profit!BA20 -> 4844044.6 | G25: =Profit!BN20 -> 5440722.2
B26: Profit After Tax (PAT) | C26: =Profit!N21 -> 9831567.1 | D26: =Profit!AA21 -> 11293066 | E26: =Profit!AN21 -> 12857894 | F26: =Profit!BA21 -> 14532134 | G26: =Profit!BN21 -> 16322166
B27: Cash Accrual (PAT + Depreciation) | C27: =Profit!N22 -> 9926567.1 | D27: =Profit!AA22 -> 11388066 | E27: =Profit!AN22 -> 12952894 | F27: =Profit!BA22 -> 14627134 | G27: =Profit!BN22 -> 16417166

Sheet Form_II_Operating
A1: FORM II — OPERATING STATEMENT
A2: Projected profitability in the format required for credit appraisal (₹).
B4: Particulars | C4: Year 1 | D4: Year 2 | E4: Year 3 | F4: Year 4 | G4: Year 5
B5: Net Sales | C5: =Annual_Summary!C8 -> 46080000 | D5: =Annual_Summary!D8 -> 51408000 | E5: =Annual_Summary!E8 -> 57153600 | F5: =Annual_Summary!F8 -> 63345240 | G5: =Annual_Summary!G8 -> 70013160
B6: Cost of Production
B7: =IFERROR(VLOOKUP(Assumptions!$J$5,Assumptions!$S$5:$Z$21,5,FALSE()),"Raw materials") -> Direct delivery cost | C7: =Annual_Summary!C10 -> 11520000 | D7: =Annual_Summary!D10 -> 12974400 | E7: =Annual_Summary!E10 -> 14561856 | F7: =Annual_Summary!F10 -> 16293099 | G7: =Annual_Summary!G10 -> 18179668
B8: =IFERROR(VLOOKUP(Assumptions!$J$5,Assumptions!$S$5:$Z$21,7,FALSE()),"Power & fuel") -> Infrastructure & hosting | C8: =Annual_Summary!C11 -> 7680000 | D8: =Annual_Summary!D11 -> 8568000 | E8: =Annual_Summary!E11 -> 9525600 | F8: =Annual_Summary!F11 -> 10557540 | G8: =Annual_Summary!G11 -> 11668860
B9: Direct wages & salaries | C9: =Annual_Summary!C12 -> 4800000 | D9: =Annual_Summary!D12 -> 5136000 | E9: =Annual_Summary!E12 -> 5495520 | F9: =Annual_Summary!F12 -> 5880206.4 | G9: =Annual_Summary!G12 -> 6291820.8
B10: Other variable cost | C10: =Annual_Summary!C13 -> 3840000 | D10: =Annual_Summary!D13 -> 4243200 | E10: =Annual_Summary!E13 -> 4672512 | F10: =Annual_Summary!F13 -> 5129379.8 | G10: =Annual_Summary!G13 -> 5615321.1
B11: =IFERROR(VLOOKUP(Assumptions!$J$5,Assumptions!$S$5:$Z$21,8,FALSE()),"Factory overheads") -> Operating overheads | C11: =Annual_Summary!C14 -> 1200000 | D11: =Annual_Summary!D14 -> 1260000 | E11: =Annual_Summary!E14 -> 1323000 | F11: =Annual_Summary!F14 -> 1389150 | G11: =Annual_Summary!G14 -> 1458607.5
B12: Repairs & maintenance | C12: =Annual_Summary!C15 -> 240000 | D12: =Annual_Summary!D15 -> 249600 | E12: =Annual_Summary!E15 -> 259584 | F12: =Annual_Summary!F15 -> 269967.36 | G12: =Annual_Summary!G15 -> 280766.05
B13: Depreciation | C13: =Annual_Summary!C18 -> 95000 | D13: =Annual_Summary!D18 -> 95000 | E13: =Annual_Summary!E18 -> 95000 | F13: =Annual_Summary!F18 -> 95000 | G13: =Annual_Summary!G18 -> 95000
B14: Cost of Production | C14: =Annual_Summary!C10+Annual_Summary!C11+Annual_Summary!C12+Annual_Summary!C13+Annual_Summary!C14+Annual_Summary!C15+Annual_Summary!C18 -> 29375000 | D14: =Annual_Summary!D10+Annual_Summary!D11+Annual_Summary!D12+Annual_Summary!D13+Annual_Summary!D14+Annual_Summary!D15+Annual_Summary!D18 -> 32526200 | E14: =Annual_Summary!E10+Annual_Summary!E11+Annual_Summary!E12+Annual_Summary!E13+Annual_Summary!E14+Annual_Summary!E15+Annual_Summary!E18 -> 35933072 | F14: =Annual_Summary!F10+Annual_Summary!F11+Annual_Summary!F12+Annual_Summary!F13+Annual_Summary!F14+Annual_Summary!F15+Annual_Summary!F18 -> 39614342 | G14: =Annual_Summary!G10+Annual_Summary!G11+Annual_Summary!G12+Annual_Summary!G13+Annual_Summary!G14+Annual_Summary!G15+Annual_Summary!G18 -> 43590044
B15: Gross Profit | C15: =Annual_Summary!C8-C14 -> 16705000 | D15: =Annual_Summary!D8-D14 -> 18881800 | E15: =Annual_Summary!E8-E14 -> 21220528 | F15: =Annual_Summary!F8-F14 -> 23730898 | G15: =Annual_Summary!G8-G14 -> 26423116
B16: (-) Administrative expenses | C16: =Annual_Summary!C16 -> 600000 | D16: =Annual_Summary!D16 -> 630000 | E16: =Annual_Summary!E16 -> 661500 | F16: =Annual_Summary!F16 -> 694575 | G16: =Annual_Summary!G16 -> 729303.75
B17: (-) Selling & distribution | C17: =Annual_Summary!C17 -> 2304000 | D17: =Annual_Summary!D17 -> 2570400 | E17: =Annual_Summary!E17 -> 2857680 | F17: =Annual_Summary!F17 -> 3167262 | G17: =Annual_Summary!G17 -> 3500658
B18: Operating Profit (EBIT) | C18: =C15-Annual_Summary!C16-Annual_Summary!C17 -> 13801000 | D18: =D15-Annual_Summary!D16-Annual_Summary!D17 -> 15681400 | E18: =E15-Annual_Summary!E16-Annual_Summary!E17 -> 17701348 | F18: =F15-Annual_Summary!F16-Annual_Summary!F17 -> 19869061 | G18: =G15-Annual_Summary!G16-Annual_Summary!G17 -> 22193155
B19: (-) Interest — Term Loan | C19: =Annual_Summary!C19 -> 420000 | D19: =Annual_Summary!D19 -> 326666.67 | E19: =Annual_Summary!E19 -> 233333.33 | F19: =Annual_Summary!F19 -> 140000 | G19: =Annual_Summary!G19 -> 46666.667
B20: (-) Interest — Working Capital | C20: =Annual_Summary!C20 -> 272243.84 | D20: =Annual_Summary!D20 -> 297311.67 | E20: =Annual_Summary!E20 -> 324156.27 | F20: =Annual_Summary!F20 -> 352882.17 | G20: =Annual_Summary!G20 -> 383599.25
B21: Profit Before Tax | C21: =C18-Annual_Summary!C19-Annual_Summary!C20 -> 13108756 | D21: =D18-Annual_Summary!D19-Annual_Summary!D20 -> 15057422 | E21: =E18-Annual_Summary!E19-Annual_Summary!E20 -> 17143858 | F21: =F18-Annual_Summary!F19-Annual_Summary!F20 -> 19376178 | G21: =G18-Annual_Summary!G19-Annual_Summary!G20 -> 21762889
B22: (-) Provision for Tax | C22: =Annual_Summary!C25 -> 3277189 | D22: =Annual_Summary!D25 -> 3764355.4 | E22: =Annual_Summary!E25 -> 4285964.6 | F22: =Annual_Summary!F25 -> 4844044.6 | G22: =Annual_Summary!G25 -> 5440722.2
B23: Profit After Tax | C23: =C21-Annual_Summary!C25 -> 9831567.1 | D23: =D21-Annual_Summary!D25 -> 11293066 | E23: =E21-Annual_Summary!E25 -> 12857894 | F23: =F21-Annual_Summary!F25 -> 14532134 | G23: =G21-Annual_Summary!G25 -> 16322166

Sheet Form_III_BalanceSheet
A1: FORM III — PROJECTED BALANCE SHEET
A2: Sources & application of funds; cash is the balancing figure (₹).
B4: Particulars | C4: Year 1 | D4: Year 2 | E4: Year 3 | F4: Year 4 | G4: Year 5
B5: LIABILITIES (₹)
B6: Capital / Promoters' equity | C6: =Assumptions!$C$9 -> 1000000 | D6: =Assumptions!$C$9 -> 1000000 | E6: =Assumptions!$C$9 -> 1000000 | F6: =Assumptions!$C$9 -> 1000000 | G6: =Assumptions!$C$9 -> 1000000
B7: Reserves & surplus (accumulated PAT) | C7: =Annual_Summary!C26 -> 9831567.1 | D7: =C7+Annual_Summary!D26 -> 21124633 | E7: =D7+Annual_Summary!E26 -> 33982527 | F7: =E7+Annual_Summary!F26 -> 48514661 | G7: =F7+Annual_Summary!G26 -> 64836827
B8: Net Worth | C8: =C6+C7 -> 10831567 | D8: =D6+D7 -> 22124633 | E8: =E6+E7 -> 34982527 | F8: =F6+F7 -> 49514661 | G8: =G6+G7 -> 65836827
B9: Term loan (closing balance) | C9: =Repayment!C8 -> 3111111.1 | D9: =Repayment!D8 -> 2222222.2 | E9: =Repayment!E8 -> 1333333.3 | F9: =Repayment!F8 -> 444444.44 | G9: =Repayment!G8 -> 0
B10: Bank borrowing — working capital | C10: =Form_V_MPBF!C11 -> 2268698.6 | D10: =Form_V_MPBF!D11 -> 2477597.3 | E10: =Form_V_MPBF!E11 -> 2701302.2 | F10: =Form_V_MPBF!F11 -> 2940684.7 | G10: =Form_V_MPBF!G11 -> 3196660.4
B11: Sundry creditors | C11: =Form_IV_CA_CL!C16 -> 946849.32 | D11: =Form_IV_CA_CL!D16 -> 1066389 | E11: =Form_IV_CA_CL!E16 -> 1196864.9 | F11: =Form_IV_CA_CL!F16 -> 1339158.8 | G11: =Form_IV_CA_CL!G16 -> 1494219.3
B12: Other current liabilities / provisions | C12: =Form_IV_CA_CL!C17 -> 0 | D12: =Form_IV_CA_CL!D17 -> 0 | E12: =Form_IV_CA_CL!E17 -> 0 | F12: =Form_IV_CA_CL!F17 -> 0 | G12: =Form_IV_CA_CL!G17 -> 0
B13: TOTAL LIABILITIES | C13: =SUM(C8:C12) -> 17158226 | D13: =SUM(D8:D12) -> 27890842 | E13: =SUM(E8:E12) -> 40214028 | F13: =SUM(F8:F12) -> 54238949 | G13: =SUM(G8:G12) -> 70527707
B14: ASSETS (₹)
B15: Gross fixed assets | C15: =Assumptions!$C$42+Assumptions!$C$43+Assumptions!$C$45+Assumptions!$C$47 -> 700000 | D15: =Assumptions!$C$42+Assumptions!$C$43+Assumptions!$C$45+Assumptions!$C$47 -> 700000 | E15: =Assumptions!$C$42+Assumptions!$C$43+Assumptions!$C$45+Assumptions!$C$47 -> 700000 | F15: =Assumptions!$C$42+Assumptions!$C$43+Assumptions!$C$45+Assumptions!$C$47 -> 700000 | G15: =Assumptions!$C$42+Assumptions!$C$43+Assumptions!$C$45+Assumptions!$C$47 -> 700000
B16: (-) Accumulated depreciation | C16: =Annual_Summary!C18 -> 95000 | D16: =C16+Annual_Summary!D18 -> 190000 | E16: =D16+Annual_Summary!E18 -> 285000 | F16: =E16+Annual_Summary!F18 -> 380000 | G16: =F16+Annual_Summary!G18 -> 475000
B17: Net fixed assets | C17: =C15-C16 -> 605000 | D17: =D15-D16 -> 510000 | E17: =E15-E16 -> 415000 | F17: =F15-F16 -> 320000 | G17: =G15-G16 -> 225000
B18: Inventory | C18: =Form_IV_CA_CL!C10+Form_IV_CA_CL!C11 -> 0 | D18: =Form_IV_CA_CL!D10+Form_IV_CA_CL!D11 -> 0 | E18: =Form_IV_CA_CL!E10+Form_IV_CA_CL!E11 -> 0 | F18: =Form_IV_CA_CL!F10+Form_IV_CA_CL!F11 -> 0 | G18: =Form_IV_CA_CL!G10+Form_IV_CA_CL!G11 -> 0
B19: Sundry debtors / receivables | C19: =Form_IV_CA_CL!C12 -> 3787397.3 | D19: =Form_IV_CA_CL!D12 -> 4225315.1 | E19: =Form_IV_CA_CL!E12 -> 4697556.2 | F19: =Form_IV_CA_CL!F12 -> 5206458.1 | G19: =Form_IV_CA_CL!G12 -> 5754506.3
B20: Cash & bank (balancing figure) | C20: =C13-(C17+C18+C19) -> 12765829 | D20: =D13-(D17+D18+D19) -> 23155527 | E20: =E13-(E17+E18+E19) -> 35101471 | F20: =F13-(F17+F18+F19) -> 48712491 | G20: =G13-(G17+G18+G19) -> 64548201
B21: TOTAL ASSETS | C21: =C17+C18+C19+C20 -> 17158226 | D21: =D17+D18+D19+D20 -> 27890842 | E21: =E17+E18+E19+E20 -> 40214028 | F21: =F17+F18+F19+F20 -> 54238949 | G21: =G17+G18+G19+G20 -> 70527707
B22: Check (Liabilities − Assets = 0) | C22: =C13-C21 -> 0 | D22: =D13-D21 -> 0 | E22: =E13-E21 -> 0 | F22: =F13-F21 -> 0 | G22: =G13-G21 -> 0

Sheet Form_IV_CA_CL
A1: FORM IV — CURRENT ASSETS & CURRENT LIABILITIES
A2: Build-up of working-capital requirement from holding-period assumptions (₹).
B4: Particulars | C4: Year 1 | D4: Year 2 | E4: Year 3 | F4: Year 4 | G4: Year 5
B5: OPERATING BASIS
B6: Cost of Production | C6: =Annual_Summary!C10+Annual_Summary!C11+Annual_Summary!C12+Annual_Summary!C13+Annual_Summary!C14+Annual_Summary!C15+Annual_Summary!C18 -> 29375000 | D6: =Annual_Summary!D10+Annual_Summary!D11+Annual_Summary!D12+Annual_Summary!D13+Annual_Summary!D14+Annual_Summary!D15+Annual_Summary!D18 -> 32526200 | E6: =Annual_Summary!E10+Annual_Summary!E11+Annual_Summary!E12+Annual_Summary!E13+Annual_Summary!E14+Annual_Summary!E15+Annual_Summary!E18 -> 35933072 | F6: =Annual_Summary!F10+Annual_Summary!F11+Annual_Summary!F12+Annual_Summary!F13+Annual_Summary!F14+Annual_Summary!F15+Annual_Summary!F18 -> 39614342 | G6: =Annual_Summary!G10+Annual_Summary!G11+Annual_Summary!G12+Annual_Summary!G13+Annual_Summary!G14+Annual_Summary!G15+Annual_Summary!G18 -> 43590044
B7: Purchases (raw material) | C7: =Annual_Summary!C10 -> 11520000 | D7: =Annual_Summary!D10 -> 12974400 | E7: =Annual_Summary!E10 -> 14561856 | F7: =Annual_Summary!F10 -> 16293099 | G7: =Annual_Summary!G10 -> 18179668
B8: Net Sales | C8: =Annual_Summary!C8 -> 46080000 | D8: =Annual_Summary!D8 -> 51408000 | E8: =Annual_Summary!E8 -> 57153600 | F8: =Annual_Summary!F8 -> 63345240 | G8: =Annual_Summary!G8 -> 70013160
B9: CURRENT ASSETS (₹)
B10: Inventory — Raw material | C10: =C7*Assumptions!$C$50/365 -> 0 | D10: =D7*Assumptions!$C$50/365 -> 0 | E10: =E7*Assumptions!$C$50/365 -> 0 | F10: =F7*Assumptions!$C$50/365 -> 0 | G10: =G7*Assumptions!$C$50/365 -> 0
B11: Inventory — Finished goods | C11: =C6*Assumptions!$C$51/365 -> 0 | D11: =D6*Assumptions!$C$51/365 -> 0 | E11: =E6*Assumptions!$C$51/365 -> 0 | F11: =F6*Assumptions!$C$51/365 -> 0 | G11: =G6*Assumptions!$C$51/365 -> 0
B12: Sundry debtors / receivables | C12: =C8*Assumptions!$C$52/365 -> 3787397.3 | D12: =D8*Assumptions!$C$52/365 -> 4225315.1 | E12: =E8*Assumptions!$C$52/365 -> 4697556.2 | F12: =F8*Assumptions!$C$52/365 -> 5206458.1 | G12: =G8*Assumptions!$C$52/365 -> 5754506.3
B13: Cash & bank (minimum) | C13: =Assumptions!$C$54 -> 500000 | D13: =Assumptions!$C$54 -> 500000 | E13: =Assumptions!$C$54 -> 500000 | F13: =Assumptions!$C$54 -> 500000 | G13: =Assumptions!$C$54 -> 500000
B14: Total Current Assets | C14: =SUM(C10:C13) -> 4287397.3 | D14: =SUM(D10:D13) -> 4725315.1 | E14: =SUM(E10:E13) -> 5197556.2 | F14: =SUM(F10:F13) -> 5706458.1 | G14: =SUM(G10:G13) -> 6254506.3
B15: CURRENT LIABILITIES (other than bank finance) (₹)
B16: Sundry creditors / payables | C16: =C7*Assumptions!$C$53/365 -> 946849.32 | D16: =D7*Assumptions!$C$53/365 -> 1066389 | E16: =E7*Assumptions!$C$53/365 -> 1196864.9 | F16: =F7*Assumptions!$C$53/365 -> 1339158.8 | G16: =G7*Assumptions!$C$53/365 -> 1494219.3
B17: Other current liabilities / provisions | C17: =0 -> 0 | D17: =0 -> 0 | E17: =0 -> 0 | F17: =0 -> 0 | G17: =0 -> 0
B18: Total Current Liabilities (excl. bank) | C18: =C16+C17 -> 946849.32 | D18: =D16+D17 -> 1066389 | E18: =E16+E17 -> 1196864.9 | F18: =F16+F17 -> 1339158.8 | G18: =G16+G17 -> 1494219.3
B19: Working Capital Gap (TCA − TCL) | C19: =C14-C18 -> 3340547.9 | D19: =D14-D18 -> 3658926 | E19: =E14-E18 -> 4000691.3 | F19: =F14-F18 -> 4367299.3 | G19: =G14-G18 -> 4760287

Sheet Form_V_MPBF
A1: FORM V — MAXIMUM PERMISSIBLE BANK FINANCE
A2: MPBF computed on the Tandon methodology; Method II drives the working-capital limit (₹).
B4: Particulars | C4: Year 1 | D4: Year 2 | E4: Year 3 | F4: Year 4 | G4: Year 5
B5: Total Current Assets | C5: =Form_IV_CA_CL!C14 -> 4287397.3 | D5: =Form_IV_CA_CL!D14 -> 4725315.1 | E5: =Form_IV_CA_CL!E14 -> 5197556.2 | F5: =Form_IV_CA_CL!F14 -> 5706458.1 | G5: =Form_IV_CA_CL!G14 -> 6254506.3
B6: Current Liabilities (other than bank) | C6: =Form_IV_CA_CL!C18 -> 946849.32 | D6: =Form_IV_CA_CL!D18 -> 1066389 | E6: =Form_IV_CA_CL!E18 -> 1196864.9 | F6: =Form_IV_CA_CL!F18 -> 1339158.8 | G6: =Form_IV_CA_CL!G18 -> 1494219.3
B7: Working Capital Gap (WCG) | C7: =Form_IV_CA_CL!C19 -> 3340547.9 | D7: =Form_IV_CA_CL!D19 -> 3658926 | E7: =Form_IV_CA_CL!E19 -> 4000691.3 | F7: =Form_IV_CA_CL!F19 -> 4367299.3 | G7: =Form_IV_CA_CL!G19 -> 4760287
B8: Min. stipulated NWC (margin × CA) | C8: =Assumptions!$C$55*Form_IV_CA_CL!C14 -> 1071849.3 | D8: =Assumptions!$C$55*Form_IV_CA_CL!D14 -> 1181328.8 | E8: =Assumptions!$C$55*Form_IV_CA_CL!E14 -> 1299389 | F8: =Assumptions!$C$55*Form_IV_CA_CL!F14 -> 1426614.5 | G8: =Assumptions!$C$55*Form_IV_CA_CL!G14 -> 1563626.6
B9: MPBF — Method I (WCG − margin) | C9: =MAX(0,Form_IV_CA_CL!C19*(1-Assumptions!$C$55)) -> 2505411 | D9: =MAX(0,Form_IV_CA_CL!D19*(1-Assumptions!$C$55)) -> 2744194.5 | E9: =MAX(0,Form_IV_CA_CL!E19*(1-Assumptions!$C$55)) -> 3000518.5 | F9: =MAX(0,Form_IV_CA_CL!F19*(1-Assumptions!$C$55)) -> 3275474.5 | G9: =MAX(0,Form_IV_CA_CL!G19*(1-Assumptions!$C$55)) -> 3570215.2
B10: MPBF — Method II (0.75·CA − CL) | C10: =MAX(0,Form_IV_CA_CL!C14*(1-Assumptions!$C$55)-Form_IV_CA_CL!C18) -> 2268698.6 | D10: =MAX(0,Form_IV_CA_CL!D14*(1-Assumptions!$C$55)-Form_IV_CA_CL!D18) -> 2477597.3 | E10: =MAX(0,Form_IV_CA_CL!E14*(1-Assumptions!$C$55)-Form_IV_CA_CL!E18) -> 2701302.2 | F10: =MAX(0,Form_IV_CA_CL!F14*(1-Assumptions!$C$55)-Form_IV_CA_CL!F18) -> 2940684.7 | G10: =MAX(0,Form_IV_CA_CL!G14*(1-Assumptions!$C$55)-Form_IV_CA_CL!G18) -> 3196660.4
B11: Recommended MPBF (Method II) | C11: =C10 -> 2268698.6 | D11: =D10 -> 2477597.3 | E11: =E10 -> 2701302.2 | F11: =F10 -> 2940684.7 | G11: =G10 -> 3196660.4

Sheet Form_VI_FundFlow
A1: FORM VI — FUND FLOW STATEMENT
A2: Year-on-year sources and applications of funds (₹).
B4: Particulars | C4: Year 1 | D4: Year 2 | E4: Year 3 | F4: Year 4 | G4: Year 5
B5: SOURCES OF FUNDS (₹)
B6: Cash accrual (PAT + Depreciation) | C6: =Annual_Summary!C27 -> 9926567.1 | D6: =Annual_Summary!D27 -> 11388066 | E6: =Annual_Summary!E27 -> 12952894 | F6: =Annual_Summary!F27 -> 14627134 | G6: =Annual_Summary!G27 -> 16417166
B7: Capital introduced | C7: =Assumptions!$C$9 -> 1000000 | D7: =0 -> 0 | E7: =0 -> 0 | F7: =0 -> 0 | G7: =0 -> 0
B8: Term loan raised | C8: =Assumptions!$C$8 -> 4000000 | D8: =0 -> 0 | E8: =0 -> 0 | F8: =0 -> 0 | G8: =0 -> 0
B9: Increase / (decrease) in bank WC finance | C9: =Form_V_MPBF!C11 -> 2268698.6 | D9: =(Form_V_MPBF!D11-Form_V_MPBF!C11) -> 208898.63 | E9: =(Form_V_MPBF!E11-Form_V_MPBF!D11) -> 223704.99 | F9: =(Form_V_MPBF!F11-Form_V_MPBF!E11) -> 239382.5 | G9: =(Form_V_MPBF!G11-Form_V_MPBF!F11) -> 255975.67
B10: Increase / (decrease) in creditors | C10: =Form_IV_CA_CL!C16 -> 946849.32 | D10: =(Form_IV_CA_CL!D16-Form_IV_CA_CL!C16) -> 119539.73 | E10: =(Form_IV_CA_CL!E16-Form_IV_CA_CL!D16) -> 130475.84 | F10: =(Form_IV_CA_CL!F16-Form_IV_CA_CL!E16) -> 142293.94 | G10: =(Form_IV_CA_CL!G16-Form_IV_CA_CL!F16) -> 155060.49
B11: TOTAL SOURCES (A) | C11: =SUM(C6:C10) -> 18142115 | D11: =SUM(D6:D10) -> 11716505 | E11: =SUM(E6:E10) -> 13307075 | F11: =SUM(F6:F10) -> 15008810 | G11: =SUM(G6:G10) -> 16828203
B12: APPLICATION OF FUNDS (₹)
B13: Capital expenditure (fixed assets) | C13: =Form_III_BalanceSheet!C15 -> 700000 | D13: =(Form_III_BalanceSheet!D15-Form_III_BalanceSheet!C15) -> 0 | E13: =(Form_III_BalanceSheet!E15-Form_III_BalanceSheet!D15) -> 0 | F13: =(Form_III_BalanceSheet!F15-Form_III_BalanceSheet!E15) -> 0 | G13: =(Form_III_BalanceSheet!G15-Form_III_BalanceSheet!F15) -> 0
B14: Repayment of term loan | C14: =Repayment!C7 -> 888888.89 | D14: =Repayment!D7 -> 888888.89 | E14: =Repayment!E7 -> 888888.89 | F14: =Repayment!F7 -> 888888.89 | G14: =Repayment!G7 -> 444444.44
B15: Increase / (decrease) in current assets | C15: =(Form_III_BalanceSheet!C18+Form_III_BalanceSheet!C19+Form_III_BalanceSheet!C20) -> 16553226 | D15: =((Form_III_BalanceSheet!D18+Form_III_BalanceSheet!D19+Form_III_BalanceSheet!D20)-(Form_III_BalanceSheet!C18+Form_III_BalanceSheet!C19+Form_III_BalanceSheet!C20)) -> 10827616 | E15: =((Form_III_BalanceSheet!E18+Form_III_BalanceSheet!E19+Form_III_BalanceSheet!E20)-(Form_III_BalanceSheet!D18+Form_III_BalanceSheet!D19+Form_III_BalanceSheet!D20)) -> 12418186 | F15: =((Form_III_BalanceSheet!F18+Form_III_BalanceSheet!F19+Form_III_BalanceSheet!F20)-(Form_III_BalanceSheet!E18+Form_III_BalanceSheet!E19+Form_III_BalanceSheet!E20)) -> 14119921 | G15: =((Form_III_BalanceSheet!G18+Form_III_BalanceSheet!G19+Form_III_BalanceSheet!G20)-(Form_III_BalanceSheet!F18+Form_III_BalanceSheet!F19+Form_III_BalanceSheet!F20)) -> 16383758
B16: TOTAL APPLICATIONS (B) | C16: =SUM(C13:C15) -> 18142115 | D16: =SUM(D13:D15) -> 11716505 | E16: =SUM(E13:E15) -> 13307075 | F16: =SUM(F13:F15) -> 15008810 | G16: =SUM(G13:G15) -> 16828203
B17: Net Surplus / (Deficit) (A − B) | C17: =C11-C16 -> 0 | D17: =D11-D16 -> 0 | E17: =E11-E16 -> 0 | F17: =F11-F16 -> 0 | G17: =G11-G16 -> 0

Sheet Repayment
A1: TERM LOAN — REPAYMENT SCHEDULE
A2: Equal annual principal after moratorium; interest on reducing balance (₹).
B4: Particulars | C4: Year 1 | D4: Year 2 | E4: Year 3 | F4: Year 4 | G4: Year 5
B5: Opening balance | C5: =Assumptions!$C$8 -> 4000000 | D5: =C8 -> 3111111.1 | E5: =D8 -> 2222222.2 | F5: =E8 -> 1333333.3 | G5: =F8 -> 444444.44
B6: Interest for the year | C6: =C5*Assumptions!$C$10 -> 420000 | D6: =D5*Assumptions!$C$10 -> 326666.67 | E6: =E5*Assumptions!$C$10 -> 233333.33 | F6: =F5*Assumptions!$C$10 -> 140000 | G6: =G5*Assumptions!$C$10 -> 46666.667
B7: Principal repayment | C7: =IF(1<=Assumptions!$C$12/12,0,MIN(C5,IFERROR(Assumptions!$C$8/(Assumptions!$C$11/12-Assumptions!$C$12/12),0))) -> 888888.89 | D7: =IF(2<=Assumptions!$C$12/12,0,MIN(D5,IFERROR(Assumptions!$C$8/(Assumptions!$C$11/12-Assumptions!$C$12/12),0))) -> 888888.89 | E7: =IF(3<=Assumptions!$C$12/12,0,MIN(E5,IFERROR(Assumptions!$C$8/(Assumptions!$C$11/12-Assumptions!$C$12/12),0))) -> 888888.89 | F7: =IF(4<=Assumptions!$C$12/12,0,MIN(F5,IFERROR(Assumptions!$C$8/(Assumptions!$C$11/12-Assumptions!$C$12/12),0))) -> 888888.89 | G7: =IF(5<=Assumptions!$C$12/12,0,MIN(G5,IFERROR(Assumptions!$C$8/(Assumptions!$C$11/12-Assumptions!$C$12/12),0))) -> 444444.44
B8: Closing balance | C8: =C5-C7 -> 3111111.1 | D8: =D5-D7 -> 2222222.2 | E8: =E5-E7 -> 1333333.3 | F8: =F5-F7 -> 444444.44 | G8: =G5-G7 -> 0
B10: Note: schedule shows the first 5 years of the projection horizon; any balance beyond Year 5 continues per the sanctioned tenure.

Sheet DSCR
A1: DEBT SERVICE COVERAGE (DSCR)
A2: Repayment capacity: cash available for debt service ÷ debt obligation.
B4: Particulars | C4: Year 1 | D4: Year 2 | E4: Year 3 | F4: Year 4 | G4: Year 5 | H4: Average
B5: Cash available for debt service (₹)
B6: Profit After Tax | C6: =Annual_Summary!C26 -> 9831567.1 | D6: =Annual_Summary!D26 -> 11293066 | E6: =Annual_Summary!E26 -> 12857894 | F6: =Annual_Summary!F26 -> 14532134 | G6: =Annual_Summary!G26 -> 16322166
B7: (+) Depreciation | C7: =Annual_Summary!C18 -> 95000 | D7: =Annual_Summary!D18 -> 95000 | E7: =Annual_Summary!E18 -> 95000 | F7: =Annual_Summary!F18 -> 95000 | G7: =Annual_Summary!G18 -> 95000
B8: (+) Interest on Term Loan | C8: =Repayment!C6 -> 420000 | D8: =Repayment!D6 -> 326666.67 | E8: =Repayment!E6 -> 233333.33 | F8: =Repayment!F6 -> 140000 | G8: =Repayment!G6 -> 46666.667
B9: Cash Available for Debt Service (A) | C9: =C6+C7+C8 -> 10346567 | D9: =D6+D7+D8 -> 11714733 | E9: =E6+E7+E8 -> 13186227 | F9: =F6+F7+F8 -> 14767134 | G9: =G6+G7+G8 -> 16463833
B10: Debt obligation (₹)
B11: Principal repayment | C11: =Repayment!C7 -> 888888.89 | D11: =Repayment!D7 -> 888888.89 | E11: =Repayment!E7 -> 888888.89 | F11: =Repayment!F7 -> 888888.89 | G11: =Repayment!G7 -> 444444.44
B12: Interest on Term Loan | C12: =Repayment!C6 -> 420000 | D12: =Repayment!D6 -> 326666.67 | E12: =Repayment!E6 -> 233333.33 | F12: =Repayment!F6 -> 140000 | G12: =Repayment!G6 -> 46666.667
B13: Total Debt Obligation (B) | C13: =C11+C12 -> 1308888.9 | D13: =D11+D12 -> 1215555.6 | E13: =E11+E12 -> 1122222.2 | F13: =F11+F12 -> 1028888.9 | G13: =G11+G12 -> 491111.11
B14: DSCR (A ÷ B) | C14: =IFERROR(C9/C13,0) -> 7.9048475 | D14: =IFERROR(D9/D13,0) -> 9.6373488 | E14: =IFERROR(E9/E13,0) -> 11.750103 | F14: =IFERROR(F9/F13,0) -> 14.352506 | G14: =IFERROR(G9/G13,0) -> 33.523642 | H14: =IFERROR(AVERAGE(C14:G14),0) -> 15.43369

Sheet Ratios
A1: FINANCIAL VIABILITY — KEY RATIOS
A2: Liquidity, leverage, profitability and coverage indicators for appraisal.
B4: Particulars | C4: Year 1 | D4: Year 2 | E4: Year 3 | F4: Year 4 | G4: Year 5
B5: LIQUIDITY & LEVERAGE
B6: Current Ratio | C6: =IFERROR((Form_III_BalanceSheet!C18+Form_III_BalanceSheet!C19+Form_III_BalanceSheet!C20)/(Form_III_BalanceSheet!C11+Form_III_BalanceSheet!C12+Form_III_BalanceSheet!C10),0) -> 5.1478711 | D6: =IFERROR((Form_III_BalanceSheet!D18+Form_III_BalanceSheet!D19+Form_III_BalanceSheet!D20)/(Form_III_BalanceSheet!D11+Form_III_BalanceSheet!D12+Form_III_BalanceSheet!D10),0) -> 7.7260011 | E6: =IFERROR((Form_III_BalanceSheet!E18+Form_III_BalanceSheet!E19+Form_III_BalanceSheet!E20)/(Form_III_BalanceSheet!E11+Form_III_BalanceSheet!E12+Form_III_BalanceSheet!E10),0) -> 10.209677 | F6: =IFERROR((Form_III_BalanceSheet!F18+Form_III_BalanceSheet!F19+Form_III_BalanceSheet!F20)/(Form_III_BalanceSheet!F11+Form_III_BalanceSheet!F12+Form_III_BalanceSheet!F10),0) -> 12.598346 | G6: =IFERROR((Form_III_BalanceSheet!G18+Form_III_BalanceSheet!G19+Form_III_BalanceSheet!G20)/(Form_III_BalanceSheet!G11+Form_III_BalanceSheet!G12+Form_III_BalanceSheet!G10),0) -> 14.987105
B7: Debt–Equity Ratio | C7: =IFERROR((Form_III_BalanceSheet!C9+Form_III_BalanceSheet!C10)/Form_III_BalanceSheet!C8,0) -> 0.4966788 | D7: =IFERROR((Form_III_BalanceSheet!D9+Form_III_BalanceSheet!D10)/Form_III_BalanceSheet!D8,0) -> 0.21242474 | E7: =IFERROR((Form_III_BalanceSheet!E9+Form_III_BalanceSheet!E10)/Form_III_BalanceSheet!E8,0) -> 0.11533288 | F7: =IFERROR((Form_III_BalanceSheet!F9+Form_III_BalanceSheet!F10)/Form_III_BalanceSheet!F8,0) -> 0.0683662 | G7: =IFERROR((Form_III_BalanceSheet!G9+Form_III_BalanceSheet!G10)/Form_III_BalanceSheet!G8,0) -> 0.04855429
B8: TOL / TNW | C8: =IFERROR((Form_III_BalanceSheet!C9+Form_III_BalanceSheet!C10+Form_III_BalanceSheet!C11+Form_III_BalanceSheet!C12)/Form_III_BalanceSheet!C8,0) -> 0.58409453 | D8: =IFERROR((Form_III_BalanceSheet!D9+Form_III_BalanceSheet!D10+Form_III_BalanceSheet!D11+Form_III_BalanceSheet!D12)/Form_III_BalanceSheet!D8,0) -> 0.26062391 | E8: =IFERROR((Form_III_BalanceSheet!E9+Form_III_BalanceSheet!E10+Form_III_BalanceSheet!E11+Form_III_BalanceSheet!E12)/Form_III_BalanceSheet!E8,0) -> 0.1495461 | F8: =IFERROR((Form_III_BalanceSheet!F9+Form_III_BalanceSheet!F10+Form_III_BalanceSheet!F11+Form_III_BalanceSheet!F12)/Form_III_BalanceSheet!F8,0) -> 0.095411903 | G8: =IFERROR((Form_III_BalanceSheet!G9+Form_III_BalanceSheet!G10+Form_III_BalanceSheet!G11+Form_III_BalanceSheet!G12)/Form_III_BalanceSheet!G8,0) -> 0.071250088
B9: PROFITABILITY
B10: EBITDA Margin | C10: =IFERROR(Annual_Summary!C22/Annual_Summary!C8,0) -> 0.3015625 | D10: =IFERROR(Annual_Summary!D22/Annual_Summary!D8,0) -> 0.30688609 | E10: =IFERROR(Annual_Summary!E22/Annual_Summary!E8,0) -> 0.31137755 | F10: =IFERROR(Annual_Summary!F22/Annual_Summary!F8,0) -> 0.31516276 | G10: =IFERROR(Annual_Summary!G22/Annual_Summary!G8,0) -> 0.31834236
B11: Net Profit Margin | C11: =IFERROR(Annual_Summary!C26/Annual_Summary!C8,0) -> 0.21335866 | D11: =IFERROR(Annual_Summary!D26/Annual_Summary!D8,0) -> 0.21967527 | E11: =IFERROR(Annual_Summary!E26/Annual_Summary!E8,0) -> 0.22497085 | F11: =IFERROR(Annual_Summary!F26/Annual_Summary!F8,0) -> 0.22941161 | G11: =IFERROR(Annual_Summary!G26/Annual_Summary!G8,0) -> 0.23312998
B12: Return on Capital Employed | C12: =IFERROR(Annual_Summary!C23/(Form_III_BalanceSheet!C8+Form_III_BalanceSheet!C9),0) -> 0.98983852 | D12: =IFERROR(Annual_Summary!D23/(Form_III_BalanceSheet!D8+Form_III_BalanceSheet!D9),0) -> 0.64408317 | E12: =IFERROR(Annual_Summary!E23/(Form_III_BalanceSheet!E8+Form_III_BalanceSheet!E9),0) -> 0.48742747 | F12: =IFERROR(Annual_Summary!F23/(Form_III_BalanceSheet!F8+Form_III_BalanceSheet!F9),0) -> 0.39770649 | G12: =IFERROR(Annual_Summary!G23/(Form_III_BalanceSheet!G8+Form_III_BalanceSheet!G9),0) -> 0.33709332
B13: COVERAGE & RISK
B14: Interest Coverage | C14: =IFERROR(Annual_Summary!C23/(Annual_Summary!C19+Annual_Summary!C20),0) -> 19.936617 | D14: =IFERROR(Annual_Summary!D23/(Annual_Summary!D19+Annual_Summary!D20),0) -> 25.131321 | E14: =IFERROR(Annual_Summary!E23/(Annual_Summary!E19+Annual_Summary!E20),0) -> 31.751889 | F14: =IFERROR(Annual_Summary!F23/(Annual_Summary!F19+Annual_Summary!F20),0) -> 40.311989 | G14: =IFERROR(Annual_Summary!G23/(Annual_Summary!G19+Annual_Summary!G20),0) -> 51.58009
B15: DSCR | C15: =DSCR!C14 -> 7.9048475 | D15: =DSCR!D14 -> 9.6373488 | E15: =DSCR!E14 -> 11.750103 | F15: =DSCR!F14 -> 14.352506 | G15: =DSCR!G14 -> 33.523642
B16: Break-even (% of sales) | C16: =IFERROR((Annual_Summary!C12+Annual_Summary!C14+Annual_Summary!C15+Annual_Summary!C16+Annual_Summary!C18+Annual_Summary!C19+Annual_Summary!C20)/(Annual_Summary!C8-(Annual_Summary!C10+Annual_Summary!C11+Annual_Summary!C13+Annual_Summary!C17)),0) -> 0.36782619 | D16: =IFERROR((Annual_Summary!D12+Annual_Summary!D14+Annual_Summary!D15+Annual_Summary!D16+Annual_Summary!D18+Annual_Summary!D19+Annual_Summary!D20)/(Annual_Summary!D8-(Annual_Summary!D10+Annual_Summary!D11+Annual_Summary!D13+Annual_Summary!D17)),0) -> 0.34680628 | E16: =IFERROR((Annual_Summary!E12+Annual_Summary!E14+Annual_Summary!E15+Annual_Summary!E16+Annual_Summary!E18+Annual_Summary!E19+Annual_Summary!E20)/(Annual_Summary!E8-(Annual_Summary!E10+Annual_Summary!E11+Annual_Summary!E13+Annual_Summary!E17)),0) -> 0.32863837 | F16: =IFERROR((Annual_Summary!F12+Annual_Summary!F14+Annual_Summary!F15+Annual_Summary!F16+Annual_Summary!F18+Annual_Summary!F19+Annual_Summary!F20)/(Annual_Summary!F8-(Annual_Summary!F10+Annual_Summary!F11+Annual_Summary!F13+Annual_Summary!F17)),0) -> 0.31285175 | G16: =IFERROR((Annual_Summary!G12+Annual_Summary!G14+Annual_Summary!G15+Annual_Summary!G16+Annual_Summary!G18+Annual_Summary!G19+Annual_Summary!G20)/(Annual_Summary!G8-(Annual_Summary!G10+Annual_Summary!G11+Annual_Summary!G13+Annual_Summary!G17)),0) -> 0.2990714
