Workbook

Sheet Cover
B2: CREDIT MONITORING ARRANGEMENT (CMA) REPORT
B3: Projected Financials for Bank Term-Loan & Working-Capital Appraisal
B5: Name of the Unit | C5: =Assumptions!C5 -> Plastic Packaging Containers Unit
B6: Constitution | C6: =Assumptions!C6 -> Proprietorship
B7: Line of Activity | C7: =Assumptions!C7 -> Manufacturing of plastic packaging containers for FMCG companies
B8: Term Loan applied for (₹) | C8: =Assumptions!C8 -> 6000000
B9: Promoters' Capital (₹) | C9: =Assumptions!C9 -> 1500000
B10: Projection horizon | C10: 5 years (60 months), monthly
B12: CONTENTS
B13: Assumptions | C13: All input variables — the single control panel for the model
B14: Production | C14: 60-month production plan (capacity × utilisation × phasing)
B15: Sales | C15: 60-month sales quantity, price and revenue
B16: Expenses | C16: 60-month operating expenses, interest and depreciation
B17: Profit | C17: 60-month P&L: EBITDA → EBIT → PBT → PAT
B18: Annual_Summary | C18: Consolidated 5-year figures feeding the CMA forms
B19: Form_II_Operating | C19: Form II — Operating statement (profitability)
B20: Form_III_BalanceSheet | C20: Form III — Projected balance sheet
B21: Form_IV_CA_CL | C21: Form IV — Current assets & current liabilities
B22: Form_V_MPBF | C22: Form V — Maximum permissible bank finance
B23: Form_VI_FundFlow | C23: Form VI — Fund-flow statement
B24: Repayment | C24: Term-loan repayment schedule
... B26: Ratios | C26: Key ratios — financial viability
B28: Enter data only in the blue cells on the Assumptions sheet; all other sheets recalculate automatically.

Sheet Assumptions
A1: ASSUMPTIONS — KEY INPUTS
A2: Enter values only in the blue/shaded cells. Every other sheet updates automatically.
B4: A. COMPANY & LOAN PARTICULARS | S4: Industry | T4: CapLabel | U4: ProdUnitLabel | V4: Cost1Long | W4: Cost1Short | X4: Cost2Long | Y4: Cost2Short | Z4: Cost3Short
B5: Name of the Unit | C5: Plastic Packaging Containers Unit | I5: INDUSTRY / BUSINESS TYPE → | J5: Manufacturing | S5: Agriculture & Farming | T5: Installed Capacity (land / livestock / output) | U5: Production (units) | V5: Raw material / input cost per unit (Year 1) | W5: Raw materials / inputs | X5: Power & fuel cost per unit (Year 1) | Y5: Power & fuel | Z5: Farm overheads
B6: Constitution (Proprietor / Partnership / Pvt Ltd) | C6: Proprietorship | S6: Technology & Software | T6: Service Delivery Capacity (billable hours/licenses p.a.) | U6: Service delivery (units) | V6: Direct delivery cost per unit (Year 1) | W6: Direct delivery cost | X6: Infrastructure & hosting cost per unit (Year 1) | Y6: Infrastructure & hosting | Z6: Operating overheads
B7: Line of Activity / Product | C7: Manufacturing of plastic packaging containers for FMCG companies | S7: Retail & E-Commerce | T7: Annual Purchase Capacity (units for resale) | U7: Purchase (units) | V7: Purchase cost of goods per unit (Year 1) | W7: Purchase cost of goods | X7: Freight & packaging cost per unit (Year 1) | Y7: Freight & packaging | Z7: Store overheads
B8: Term Loan applied for | C8: 6000000 | H8: ₹ | S8: Manufacturing | T8: Installed Capacity | U8: Production (units) | V8: Raw material cost per unit (Year 1) | W8: Raw materials | X8: Power & fuel cost per unit (Year 1) | Y8: Power & fuel | Z8: Factory overheads
B9: Promoters' Capital / Equity brought in | C9: 1500000 | H9: ₹ | S9: Tourism & Hospitality | T9: Room / Cover Capacity (room-nights or covers p.a.) | U9: Rooms sold / covers served (units) | V9: Direct service cost per unit (F&B, housekeeping) (Year 1) | W9: Direct service cost | X9: Power & fuel cost per unit (Year 1) | Y9: Power & fuel | Z9: Property overheads
B10: Interest rate on Term Loan | C10: 0.105 | H10: % p.a. | S10: Renewable Energy | T10: Installed Generation Capacity (units of energy p.a.) | U10: Energy generated (units) | V10: O&M cost per unit generated (Year 1) | W10: O&M cost | X10: Grid / power evacuation cost per unit (Year 1) | Y10: Grid / evacuation cost | Z10: Plant overheads
B11: Term Loan tenure | C11: 60 | H11: years | S11: Healthcare & Pharma | T11: Service / Production Capacity (patients or units p.a.) | U11: Patients served / units produced | V11: Consumables & medicine cost per unit (Year 1) | W11: Consumables & medicine | X11: Power & equipment running cost per unit (Year 1) | Y11: Power & equipment cost | Z11: Facility overheads
B12: Moratorium / holiday period | C12: 6 | H12: months | S12: Education & Training | T12: Service Capacity (student seats / batches p.a.) | U12: Students / batches served | V12: Direct delivery cost per unit (faculty, material) (Year 1) | W12: Direct delivery cost | X12: Infrastructure cost per unit (Year 1) | Y12: Infrastructure cost | Z12: Institute overheads
B13: Interest rate on Working Capital | C13: 0.12 | H13: % p.a. | S13: General Business | T13: Capacity (units / customers / hours p.a.) | U13: Output (units) | V13: Direct cost per unit (Year 1) | W13: Direct cost | X13: Overhead cost per unit (Year 1) | Y13: Overhead cost | Z13: Operating overheads
B14: Income Tax rate | C14: 0.25 | H14: % | S14: Construction & Real Estate | T14: Project Execution Capacity (sq.ft / units p.a.) | U14: Construction / units completed | V14: Construction material cost per unit (Year 1) | W14: Construction materials | X14: Site power & machinery cost per unit (Year 1) | Y14: Site power & machinery | Z14: Project overheads
B15: B. CAPACITY & PRODUCTION | S15: Food & Beverage / Restaurant | T15: Seating / Covers Capacity (covers p.a.) | U15: Covers served (units) | V15: Raw material (food & beverage) cost per unit (Year 1) | W15: Food & beverage cost | X15: Kitchen power & fuel cost per unit (Year 1) | Y15: Kitchen power & fuel | Z15: Restaurant overheads
B16: =IFERROR(VLOOKUP($J$5,$S$5:$Z$21,2,FALSE()),"Installed Capacity") -> Installed Capacity | C16: 12000000 | H16: units p.a. | S16: Transportation & Logistics | T16: Fleet / Route Capacity (trips or tonnage p.a.) | U16: Trips / tonnage handled (units) | V16: Fuel & running cost per unit (Year 1) | W16: Fuel & running cost | X16: Vehicle maintenance cost per unit (Year 1) | Y16: Vehicle maintenance | Z16: Fleet overheads
B17: Capacity Utilisation | C17: Yr 1 | D17: Yr 2 | E17: Yr 3 | F17: Yr 4 | G17: Yr 5 | S17: Textile & Garments | T17: Installed Capacity (garments/fabric units p.a.) | U17: Production (units) | V17: Raw material (yarn/fabric) cost per unit (Year 1) | W17: Raw materials (yarn/fabric) | X17: Power & fuel cost per unit (Year 1) | Y17: Power & fuel | Z17: Factory overheads
B18: → enter % for Year 1 … 5 | C18: 0.6 | D18: 0.65 | E18: 0.7 | F18: 0.75 | G18: 0.8 | H18: % | S18: Automobile / Auto Ancillary | T18: Installed Capacity (components/vehicles p.a.) | U18: Production (units) | V18: Raw material / component cost per unit (Year 1) | W18: Raw materials / components | X18: Power & fuel cost per unit (Year 1) | Y18: Power & fuel | Z18: Factory overheads
B19: C. MONTHLY PHASING FACTOR (optional — blank = equal spread) | S19: Import / Export Trading | T19: Annual Trading Capacity (units for import/export) | U19: Trading volume (units) | V19: Purchase / import cost per unit (Year 1) | W19: Purchase / import cost | X19: Freight, customs & logistics cost per unit (Year 1) | Y19: Freight & customs | Z19: Trading overheads
B20: Relative weight per month (M1…M12) | C20: M1 | D20: M2 | E20: M3 | F20: M4 | G20: M5 | H20: M6 | I20: M7 | J20: M8 | K20: M9 | L20: M10 | M20: M11 | N20: M12 | S20: Media & Entertainment | T20: Content / Production Capacity (units/hours p.a.) | U20: Content produced (units) | V20: Production cost per unit (Year 1) | W20: Production cost | X20: Equipment & studio cost per unit (Year 1) | Y20: Equipment & studio cost | Z20: Studio overheads
B21: → weights (e.g. 1.0 each, or seasonal) | C21: 0.08 | D21: 0.08 | E21: 0.08 | F21: 0.09 | G21: 0.09 | H21: 0.09 | I21: 0.08 | J21: 0.08 | K21: 0.08 | L21: 0.09 | M21: 0.09 | N21: 0.07 | S21: Mining & Minerals | T21: Installed Extraction Capacity (tonnes p.a.) | U21: Extraction (units) | V21: Raw material / extraction cost per unit (Year 1) | W21: Extraction cost | X21: Power & fuel cost per unit (Year 1) | Y21: Power & fuel | Z21: Mine overheads
B22: D. PRICE & VARIABLE COSTS (Year-1 base, escalated by the % below)
B23: Selling price per unit (Year 1) | C23: 5 | H23: ₹/unit
B24: annual price escalation | C24: 0.04 | H24: %
B25: =IFERROR(VLOOKUP($J$5,$S$5:$Z$21,4,FALSE()),"Raw material cost per unit (Year 1)") -> Raw material cost per unit (Year 1) | C25: 2.5 | H25: ₹/unit
B26: annual RM cost escalation | C26: 0.05 | H26: %
B27: =IFERROR(VLOOKUP($J$5,$S$5:$Z$21,6,FALSE()),"Power & fuel cost per unit (Year 1)") -> Power & fuel cost per unit (Year 1) | C27: 0.3 | H27: ₹/unit
B28: annual power cost escalation | C28: 0.06 | H28: %
B29: Other variable cost per unit (Year 1) | C29: 0.2 | H29: ₹/unit
B30: annual other-variable escalation | C30: 0.04 | H30: %
B31: E. FIXED / PERIOD COSTS (per month, Year-1 base, escalated below)
B32: Direct wages & salaries / month (Year 1) | C32: 150000 | H32: ₹/month
B33: annual wages escalation | C33: 0.05 | H33: %
B34: Factory overheads / month (Year 1) | C34: 100000 | H34: ₹/month
B35: annual factory-OH escalation | C35: 0.05 | H35: %
B36: Repairs & maintenance / month (Year 1) | C36: 30000 | H36: ₹/month
B37: annual R&M escalation | C37: 0.04 | H37: %
B38: Administrative expenses / month (Year 1) | C38: 50000 | H38: ₹/month
B39: annual admin escalation | C39: 0.04 | H39: %
B40: Selling & distribution | C40: 0.02 | H40: % of sales
B41: F. FIXED ASSETS & DEPRECIATION (straight-line on cost)
B42: Land (no depreciation) | C42: 0 | H42: ₹
B43: Building — cost | C43: 0 | H43: ₹
B44: Building — depreciation rate | C44: 0.1 | H44: %
B45: Plant & Machinery — cost | C45: 6000000 | H45: ₹
B46: Plant & Machinery — depreciation rate | C46: 0.15 | H46: %
B47: Furniture / other — cost | C47: 200000 | H47: ₹
B48: Furniture / other — depreciation rate | C48: 0.1 | H48: %
B49: G. WORKING CAPITAL CYCLE
B50: Raw material holding | C50: 15 | H50: days
B51: Finished goods holding | C51: 10 | H51: days
B52: Receivables / debtors | C52: 30 | H52: days
B53: Creditors / payables | C53: 45 | H53: days
B54: Minimum cash & bank balance | C54: 200000 | H54: ₹
B55: Bank's WC margin (borrower's stake) | C55: 0.25 | H55: % | P55: Tandon Method-II uses 25%

Sheet Production
A1: PRODUCTION PLAN — 60-MONTH PROJECTION
A2: Driven by Installed Capacity × Capacity Utilisation × Monthly phasing (Assumptions).
B3: YEAR 1 | O3: YEAR 2 | AB3: YEAR 3 | AO3: YEAR 4 | BB3: YEAR 5
A4: Particulars | B4: M1 | C4: M2 | D4: M3 | E4: M4 | F4: M5 | G4: M6 | H4: M7 | I4: M8 | J4: M9 | K4: M10 | L4: M11 | M4: M12 | N4: Yr 1 Total | O4: M13 | P4: M14 | Q4: M15 | R4: M16 | S4: M17 | T4: M18 | U4: M19 | V4: M20 | W4: M21 | X4: M22 | Y4: M23 | Z4: M24 | AA4: Yr 2 Total | AB4: M25 | AC4: M26 | AD4: M27 | AE4: M28 | AF4: M29 | AG4: M30 | AH4: M31 | AI4: M32 | AJ4: M33 | AK4: M34 | AL4: M35 | AM4: M36 | AN4: Yr 3 Total | AO4: M37 | AP4: M38 | AQ4: M39 | AR4: M40 | AS4: M41 | AT4: M42 | AU4: M43 | AV4: M44 | AW4: M45 | AX4: M46 | AY4: M47 | AZ4: M48 | BA4: Yr 4 Total | BB4: M49 | BC4: M50 | BD4: M51 | BE4: M52 | BF4: M53 | BG4: M54 | BH4: M55 | BI4: M56 | BJ4: M57 | BK4: M58 | BL4: M59 | BM4: M60 | BN4: Yr 5 Total
A5: Capacity utilisation (%) | B5: =Assumptions!$C$18 -> 0.6 | C5: =Assumptions!$C$18 -> 0.6 | D5: =Assumptions!$C$18 -> 0.6 | E5: =Assumptions!$C$18 -> 0.6 | F5: =Assumptions!$C$18 -> 0.6 | G5: =Assumptions!$C$18 -> 0.6 | H5: =Assumptions!$C$18 -> 0.6 | I5: =Assumptions!$C$18 -> 0.6 | ... N5: =Assumptions!$C$18 -> 0.6 | O5: =Assumptions!$D$18 -> 0.65 | P5: =Assumptions!$D$18 -> 0.65 | Q5: =Assumptions!$D$18 -> 0.65 | R5: =Assumptions!$D$18 -> 0.65 | S5: =Assumptions!$D$18 -> 0.65 | T5: =Assumptions!$D$18 -> 0.65 | U5: =Assumptions!$D$18 -> 0.65 | V5: =Assumptions!$D$18 -> 0.65 | ... AA5: =Assumptions!$D$18 -> 0.65 | AB5: =Assumptions!$E$18 -> 0.7 | AC5: =Assumptions!$E$18 -> 0.7 | AD5: =Assumptions!$E$18 -> 0.7 | AE5: =Assumptions!$E$18 -> 0.7 | AF5: =Assumptions!$E$18 -> 0.7 | AG5: =Assumptions!$E$18 -> 0.7 | AH5: =Assumptions!$E$18 -> 0.7 | AI5: =Assumptions!$E$18 -> 0.7 | ... AN5: =Assumptions!$E$18 -> 0.7 | AO5: =Assumptions!$F$18 -> 0.75 | AP5: =Assumptions!$F$18 -> 0.75 | AQ5: =Assumptions!$F$18 -> 0.75 | AR5: =Assumptions!$F$18 -> 0.75 | AS5: =Assumptions!$F$18 -> 0.75 | AT5: =Assumptions!$F$18 -> 0.75 | AU5: =Assumptions!$F$18 -> 0.75 | AV5: =Assumptions!$F$18 -> 0.75 | ... BA5: =Assumptions!$F$18 -> 0.75 | BB5: =Assumptions!$G$18 -> 0.8 | BC5: =Assumptions!$G$18 -> 0.8 | BD5: =Assumptions!$G$18 -> 0.8 | BE5: =Assumptions!$G$18 -> 0.8 | BF5: =Assumptions!$G$18 -> 0.8 | BG5: =Assumptions!$G$18 -> 0.8 | BH5: =Assumptions!$G$18 -> 0.8 | BI5: =Assumptions!$G$18 -> 0.8 | ... BN5: =Assumptions!$G$18 -> 0.8
A6: =IFERROR(VLOOKUP(Assumptions!$J$5,Assumptions!$S$5:$Z$21,3,FALSE()),"Production (units)") -> Production (units) | B6: =(Assumptions!$C$16*Assumptions!$C$18/12)*IF(SUM(Assumptions!$C$21:$N$21)=0,1,12*Assumptions!$C$21/SUM(Assumptions!$C$21:$N$21)) -> 576000 | C6: =(Assumptions!$C$16*Assumptions!$C$18/12)*IF(SUM(Assumptions!$C$21:$N$21)=0,1,12*Assumptions!$D$21/SUM(Assumptions!$C$21:$N$21)) -> 576000 | D6: =(Assumptions!$C$16*Assumptions!$C$18/12)*IF(SUM(Assumptions!$C$21:$N$21)=0,1,12*Assumptions!$E$21/SUM(Assumptions!$C$21:$N$21)) -> 576000 | E6: =(Assumptions!$C$16*Assumptions!$C$18/12)*IF(SUM(Assumptions!$C$21:$N$21)=0,1,12*Assumptions!$F$21/SUM(Assumptions!$C$21:$N$21)) -> 648000 | F6: =(Assumptions!$C$16*Assumptions!$C$18/12)*IF(SUM(Assumptions!$C$21:$N$21)=0,1,12*Assumptions!$G$21/SUM(Assumptions!$C$21:$N$21)) -> 648000 | G6: =(Assumptions!$C$16*Assumptions!$C$18/12)*IF(SUM(Assumptions!$C$21:$N$21)=0,1,12*Assumptions!$H$21/SUM(Assumptions!$C$21:$N$21)) -> 648000 | H6: =(Assumptions!$C$16*Assumptions!$C$18/12)*IF(SUM(Assumptions!$C$21:$N$21)=0,1,12*Assumptions!$I$21/SUM(Assumptions!$C$21:$N$21)) -> 576000 | I6: =(Assumptions!$C$16*Assumptions!$C$18/12)*IF(SUM(Assumptions!$C$21:$N$21)=0,1,12*Assumptions!$J$21/SUM(Assumptions!$C$21:$N$21)) -> 576000 | J6: =(Assumptions!$C$16*Assumptions!$C$18/12)*IF(SUM(Assumptions!$C$21:$N$21)=0,1,12*Assumptions!$K$21/SUM(Assumptions!$C$21:$N$21)) -> 576000 | K6: =(Assumptions!$C$16*Assumptions!$C$18/12)*IF(SUM(Assumptions!$C$21:$N$21)=0,1,12*Assumptions!$L$21/SUM(Assumptions!$C$21:$N$21)) -> 648000 | L6: =(Assumptions!$C$16*Assumptions!$C$18/12)*IF(SUM(Assumptions!$C$21:$N$21)=0,1,12*Assumptions!$M$21/SUM(Assumptions!$C$21:$N$21)) -> 648000 | M6: =(Assumptions!$C$16*Assumptions!$C$18/12)*IF(SUM(Assumptions!$C$21:$N$21)=0,1,12*Assumptions!$N$21/SUM(Assumptions!$C$21:$N$21)) -> 504000 | N6: =SUM(B6:M6) -> 7200000 | O6: =(Assumptions!$C$16*Assumptions!$D$18/12)*IF(SUM(Assumptions!$C$21:$N$21)=0,1,12*Assumptions!$C$21/SUM(Assumptions!$C$21:$N$21)) -> 624000 | P6: =(Assumptions!$C$16*Assumptions!$D$18/12)*IF(SUM(Assumptions!$C$21:$N$21)=0,1,12*Assumptions!$D$21/SUM(Assumptions!$C$21:$N$21)) -> 624000 | Q6: =(Assumptions!$C$16*Assumptions!$D$18/12)*IF(SUM(Assumptions!$C$21:$N$21)=0,1,12*Assumptions!$E$21/SUM(Assumptions!$C$21:$N$21)) -> 624000 | R6: =(Assumptions!$C$16*Assumptions!$D$18/12)*IF(SUM(Assumptions!$C$21:$N$21)=0,1,12*Assumptions!$F$21/SUM(Assumptions!$C$21:$N$21)) -> 702000 | S6: =(Assumptions!$C$16*Assumptions!$D$18/12)*IF(SUM(Assumptions!$C$21:$N$21)=0,1,12*Assumptions!$G$21/SUM(Assumptions!$C$21:$N$21)) -> 702000 | T6: =(Assumptions!$C$16*Assumptions!$D$18/12)*IF(SUM(Assumptions!$C$21:$N$21)=0,1,12*Assumptions!$H$21/SUM(Assumptions!$C$21:$N$21)) -> 702000 | U6: =(Assumptions!$C$16*Assumptions!$D$18/12)*IF(SUM(Assumptions!$C$21:$N$21)=0,1,12*Assumptions!$I$21/SUM(Assumptions!$C$21:$N$21)) -> 624000 | V6: =(Assumptions!$C$16*Assumptions!$D$18/12)*IF(SUM(Assumptions!$C$21:$N$21)=0,1,12*Assumptions!$J$21/SUM(Assumptions!$C$21:$N$21)) -> 624000 | W6: =(Assumptions!$C$16*Assumptions!$D$18/12)*IF(SUM(Assumptions!$C$21:$N$21)=0,1,12*Assumptions!$K$21/SUM(Assumptions!$C$21:$N$21)) -> 624000 | X6: =(Assumptions!$C$16*Assumptions!$D$18/12)*IF(SUM(Assumptions!$C$21:$N$21)=0,1,12*Assumptions!$L$21/SUM(Assumptions!$C$21:$N$21)) -> 702000 | Y6: =(Assumptions!$C$16*Assumptions!$D$18/12)*IF(SUM(Assumptions!$C$21:$N$21)=0,1,12*Assumptions!$M$21/SUM(Assumptions!$C$21:$N$21)) -> 702000 | Z6: =(Assumptions!$C$16*Assumptions!$D$18/12)*IF(SUM(Assumptions!$C$21:$N$21)=0,1,12*Assumptions!$N$21/SUM(Assumptions!$C$21:$N$21)) -> 546000 | AA6: =SUM(O6:Z6) -> 7800000 | AB6: =(Assumptions!$C$16*Assumptions!$E$18/12)*IF(SUM(Assumptions!$C$21:$N$21)=0,1,12*Assumptions!$C$21/SUM(Assumptions!$C$21:$N$21)) -> 672000 | AC6: =(Assumptions!$C$16*Assumptions!$E$18/12)*IF(SUM(Assumptions!$C$21:$N$21)=0,1,12*Assumptions!$D$21/SUM(Assumptions!$C$21:$N$21)) -> 672000 | AD6: =(Assumptions!$C$16*Assumptions!$E$18/12)*IF(SUM(Assumptions!$C$21:$N$21)=0,1,12*Assumptions!$E$21/SUM(Assumptions!$C$21:$N$21)) -> 672000 | AE6: =(Assumptions!$C$16*Assumptions!$E$18/12)*IF(SUM(Assumptions!$C$21:$N$21)=0,1,12*Assumptions!$F$21/SUM(Assumptions!$C$21:$N$21)) -> 756000 | AF6: =(Assumptions!$C$16*Assumptions!$E$18/12)*IF(SUM(Assumptions!$C$21:$N$21)=0,1,12*Assumptions!$G$21/SUM(Assumptions!$C$21:$N$21)) -> 756000 | AG6: =(Assumptions!$C$16*Assumptions!$E$18/12)*IF(SUM(Assumptions!$C$21:$N$21)=0,1,12*Assumptions!$H$21/SUM(Assumptions!$C$21:$N$21)) -> 756000 | AH6: =(Assumptions!$C$16*Assumptions!$E$18/12)*IF(SUM(Assumptions!$C$21:$N$21)=0,1,12*Assumptions!$I$21/SUM(Assumptions!$C$21:$N$21)) -> 672000 | AI6: =(Assumptions!$C$16*Assumptions!$E$18/12)*IF(SUM(Assumptions!$C$21:$N$21)=0,1,12*Assumptions!$J$21/SUM(Assumptions!$C$21:$N$21)) -> 672000 | AJ6: =(Assumptions!$C$16*Assumptions!$E$18/12)*IF(SUM(Assumptions!$C$21:$N$21)=0,1,12*Assumptions!$K$21/SUM(Assumptions!$C$21:$N$21)) -> 672000 | AK6: =(Assumptions!$C$16*Assumptions!$E$18/12)*IF(SUM(Assumptions!$C$21:$N$21)=0,1,12*Assumptions!$L$21/SUM(Assumptions!$C$21:$N$21)) -> 756000 | AL6: =(Assumptions!$C$16*Assumptions!$E$18/12)*IF(SUM(Assumptions!$C$21:$N$21)=0,1,12*Assumptions!$M$21/SUM(Assumptions!$C$21:$N$21)) -> 756000 | AM6: =(Assumptions!$C$16*Assumptions!$E$18/12)*IF(SUM(Assumptions!$C$21:$N$21)=0,1,12*Assumptions!$N$21/SUM(Assumptions!$C$21:$N$21)) -> 588000 | AN6: =SUM(AB6:AM6) -> 8400000 | AO6: =(Assumptions!$C$16*Assumptions!$F$18/12)*IF(SUM(Assumptions!$C$21:$N$21)=0,1,12*Assumptions!$C$21/SUM(Assumptions!$C$21:$N$21)) -> 720000 | AP6: =(Assumptions!$C$16*Assumptions!$F$18/12)*IF(SUM(Assumptions!$C$21:$N$21)=0,1,12*Assumptions!$D$21/SUM(Assumptions!$C$21:$N$21)) -> 720000 | AQ6: =(Assumptions!$C$16*Assumptions!$F$18/12)*IF(SUM(Assumptions!$C$21:$N$21)=0,1,12*Assumptions!$E$21/SUM(Assumptions!$C$21:$N$21)) -> 720000 | AR6: =(Assumptions!$C$16*Assumptions!$F$18/12)*IF(SUM(Assumptions!$C$21:$N$21)=0,1,12*Assumptions!$F$21/SUM(Assumptions!$C$21:$N$21)) -> 810000 | AS6: =(Assumptions!$C$16*Assumptions!$F$18/12)*IF(SUM(Assumptions!$C$21:$N$21)=0,1,12*Assumptions!$G$21/SUM(Assumptions!$C$21:$N$21)) -> 810000 | AT6: =(Assumptions!$C$16*Assumptions!$F$18/12)*IF(SUM(Assumptions!$C$21:$N$21)=0,1,12*Assumptions!$H$21/SUM(Assumptions!$C$21:$N$21)) -> 810000 | AU6: =(Assumptions!$C$16*Assumptions!$F$18/12)*IF(SUM(Assumptions!$C$21:$N$21)=0,1,12*Assumptions!$I$21/SUM(Assumptions!$C$21:$N$21)) -> 720000 | AV6: =(Assumptions!$C$16*Assumptions!$F$18/12)*IF(SUM(Assumptions!$C$21:$N$21)=0,1,12*Assumptions!$J$21/SUM(Assumptions!$C$21:$N$21)) -> 720000 | AW6: =(Assumptions!$C$16*Assumptions!$F$18/12)*IF(SUM(Assumptions!$C$21:$N$21)=0,1,12*Assumptions!$K$21/SUM(Assumptions!$C$21:$N$21)) -> 720000 | AX6: =(Assumptions!$C$16*Assumptions!$F$18/12)*IF(SUM(Assumptions!$C$21:$N$21)=0,1,12*Assumptions!$L$21/SUM(Assumptions!$C$21:$N$21)) -> 810000 | AY6: =(Assumptions!$C$16*Assumptions!$F$18/12)*IF(SUM(Assumptions!$C$21:$N$21)=0,1,12*Assumptions!$M$21/SUM(Assumptions!$C$21:$N$21)) -> 810000 | AZ6: =(Assumptions!$C$16*Assumptions!$F$18/12)*IF(SUM(Assumptions!$C$21:$N$21)=0,1,12*Assumptions!$N$21/SUM(Assumptions!$C$21:$N$21)) -> 630000 | BA6: =SUM(AO6:AZ6) -> 9000000 | BB6: =(Assumptions!$C$16*Assumptions!$G$18/12)*IF(SUM(Assumptions!$C$21:$N$21)=0,1,12*Assumptions!$C$21/SUM(Assumptions!$C$21:$N$21)) -> 768000 | BC6: =(Assumptions!$C$16*Assumptions!$G$18/12)*IF(SUM(Assumptions!$C$21:$N$21)=0,1,12*Assumptions!$D$21/SUM(Assumptions!$C$21:$N$21)) -> 768000 | BD6: =(Assumptions!$C$16*Assumptions!$G$18/12)*IF(SUM(Assumptions!$C$21:$N$21)=0,1,12*Assumptions!$E$21/SUM(Assumptions!$C$21:$N$21)) -> 768000 | BE6: =(Assumptions!$C$16*Assumptions!$G$18/12)*IF(SUM(Assumptions!$C$21:$N$21)=0,1,12*Assumptions!$F$21/SUM(Assumptions!$C$21:$N$21)) -> 864000 | BF6: =(Assumptions!$C$16*Assumptions!$G$18/12)*IF(SUM(Assumptions!$C$21:$N$21)=0,1,12*Assumptions!$G$21/SUM(Assumptions!$C$21:$N$21)) -> 864000 | BG6: =(Assumptions!$C$16*Assumptions!$G$18/12)*IF(SUM(Assumptions!$C$21:$N$21)=0,1,12*Assumptions!$H$21/SUM(Assumptions!$C$21:$N$21)) -> 864000 | BH6: =(Assumptions!$C$16*Assumptions!$G$18/12)*IF(SUM(Assumptions!$C$21:$N$21)=0,1,12*Assumptions!$I$21/SUM(Assumptions!$C$21:$N$21)) -> 768000 | BI6: =(Assumptions!$C$16*Assumptions!$G$18/12)*IF(SUM(Assumptions!$C$21:$N$21)=0,1,12*Assumptions!$J$21/SUM(Assumptions!$C$21:$N$21)) -> 768000 | BJ6: =(Assumptions!$C$16*Assumptions!$G$18/12)*IF(SUM(Assumptions!$C$21:$N$21)=0,1,12*Assumptions!$K$21/SUM(Assumptions!$C$21:$N$21)) -> 768000 | BK6: =(Assumptions!$C$16*Assumptions!$G$18/12)*IF(SUM(Assumptions!$C$21:$N$21)=0,1,12*Assumptions!$L$21/SUM(Assumptions!$C$21:$N$21)) -> 864000 | BL6: =(Assumptions!$C$16*Assumptions!$G$18/12)*IF(SUM(Assumptions!$C$21:$N$21)=0,1,12*Assumptions!$M$21/SUM(Assumptions!$C$21:$N$21)) -> 864000 | BM6: =(Assumptions!$C$16*Assumptions!$G$18/12)*IF(SUM(Assumptions!$C$21:$N$21)=0,1,12*Assumptions!$N$21/SUM(Assumptions!$C$21:$N$21)) -> 672000 | BN6: =SUM(BB6:BM6) -> 9600000

Sheet Sales
A1: SALES PLAN — 60-MONTH PROJECTION
A2: Sales quantity = production; revenue = quantity × escalated selling price.
B3: YEAR 1 | O3: YEAR 2 | AB3: YEAR 3 | AO3: YEAR 4 | BB3: YEAR 5
A4: Particulars | B4: M1 | C4: M2 | D4: M3 | E4: M4 | F4: M5 | G4: M6 | H4: M7 | I4: M8 | J4: M9 | K4: M10 | L4: M11 | M4: M12 | N4: Yr 1 Total | O4: M13 | P4: M14 | Q4: M15 | R4: M16 | S4: M17 | T4: M18 | U4: M19 | V4: M20 | W4: M21 | X4: M22 | Y4: M23 | Z4: M24 | AA4: Yr 2 Total | AB4: M25 | AC4: M26 | AD4: M27 | AE4: M28 | AF4: M29 | AG4: M30 | AH4: M31 | AI4: M32 | AJ4: M33 | AK4: M34 | AL4: M35 | AM4: M36 | AN4: Yr 3 Total | AO4: M37 | AP4: M38 | AQ4: M39 | AR4: M40 | AS4: M41 | AT4: M42 | AU4: M43 | AV4: M44 | AW4: M45 | AX4: M46 | AY4: M47 | AZ4: M48 | BA4: Yr 4 Total | BB4: M49 | BC4: M50 | BD4: M51 | BE4: M52 | BF4: M53 | BG4: M54 | BH4: M55 | BI4: M56 | BJ4: M57 | BK4: M58 | BL4: M59 | BM4: M60 | BN4: Yr 5 Total
A5: Sales quantity (units) | B5: =Production!B6 -> 576000 | C5: =Production!C6 -> 576000 | D5: =Production!D6 -> 576000 | E5: =Production!E6 -> 648000 | F5: =Production!F6 -> 648000 | G5: =Production!G6 -> 648000 | H5: =Production!H6 -> 576000 | I5: =Production!I6 -> 576000 | ... M5: =Production!M6 -> 504000 | N5: =SUM(B5:M5) -> 7200000 | O5: =Production!O6 -> 624000 | P5: =Production!P6 -> 624000 | Q5: =Production!Q6 -> 624000 | R5: =Production!R6 -> 702000 | S5: =Production!S6 -> 702000 | T5: =Production!T6 -> 702000 | U5: =Production!U6 -> 624000 | V5: =Production!V6 -> 624000 | ... Z5: =Production!Z6 -> 546000 | AA5: =SUM(O5:Z5) -> 7800000 | AB5: =Production!AB6 -> 672000 | AC5: =Production!AC6 -> 672000 | AD5: =Production!AD6 -> 672000 | AE5: =Production!AE6 -> 756000 | AF5: =Production!AF6 -> 756000 | AG5: =Production!AG6 -> 756000 | AH5: =Production!AH6 -> 672000 | AI5: =Production!AI6 -> 672000 | ... AM5: =Production!AM6 -> 588000 | AN5: =SUM(AB5:AM5) -> 8400000 | AO5: =Production!AO6 -> 720000 | AP5: =Production!AP6 -> 720000 | AQ5: =Production!AQ6 -> 720000 | AR5: =Production!AR6 -> 810000 | AS5: =Production!AS6 -> 810000 | AT5: =Production!AT6 -> 810000 | AU5: =Production!AU6 -> 720000 | AV5: =Production!AV6 -> 720000 | ... AZ5: =Production!AZ6 -> 630000 | BA5: =SUM(AO5:AZ5) -> 9000000 | BB5: =Production!BB6 -> 768000 | BC5: =Production!BC6 -> 768000 | BD5: =Production!BD6 -> 768000 | BE5: =Production!BE6 -> 864000 | BF5: =Production!BF6 -> 864000 | BG5: =Production!BG6 -> 864000 | BH5: =Production!BH6 -> 768000 | BI5: =Production!BI6 -> 768000 | ... BM5: =Production!BM6 -> 672000 | BN5: =SUM(BB5:BM5) -> 9600000
A6: Selling price (₹ / unit) | B6: =Assumptions!$C$23*(1+Assumptions!$C$24)^0 -> 5 | C6: =Assumptions!$C$23*(1+Assumptions!$C$24)^0 -> 5 | D6: =Assumptions!$C$23*(1+Assumptions!$C$24)^0 -> 5 | E6: =Assumptions!$C$23*(1+Assumptions!$C$24)^0 -> 5 | F6: =Assumptions!$C$23*(1+Assumptions!$C$24)^0 -> 5 | G6: =Assumptions!$C$23*(1+Assumptions!$C$24)^0 -> 5 | H6: =Assumptions!$C$23*(1+Assumptions!$C$24)^0 -> 5 | I6: =Assumptions!$C$23*(1+Assumptions!$C$24)^0 -> 5 | ... N6: =Assumptions!$C$23*(1+Assumptions!$C$24)^0 -> 5 | O6: =Assumptions!$C$23*(1+Assumptions!$C$24)^1 -> 5.2 | P6: =Assumptions!$C$23*(1+Assumptions!$C$24)^1 -> 5.2 | Q6: =Assumptions!$C$23*(1+Assumptions!$C$24)^1 -> 5.2 | R6: =Assumptions!$C$23*(1+Assumptions!$C$24)^1 -> 5.2 | S6: =Assumptions!$C$23*(1+Assumptions!$C$24)^1 -> 5.2 | T6: =Assumptions!$C$23*(1+Assumptions!$C$24)^1 -> 5.2 | U6: =Assumptions!$C$23*(1+Assumptions!$C$24)^1 -> 5.2 | V6: =Assumptions!$C$23*(1+Assumptions!$C$24)^1 -> 5.2 | ... AA6: =Assumptions!$C$23*(1+Assumptions!$C$24)^1 -> 5.2 | AB6: =Assumptions!$C$23*(1+Assumptions!$C$24)^2 -> 5.408 | AC6: =Assumptions!$C$23*(1+Assumptions!$C$24)^2 -> 5.408 | AD6: =Assumptions!$C$23*(1+Assumptions!$C$24)^2 -> 5.408 | AE6: =Assumptions!$C$23*(1+Assumptions!$C$24)^2 -> 5.408 | AF6: =Assumptions!$C$23*(1+Assumptions!$C$24)^2 -> 5.408 | AG6: =Assumptions!$C$23*(1+Assumptions!$C$24)^2 -> 5.408 | AH6: =Assumptions!$C$23*(1+Assumptions!$C$24)^2 -> 5.408 | AI6: =Assumptions!$C$23*(1+Assumptions!$C$24)^2 -> 5.408 | ... AN6: =Assumptions!$C$23*(1+Assumptions!$C$24)^2 -> 5.408 | AO6: =Assumptions!$C$23*(1+Assumptions!$C$24)^3 -> 5.62432 | AP6: =Assumptions!$C$23*(1+Assumptions!$C$24)^3 -> 5.62432 | AQ6: =Assumptions!$C$23*(1+Assumptions!$C$24)^3 -> 5.62432 | AR6: =Assumptions!$C$23*(1+Assumptions!$C$24)^3 -> 5.62432 | AS6: =Assumptions!$C$23*(1+Assumptions!$C$24)^3 -> 5.62432 | AT6: =Assumptions!$C$23*(1+Assumptions!$C$24)^3 -> 5.62432 | AU6: =Assumptions!$C$23*(1+Assumptions!$C$24)^3 -> 5.62432 | AV6: =Assumptions!$C$23*(1+Assumptions!$C$24)^3 -> 5.62432 | ... BA6: =Assumptions!$C$23*(1+Assumptions!$C$24)^3 -> 5.62432 | BB6: =Assumptions!$C$23*(1+Assumptions!$C$24)^4 -> 5.8492928 | BC6: =Assumptions!$C$23*(1+Assumptions!$C$24)^4 -> 5.8492928 | BD6: =Assumptions!$C$23*(1+Assumptions!$C$24)^4 -> 5.8492928 | BE6: =Assumptions!$C$23*(1+Assumptions!$C$24)^4 -> 5.8492928 | BF6: =Assumptions!$C$23*(1+Assumptions!$C$24)^4 -> 5.8492928 | BG6: =Assumptions!$C$23*(1+Assumptions!$C$24)^4 -> 5.8492928 | BH6: =Assumptions!$C$23*(1+Assumptions!$C$24)^4 -> 5.8492928 | BI6: =Assumptions!$C$23*(1+Assumptions!$C$24)^4 -> 5.8492928 | ... BN6: =Assumptions!$C$23*(1+Assumptions!$C$24)^4 -> 5.8492928
A7: Net Sales / Revenue (₹) | B7: =B5*B6 -> 2880000 | C7: =C5*C6 -> 2880000 | D7: =D5*D6 -> 2880000 | E7: =E5*E6 -> 3240000 | F7: =F5*F6 -> 3240000 | G7: =G5*G6 -> 3240000 | H7: =H5*H6 -> 2880000 | I7: =I5*I6 -> 2880000 | ... M7: =M5*M6 -> 2520000 | N7: =SUM(B7:M7) -> 36000000 | O7: =O5*O6 -> 3244800 | P7: =P5*P6 -> 3244800 | Q7: =Q5*Q6 -> 3244800 | R7: =R5*R6 -> 3650400 | S7: =S5*S6 -> 3650400 | T7: =T5*T6 -> 3650400 | U7: =U5*U6 -> 3244800 | V7: =V5*V6 -> 3244800 | ... Z7: =Z5*Z6 -> 2839200 | AA7: =SUM(O7:Z7) -> 40560000 | AB7: =AB5*AB6 -> 3634176 | AC7: =AC5*AC6 -> 3634176 | AD7: =AD5*AD6 -> 3634176 | AE7: =AE5*AE6 -> 4088448 | AF7: =AF5*AF6 -> 4088448 | AG7: =AG5*AG6 -> 4088448 | AH7: =AH5*AH6 -> 3634176 | AI7: =AI5*AI6 -> 3634176 | ... AM7: =AM5*AM6 -> 3179904 | AN7: =SUM(AB7:AM7) -> 45427200 | AO7: =AO5*AO6 -> 4049510.4 | AP7: =AP5*AP6 -> 4049510.4 | AQ7: =AQ5*AQ6 -> 4049510.4 | AR7: =AR5*AR6 -> 4555699.2 | AS7: =AS5*AS6 -> 4555699.2 | AT7: =AT5*AT6 -> 4555699.2 | AU7: =AU5*AU6 -> 4049510.4 | AV7: =AV5*AV6 -> 4049510.4 | ... AZ7: =AZ5*AZ6 -> 3543321.6 | BA7: =SUM(AO7:AZ7) -> 50618880 | BB7: =BB5*BB6 -> 4492256.9 | BC7: =BC5*BC6 -> 4492256.9 | BD7: =BD5*BD6 -> 4492256.9 | BE7: =BE5*BE6 -> 5053789 | BF7: =BF5*BF6 -> 5053789 | BG7: =BG5*BG6 -> 5053789 | BH7: =BH5*BH6 -> 4492256.9 | BI7: =BI5*BI6 -> 4492256.9 | ... BM7: =BM5*BM6 -> 3930724.8 | BN7: =SUM(BB7:BM7) -> 56153211

Sheet Expenses
A1: OPERATING EXPENSES — 60-MONTH PROJECTION
A2: Variable costs scale with production; period costs escalate annually; interest & depreciation linked.
B3: YEAR 1 | O3: YEAR 2 | AB3: YEAR 3 | AO3: YEAR 4 | BB3: YEAR 5
A4: Particulars | B4: M1 | C4: M2 | D4: M3 | E4: M4 | F4: M5 | G4: M6 | H4: M7 | I4: M8 | J4: M9 | K4: M10 | L4: M11 | M4: M12 | N4: Yr 1 Total | O4: M13 | P4: M14 | Q4: M15 | R4: M16 | S4: M17 | T4: M18 | U4: M19 | V4: M20 | W4: M21 | X4: M22 | Y4: M23 | Z4: M24 | AA4: Yr 2 Total | AB4: M25 | AC4: M26 | AD4: M27 | AE4: M28 | AF4: M29 | AG4: M30 | AH4: M31 | AI4: M32 | AJ4: M33 | AK4: M34 | AL4: M35 | AM4: M36 | AN4: Yr 3 Total | AO4: M37 | AP4: M38 | AQ4: M39 | AR4: M40 | AS4: M41 | AT4: M42 | AU4: M43 | AV4: M44 | AW4: M45 | AX4: M46 | AY4: M47 | AZ4: M48 | BA4: Yr 4 Total | BB4: M49 | BC4: M50 | BD4: M51 | BE4: M52 | BF4: M53 | BG4: M54 | BH4: M55 | BI4: M56 | BJ4: M57 | BK4: M58 | BL4: M59 | BM4: M60 | BN4: Yr 5 Total
A5: =IFERROR(VLOOKUP(Assumptions!$J$5,Assumptions!$S$5:$Z$21,5,FALSE()),"Raw materials") -> Raw materials | B5: =Production!B6*(Assumptions!$C$25*(1+Assumptions!$C$26)^0) -> 1440000 | C5: =Production!C6*(Assumptions!$C$25*(1+Assumptions!$C$26)^0) -> 1440000 | D5: =Production!D6*(Assumptions!$C$25*(1+Assumptions!$C$26)^0) -> 1440000 | E5: =Production!E6*(Assumptions!$C$25*(1+Assumptions!$C$26)^0) -> 1620000 | F5: =Production!F6*(Assumptions!$C$25*(1+Assumptions!$C$26)^0) -> 1620000 | G5: =Production!G6*(Assumptions!$C$25*(1+Assumptions!$C$26)^0) -> 1620000 | H5: =Production!H6*(Assumptions!$C$25*(1+Assumptions!$C$26)^0) -> 1440000 | I5: =Production!I6*(Assumptions!$C$25*(1+Assumptions!$C$26)^0) -> 1440000 | ... M5: =Production!M6*(Assumptions!$C$25*(1+Assumptions!$C$26)^0) -> 1260000 | N5: =SUM(B5:M5) -> 18000000 | O5: =Production!O6*(Assumptions!$C$25*(1+Assumptions!$C$26)^1) -> 1638000 | P5: =Production!P6*(Assumptions!$C$25*(1+Assumptions!$C$26)^1) -> 1638000 | Q5: =Production!Q6*(Assumptions!$C$25*(1+Assumptions!$C$26)^1) -> 1638000 | R5: =Production!R6*(Assumptions!$C$25*(1+Assumptions!$C$26)^1) -> 1842750 | S5: =Production!S6*(Assumptions!$C$25*(1+Assumptions!$C$26)^1) -> 1842750 | T5: =Production!T6*(Assumptions!$C$25*(1+Assumptions!$C$26)^1) -> 1842750 | U5: =Production!U6*(Assumptions!$C$25*(1+Assumptions!$C$26)^1) -> 1638000 | V5: =Production!V6*(Assumptions!$C$25*(1+Assumptions!$C$26)^1) -> 1638000 | ... Z5: =Production!Z6*(Assumptions!$C$25*(1+Assumptions!$C$26)^1) -> 1433250 | AA5: =SUM(O5:Z5) -> 20475000 | AB5: =Production!AB6*(Assumptions!$C$25*(1+Assumptions!$C$26)^2) -> 1852200 | AC5: =Production!AC6*(Assumptions!$C$25*(1+Assumptions!$C$26)^2) -> 1852200 | AD5: =Production!AD6*(Assumptions!$C$25*(1+Assumptions!$C$26)^2) -> 1852200 | AE5: =Production!AE6*(Assumptions!$C$25*(1+Assumptions!$C$26)^2) -> 2083725 | AF5: =Production!AF6*(Assumptions!$C$25*(1+Assumptions!$C$26)^2) -> 2083725 | AG5: =Production!AG6*(Assumptions!$C$25*(1+Assumptions!$C$26)^2) -> 2083725 | AH5: =Production!AH6*(Assumptions!$C$25*(1+Assumptions!$C$26)^2) -> 1852200 | AI5: =Production!AI6*(Assumptions!$C$25*(1+Assumptions!$C$26)^2) -> 1852200 | ... AM5: =Production!AM6*(Assumptions!$C$25*(1+Assumptions!$C$26)^2) -> 1620675 | AN5: =SUM(AB5:AM5) -> 23152500 | AO5: =Production!AO6*(Assumptions!$C$25*(1+Assumptions!$C$26)^3) -> 2083725 | AP5: =Production!AP6*(Assumptions!$C$25*(1+Assumptions!$C$26)^3) -> 2083725 | AQ5: =Production!AQ6*(Assumptions!$C$25*(1+Assumptions!$C$26)^3) -> 2083725 | AR5: =Production!AR6*(Assumptions!$C$25*(1+Assumptions!$C$26)^3) -> 2344190.6 | AS5: =Production!AS6*(Assumptions!$C$25*(1+Assumptions!$C$26)^3) -> 2344190.6 | AT5: =Production!AT6*(Assumptions!$C$25*(1+Assumptions!$C$26)^3) -> 2344190.6 | AU5: =Production!AU6*(Assumptions!$C$25*(1+Assumptions!$C$26)^3) -> 2083725 | AV5: =Production!AV6*(Assumptions!$C$25*(1+Assumptions!$C$26)^3) -> 2083725 | ... AZ5: =Production!AZ6*(Assumptions!$C$25*(1+Assumptions!$C$26)^3) -> 1823259.4 | BA5: =SUM(AO5:AZ5) -> 26046563 | BB5: =Production!BB6*(Assumptions!$C$25*(1+Assumptions!$C$26)^4) -> 2333772 | BC5: =Production!BC6*(Assumptions!$C$25*(1+Assumptions!$C$26)^4) -> 2333772 | BD5: =Production!BD6*(Assumptions!$C$25*(1+Assumptions!$C$26)^4) -> 2333772 | BE5: =Production!BE6*(Assumptions!$C$25*(1+Assumptions!$C$26)^4) -> 2625493.5 | BF5: =Production!BF6*(Assumptions!$C$25*(1+Assumptions!$C$26)^4) -> 2625493.5 | BG5: =Production!BG6*(Assumptions!$C$25*(1+Assumptions!$C$26)^4) -> 2625493.5 | BH5: =Production!BH6*(Assumptions!$C$25*(1+Assumptions!$C$26)^4) -> 2333772 | BI5: =Production!BI6*(Assumptions!$C$25*(1+Assumptions!$C$26)^4) -> 2333772 | ... BM5: =Production!BM6*(Assumptions!$C$25*(1+Assumptions!$C$26)^4) -> 2042050.5 | BN5: =SUM(BB5:BM5) -> 29172150
A6: =IFERROR(VLOOKUP(Assumptions!$J$5,Assumptions!$S$5:$Z$21,7,FALSE()),"Power & fuel") -> Power & fuel | B6: =Production!B6*(Assumptions!$C$27*(1+Assumptions!$C$28)^0) -> 172800 | C6: =Production!C6*(Assumptions!$C$27*(1+Assumptions!$C$28)^0) -> 172800 | D6: =Production!D6*(Assumptions!$C$27*(1+Assumptions!$C$28)^0) -> 172800 | E6: =Production!E6*(Assumptions!$C$27*(1+Assumptions!$C$28)^0) -> 194400 | F6: =Production!F6*(Assumptions!$C$27*(1+Assumptions!$C$28)^0) -> 194400 | G6: =Production!G6*(Assumptions!$C$27*(1+Assumptions!$C$28)^0) -> 194400 | H6: =Production!H6*(Assumptions!$C$27*(1+Assumptions!$C$28)^0) -> 172800 | I6: =Production!I6*(Assumptions!$C$27*(1+Assumptions!$C$28)^0) -> 172800 | ... M6: =Production!M6*(Assumptions!$C$27*(1+Assumptions!$C$28)^0) -> 151200 | N6: =SUM(B6:M6) -> 2160000 | O6: =Production!O6*(Assumptions!$C$27*(1+Assumptions!$C$28)^1) -> 198432 | P6: =Production!P6*(Assumptions!$C$27*(1+Assumptions!$C$28)^1) -> 198432 | Q6: =Production!Q6*(Assumptions!$C$27*(1+Assumptions!$C$28)^1) -> 198432 | R6: =Production!R6*(Assumptions!$C$27*(1+Assumptions!$C$28)^1) -> 223236 | S6: =Production!S6*(Assumptions!$C$27*(1+Assumptions!$C$28)^1) -> 223236 | T6: =Production!T6*(Assumptions!$C$27*(1+Assumptions!$C$28)^1) -> 223236 | U6: =Production!U6*(Assumptions!$C$27*(1+Assumptions!$C$28)^1) -> 198432 | V6: =Production!V6*(Assumptions!$C$27*(1+Assumptions!$C$28)^1) -> 198432 | ... Z6: =Production!Z6*(Assumptions!$C$27*(1+Assumptions!$C$28)^1) -> 173628 | AA6: =SUM(O6:Z6) -> 2480400 | AB6: =Production!AB6*(Assumptions!$C$27*(1+Assumptions!$C$28)^2) -> 226517.76 | AC6: =Production!AC6*(Assumptions!$C$27*(1+Assumptions!$C$28)^2) -> 226517.76 | AD6: =Production!AD6*(Assumptions!$C$27*(1+Assumptions!$C$28)^2) -> 226517.76 | AE6: =Production!AE6*(Assumptions!$C$27*(1+Assumptions!$C$28)^2) -> 254832.48 | AF6: =Production!AF6*(Assumptions!$C$27*(1+Assumptions!$C$28)^2) -> 254832.48 | AG6: =Production!AG6*(Assumptions!$C$27*(1+Assumptions!$C$28)^2) -> 254832.48 | AH6: =Production!AH6*(Assumptions!$C$27*(1+Assumptions!$C$28)^2) -> 226517.76 | AI6: =Production!AI6*(Assumptions!$C$27*(1+Assumptions!$C$28)^2) -> 226517.76 | ... AM6: =Production!AM6*(Assumptions!$C$27*(1+Assumptions!$C$28)^2) -> 198203.04 | AN6: =SUM(AB6:AM6) -> 2831472 | AO6: =Production!AO6*(Assumptions!$C$27*(1+Assumptions!$C$28)^3) -> 257259.46 | AP6: =Production!AP6*(Assumptions!$C$27*(1+Assumptions!$C$28)^3) -> 257259.46 | AQ6: =Production!AQ6*(Assumptions!$C$27*(1+Assumptions!$C$28)^3) -> 257259.46 | AR6: =Production!AR6*(Assumptions!$C$27*(1+Assumptions!$C$28)^3) -> 289416.89 | AS6: =Production!AS6*(Assumptions!$C$27*(1+Assumptions!$C$28)^3) -> 289416.89 | AT6: =Production!AT6*(Assumptions!$C$27*(1+Assumptions!$C$28)^3) -> 289416.89 | AU6: =Production!AU6*(Assumptions!$C$27*(1+Assumptions!$C$28)^3) -> 257259.46 | AV6: =Production!AV6*(Assumptions!$C$27*(1+Assumptions!$C$28)^3) -> 257259.46 | ... AZ6: =Production!AZ6*(Assumptions!$C$27*(1+Assumptions!$C$28)^3) -> 225102.02 | BA6: =SUM(AO6:AZ6) -> 3215743.2 | BB6: =Production!BB6*(Assumptions!$C$27*(1+Assumptions!$C$28)^4) -> 290874.69 | BC6: =Production!BC6*(Assumptions!$C$27*(1+Assumptions!$C$28)^4) -> 290874.69 | BD6: =Production!BD6*(Assumptions!$C$27*(1+Assumptions!$C$28)^4) -> 290874.69 | BE6: =Production!BE6*(Assumptions!$C$27*(1+Assumptions!$C$28)^4) -> 327234.03 | BF6: =Production!BF6*(Assumptions!$C$27*(1+Assumptions!$C$28)^4) -> 327234.03 | BG6: =Production!BG6*(Assumptions!$C$27*(1+Assumptions!$C$28)^4) -> 327234.03 | BH6: =Production!BH6*(Assumptions!$C$27*(1+Assumptions!$C$28)^4) -> 290874.69 | BI6: =Production!BI6*(Assumptions!$C$27*(1+Assumptions!$C$28)^4) -> 290874.69 | ... BM6: =Production!BM6*(Assumptions!$C$27*(1+Assumptions!$C$28)^4) -> 254515.36 | BN6: =SUM(BB6:BM6) -> 3635933.6
A7: Direct wages & salaries | B7: =Assumptions!$C$32*(1+Assumptions!$C$33)^0 -> 150000 | C7: =Assumptions!$C$32*(1+Assumptions!$C$33)^0 -> 150000 | D7: =Assumptions!$C$32*(1+Assumptions!$C$33)^0 -> 150000 | E7: =Assumptions!$C$32*(1+Assumptions!$C$33)^0 -> 150000 | F7: =Assumptions!$C$32*(1+Assumptions!$C$33)^0 -> 150000 | G7: =Assumptions!$C$32*(1+Assumptions!$C$33)^0 -> 150000 | H7: =Assumptions!$C$32*(1+Assumptions!$C$33)^0 -> 150000 | I7: =Assumptions!$C$32*(1+Assumptions!$C$33)^0 -> 150000 | ... M7: =Assumptions!$C$32*(1+Assumptions!$C$33)^0 -> 150000 | N7: =SUM(B7:M7) -> 1800000 | O7: =Assumptions!$C$32*(1+Assumptions!$C$33)^1 -> 157500 | P7: =Assumptions!$C$32*(1+Assumptions!$C$33)^1 -> 157500 | Q7: =Assumptions!$C$32*(1+Assumptions!$C$33)^1 -> 157500 | R7: =Assumptions!$C$32*(1+Assumptions!$C$33)^1 -> 157500 | S7: =Assumptions!$C$32*(1+Assumptions!$C$33)^1 -> 157500 | T7: =Assumptions!$C$32*(1+Assumptions!$C$33)^1 -> 157500 | U7: =Assumptions!$C$32*(1+Assumptions!$C$33)^1 -> 157500 | V7: =Assumptions!$C$32*(1+Assumptions!$C$33)^1 -> 157500 | ... Z7: =Assumptions!$C$32*(1+Assumptions!$C$33)^1 -> 157500 | AA7: =SUM(O7:Z7) -> 1890000 | AB7: =Assumptions!$C$32*(1+Assumptions!$C$33)^2 -> 165375 | AC7: =Assumptions!$C$32*(1+Assumptions!$C$33)^2 -> 165375 | AD7: =Assumptions!$C$32*(1+Assumptions!$C$33)^2 -> 165375 | AE7: =Assumptions!$C$32*(1+Assumptions!$C$33)^2 -> 165375 | AF7: =Assumptions!$C$32*(1+Assumptions!$C$33)^2 -> 165375 | AG7: =Assumptions!$C$32*(1+Assumptions!$C$33)^2 -> 165375 | AH7: =Assumptions!$C$32*(1+Assumptions!$C$33)^2 -> 165375 | AI7: =Assumptions!$C$32*(1+Assumptions!$C$33)^2 -> 165375 | ... AM7: =Assumptions!$C$32*(1+Assumptions!$C$33)^2 -> 165375 | AN7: =SUM(AB7:AM7) -> 1984500 | AO7: =Assumptions!$C$32*(1+Assumptions!$C$33)^3 -> 173643.75 | AP7: =Assumptions!$C$32*(1+Assumptions!$C$33)^3 -> 173643.75 | AQ7: =Assumptions!$C$32*(1+Assumptions!$C$33)^3 -> 173643.75 | AR7: =Assumptions!$C$32*(1+Assumptions!$C$33)^3 -> 173643.75 | AS7: =Assumptions!$C$32*(1+Assumptions!$C$33)^3 -> 173643.75 | AT7: =Assumptions!$C$32*(1+Assumptions!$C$33)^3 -> 173643.75 | AU7: =Assumptions!$C$32*(1+Assumptions!$C$33)^3 -> 173643.75 | AV7: =Assumptions!$C$32*(1+Assumptions!$C$33)^3 -> 173643.75 | ... AZ7: =Assumptions!$C$32*(1+Assumptions!$C$33)^3 -> 173643.75 | BA7: =SUM(AO7:AZ7) -> 2083725 | BB7: =Assumptions!$C$32*(1+Assumptions!$C$33)^4 -> 182325.94 | BC7: =Assumptions!$C$32*(1+Assumptions!$C$33)^4 -> 182325.94 | BD7: =Assumptions!$C$32*(1+Assumptions!$C$33)^4 -> 182325.94 | BE7: =Assumptions!$C$32*(1+Assumptions!$C$33)^4 -> 182325.94 | BF7: =Assumptions!$C$32*(1+Assumptions!$C$33)^4 -> 182325.94 | BG7: =Assumptions!$C$32*(1+Assumptions!$C$33)^4 -> 182325.94 | BH7: =Assumptions!$C$32*(1+Assumptions!$C$33)^4 -> 182325.94 | BI7: =Assumptions!$C$32*(1+Assumptions!$C$33)^4 -> 182325.94 | ... BM7: =Assumptions!$C$32*(1+Assumptions!$C$33)^4 -> 182325.94 | BN7: =SUM(BB7:BM7) -> 2187911.2
A8: Other variable cost | B8: =Production!B6*(Assumptions!$C$29*(1+Assumptions!$C$30)^0) -> 115200 | C8: =Production!C6*(Assumptions!$C$29*(1+Assumptions!$C$30)^0) -> 115200 | D8: =Production!D6*(Assumptions!$C$29*(1+Assumptions!$C$30)^0) -> 115200 | E8: =Production!E6*(Assumptions!$C$29*(1+Assumptions!$C$30)^0) -> 129600 | F8: =Production!F6*(Assumptions!$C$29*(1+Assumptions!$C$30)^0) -> 129600 | G8: =Production!G6*(Assumptions!$C$29*(1+Assumptions!$C$30)^0) -> 129600 | H8: =Production!H6*(Assumptions!$C$29*(1+Assumptions!$C$30)^0) -> 115200 | I8: =Production!I6*(Assumptions!$C$29*(1+Assumptions!$C$30)^0) -> 115200 | ... M8: =Production!M6*(Assumptions!$C$29*(1+Assumptions!$C$30)^0) -> 100800 | N8: =SUM(B8:M8) -> 1440000 | O8: =Production!O6*(Assumptions!$C$29*(1+Assumptions!$C$30)^1) -> 129792 | P8: =Production!P6*(Assumptions!$C$29*(1+Assumptions!$C$30)^1) -> 129792 | Q8: =Production!Q6*(Assumptions!$C$29*(1+Assumptions!$C$30)^1) -> 129792 | R8: =Production!R6*(Assumptions!$C$29*(1+Assumptions!$C$30)^1) -> 146016 | S8: =Production!S6*(Assumptions!$C$29*(1+Assumptions!$C$30)^1) -> 146016 | T8: =Production!T6*(Assumptions!$C$29*(1+Assumptions!$C$30)^1) -> 146016 | U8: =Production!U6*(Assumptions!$C$29*(1+Assumptions!$C$30)^1) -> 129792 | V8: =Production!V6*(Assumptions!$C$29*(1+Assumptions!$C$30)^1) -> 129792 | ... Z8: =Production!Z6*(Assumptions!$C$29*(1+Assumptions!$C$30)^1) -> 113568 | AA8: =SUM(O8:Z8) -> 1622400 | AB8: =Production!AB6*(Assumptions!$C$29*(1+Assumptions!$C$30)^2) -> 145367.04 | AC8: =Production!AC6*(Assumptions!$C$29*(1+Assumptions!$C$30)^2) -> 145367.04 | AD8: =Production!AD6*(Assumptions!$C$29*(1+Assumptions!$C$30)^2) -> 145367.04 | AE8: =Production!AE6*(Assumptions!$C$29*(1+Assumptions!$C$30)^2) -> 163537.92 | AF8: =Production!AF6*(Assumptions!$C$29*(1+Assumptions!$C$30)^2) -> 163537.92 | AG8: =Production!AG6*(Assumptions!$C$29*(1+Assumptions!$C$30)^2) -> 163537.92 | AH8: =Production!AH6*(Assumptions!$C$29*(1+Assumptions!$C$30)^2) -> 145367.04 | AI8: =Production!AI6*(Assumptions!$C$29*(1+Assumptions!$C$30)^2) -> 145367.04 | ... AM8: =Production!AM6*(Assumptions!$C$29*(1+Assumptions!$C$30)^2) -> 127196.16 | AN8: =SUM(AB8:AM8) -> 1817088 | AO8: =Production!AO6*(Assumptions!$C$29*(1+Assumptions!$C$30)^3) -> 161980.42 | AP8: =Production!AP6*(Assumptions!$C$29*(1+Assumptions!$C$30)^3) -> 161980.42 | AQ8: =Production!AQ6*(Assumptions!$C$29*(1+Assumptions!$C$30)^3) -> 161980.42 | AR8: =Production!AR6*(Assumptions!$C$29*(1+Assumptions!$C$30)^3) -> 182227.97 | AS8: =Production!AS6*(Assumptions!$C$29*(1+Assumptions!$C$30)^3) -> 182227.97 | AT8: =Production!AT6*(Assumptions!$C$29*(1+Assumptions!$C$30)^3) -> 182227.97 | AU8: =Production!AU6*(Assumptions!$C$29*(1+Assumptions!$C$30)^3) -> 161980.42 | AV8: =Production!AV6*(Assumptions!$C$29*(1+Assumptions!$C$30)^3) -> 161980.42 | ... AZ8: =Production!AZ6*(Assumptions!$C$29*(1+Assumptions!$C$30)^3) -> 141732.86 | BA8: =SUM(AO8:AZ8) -> 2024755.2 | BB8: =Production!BB6*(Assumptions!$C$29*(1+Assumptions!$C$30)^4) -> 179690.27 | BC8: =Production!BC6*(Assumptions!$C$29*(1+Assumptions!$C$30)^4) -> 179690.27 | BD8: =Production!BD6*(Assumptions!$C$29*(1+Assumptions!$C$30)^4) -> 179690.27 | BE8: =Production!BE6*(Assumptions!$C$29*(1+Assumptions!$C$30)^4) -> 202151.56 | BF8: =Production!BF6*(Assumptions!$C$29*(1+Assumptions!$C$30)^4) -> 202151.56 | BG8: =Production!BG6*(Assumptions!$C$29*(1+Assumptions!$C$30)^4) -> 202151.56 | BH8: =Production!BH6*(Assumptions!$C$29*(1+Assumptions!$C$30)^4) -> 179690.27 | BI8: =Production!BI6*(Assumptions!$C$29*(1+Assumptions!$C$30)^4) -> 179690.27 | ... BM8: =Production!BM6*(Assumptions!$C$29*(1+Assumptions!$C$30)^4) -> 157228.99 | BN8: =SUM(BB8:BM8) -> 2246128.4
A9: =IFERROR(VLOOKUP(Assumptions!$J$5,Assumptions!$S$5:$Z$21,8,FALSE()),"Factory overheads") -> Factory overheads | B9: =Assumptions!$C$34*(1+Assumptions!$C$35)^0 -> 100000 | C9: =Assumptions!$C$34*(1+Assumptions!$C$35)^0 -> 100000 | D9: =Assumptions!$C$34*(1+Assumptions!$C$35)^0 -> 100000 | E9: =Assumptions!$C$34*(1+Assumptions!$C$35)^0 -> 100000 | F9: =Assumptions!$C$34*(1+Assumptions!$C$35)^0 -> 100000 | G9: =Assumptions!$C$34*(1+Assumptions!$C$35)^0 -> 100000 | H9: =Assumptions!$C$34*(1+Assumptions!$C$35)^0 -> 100000 | I9: =Assumptions!$C$34*(1+Assumptions!$C$35)^0 -> 100000 | ... M9: =Assumptions!$C$34*(1+Assumptions!$C$35)^0 -> 100000 | N9: =SUM(B9:M9) -> 1200000 | O9: =Assumptions!$C$34*(1+Assumptions!$C$35)^1 -> 105000 | P9: =Assumptions!$C$34*(1+Assumptions!$C$35)^1 -> 105000 | Q9: =Assumptions!$C$34*(1+Assumptions!$C$35)^1 -> 105000 | R9: =Assumptions!$C$34*(1+Assumptions!$C$35)^1 -> 105000 | S9: =Assumptions!$C$34*(1+Assumptions!$C$35)^1 -> 105000 | T9: =Assumptions!$C$34*(1+Assumptions!$C$35)^1 -> 105000 | U9: =Assumptions!$C$34*(1+Assumptions!$C$35)^1 -> 105000 | V9: =Assumptions!$C$34*(1+Assumptions!$C$35)^1 -> 105000 | ... Z9: =Assumptions!$C$34*(1+Assumptions!$C$35)^1 -> 105000 | AA9: =SUM(O9:Z9) -> 1260000 | AB9: =Assumptions!$C$34*(1+Assumptions!$C$35)^2 -> 110250 | AC9: =Assumptions!$C$34*(1+Assumptions!$C$35)^2 -> 110250 | AD9: =Assumptions!$C$34*(1+Assumptions!$C$35)^2 -> 110250 | AE9: =Assumptions!$C$34*(1+Assumptions!$C$35)^2 -> 110250 | AF9: =Assumptions!$C$34*(1+Assumptions!$C$35)^2 -> 110250 | AG9: =Assumptions!$C$34*(1+Assumptions!$C$35)^2 -> 110250 | AH9: =Assumptions!$C$34*(1+Assumptions!$C$35)^2 -> 110250 | AI9: =Assumptions!$C$34*(1+Assumptions!$C$35)^2 -> 110250 | ... AM9: =Assumptions!$C$34*(1+Assumptions!$C$35)^2 -> 110250 | AN9: =SUM(AB9:AM9) -> 1323000 | AO9: =Assumptions!$C$34*(1+Assumptions!$C$35)^3 -> 115762.5 | AP9: =Assumptions!$C$34*(1+Assumptions!$C$35)^3 -> 115762.5 | AQ9: =Assumptions!$C$34*(1+Assumptions!$C$35)^3 -> 115762.5 | AR9: =Assumptions!$C$34*(1+Assumptions!$C$35)^3 -> 115762.5 | AS9: =Assumptions!$C$34*(1+Assumptions!$C$35)^3 -> 115762.5 | AT9: =Assumptions!$C$34*(1+Assumptions!$C$35)^3 -> 115762.5 | AU9: =Assumptions!$C$34*(1+Assumptions!$C$35)^3 -> 115762.5 | AV9: =Assumptions!$C$34*(1+Assumptions!$C$35)^3 -> 115762.5 | ... AZ9: =Assumptions!$C$34*(1+Assumptions!$C$35)^3 -> 115762.5 | BA9: =SUM(AO9:AZ9) -> 1389150 | BB9: =Assumptions!$C$34*(1+Assumptions!$C$35)^4 -> 121550.62 | BC9: =Assumptions!$C$34*(1+Assumptions!$C$35)^4 -> 121550.62 | BD9: =Assumptions!$C$34*(1+Assumptions!$C$35)^4 -> 121550.62 | BE9: =Assumptions!$C$34*(1+Assumptions!$C$35)^4 -> 121550.62 | BF9: =Assumptions!$C$34*(1+Assumptions!$C$35)^4 -> 121550.62 | BG9: =Assumptions!$C$34*(1+Assumptions!$C$35)^4 -> 121550.62 | BH9: =Assumptions!$C$34*(1+Assumptions!$C$35)^4 -> 121550.62 | BI9: =Assumptions!$C$34*(1+Assumptions!$C$35)^4 -> 121550.62 | ... BM9: =Assumptions!$C$34*(1+Assumptions!$C$35)^4 -> 121550.62 | BN9: =SUM(BB9:BM9) -> 1458607.5
A10: Repairs & maintenance | B10: =Assumptions!$C$36*(1+Assumptions!$C$37)^0 -> 30000 | C10: =Assumptions!$C$36*(1+Assumptions!$C$37)^0 -> 30000 | D10: =Assumptions!$C$36*(1+Assumptions!$C$37)^0 -> 30000 | E10: =Assumptions!$C$36*(1+Assumptions!$C$37)^0 -> 30000 | F10: =Assumptions!$C$36*(1+Assumptions!$C$37)^0 -> 30000 | G10: =Assumptions!$C$36*(1+Assumptions!$C$37)^0 -> 30000 | H10: =Assumptions!$C$36*(1+Assumptions!$C$37)^0 -> 30000 | I10: =Assumptions!$C$36*(1+Assumptions!$C$37)^0 -> 30000 | ... M10: =Assumptions!$C$36*(1+Assumptions!$C$37)^0 -> 30000 | N10: =SUM(B10:M10) -> 360000 | O10: =Assumptions!$C$36*(1+Assumptions!$C$37)^1 -> 31200 | P10: =Assumptions!$C$36*(1+Assumptions!$C$37)^1 -> 31200 | Q10: =Assumptions!$C$36*(1+Assumptions!$C$37)^1 -> 31200 | R10: =Assumptions!$C$36*(1+Assumptions!$C$37)^1 -> 31200 | S10: =Assumptions!$C$36*(1+Assumptions!$C$37)^1 -> 31200 | T10: =Assumptions!$C$36*(1+Assumptions!$C$37)^1 -> 31200 | U10: =Assumptions!$C$36*(1+Assumptions!$C$37)^1 -> 31200 | V10: =Assumptions!$C$36*(1+Assumptions!$C$37)^1 -> 31200 | ... Z10: =Assumptions!$C$36*(1+Assumptions!$C$37)^1 -> 31200 | AA10: =SUM(O10:Z10) -> 374400 | AB10: =Assumptions!$C$36*(1+Assumptions!$C$37)^2 -> 32448 | AC10: =Assumptions!$C$36*(1+Assumptions!$C$37)^2 -> 32448 | AD10: =Assumptions!$C$36*(1+Assumptions!$C$37)^2 -> 32448 | AE10: =Assumptions!$C$36*(1+Assumptions!$C$37)^2 -> 32448 | AF10: =Assumptions!$C$36*(1+Assumptions!$C$37)^2 -> 32448 | AG10: =Assumptions!$C$36*(1+Assumptions!$C$37)^2 -> 32448 | AH10: =Assumptions!$C$36*(1+Assumptions!$C$37)^2 -> 32448 | AI10: =Assumptions!$C$36*(1+Assumptions!$C$37)^2 -> 32448 | ... AM10: =Assumptions!$C$36*(1+Assumptions!$C$37)^2 -> 32448 | AN10: =SUM(AB10:AM10) -> 389376 | AO10: =Assumptions!$C$36*(1+Assumptions!$C$37)^3 -> 33745.92 | AP10: =Assumptions!$C$36*(1+Assumptions!$C$37)^3 -> 33745.92 | AQ10: =Assumptions!$C$36*(1+Assumptions!$C$37)^3 -> 33745.92 | AR10: =Assumptions!$C$36*(1+Assumptions!$C$37)^3 -> 33745.92 | AS10: =Assumptions!$C$36*(1+Assumptions!$C$37)^3 -> 33745.92 | AT10: =Assumptions!$C$36*(1+Assumptions!$C$37)^3 -> 33745.92 | AU10: =Assumptions!$C$36*(1+Assumptions!$C$37)^3 -> 33745.92 | AV10: =Assumptions!$C$36*(1+Assumptions!$C$37)^3 -> 33745.92 | ... AZ10: =Assumptions!$C$36*(1+Assumptions!$C$37)^3 -> 33745.92 | BA10: =SUM(AO10:AZ10) -> 404951.04 | BB10: =Assumptions!$C$36*(1+Assumptions!$C$37)^4 -> 35095.757 | BC10: =Assumptions!$C$36*(1+Assumptions!$C$37)^4 -> 35095.757 | BD10: =Assumptions!$C$36*(1+Assumptions!$C$37)^4 -> 35095.757 | BE10: =Assumptions!$C$36*(1+Assumptions!$C$37)^4 -> 35095.757 | BF10: =Assumptions!$C$36*(1+Assumptions!$C$37)^4 -> 35095.757 | BG10: =Assumptions!$C$36*(1+Assumptions!$C$37)^4 -> 35095.757 | BH10: =Assumptions!$C$36*(1+Assumptions!$C$37)^4 -> 35095.757 | BI10: =Assumptions!$C$36*(1+Assumptions!$C$37)^4 -> 35095.757 | ... BM10: =Assumptions!$C$36*(1+Assumptions!$C$37)^4 -> 35095.757 | BN10: =SUM(BB10:BM10) -> 421149.08
A11: Administrative expenses | B11: =Assumptions!$C$38*(1+Assumptions!$C$39)^0 -> 50000 | C11: =Assumptions!$C$38*(1+Assumptions!$C$39)^0 -> 50000 | D11: =Assumptions!$C$38*(1+Assumptions!$C$39)^0 -> 50000 | E11: =Assumptions!$C$38*(1+Assumptions!$C$39)^0 -> 50000 | F11: =Assumptions!$C$38*(1+Assumptions!$C$39)^0 -> 50000 | G11: =Assumptions!$C$38*(1+Assumptions!$C$39)^0 -> 50000 | H11: =Assumptions!$C$38*(1+Assumptions!$C$39)^0 -> 50000 | I11: =Assumptions!$C$38*(1+Assumptions!$C$39)^0 -> 50000 | ... M11: =Assumptions!$C$38*(1+Assumptions!$C$39)^0 -> 50000 | N11: =SUM(B11:M11) -> 600000 | O11: =Assumptions!$C$38*(1+Assumptions!$C$39)^1 -> 52000 | P11: =Assumptions!$C$38*(1+Assumptions!$C$39)^1 -> 52000 | Q11: =Assumptions!$C$38*(1+Assumptions!$C$39)^1 -> 52000 | R11: =Assumptions!$C$38*(1+Assumptions!$C$39)^1 -> 52000 | S11: =Assumptions!$C$38*(1+Assumptions!$C$39)^1 -> 52000 | T11: =Assumptions!$C$38*(1+Assumptions!$C$39)^1 -> 52000 | U11: =Assumptions!$C$38*(1+Assumptions!$C$39)^1 -> 52000 | V11: =Assumptions!$C$38*(1+Assumptions!$C$39)^1 -> 52000 | ... Z11: =Assumptions!$C$38*(1+Assumptions!$C$39)^1 -> 52000 | AA11: =SUM(O11:Z11) -> 624000 | AB11: =Assumptions!$C$38*(1+Assumptions!$C$39)^2 -> 54080 | AC11: =Assumptions!$C$38*(1+Assumptions!$C$39)^2 -> 54080 | AD11: =Assumptions!$C$38*(1+Assumptions!$C$39)^2 -> 54080 | AE11: =Assumptions!$C$38*(1+Assumptions!$C$39)^2 -> 54080 | AF11: =Assumptions!$C$38*(1+Assumptions!$C$39)^2 -> 54080 | AG11: =Assumptions!$C$38*(1+Assumptions!$C$39)^2 -> 54080 | AH11: =Assumptions!$C$38*(1+Assumptions!$C$39)^2 -> 54080 | AI11: =Assumptions!$C$38*(1+Assumptions!$C$39)^2 -> 54080 | ... AM11: =Assumptions!$C$38*(1+Assumptions!$C$39)^2 -> 54080 | AN11: =SUM(AB11:AM11) -> 648960 | AO11: =Assumptions!$C$38*(1+Assumptions!$C$39)^3 -> 56243.2 | AP11: =Assumptions!$C$38*(1+Assumptions!$C$39)^3 -> 56243.2 | AQ11: =Assumptions!$C$38*(1+Assumptions!$C$39)^3 -> 56243.2 | AR11: =Assumptions!$C$38*(1+Assumptions!$C$39)^3 -> 56243.2 | AS11: =Assumptions!$C$38*(1+Assumptions!$C$39)^3 -> 56243.2 | AT11: =Assumptions!$C$38*(1+Assumptions!$C$39)^3 -> 56243.2 | AU11: =Assumptions!$C$38*(1+Assumptions!$C$39)^3 -> 56243.2 | AV11: =Assumptions!$C$38*(1+Assumptions!$C$39)^3 -> 56243.2 | ... AZ11: =Assumptions!$C$38*(1+Assumptions!$C$39)^3 -> 56243.2 | BA11: =SUM(AO11:AZ11) -> 674918.4 | BB11: =Assumptions!$C$38*(1+Assumptions!$C$39)^4 -> 58492.928 | BC11: =Assumptions!$C$38*(1+Assumptions!$C$39)^4 -> 58492.928 | BD11: =Assumptions!$C$38*(1+Assumptions!$C$39)^4 -> 58492.928 | BE11: =Assumptions!$C$38*(1+Assumptions!$C$39)^4 -> 58492.928 | BF11: =Assumptions!$C$38*(1+Assumptions!$C$39)^4 -> 58492.928 | BG11: =Assumptions!$C$38*(1+Assumptions!$C$39)^4 -> 58492.928 | BH11: =Assumptions!$C$38*(1+Assumptions!$C$39)^4 -> 58492.928 | BI11: =Assumptions!$C$38*(1+Assumptions!$C$39)^4 -> 58492.928 | ... BM11: =Assumptions!$C$38*(1+Assumptions!$C$39)^4 -> 58492.928 | BN11: =SUM(BB11:BM11) -> 701915.14
A12: Selling & distribution | B12: =Sales!B7*Assumptions!$C$40 -> 57600 | C12: =Sales!C7*Assumptions!$C$40 -> 57600 | D12: =Sales!D7*Assumptions!$C$40 -> 57600 | E12: =Sales!E7*Assumptions!$C$40 -> 64800 | F12: =Sales!F7*Assumptions!$C$40 -> 64800 | G12: =Sales!G7*Assumptions!$C$40 -> 64800 | H12: =Sales!H7*Assumptions!$C$40 -> 57600 | I12: =Sales!I7*Assumptions!$C$40 -> 57600 | ... M12: =Sales!M7*Assumptions!$C$40 -> 50400 | N12: =SUM(B12:M12) -> 720000 | O12: =Sales!O7*Assumptions!$C$40 -> 64896 | P12: =Sales!P7*Assumptions!$C$40 -> 64896 | Q12: =Sales!Q7*Assumptions!$C$40 -> 64896 | R12: =Sales!R7*Assumptions!$C$40 -> 73008 | S12: =Sales!S7*Assumptions!$C$40 -> 73008 | T12: =Sales!T7*Assumptions!$C$40 -> 73008 | U12: =Sales!U7*Assumptions!$C$40 -> 64896 | V12: =Sales!V7*Assumptions!$C$40 -> 64896 | ... Z12: =Sales!Z7*Assumptions!$C$40 -> 56784 | AA12: =SUM(O12:Z12) -> 811200 | AB12: =Sales!AB7*Assumptions!$C$40 -> 72683.52 | AC12: =Sales!AC7*Assumptions!$C$40 -> 72683.52 | AD12: =Sales!AD7*Assumptions!$C$40 -> 72683.52 | AE12: =Sales!AE7*Assumptions!$C$40 -> 81768.96 | AF12: =Sales!AF7*Assumptions!$C$40 -> 81768.96 | AG12: =Sales!AG7*Assumptions!$C$40 -> 81768.96 | AH12: =Sales!AH7*Assumptions!$C$40 -> 72683.52 | AI12: =Sales!AI7*Assumptions!$C$40 -> 72683.52 | ... AM12: =Sales!AM7*Assumptions!$C$40 -> 63598.08 | AN12: =SUM(AB12:AM12) -> 908544 | AO12: =Sales!AO7*Assumptions!$C$40 -> 80990.208 | AP12: =Sales!AP7*Assumptions!$C$40 -> 80990.208 | AQ12: =Sales!AQ7*Assumptions!$C$40 -> 80990.208 | AR12: =Sales!AR7*Assumptions!$C$40 -> 91113.984 | AS12: =Sales!AS7*Assumptions!$C$40 -> 91113.984 | AT12: =Sales!AT7*Assumptions!$C$40 -> 91113.984 | AU12: =Sales!AU7*Assumptions!$C$40 -> 80990.208 | AV12: =Sales!AV7*Assumptions!$C$40 -> 80990.208 | ... AZ12: =Sales!AZ7*Assumptions!$C$40 -> 70866.432 | BA12: =SUM(AO12:AZ12) -> 1012377.6 | BB12: =Sales!BB7*Assumptions!$C$40 -> 89845.137 | BC12: =Sales!BC7*Assumptions!$C$40 -> 89845.137 | BD12: =Sales!BD7*Assumptions!$C$40 -> 89845.137 | BE12: =Sales!BE7*Assumptions!$C$40 -> 101075.78 | BF12: =Sales!BF7*Assumptions!$C$40 -> 101075.78 | BG12: =Sales!BG7*Assumptions!$C$40 -> 101075.78 | BH12: =Sales!BH7*Assumptions!$C$40 -> 89845.137 | BI12: =Sales!BI7*Assumptions!$C$40 -> 89845.137 | ... BM12: =Sales!BM7*Assumptions!$C$40 -> 78614.495 | BN12: =SUM(BB12:BM12) -> 1123064.2
A13: Depreciation | B13: =(Assumptions!$C$43*Assumptions!$C$44+Assumptions!$C$45*Assumptions!$C$46+Assumptions!$C$47*Assumptions!$C$48)/12 -> 76666.667 | C13: =(Assumptions!$C$43*Assumptions!$C$44+Assumptions!$C$45*Assumptions!$C$46+Assumptions!$C$47*Assumptions!$C$48)/12 -> 76666.667 | D13: =(Assumptions!$C$43*Assumptions!$C$44+Assumptions!$C$45*Assumptions!$C$46+Assumptions!$C$47*Assumptions!$C$48)/12 -> 76666.667 | E13: =(Assumptions!$C$43*Assumptions!$C$44+Assumptions!$C$45*Assumptions!$C$46+Assumptions!$C$47*Assumptions!$C$48)/12 -> 76666.667 | F13: =(Assumptions!$C$43*Assumptions!$C$44+Assumptions!$C$45*Assumptions!$C$46+Assumptions!$C$47*Assumptions!$C$48)/12 -> 76666.667 | G13: =(Assumptions!$C$43*Assumptions!$C$44+Assumptions!$C$45*Assumptions!$C$46+Assumptions!$C$47*Assumptions!$C$48)/12 -> 76666.667 | H13: =(Assumptions!$C$43*Assumptions!$C$44+Assumptions!$C$45*Assumptions!$C$46+Assumptions!$C$47*Assumptions!$C$48)/12 -> 76666.667 | I13: =(Assumptions!$C$43*Assumptions!$C$44+Assumptions!$C$45*Assumptions!$C$46+Assumptions!$C$47*Assumptions!$C$48)/12 -> 76666.667 | ... M13: =(Assumptions!$C$43*Assumptions!$C$44+Assumptions!$C$45*Assumptions!$C$46+Assumptions!$C$47*Assumptions!$C$48)/12 -> 76666.667 | N13: =SUM(B13:M13) -> 920000 | O13: =(Assumptions!$C$43*Assumptions!$C$44+Assumptions!$C$45*Assumptions!$C$46+Assumptions!$C$47*Assumptions!$C$48)/12 -> 76666.667 | P13: =(Assumptions!$C$43*Assumptions!$C$44+Assumptions!$C$45*Assumptions!$C$46+Assumptions!$C$47*Assumptions!$C$48)/12 -> 76666.667 | Q13: =(Assumptions!$C$43*Assumptions!$C$44+Assumptions!$C$45*Assumptions!$C$46+Assumptions!$C$47*Assumptions!$C$48)/12 -> 76666.667 | R13: =(Assumptions!$C$43*Assumptions!$C$44+Assumptions!$C$45*Assumptions!$C$46+Assumptions!$C$47*Assumptions!$C$48)/12 -> 76666.667 | S13: =(Assumptions!$C$43*Assumptions!$C$44+Assumptions!$C$45*Assumptions!$C$46+Assumptions!$C$47*Assumptions!$C$48)/12 -> 76666.667 | T13: =(Assumptions!$C$43*Assumptions!$C$44+Assumptions!$C$45*Assumptions!$C$46+Assumptions!$C$47*Assumptions!$C$48)/12 -> 76666.667 | U13: =(Assumptions!$C$43*Assumptions!$C$44+Assumptions!$C$45*Assumptions!$C$46+Assumptions!$C$47*Assumptions!$C$48)/12 -> 76666.667 | V13: =(Assumptions!$C$43*Assumptions!$C$44+Assumptions!$C$45*Assumptions!$C$46+Assumptions!$C$47*Assumptions!$C$48)/12 -> 76666.667 | ... Z13: =(Assumptions!$C$43*Assumptions!$C$44+Assumptions!$C$45*Assumptions!$C$46+Assumptions!$C$47*Assumptions!$C$48)/12 -> 76666.667 | AA13: =SUM(O13:Z13) -> 920000 | AB13: =(Assumptions!$C$43*Assumptions!$C$44+Assumptions!$C$45*Assumptions!$C$46+Assumptions!$C$47*Assumptions!$C$48)/12 -> 76666.667 | AC13: =(Assumptions!$C$43*Assumptions!$C$44+Assumptions!$C$45*Assumptions!$C$46+Assumptions!$C$47*Assumptions!$C$48)/12 -> 76666.667 | AD13: =(Assumptions!$C$43*Assumptions!$C$44+Assumptions!$C$45*Assumptions!$C$46+Assumptions!$C$47*Assumptions!$C$48)/12 -> 76666.667 | AE13: =(Assumptions!$C$43*Assumptions!$C$44+Assumptions!$C$45*Assumptions!$C$46+Assumptions!$C$47*Assumptions!$C$48)/12 -> 76666.667 | AF13: =(Assumptions!$C$43*Assumptions!$C$44+Assumptions!$C$45*Assumptions!$C$46+Assumptions!$C$47*Assumptions!$C$48)/12 -> 76666.667 | AG13: =(Assumptions!$C$43*Assumptions!$C$44+Assumptions!$C$45*Assumptions!$C$46+Assumptions!$C$47*Assumptions!$C$48)/12 -> 76666.667 | AH13: =(Assumptions!$C$43*Assumptions!$C$44+Assumptions!$C$45*Assumptions!$C$46+Assumptions!$C$47*Assumptions!$C$48)/12 -> 76666.667 | AI13: =(Assumptions!$C$43*Assumptions!$C$44+Assumptions!$C$45*Assumptions!$C$46+Assumptions!$C$47*Assumptions!$C$48)/12 -> 76666.667 | ... AM13: =(Assumptions!$C$43*Assumptions!$C$44+Assumptions!$C$45*Assumptions!$C$46+Assumptions!$C$47*Assumptions!$C$48)/12 -> 76666.667 | AN13: =SUM(AB13:AM13) -> 920000 | AO13: =(Assumptions!$C$43*Assumptions!$C$44+Assumptions!$C$45*Assumptions!$C$46+Assumptions!$C$47*Assumptions!$C$48)/12 -> 76666.667 | AP13: =(Assumptions!$C$43*Assumptions!$C$44+Assumptions!$C$45*Assumptions!$C$46+Assumptions!$C$47*Assumptions!$C$48)/12 -> 76666.667 | AQ13: =(Assumptions!$C$43*Assumptions!$C$44+Assumptions!$C$45*Assumptions!$C$46+Assumptions!$C$47*Assumptions!$C$48)/12 -> 76666.667 | AR13: =(Assumptions!$C$43*Assumptions!$C$44+Assumptions!$C$45*Assumptions!$C$46+Assumptions!$C$47*Assumptions!$C$48)/12 -> 76666.667 | AS13: =(Assumptions!$C$43*Assumptions!$C$44+Assumptions!$C$45*Assumptions!$C$46+Assumptions!$C$47*Assumptions!$C$48)/12 -> 76666.667 | AT13: =(Assumptions!$C$43*Assumptions!$C$44+Assumptions!$C$45*Assumptions!$C$46+Assumptions!$C$47*Assumptions!$C$48)/12 -> 76666.667 | AU13: =(Assumptions!$C$43*Assumptions!$C$44+Assumptions!$C$45*Assumptions!$C$46+Assumptions!$C$47*Assumptions!$C$48)/12 -> 76666.667 | AV13: =(Assumptions!$C$43*Assumptions!$C$44+Assumptions!$C$45*Assumptions!$C$46+Assumptions!$C$47*Assumptions!$C$48)/12 -> 76666.667 | ... AZ13: =(Assumptions!$C$43*Assumptions!$C$44+Assumptions!$C$45*Assumptions!$C$46+Assumptions!$C$47*Assumptions!$C$48)/12 -> 76666.667 | BA13: =SUM(AO13:AZ13) -> 920000 | BB13: =(Assumptions!$C$43*Assumptions!$C$44+Assumptions!$C$45*Assumptions!$C$46+Assumptions!$C$47*Assumptions!$C$48)/12 -> 76666.667 | BC13: =(Assumptions!$C$43*Assumptions!$C$44+Assumptions!$C$45*Assumptions!$C$46+Assumptions!$C$47*Assumptions!$C$48)/12 -> 76666.667 | BD13: =(Assumptions!$C$43*Assumptions!$C$44+Assumptions!$C$45*Assumptions!$C$46+Assumptions!$C$47*Assumptions!$C$48)/12 -> 76666.667 | BE13: =(Assumptions!$C$43*Assumptions!$C$44+Assumptions!$C$45*Assumptions!$C$46+Assumptions!$C$47*Assumptions!$C$48)/12 -> 76666.667 | BF13: =(Assumptions!$C$43*Assumptions!$C$44+Assumptions!$C$45*Assumptions!$C$46+Assumptions!$C$47*Assumptions!$C$48)/12 -> 76666.667 | BG13: =(Assumptions!$C$43*Assumptions!$C$44+Assumptions!$C$45*Assumptions!$C$46+Assumptions!$C$47*Assumptions!$C$48)/12 -> 76666.667 | BH13: =(Assumptions!$C$43*Assumptions!$C$44+Assumptions!$C$45*Assumptions!$C$46+Assumptions!$C$47*Assumptions!$C$48)/12 -> 76666.667 | BI13: =(Assumptions!$C$43*Assumptions!$C$44+Assumptions!$C$45*Assumptions!$C$46+Assumptions!$C$47*Assumptions!$C$48)/12 -> 76666.667 | ... BM13: =(Assumptions!$C$43*Assumptions!$C$44+Assumptions!$C$45*Assumptions!$C$46+Assumptions!$C$47*Assumptions!$C$48)/12 -> 76666.667 | BN13: =SUM(BB13:BM13) -> 920000
A14: Interest — Term Loan | B14: =Repayment!C6/12 -> 52500 | C14: =Repayment!C6/12 -> 52500 | D14: =Repayment!C6/12 -> 52500 | E14: =Repayment!C6/12 -> 52500 | F14: =Repayment!C6/12 -> 52500 | G14: =Repayment!C6/12 -> 52500 | H14: =Repayment!C6/12 -> 52500 | I14: =Repayment!C6/12 -> 52500 | J14: =Repayment!C6/12 -> 52500 | K14: =Repayment!C6/12 -> 52500 | L14: =Repayment!C6/12 -> 52500 | M14: =Repayment!C6/12 -> 52500 | N14: =SUM(B14:M14) -> 630000 | O14: =Repayment!D6/12 -> 51617.647 | P14: =Repayment!D6/12 -> 51617.647 | Q14: =Repayment!D6/12 -> 51617.647 | R14: =Repayment!D6/12 -> 51617.647 | S14: =Repayment!D6/12 -> 51617.647 | T14: =Repayment!D6/12 -> 51617.647 | U14: =Repayment!D6/12 -> 51617.647 | V14: =Repayment!D6/12 -> 51617.647 | W14: =Repayment!D6/12 -> 51617.647 | X14: =Repayment!D6/12 -> 51617.647 | Y14: =Repayment!D6/12 -> 51617.647 | Z14: =Repayment!D6/12 -> 51617.647 | AA14: =SUM(O14:Z14) -> 619411.76 | AB14: =Repayment!E6/12 -> 50735.294 | AC14: =Repayment!E6/12 -> 50735.294 | AD14: =Repayment!E6/12 -> 50735.294 | AE14: =Repayment!E6/12 -> 50735.294 | AF14: =Repayment!E6/12 -> 50735.294 | AG14: =Repayment!E6/12 -> 50735.294 | AH14: =Repayment!E6/12 -> 50735.294 | AI14: =Repayment!E6/12 -> 50735.294 | AJ14: =Repayment!E6/12 -> 50735.294 | AK14: =Repayment!E6/12 -> 50735.294 | AL14: =Repayment!E6/12 -> 50735.294 | AM14: =Repayment!E6/12 -> 50735.294 | AN14: =SUM(AB14:AM14) -> 608823.53 | AO14: =Repayment!F6/12 -> 49852.941 | AP14: =Repayment!F6/12 -> 49852.941 | AQ14: =Repayment!F6/12 -> 49852.941 | AR14: =Repayment!F6/12 -> 49852.941 | AS14: =Repayment!F6/12 -> 49852.941 | AT14: =Repayment!F6/12 -> 49852.941 | AU14: =Repayment!F6/12 -> 49852.941 | AV14: =Repayment!F6/12 -> 49852.941 | AW14: =Repayment!F6/12 -> 49852.941 | AX14: =Repayment!F6/12 -> 49852.941 | AY14: =Repayment!F6/12 -> 49852.941 | AZ14: =Repayment!F6/12 -> 49852.941 | BA14: =SUM(AO14:AZ14) -> 598235.29 | BB14: =Repayment!G6/12 -> 48970.588 | BC14: =Repayment!G6/12 -> 48970.588 | BD14: =Repayment!G6/12 -> 48970.588 | BE14: =Repayment!G6/12 -> 48970.588 | BF14: =Repayment!G6/12 -> 48970.588 | BG14: =Repayment!G6/12 -> 48970.588 | BH14: =Repayment!G6/12 -> 48970.588 | BI14: =Repayment!G6/12 -> 48970.588 | BJ14: =Repayment!G6/12 -> 48970.588 | BK14: =Repayment!G6/12 -> 48970.588 | BL14: =Repayment!G6/12 -> 48970.588 | BM14: =Repayment!G6/12 -> 48970.588 | BN14: =SUM(BB14:BM14) -> 587647.06
A15: Interest — Working Capital | B15: =Form_V_MPBF!C11*Assumptions!$C$13/12 -> 12365.753 | C15: =Form_V_MPBF!C11*Assumptions!$C$13/12 -> 12365.753 | D15: =Form_V_MPBF!C11*Assumptions!$C$13/12 -> 12365.753 | E15: =Form_V_MPBF!C11*Assumptions!$C$13/12 -> 12365.753 | F15: =Form_V_MPBF!C11*Assumptions!$C$13/12 -> 12365.753 | G15: =Form_V_MPBF!C11*Assumptions!$C$13/12 -> 12365.753 | H15: =Form_V_MPBF!C11*Assumptions!$C$13/12 -> 12365.753 | I15: =Form_V_MPBF!C11*Assumptions!$C$13/12 -> 12365.753 | J15: =Form_V_MPBF!C11*Assumptions!$C$13/12 -> 12365.753 | K15: =Form_V_MPBF!C11*Assumptions!$C$13/12 -> 12365.753 | L15: =Form_V_MPBF!C11*Assumptions!$C$13/12 -> 12365.753 | M15: =Form_V_MPBF!C11*Assumptions!$C$13/12 -> 12365.753 | N15: =SUM(B15:M15) -> 148389.04 | O15: =Form_V_MPBF!D11*Assumptions!$C$13/12 -> 13533.842 | P15: =Form_V_MPBF!D11*Assumptions!$C$13/12 -> 13533.842 | Q15: =Form_V_MPBF!D11*Assumptions!$C$13/12 -> 13533.842 | R15: =Form_V_MPBF!D11*Assumptions!$C$13/12 -> 13533.842 | S15: =Form_V_MPBF!D11*Assumptions!$C$13/12 -> 13533.842 | T15: =Form_V_MPBF!D11*Assumptions!$C$13/12 -> 13533.842 | U15: =Form_V_MPBF!D11*Assumptions!$C$13/12 -> 13533.842 | V15: =Form_V_MPBF!D11*Assumptions!$C$13/12 -> 13533.842 | W15: =Form_V_MPBF!D11*Assumptions!$C$13/12 -> 13533.842 | X15: =Form_V_MPBF!D11*Assumptions!$C$13/12 -> 13533.842 | Y15: =Form_V_MPBF!D11*Assumptions!$C$13/12 -> 13533.842 | Z15: =Form_V_MPBF!D11*Assumptions!$C$13/12 -> 13533.842 | AA15: =SUM(O15:Z15) -> 162406.11 | AB15: =Form_V_MPBF!E11*Assumptions!$C$13/12 -> 14756.155 | AC15: =Form_V_MPBF!E11*Assumptions!$C$13/12 -> 14756.155 | AD15: =Form_V_MPBF!E11*Assumptions!$C$13/12 -> 14756.155 | AE15: =Form_V_MPBF!E11*Assumptions!$C$13/12 -> 14756.155 | AF15: =Form_V_MPBF!E11*Assumptions!$C$13/12 -> 14756.155 | AG15: =Form_V_MPBF!E11*Assumptions!$C$13/12 -> 14756.155 | AH15: =Form_V_MPBF!E11*Assumptions!$C$13/12 -> 14756.155 | AI15: =Form_V_MPBF!E11*Assumptions!$C$13/12 -> 14756.155 | AJ15: =Form_V_MPBF!E11*Assumptions!$C$13/12 -> 14756.155 | AK15: =Form_V_MPBF!E11*Assumptions!$C$13/12 -> 14756.155 | AL15: =Form_V_MPBF!E11*Assumptions!$C$13/12 -> 14756.155 | AM15: =Form_V_MPBF!E11*Assumptions!$C$13/12 -> 14756.155 | AN15: =SUM(AB15:AM15) -> 177073.86 | AO15: =Form_V_MPBF!F11*Assumptions!$C$13/12 -> 16033.972 | AP15: =Form_V_MPBF!F11*Assumptions!$C$13/12 -> 16033.972 | AQ15: =Form_V_MPBF!F11*Assumptions!$C$13/12 -> 16033.972 | AR15: =Form_V_MPBF!F11*Assumptions!$C$13/12 -> 16033.972 | AS15: =Form_V_MPBF!F11*Assumptions!$C$13/12 -> 16033.972 | AT15: =Form_V_MPBF!F11*Assumptions!$C$13/12 -> 16033.972 | AU15: =Form_V_MPBF!F11*Assumptions!$C$13/12 -> 16033.972 | AV15: =Form_V_MPBF!F11*Assumptions!$C$13/12 -> 16033.972 | AW15: =Form_V_MPBF!F11*Assumptions!$C$13/12 -> 16033.972 | AX15: =Form_V_MPBF!F11*Assumptions!$C$13/12 -> 16033.972 | AY15: =Form_V_MPBF!F11*Assumptions!$C$13/12 -> 16033.972 | AZ15: =Form_V_MPBF!F11*Assumptions!$C$13/12 -> 16033.972 | BA15: =SUM(AO15:AZ15) -> 192407.66 | BB15: =Form_V_MPBF!G11*Assumptions!$C$13/12 -> 17368.528 | BC15: =Form_V_MPBF!G11*Assumptions!$C$13/12 -> 17368.528 | BD15: =Form_V_MPBF!G11*Assumptions!$C$13/12 -> 17368.528 | BE15: =Form_V_MPBF!G11*Assumptions!$C$13/12 -> 17368.528 | BF15: =Form_V_MPBF!G11*Assumptions!$C$13/12 -> 17368.528 | BG15: =Form_V_MPBF!G11*Assumptions!$C$13/12 -> 17368.528 | BH15: =Form_V_MPBF!G11*Assumptions!$C$13/12 -> 17368.528 | BI15: =Form_V_MPBF!G11*Assumptions!$C$13/12 -> 17368.528 | BJ15: =Form_V_MPBF!G11*Assumptions!$C$13/12 -> 17368.528 | BK15: =Form_V_MPBF!G11*Assumptions!$C$13/12 -> 17368.528 | BL15: =Form_V_MPBF!G11*Assumptions!$C$13/12 -> 17368.528 | BM15: =Form_V_MPBF!G11*Assumptions!$C$13/12 -> 17368.528 | BN15: =SUM(BB15:BM15) -> 208422.34
A16: Total Operating Expenses | B16: =SUM(B5:B15) -> 2257132.4 | C16: =SUM(C5:C15) -> 2257132.4 | D16: =SUM(D5:D15) -> 2257132.4 | E16: =SUM(E5:E15) -> 2480332.4 | F16: =SUM(F5:F15) -> 2480332.4 | G16: =SUM(G5:G15) -> 2480332.4 | H16: =SUM(H5:H15) -> 2257132.4 | I16: =SUM(I5:I15) -> 2257132.4 | ... M16: =SUM(M5:M15) -> 2033932.4 | N16: =SUM(B16:M16) -> 27978389 | O16: =SUM(O5:O15) -> 2518638.2 | P16: =SUM(P5:P15) -> 2518638.2 | Q16: =SUM(Q5:Q15) -> 2518638.2 | R16: =SUM(R5:R15) -> 2772528.2 | S16: =SUM(S5:S15) -> 2772528.2 | T16: =SUM(T5:T15) -> 2772528.2 | U16: =SUM(U5:U15) -> 2518638.2 | V16: =SUM(V5:V15) -> 2518638.2 | ... Z16: =SUM(Z5:Z15) -> 2264748.2 | AA16: =SUM(O16:Z16) -> 31239218 | AB16: =SUM(AB5:AB15) -> 2801079.4 | AC16: =SUM(AC5:AC15) -> 2801079.4 | AD16: =SUM(AD5:AD15) -> 2801079.4 | AE16: =SUM(AE5:AE15) -> 3088175.5 | AF16: =SUM(AF5:AF15) -> 3088175.5 | AG16: =SUM(AG5:AG15) -> 3088175.5 | AH16: =SUM(AH5:AH15) -> 2801079.4 | AI16: =SUM(AI5:AI15) -> 2801079.4 | ... AM16: =SUM(AM5:AM15) -> 2513983.4 | AN16: =SUM(AB16:AM16) -> 34761337 | AO16: =SUM(AO5:AO15) -> 3105904 | AP16: =SUM(AP5:AP15) -> 3105904 | AQ16: =SUM(AQ5:AQ15) -> 3105904 | AR16: =SUM(AR5:AR15) -> 3428898.4 | AS16: =SUM(AS5:AS15) -> 3428898.4 | AT16: =SUM(AT5:AT15) -> 3428898.4 | AU16: =SUM(AU5:AU15) -> 3105904 | AV16: =SUM(AV5:AV15) -> 3105904 | ... AZ16: =SUM(AZ5:AZ15) -> 2782909.6 | BA16: =SUM(AO16:AZ16) -> 38562826 | BB16: =SUM(BB5:BB15) -> 3434653.1 | BC16: =SUM(BC5:BC15) -> 3434653.1 | BD16: =SUM(BD5:BD15) -> 3434653.1 | BE16: =SUM(BE5:BE15) -> 3796425.9 | BF16: =SUM(BF5:BF15) -> 3796425.9 | BG16: =SUM(BG5:BG15) -> 3796425.9 | BH16: =SUM(BH5:BH15) -> 3434653.1 | BI16: =SUM(BI5:BI15) -> 3434653.1 | ... BM16: =SUM(BM5:BM15) -> 3072880.4 | BN16: =SUM(BB16:BM16) -> 42662929

Sheet Profit
A1: PROFITABILITY (P&L) — 60-MONTH PROJECTION
A2: EBITDA → EBIT → PBT → PAT, fully linked to Sales and Expenses.
B3: YEAR 1 | O3: YEAR 2 | AB3: YEAR 3 | AO3: YEAR 4 | BB3: YEAR 5
A4: Particulars | B4: M1 | C4: M2 | D4: M3 | E4: M4 | F4: M5 | G4: M6 | H4: M7 | I4: M8 | J4: M9 | K4: M10 | L4: M11 | M4: M12 | N4: Yr 1 Total | O4: M13 | P4: M14 | Q4: M15 | R4: M16 | S4: M17 | T4: M18 | U4: M19 | V4: M20 | W4: M21 | X4: M22 | Y4: M23 | Z4: M24 | AA4: Yr 2 Total | AB4: M25 | AC4: M26 | AD4: M27 | AE4: M28 | AF4: M29 | AG4: M30 | AH4: M31 | AI4: M32 | AJ4: M33 | AK4: M34 | AL4: M35 | AM4: M36 | AN4: Yr 3 Total | AO4: M37 | AP4: M38 | AQ4: M39 | AR4: M40 | AS4: M41 | AT4: M42 | AU4: M43 | AV4: M44 | AW4: M45 | AX4: M46 | AY4: M47 | AZ4: M48 | BA4: Yr 4 Total | BB4: M49 | BC4: M50 | BD4: M51 | BE4: M52 | BF4: M53 | BG4: M54 | BH4: M55 | BI4: M56 | BJ4: M57 | BK4: M58 | BL4: M59 | BM4: M60 | BN4: Yr 5 Total
A5: Net Sales | B5: =Sales!B7 -> 2880000 | C5: =Sales!C7 -> 2880000 | D5: =Sales!D7 -> 2880000 | E5: =Sales!E7 -> 3240000 | F5: =Sales!F7 -> 3240000 | G5: =Sales!G7 -> 3240000 | H5: =Sales!H7 -> 2880000 | I5: =Sales!I7 -> 2880000 | ... M5: =Sales!M7 -> 2520000 | N5: =SUM(B5:M5) -> 36000000 | O5: =Sales!O7 -> 3244800 | P5: =Sales!P7 -> 3244800 | Q5: =Sales!Q7 -> 3244800 | R5: =Sales!R7 -> 3650400 | S5: =Sales!S7 -> 3650400 | T5: =Sales!T7 -> 3650400 | U5: =Sales!U7 -> 3244800 | V5: =Sales!V7 -> 3244800 | ... Z5: =Sales!Z7 -> 2839200 | AA5: =SUM(O5:Z5) -> 40560000 | AB5: =Sales!AB7 -> 3634176 | AC5: =Sales!AC7 -> 3634176 | AD5: =Sales!AD7 -> 3634176 | AE5: =Sales!AE7 -> 4088448 | AF5: =Sales!AF7 -> 4088448 | AG5: =Sales!AG7 -> 4088448 | AH5: =Sales!AH7 -> 3634176 | AI5: =Sales!AI7 -> 3634176 | ... AM5: =Sales!AM7 -> 3179904 | AN5: =SUM(AB5:AM5) -> 45427200 | AO5: =Sales!AO7 -> 4049510.4 | AP5: =Sales!AP7 -> 4049510.4 | AQ5: =Sales!AQ7 -> 4049510.4 | AR5: =Sales!AR7 -> 4555699.2 | AS5: =Sales!AS7 -> 4555699.2 | AT5: =Sales!AT7 -> 4555699.2 | AU5: =Sales!AU7 -> 4049510.4 | AV5: =Sales!AV7 -> 4049510.4 | ... AZ5: =Sales!AZ7 -> 3543321.6 | BA5: =SUM(AO5:AZ5) -> 50618880 | BB5: =Sales!BB7 -> 4492256.9 | BC5: =Sales!BC7 -> 4492256.9 | BD5: =Sales!BD7 -> 4492256.9 | BE5: =Sales!BE7 -> 5053789 | BF5: =Sales!BF7 -> 5053789 | BG5: =Sales!BG7 -> 5053789 | BH5: =Sales!BH7 -> 4492256.9 | BI5: =Sales!BI7 -> 4492256.9 | ... BM5: =Sales!BM7 -> 3930724.8 | BN5: =SUM(BB5:BM5) -> 56153211
A6: =IFERROR("(-) "&VLOOKUP(Assumptions!$J$5,Assumptions!$S$5:$Z$21,5,FALSE()),"(-) Raw materials") -> (-) Raw materials | B6: =Expenses!B5 -> 1440000 | C6: =Expenses!C5 -> 1440000 | D6: =Expenses!D5 -> 1440000 | E6: =Expenses!E5 -> 1620000 | F6: =Expenses!F5 -> 1620000 | G6: =Expenses!G5 -> 1620000 | H6: =Expenses!H5 -> 1440000 | I6: =Expenses!I5 -> 1440000 | ... M6: =Expenses!M5 -> 1260000 | N6: =SUM(B6:M6) -> 18000000 | O6: =Expenses!O5 -> 1638000 | P6: =Expenses!P5 -> 1638000 | Q6: =Expenses!Q5 -> 1638000 | R6: =Expenses!R5 -> 1842750 | S6: =Expenses!S5 -> 1842750 | T6: =Expenses!T5 -> 1842750 | U6: =Expenses!U5 -> 1638000 | V6: =Expenses!V5 -> 1638000 | ... Z6: =Expenses!Z5 -> 1433250 | AA6: =SUM(O6:Z6) -> 20475000 | AB6: =Expenses!AB5 -> 1852200 | AC6: =Expenses!AC5 -> 1852200 | AD6: =Expenses!AD5 -> 1852200 | AE6: =Expenses!AE5 -> 2083725 | AF6: =Expenses!AF5 -> 2083725 | AG6: =Expenses!AG5 -> 2083725 | AH6: =Expenses!AH5 -> 1852200 | AI6: =Expenses!AI5 -> 1852200 | ... AM6: =Expenses!AM5 -> 1620675 | AN6: =SUM(AB6:AM6) -> 23152500 | AO6: =Expenses!AO5 -> 2083725 | AP6: =Expenses!AP5 -> 2083725 | AQ6: =Expenses!AQ5 -> 2083725 | AR6: =Expenses!AR5 -> 2344190.6 | AS6: =Expenses!AS5 -> 2344190.6 | AT6: =Expenses!AT5 -> 2344190.6 | AU6: =Expenses!AU5 -> 2083725 | AV6: =Expenses!AV5 -> 2083725 | ... AZ6: =Expenses!AZ5 -> 1823259.4 | BA6: =SUM(AO6:AZ6) -> 26046563 | BB6: =Expenses!BB5 -> 2333772 | BC6: =Expenses!BC5 -> 2333772 | BD6: =Expenses!BD5 -> 2333772 | BE6: =Expenses!BE5 -> 2625493.5 | BF6: =Expenses!BF5 -> 2625493.5 | BG6: =Expenses!BG5 -> 2625493.5 | BH6: =Expenses!BH5 -> 2333772 | BI6: =Expenses!BI5 -> 2333772 | ... BM6: =Expenses!BM5 -> 2042050.5 | BN6: =SUM(BB6:BM6) -> 29172150
A7: =IFERROR("(-) "&VLOOKUP(Assumptions!$J$5,Assumptions!$S$5:$Z$21,7,FALSE()),"(-) Power & fuel") -> (-) Power & fuel | B7: =Expenses!B6 -> 172800 | C7: =Expenses!C6 -> 172800 | D7: =Expenses!D6 -> 172800 | E7: =Expenses!E6 -> 194400 | F7: =Expenses!F6 -> 194400 | G7: =Expenses!G6 -> 194400 | H7: =Expenses!H6 -> 172800 | I7: =Expenses!I6 -> 172800 | ... M7: =Expenses!M6 -> 151200 | N7: =SUM(B7:M7) -> 2160000 | O7: =Expenses!O6 -> 198432 | P7: =Expenses!P6 -> 198432 | Q7: =Expenses!Q6 -> 198432 | R7: =Expenses!R6 -> 223236 | S7: =Expenses!S6 -> 223236 | T7: =Expenses!T6 -> 223236 | U7: =Expenses!U6 -> 198432 | V7: =Expenses!V6 -> 198432 | ... Z7: =Expenses!Z6 -> 173628 | AA7: =SUM(O7:Z7) -> 2480400 | AB7: =Expenses!AB6 -> 226517.76 | AC7: =Expenses!AC6 -> 226517.76 | AD7: =Expenses!AD6 -> 226517.76 | AE7: =Expenses!AE6 -> 254832.48 | AF7: =Expenses!AF6 -> 254832.48 | AG7: =Expenses!AG6 -> 254832.48 | AH7: =Expenses!AH6 -> 226517.76 | AI7: =Expenses!AI6 -> 226517.76 | ... AM7: =Expenses!AM6 -> 198203.04 | AN7: =SUM(AB7:AM7) -> 2831472 | AO7: =Expenses!AO6 -> 257259.46 | AP7: =Expenses!AP6 -> 257259.46 | AQ7: =Expenses!AQ6 -> 257259.46 | AR7: =Expenses!AR6 -> 289416.89 | AS7: =Expenses!AS6 -> 289416.89 | AT7: =Expenses!AT6 -> 289416.89 | AU7: =Expenses!AU6 -> 257259.46 | AV7: =Expenses!AV6 -> 257259.46 | ... AZ7: =Expenses!AZ6 -> 225102.02 | BA7: =SUM(AO7:AZ7) -> 3215743.2 | BB7: =Expenses!BB6 -> 290874.69 | BC7: =Expenses!BC6 -> 290874.69 | BD7: =Expenses!BD6 -> 290874.69 | BE7: =Expenses!BE6 -> 327234.03 | BF7: =Expenses!BF6 -> 327234.03 | BG7: =Expenses!BG6 -> 327234.03 | BH7: =Expenses!BH6 -> 290874.69 | BI7: =Expenses!BI6 -> 290874.69 | ... BM7: =Expenses!BM6 -> 254515.36 | BN7: =SUM(BB7:BM7) -> 3635933.6
A8: (-) Direct wages & salaries | B8: =Expenses!B7 -> 150000 | C8: =Expenses!C7 -> 150000 | D8: =Expenses!D7 -> 150000 | E8: =Expenses!E7 -> 150000 | F8: =Expenses!F7 -> 150000 | G8: =Expenses!G7 -> 150000 | H8: =Expenses!H7 -> 150000 | I8: =Expenses!I7 -> 150000 | ... M8: =Expenses!M7 -> 150000 | N8: =SUM(B8:M8) -> 1800000 | O8: =Expenses!O7 -> 157500 | P8: =Expenses!P7 -> 157500 | Q8: =Expenses!Q7 -> 157500 | R8: =Expenses!R7 -> 157500 | S8: =Expenses!S7 -> 157500 | T8: =Expenses!T7 -> 157500 | U8: =Expenses!U7 -> 157500 | V8: =Expenses!V7 -> 157500 | ... Z8: =Expenses!Z7 -> 157500 | AA8: =SUM(O8:Z8) -> 1890000 | AB8: =Expenses!AB7 -> 165375 | AC8: =Expenses!AC7 -> 165375 | AD8: =Expenses!AD7 -> 165375 | AE8: =Expenses!AE7 -> 165375 | AF8: =Expenses!AF7 -> 165375 | AG8: =Expenses!AG7 -> 165375 | AH8: =Expenses!AH7 -> 165375 | AI8: =Expenses!AI7 -> 165375 | ... AM8: =Expenses!AM7 -> 165375 | AN8: =SUM(AB8:AM8) -> 1984500 | AO8: =Expenses!AO7 -> 173643.75 | AP8: =Expenses!AP7 -> 173643.75 | AQ8: =Expenses!AQ7 -> 173643.75 | AR8: =Expenses!AR7 -> 173643.75 | AS8: =Expenses!AS7 -> 173643.75 | AT8: =Expenses!AT7 -> 173643.75 | AU8: =Expenses!AU7 -> 173643.75 | AV8: =Expenses!AV7 -> 173643.75 | ... AZ8: =Expenses!AZ7 -> 173643.75 | BA8: =SUM(AO8:AZ8) -> 2083725 | BB8: =Expenses!BB7 -> 182325.94 | BC8: =Expenses!BC7 -> 182325.94 | BD8: =Expenses!BD7 -> 182325.94 | BE8: =Expenses!BE7 -> 182325.94 | BF8: =Expenses!BF7 -> 182325.94 | BG8: =Expenses!BG7 -> 182325.94 | BH8: =Expenses!BH7 -> 182325.94 | BI8: =Expenses!BI7 -> 182325.94 | ... BM8: =Expenses!BM7 -> 182325.94 | BN8: =SUM(BB8:BM8) -> 2187911.2
A9: (-) Other variable cost | B9: =Expenses!B8 -> 115200 | C9: =Expenses!C8 -> 115200 | D9: =Expenses!D8 -> 115200 | E9: =Expenses!E8 -> 129600 | F9: =Expenses!F8 -> 129600 | G9: =Expenses!G8 -> 129600 | H9: =Expenses!H8 -> 115200 | I9: =Expenses!I8 -> 115200 | ... M9: =Expenses!M8 -> 100800 | N9: =SUM(B9:M9) -> 1440000 | O9: =Expenses!O8 -> 129792 | P9: =Expenses!P8 -> 129792 | Q9: =Expenses!Q8 -> 129792 | R9: =Expenses!R8 -> 146016 | S9: =Expenses!S8 -> 146016 | T9: =Expenses!T8 -> 146016 | U9: =Expenses!U8 -> 129792 | V9: =Expenses!V8 -> 129792 | ... Z9: =Expenses!Z8 -> 113568 | AA9: =SUM(O9:Z9) -> 1622400 | AB9: =Expenses!AB8 -> 145367.04 | AC9: =Expenses!AC8 -> 145367.04 | AD9: =Expenses!AD8 -> 145367.04 | AE9: =Expenses!AE8 -> 163537.92 | AF9: =Expenses!AF8 -> 163537.92 | AG9: =Expenses!AG8 -> 163537.92 | AH9: =Expenses!AH8 -> 145367.04 | AI9: =Expenses!AI8 -> 145367.04 | ... AM9: =Expenses!AM8 -> 127196.16 | AN9: =SUM(AB9:AM9) -> 1817088 | AO9: =Expenses!AO8 -> 161980.42 | AP9: =Expenses!AP8 -> 161980.42 | AQ9: =Expenses!AQ8 -> 161980.42 | AR9: =Expenses!AR8 -> 182227.97 | AS9: =Expenses!AS8 -> 182227.97 | AT9: =Expenses!AT8 -> 182227.97 | AU9: =Expenses!AU8 -> 161980.42 | AV9: =Expenses!AV8 -> 161980.42 | ... AZ9: =Expenses!AZ8 -> 141732.86 | BA9: =SUM(AO9:AZ9) -> 2024755.2 | BB9: =Expenses!BB8 -> 179690.27 | BC9: =Expenses!BC8 -> 179690.27 | BD9: =Expenses!BD8 -> 179690.27 | BE9: =Expenses!BE8 -> 202151.56 | BF9: =Expenses!BF8 -> 202151.56 | BG9: =Expenses!BG8 -> 202151.56 | BH9: =Expenses!BH8 -> 179690.27 | BI9: =Expenses!BI8 -> 179690.27 | ... BM9: =Expenses!BM8 -> 157228.99 | BN9: =SUM(BB9:BM9) -> 2246128.4
A10: =IFERROR("(-) "&VLOOKUP(Assumptions!$J$5,Assumptions!$S$5:$Z$21,8,FALSE()),"(-) Factory overheads") -> (-) Factory overheads | B10: =Expenses!B9 -> 100000 | C10: =Expenses!C9 -> 100000 | D10: =Expenses!D9 -> 100000 | E10: =Expenses!E9 -> 100000 | F10: =Expenses!F9 -> 100000 | G10: =Expenses!G9 -> 100000 | H10: =Expenses!H9 -> 100000 | I10: =Expenses!I9 -> 100000 | ... M10: =Expenses!M9 -> 100000 | N10: =SUM(B10:M10) -> 1200000 | O10: =Expenses!O9 -> 105000 | P10: =Expenses!P9 -> 105000 | Q10: =Expenses!Q9 -> 105000 | R10: =Expenses!R9 -> 105000 | S10: =Expenses!S9 -> 105000 | T10: =Expenses!T9 -> 105000 | U10: =Expenses!U9 -> 105000 | V10: =Expenses!V9 -> 105000 | ... Z10: =Expenses!Z9 -> 105000 | AA10: =SUM(O10:Z10) -> 1260000 | AB10: =Expenses!AB9 -> 110250 | AC10: =Expenses!AC9 -> 110250 | AD10: =Expenses!AD9 -> 110250 | AE10: =Expenses!AE9 -> 110250 | AF10: =Expenses!AF9 -> 110250 | AG10: =Expenses!AG9 -> 110250 | AH10: =Expenses!AH9 -> 110250 | AI10: =Expenses!AI9 -> 110250 | ... AM10: =Expenses!AM9 -> 110250 | AN10: =SUM(AB10:AM10) -> 1323000 | AO10: =Expenses!AO9 -> 115762.5 | AP10: =Expenses!AP9 -> 115762.5 | AQ10: =Expenses!AQ9 -> 115762.5 | AR10: =Expenses!AR9 -> 115762.5 | AS10: =Expenses!AS9 -> 115762.5 | AT10: =Expenses!AT9 -> 115762.5 | AU10: =Expenses!AU9 -> 115762.5 | AV10: =Expenses!AV9 -> 115762.5 | ... AZ10: =Expenses!AZ9 -> 115762.5 | BA10: =SUM(AO10:AZ10) -> 1389150 | BB10: =Expenses!BB9 -> 121550.62 | BC10: =Expenses!BC9 -> 121550.62 | BD10: =Expenses!BD9 -> 121550.62 | BE10: =Expenses!BE9 -> 121550.62 | BF10: =Expenses!BF9 -> 121550.62 | BG10: =Expenses!BG9 -> 121550.62 | BH10: =Expenses!BH9 -> 121550.62 | BI10: =Expenses!BI9 -> 121550.62 | ... BM10: =Expenses!BM9 -> 121550.62 | BN10: =SUM(BB10:BM10) -> 1458607.5
A11: (-) Repairs & maintenance | B11: =Expenses!B10 -> 30000 | C11: =Expenses!C10 -> 30000 | D11: =Expenses!D10 -> 30000 | E11: =Expenses!E10 -> 30000 | F11: =Expenses!F10 -> 30000 | G11: =Expenses!G10 -> 30000 | H11: =Expenses!H10 -> 30000 | I11: =Expenses!I10 -> 30000 | ... M11: =Expenses!M10 -> 30000 | N11: =SUM(B11:M11) -> 360000 | O11: =Expenses!O10 -> 31200 | P11: =Expenses!P10 -> 31200 | Q11: =Expenses!Q10 -> 31200 | R11: =Expenses!R10 -> 31200 | S11: =Expenses!S10 -> 31200 | T11: =Expenses!T10 -> 31200 | U11: =Expenses!U10 -> 31200 | V11: =Expenses!V10 -> 31200 | ... Z11: =Expenses!Z10 -> 31200 | AA11: =SUM(O11:Z11) -> 374400 | AB11: =Expenses!AB10 -> 32448 | AC11: =Expenses!AC10 -> 32448 | AD11: =Expenses!AD10 -> 32448 | AE11: =Expenses!AE10 -> 32448 | AF11: =Expenses!AF10 -> 32448 | AG11: =Expenses!AG10 -> 32448 | AH11: =Expenses!AH10 -> 32448 | AI11: =Expenses!AI10 -> 32448 | ... AM11: =Expenses!AM10 -> 32448 | AN11: =SUM(AB11:AM11) -> 389376 | AO11: =Expenses!AO10 -> 33745.92 | AP11: =Expenses!AP10 -> 33745.92 | AQ11: =Expenses!AQ10 -> 33745.92 | AR11: =Expenses!AR10 -> 33745.92 | AS11: =Expenses!AS10 -> 33745.92 | AT11: =Expenses!AT10 -> 33745.92 | AU11: =Expenses!AU10 -> 33745.92 | AV11: =Expenses!AV10 -> 33745.92 | ... AZ11: =Expenses!AZ10 -> 33745.92 | BA11: =SUM(AO11:AZ11) -> 404951.04 | BB11: =Expenses!BB10 -> 35095.757 | BC11: =Expenses!BC10 -> 35095.757 | BD11: =Expenses!BD10 -> 35095.757 | BE11: =Expenses!BE10 -> 35095.757 | BF11: =Expenses!BF10 -> 35095.757 | BG11: =Expenses!BG10 -> 35095.757 | BH11: =Expenses!BH10 -> 35095.757 | BI11: =Expenses!BI10 -> 35095.757 | ... BM11: =Expenses!BM10 -> 35095.757 | BN11: =SUM(BB11:BM11) -> 421149.08
A12: (-) Administrative expenses | B12: =Expenses!B11 -> 50000 | C12: =Expenses!C11 -> 50000 | D12: =Expenses!D11 -> 50000 | E12: =Expenses!E11 -> 50000 | F12: =Expenses!F11 -> 50000 | G12: =Expenses!G11 -> 50000 | H12: =Expenses!H11 -> 50000 | I12: =Expenses!I11 -> 50000 | ... M12: =Expenses!M11 -> 50000 | N12: =SUM(B12:M12) -> 600000 | O12: =Expenses!O11 -> 52000 | P12: =Expenses!P11 -> 52000 | Q12: =Expenses!Q11 -> 52000 | R12: =Expenses!R11 -> 52000 | S12: =Expenses!S11 -> 52000 | T12: =Expenses!T11 -> 52000 | U12: =Expenses!U11 -> 52000 | V12: =Expenses!V11 -> 52000 | ... Z12: =Expenses!Z11 -> 52000 | AA12: =SUM(O12:Z12) -> 624000 | AB12: =Expenses!AB11 -> 54080 | AC12: =Expenses!AC11 -> 54080 | AD12: =Expenses!AD11 -> 54080 | AE12: =Expenses!AE11 -> 54080 | AF12: =Expenses!AF11 -> 54080 | AG12: =Expenses!AG11 -> 54080 | AH12: =Expenses!AH11 -> 54080 | AI12: =Expenses!AI11 -> 54080 | ... AM12: =Expenses!AM11 -> 54080 | AN12: =SUM(AB12:AM12) -> 648960 | AO12: =Expenses!AO11 -> 56243.2 | AP12: =Expenses!AP11 -> 56243.2 | AQ12: =Expenses!AQ11 -> 56243.2 | AR12: =Expenses!AR11 -> 56243.2 | AS12: =Expenses!AS11 -> 56243.2 | AT12: =Expenses!AT11 -> 56243.2 | AU12: =Expenses!AU11 -> 56243.2 | AV12: =Expenses!AV11 -> 56243.2 | ... AZ12: =Expenses!AZ11 -> 56243.2 | BA12: =SUM(AO12:AZ12) -> 674918.4 | BB12: =Expenses!BB11 -> 58492.928 | BC12: =Expenses!BC11 -> 58492.928 | BD12: =Expenses!BD11 -> 58492.928 | BE12: =Expenses!BE11 -> 58492.928 | BF12: =Expenses!BF11 -> 58492.928 | BG12: =Expenses!BG11 -> 58492.928 | BH12: =Expenses!BH11 -> 58492.928 | BI12: =Expenses!BI11 -> 58492.928 | ... BM12: =Expenses!BM11 -> 58492.928 | BN12: =SUM(BB12:BM12) -> 701915.14
A13: (-) Selling & distribution | B13: =Expenses!B12 -> 57600 | C13: =Expenses!C12 -> 57600 | D13: =Expenses!D12 -> 57600 | E13: =Expenses!E12 -> 64800 | F13: =Expenses!F12 -> 64800 | G13: =Expenses!G12 -> 64800 | H13: =Expenses!H12 -> 57600 | I13: =Expenses!I12 -> 57600 | ... M13: =Expenses!M12 -> 50400 | N13: =SUM(B13:M13) -> 720000 | O13: =Expenses!O12 -> 64896 | P13: =Expenses!P12 -> 64896 | Q13: =Expenses!Q12 -> 64896 | R13: =Expenses!R12 -> 73008 | S13: =Expenses!S12 -> 73008 | T13: =Expenses!T12 -> 73008 | U13: =Expenses!U12 -> 64896 | V13: =Expenses!V12 -> 64896 | ... Z13: =Expenses!Z12 -> 56784 | AA13: =SUM(O13:Z13) -> 811200 | AB13: =Expenses!AB12 -> 72683.52 | AC13: =Expenses!AC12 -> 72683.52 | AD13: =Expenses!AD12 -> 72683.52 | AE13: =Expenses!AE12 -> 81768.96 | AF13: =Expenses!AF12 -> 81768.96 | AG13: =Expenses!AG12 -> 81768.96 | AH13: =Expenses!AH12 -> 72683.52 | AI13: =Expenses!AI12 -> 72683.52 | ... AM13: =Expenses!AM12 -> 63598.08 | AN13: =SUM(AB13:AM13) -> 908544 | AO13: =Expenses!AO12 -> 80990.208 | AP13: =Expenses!AP12 -> 80990.208 | AQ13: =Expenses!AQ12 -> 80990.208 | AR13: =Expenses!AR12 -> 91113.984 | AS13: =Expenses!AS12 -> 91113.984 | AT13: =Expenses!AT12 -> 91113.984 | AU13: =Expenses!AU12 -> 80990.208 | AV13: =Expenses!AV12 -> 80990.208 | ... AZ13: =Expenses!AZ12 -> 70866.432 | BA13: =SUM(AO13:AZ13) -> 1012377.6 | BB13: =Expenses!BB12 -> 89845.137 | BC13: =Expenses!BC12 -> 89845.137 | BD13: =Expenses!BD12 -> 89845.137 | BE13: =Expenses!BE12 -> 101075.78 | BF13: =Expenses!BF12 -> 101075.78 | BG13: =Expenses!BG12 -> 101075.78 | BH13: =Expenses!BH12 -> 89845.137 | BI13: =Expenses!BI12 -> 89845.137 | ... BM13: =Expenses!BM12 -> 78614.495 | BN13: =SUM(BB13:BM13) -> 1123064.2
A14: EBITDA | B14: =B5-SUM(B6:B13) -> 764400 | C14: =C5-SUM(C6:C13) -> 764400 | D14: =D5-SUM(D6:D13) -> 764400 | E14: =E5-SUM(E6:E13) -> 901200 | F14: =F5-SUM(F6:F13) -> 901200 | G14: =G5-SUM(G6:G13) -> 901200 | H14: =H5-SUM(H6:H13) -> 764400 | I14: =I5-SUM(I6:I13) -> 764400 | ... M14: =M5-SUM(M6:M13) -> 627600 | N14: =SUM(B14:M14) -> 9720000 | O14: =O5-SUM(O6:O13) -> 867980 | P14: =P5-SUM(P6:P13) -> 867980 | Q14: =Q5-SUM(Q6:Q13) -> 867980 | R14: =R5-SUM(R6:R13) -> 1019690 | S14: =S5-SUM(S6:S13) -> 1019690 | T14: =T5-SUM(T6:T13) -> 1019690 | U14: =U5-SUM(U6:U13) -> 867980 | V14: =V5-SUM(V6:V13) -> 867980 | ... Z14: =Z5-SUM(Z6:Z13) -> 716270 | AA14: =SUM(O14:Z14) -> 11022600 | AB14: =AB5-SUM(AB6:AB13) -> 975254.68 | AC14: =AC5-SUM(AC6:AC13) -> 975254.68 | AD14: =AD5-SUM(AD6:AD13) -> 975254.68 | AE14: =AE5-SUM(AE6:AE13) -> 1142430.6 | AF14: =AF5-SUM(AF6:AF13) -> 1142430.6 | AG14: =AG5-SUM(AG6:AG13) -> 1142430.6 | AH14: =AH5-SUM(AH6:AH13) -> 975254.68 | AI14: =AI5-SUM(AI6:AI13) -> 975254.68 | ... AM14: =AM5-SUM(AM6:AM13) -> 808078.72 | AN14: =SUM(AB14:AM14) -> 12371760 | AO14: =AO5-SUM(AO6:AO13) -> 1086160 | AP14: =AP5-SUM(AP6:AP13) -> 1086160 | AQ14: =AQ5-SUM(AQ6:AQ13) -> 1086160 | AR14: =AR5-SUM(AR6:AR13) -> 1269354.4 | AS14: =AS5-SUM(AS6:AS13) -> 1269354.4 | AT14: =AT5-SUM(AT6:AT13) -> 1269354.4 | AU14: =AU5-SUM(AU6:AU13) -> 1086160 | AV14: =AV5-SUM(AV6:AV13) -> 1086160 | ... AZ14: =AZ5-SUM(AZ6:AZ13) -> 902965.54 | BA14: =SUM(AO14:AZ14) -> 13766697 | BB14: =BB5-SUM(BB6:BB13) -> 1200609.5 | BC14: =BC5-SUM(BC6:BC13) -> 1200609.5 | BD14: =BD5-SUM(BD6:BD13) -> 1200609.5 | BE14: =BE5-SUM(BE6:BE13) -> 1400368.9 | BF14: =BF5-SUM(BF6:BF13) -> 1400368.9 | BG14: =BG5-SUM(BG6:BG13) -> 1400368.9 | BH14: =BH5-SUM(BH6:BH13) -> 1200609.5 | BI14: =BI5-SUM(BI6:BI13) -> 1200609.5 | ... BM14: =BM5-SUM(BM6:BM13) -> 1000850.2 | BN14: =SUM(BB14:BM14) -> 15206352
A15: (-) Depreciation | B15: =Expenses!B13 -> 76666.667 | C15: =Expenses!C13 -> 76666.667 | D15: =Expenses!D13 -> 76666.667 | E15: =Expenses!E13 -> 76666.667 | F15: =Expenses!F13 -> 76666.667 | G15: =Expenses!G13 -> 76666.667 | H15: =Expenses!H13 -> 76666.667 | I15: =Expenses!I13 -> 76666.667 | ... M15: =Expenses!M13 -> 76666.667 | N15: =SUM(B15:M15) -> 920000 | O15: =Expenses!O13 -> 76666.667 | P15: =Expenses!P13 -> 76666.667 | Q15: =Expenses!Q13 -> 76666.667 | R15: =Expenses!R13 -> 76666.667 | S15: =Expenses!S13 -> 76666.667 | T15: =Expenses!T13 -> 76666.667 | U15: =Expenses!U13 -> 76666.667 | V15: =Expenses!V13 -> 76666.667 | ... Z15: =Expenses!Z13 -> 76666.667 | AA15: =SUM(O15:Z15) -> 920000 | AB15: =Expenses!AB13 -> 76666.667 | AC15: =Expenses!AC13 -> 76666.667 | AD15: =Expenses!AD13 -> 76666.667 | AE15: =Expenses!AE13 -> 76666.667 | AF15: =Expenses!AF13 -> 76666.667 | AG15: =Expenses!AG13 -> 76666.667 | AH15: =Expenses!AH13 -> 76666.667 | AI15: =Expenses!AI13 -> 76666.667 | ... AM15: =Expenses!AM13 -> 76666.667 | AN15: =SUM(AB15:AM15) -> 920000 | AO15: =Expenses!AO13 -> 76666.667 | AP15: =Expenses!AP13 -> 76666.667 | AQ15: =Expenses!AQ13 -> 76666.667 | AR15: =Expenses!AR13 -> 76666.667 | AS15: =Expenses!AS13 -> 76666.667 | AT15: =Expenses!AT13 -> 76666.667 | AU15: =Expenses!AU13 -> 76666.667 | AV15: =Expenses!AV13 -> 76666.667 | ... AZ15: =Expenses!AZ13 -> 76666.667 | BA15: =SUM(AO15:AZ15) -> 920000 | BB15: =Expenses!BB13 -> 76666.667 | BC15: =Expenses!BC13 -> 76666.667 | BD15: =Expenses!BD13 -> 76666.667 | BE15: =Expenses!BE13 -> 76666.667 | BF15: =Expenses!BF13 -> 76666.667 | BG15: =Expenses!BG13 -> 76666.667 | BH15: =Expenses!BH13 -> 76666.667 | BI15: =Expenses!BI13 -> 76666.667 | ... BM15: =Expenses!BM13 -> 76666.667 | BN15: =SUM(BB15:BM15) -> 920000
A16: EBIT (Operating Profit) | B16: =B14-B15 -> 687733.33 | C16: =C14-C15 -> 687733.33 | D16: =D14-D15 -> 687733.33 | E16: =E14-E15 -> 824533.33 | F16: =F14-F15 -> 824533.33 | G16: =G14-G15 -> 824533.33 | H16: =H14-H15 -> 687733.33 | I16: =I14-I15 -> 687733.33 | ... M16: =M14-M15 -> 550933.33 | N16: =SUM(B16:M16) -> 8800000 | O16: =O14-O15 -> 791313.33 | P16: =P14-P15 -> 791313.33 | Q16: =Q14-Q15 -> 791313.33 | R16: =R14-R15 -> 943023.33 | S16: =S14-S15 -> 943023.33 | T16: =T14-T15 -> 943023.33 | U16: =U14-U15 -> 791313.33 | V16: =V14-V15 -> 791313.33 | ... Z16: =Z14-Z15 -> 639603.33 | AA16: =SUM(O16:Z16) -> 10102600 | AB16: =AB14-AB15 -> 898588.01 | AC16: =AC14-AC15 -> 898588.01 | AD16: =AD14-AD15 -> 898588.01 | AE16: =AE14-AE15 -> 1065764 | AF16: =AF14-AF15 -> 1065764 | AG16: =AG14-AG15 -> 1065764 | AH16: =AH14-AH15 -> 898588.01 | AI16: =AI14-AI15 -> 898588.01 | ... AM16: =AM14-AM15 -> 731412.05 | AN16: =SUM(AB16:AM16) -> 11451760 | AO16: =AO14-AO15 -> 1009493.3 | AP16: =AP14-AP15 -> 1009493.3 | AQ16: =AQ14-AQ15 -> 1009493.3 | AR16: =AR14-AR15 -> 1192687.7 | AS16: =AS14-AS15 -> 1192687.7 | AT16: =AT14-AT15 -> 1192687.7 | AU16: =AU14-AU15 -> 1009493.3 | AV16: =AV14-AV15 -> 1009493.3 | ... AZ16: =AZ14-AZ15 -> 826298.87 | BA16: =SUM(AO16:AZ16) -> 12846697 | BB16: =BB14-BB15 -> 1123942.9 | BC16: =BC14-BC15 -> 1123942.9 | BD16: =BD14-BD15 -> 1123942.9 | BE16: =BE14-BE15 -> 1323702.2 | BF16: =BF14-BF15 -> 1323702.2 | BG16: =BG14-BG15 -> 1323702.2 | BH16: =BH14-BH15 -> 1123942.9 | BI16: =BI14-BI15 -> 1123942.9 | ... BM16: =BM14-BM15 -> 924183.51 | BN16: =SUM(BB16:BM16) -> 14286352
A17: (-) Interest — Term Loan | B17: =Expenses!B14 -> 52500 | C17: =Expenses!C14 -> 52500 | D17: =Expenses!D14 -> 52500 | E17: =Expenses!E14 -> 52500 | F17: =Expenses!F14 -> 52500 | G17: =Expenses!G14 -> 52500 | H17: =Expenses!H14 -> 52500 | I17: =Expenses!I14 -> 52500 | ... M17: =Expenses!M14 -> 52500 | N17: =SUM(B17:M17) -> 630000 | O17: =Expenses!O14 -> 51617.647 | P17: =Expenses!P14 -> 51617.647 | Q17: =Expenses!Q14 -> 51617.647 | R17: =Expenses!R14 -> 51617.647 | S17: =Expenses!S14 -> 51617.647 | T17: =Expenses!T14 -> 51617.647 | U17: =Expenses!U14 -> 51617.647 | V17: =Expenses!V14 -> 51617.647 | ... Z17: =Expenses!Z14 -> 51617.647 | AA17: =SUM(O17:Z17) -> 619411.76 | AB17: =Expenses!AB14 -> 50735.294 | AC17: =Expenses!AC14 -> 50735.294 | AD17: =Expenses!AD14 -> 50735.294 | AE17: =Expenses!AE14 -> 50735.294 | AF17: =Expenses!AF14 -> 50735.294 | AG17: =Expenses!AG14 -> 50735.294 | AH17: =Expenses!AH14 -> 50735.294 | AI17: =Expenses!AI14 -> 50735.294 | ... AM17: =Expenses!AM14 -> 50735.294 | AN17: =SUM(AB17:AM17) -> 608823.53 | AO17: =Expenses!AO14 -> 49852.941 | AP17: =Expenses!AP14 -> 49852.941 | AQ17: =Expenses!AQ14 -> 49852.941 | AR17: =Expenses!AR14 -> 49852.941 | AS17: =Expenses!AS14 -> 49852.941 | AT17: =Expenses!AT14 -> 49852.941 | AU17: =Expenses!AU14 -> 49852.941 | AV17: =Expenses!AV14 -> 49852.941 | ... AZ17: =Expenses!AZ14 -> 49852.941 | BA17: =SUM(AO17:AZ17) -> 598235.29 | BB17: =Expenses!BB14 -> 48970.588 | BC17: =Expenses!BC14 -> 48970.588 | BD17: =Expenses!BD14 -> 48970.588 | BE17: =Expenses!BE14 -> 48970.588 | BF17: =Expenses!BF14 -> 48970.588 | BG17: =Expenses!BG14 -> 48970.588 | BH17: =Expenses!BH14 -> 48970.588 | BI17: =Expenses!BI14 -> 48970.588 | ... BM17: =Expenses!BM14 -> 48970.588 | BN17: =SUM(BB17:BM17) -> 587647.06
A18: (-) Interest — Working Capital | B18: =Expenses!B15 -> 12365.753 | C18: =Expenses!C15 -> 12365.753 | D18: =Expenses!D15 -> 12365.753 | E18: =Expenses!E15 -> 12365.753 | F18: =Expenses!F15 -> 12365.753 | G18: =Expenses!G15 -> 12365.753 | H18: =Expenses!H15 -> 12365.753 | I18: =Expenses!I15 -> 12365.753 | ... M18: =Expenses!M15 -> 12365.753 | N18: =SUM(B18:M18) -> 148389.04 | O18: =Expenses!O15 -> 13533.842 | P18: =Expenses!P15 -> 13533.842 | Q18: =Expenses!Q15 -> 13533.842 | R18: =Expenses!R15 -> 13533.842 | S18: =Expenses!S15 -> 13533.842 | T18: =Expenses!T15 -> 13533.842 | U18: =Expenses!U15 -> 13533.842 | V18: =Expenses!V15 -> 13533.842 | ... Z18: =Expenses!Z15 -> 13533.842 | AA18: =SUM(O18:Z18) -> 162406.11 | AB18: =Expenses!AB15 -> 14756.155 | AC18: =Expenses!AC15 -> 14756.155 | AD18: =Expenses!AD15 -> 14756.155 | AE18: =Expenses!AE15 -> 14756.155 | AF18: =Expenses!AF15 -> 14756.155 | AG18: =Expenses!AG15 -> 14756.155 | AH18: =Expenses!AH15 -> 14756.155 | AI18: =Expenses!AI15 -> 14756.155 | ... AM18: =Expenses!AM15 -> 14756.155 | AN18: =SUM(AB18:AM18) -> 177073.86 | AO18: =Expenses!AO15 -> 16033.972 | AP18: =Expenses!AP15 -> 16033.972 | AQ18: =Expenses!AQ15 -> 16033.972 | AR18: =Expenses!AR15 -> 16033.972 | AS18: =Expenses!AS15 -> 16033.972 | AT18: =Expenses!AT15 -> 16033.972 | AU18: =Expenses!AU15 -> 16033.972 | AV18: =Expenses!AV15 -> 16033.972 | ... AZ18: =Expenses!AZ15 -> 16033.972 | BA18: =SUM(AO18:AZ18) -> 192407.66 | BB18: =Expenses!BB15 -> 17368.528 | BC18: =Expenses!BC15 -> 17368.528 | BD18: =Expenses!BD15 -> 17368.528 | BE18: =Expenses!BE15 -> 17368.528 | BF18: =Expenses!BF15 -> 17368.528 | BG18: =Expenses!BG15 -> 17368.528 | BH18: =Expenses!BH15 -> 17368.528 | BI18: =Expenses!BI15 -> 17368.528 | ... BM18: =Expenses!BM15 -> 17368.528 | BN18: =SUM(BB18:BM18) -> 208422.34
A19: Profit Before Tax (PBT) | B19: =B16-B17-B18 -> 622867.58 | C19: =C16-C17-C18 -> 622867.58 | D19: =D16-D17-D18 -> 622867.58 | E19: =E16-E17-E18 -> 759667.58 | F19: =F16-F17-F18 -> 759667.58 | G19: =G16-G17-G18 -> 759667.58 | H19: =H16-H17-H18 -> 622867.58 | I19: =I16-I17-I18 -> 622867.58 | ... M19: =M16-M17-M18 -> 486067.58 | N19: =SUM(B19:M19) -> 8021611 | O19: =O16-O17-O18 -> 726161.84 | P19: =P16-P17-P18 -> 726161.84 | Q19: =Q16-Q17-Q18 -> 726161.84 | R19: =R16-R17-R18 -> 877871.84 | S19: =S16-S17-S18 -> 877871.84 | T19: =T16-T17-T18 -> 877871.84 | U19: =U16-U17-U18 -> 726161.84 | V19: =V16-V17-V18 -> 726161.84 | ... Z19: =Z16-Z17-Z18 -> 574451.84 | AA19: =SUM(O19:Z19) -> 9320782.1 | AB19: =AB16-AB17-AB18 -> 833096.56 | AC19: =AC16-AC17-AC18 -> 833096.56 | AD19: =AD16-AD17-AD18 -> 833096.56 | AE19: =AE16-AE17-AE18 -> 1000272.5 | AF19: =AF16-AF17-AF18 -> 1000272.5 | AG19: =AG16-AG17-AG18 -> 1000272.5 | AH19: =AH16-AH17-AH18 -> 833096.56 | AI19: =AI16-AI17-AI18 -> 833096.56 | ... AM19: =AM16-AM17-AM18 -> 665920.6 | AN19: =SUM(AB19:AM19) -> 10665863 | AO19: =AO16-AO17-AO18 -> 943606.37 | AP19: =AP16-AP17-AP18 -> 943606.37 | AQ19: =AQ16-AQ17-AQ18 -> 943606.37 | AR19: =AR16-AR17-AR18 -> 1126800.8 | AS19: =AS16-AS17-AS18 -> 1126800.8 | AT19: =AT16-AT17-AT18 -> 1126800.8 | AU19: =AU16-AU17-AU18 -> 943606.37 | AV19: =AV16-AV17-AV18 -> 943606.37 | ... AZ19: =AZ16-AZ17-AZ18 -> 760411.96 | BA19: =SUM(AO19:AZ19) -> 12056054 | BB19: =BB16-BB17-BB18 -> 1057603.7 | BC19: =BC16-BC17-BC18 -> 1057603.7 | BD19: =BD16-BD17-BD18 -> 1057603.7 | BE19: =BE16-BE17-BE18 -> 1257363.1 | BF19: =BF16-BF17-BF18 -> 1257363.1 | BG19: =BG16-BG17-BG18 -> 1257363.1 | BH19: =BH16-BH17-BH18 -> 1057603.7 | BI19: =BI16-BI17-BI18 -> 1057603.7 | ... BM19: =BM16-BM17-BM18 -> 857844.39 | BN19: =SUM(BB19:BM19) -> 13490282
A20: (-) Income Tax | B20: =IF(B19>0,B19*Assumptions!$C$14,0) -> 155716.89 | C20: =IF(C19>0,C19*Assumptions!$C$14,0) -> 155716.89 | D20: =IF(D19>0,D19*Assumptions!$C$14,0) -> 155716.89 | E20: =IF(E19>0,E19*Assumptions!$C$14,0) -> 189916.89 | F20: =IF(F19>0,F19*Assumptions!$C$14,0) -> 189916.89 | G20: =IF(G19>0,G19*Assumptions!$C$14,0) -> 189916.89 | H20: =IF(H19>0,H19*Assumptions!$C$14,0) -> 155716.89 | I20: =IF(I19>0,I19*Assumptions!$C$14,0) -> 155716.89 | ... M20: =IF(M19>0,M19*Assumptions!$C$14,0) -> 121516.89 | N20: =SUM(B20:M20) -> 2005402.7 | O20: =IF(O19>0,O19*Assumptions!$C$14,0) -> 181540.46 | P20: =IF(P19>0,P19*Assumptions!$C$14,0) -> 181540.46 | Q20: =IF(Q19>0,Q19*Assumptions!$C$14,0) -> 181540.46 | R20: =IF(R19>0,R19*Assumptions!$C$14,0) -> 219467.96 | S20: =IF(S19>0,S19*Assumptions!$C$14,0) -> 219467.96 | T20: =IF(T19>0,T19*Assumptions!$C$14,0) -> 219467.96 | U20: =IF(U19>0,U19*Assumptions!$C$14,0) -> 181540.46 | V20: =IF(V19>0,V19*Assumptions!$C$14,0) -> 181540.46 | ... Z20: =IF(Z19>0,Z19*Assumptions!$C$14,0) -> 143612.96 | AA20: =SUM(O20:Z20) -> 2330195.5 | AB20: =IF(AB19>0,AB19*Assumptions!$C$14,0) -> 208274.14 | AC20: =IF(AC19>0,AC19*Assumptions!$C$14,0) -> 208274.14 | AD20: =IF(AD19>0,AD19*Assumptions!$C$14,0) -> 208274.14 | AE20: =IF(AE19>0,AE19*Assumptions!$C$14,0) -> 250068.13 | AF20: =IF(AF19>0,AF19*Assumptions!$C$14,0) -> 250068.13 | AG20: =IF(AG19>0,AG19*Assumptions!$C$14,0) -> 250068.13 | AH20: =IF(AH19>0,AH19*Assumptions!$C$14,0) -> 208274.14 | AI20: =IF(AI19>0,AI19*Assumptions!$C$14,0) -> 208274.14 | ... AM20: =IF(AM19>0,AM19*Assumptions!$C$14,0) -> 166480.15 | AN20: =SUM(AB20:AM20) -> 2666465.7 | AO20: =IF(AO19>0,AO19*Assumptions!$C$14,0) -> 235901.59 | AP20: =IF(AP19>0,AP19*Assumptions!$C$14,0) -> 235901.59 | AQ20: =IF(AQ19>0,AQ19*Assumptions!$C$14,0) -> 235901.59 | AR20: =IF(AR19>0,AR19*Assumptions!$C$14,0) -> 281700.2 | AS20: =IF(AS19>0,AS19*Assumptions!$C$14,0) -> 281700.2 | AT20: =IF(AT19>0,AT19*Assumptions!$C$14,0) -> 281700.2 | AU20: =IF(AU19>0,AU19*Assumptions!$C$14,0) -> 235901.59 | AV20: =IF(AV19>0,AV19*Assumptions!$C$14,0) -> 235901.59 | ... AZ20: =IF(AZ19>0,AZ19*Assumptions!$C$14,0) -> 190102.99 | BA20: =SUM(AO20:AZ20) -> 3014013.5 | BB20: =IF(BB19>0,BB19*Assumptions!$C$14,0) -> 264400.93 | BC20: =IF(BC19>0,BC19*Assumptions!$C$14,0) -> 264400.93 | BD20: =IF(BD19>0,BD19*Assumptions!$C$14,0) -> 264400.93 | BE20: =IF(BE19>0,BE19*Assumptions!$C$14,0) -> 314340.77 | BF20: =IF(BF19>0,BF19*Assumptions!$C$14,0) -> 314340.77 | BG20: =IF(BG19>0,BG19*Assumptions!$C$14,0) -> 314340.77 | BH20: =IF(BH19>0,BH19*Assumptions!$C$14,0) -> 264400.93 | BI20: =IF(BI19>0,BI19*Assumptions!$C$14,0) -> 264400.93 | ... BM20: =IF(BM19>0,BM19*Assumptions!$C$14,0) -> 214461.1 | BN20: =SUM(BB20:BM20) -> 3372570.6
A21: Profit After Tax (PAT) | B21: =B19-B20 -> 467150.68 | C21: =C19-C20 -> 467150.68 | D21: =D19-D20 -> 467150.68 | E21: =E19-E20 -> 569750.68 | F21: =F19-F20 -> 569750.68 | G21: =G19-G20 -> 569750.68 | H21: =H19-H20 -> 467150.68 | I21: =I19-I20 -> 467150.68 | ... M21: =M19-M20 -> 364550.68 | N21: =SUM(B21:M21) -> 6016208.2 | O21: =O19-O20 -> 544621.38 | P21: =P19-P20 -> 544621.38 | Q21: =Q19-Q20 -> 544621.38 | R21: =R19-R20 -> 658403.88 | S21: =S19-S20 -> 658403.88 | T21: =T19-T20 -> 658403.88 | U21: =U19-U20 -> 544621.38 | V21: =V19-V20 -> 544621.38 | ... Z21: =Z19-Z20 -> 430838.88 | AA21: =SUM(O21:Z21) -> 6990586.6 | AB21: =AB19-AB20 -> 624822.42 | AC21: =AC19-AC20 -> 624822.42 | AD21: =AD19-AD20 -> 624822.42 | AE21: =AE19-AE20 -> 750204.39 | AF21: =AF19-AF20 -> 750204.39 | AG21: =AG19-AG20 -> 750204.39 | AH21: =AH19-AH20 -> 624822.42 | AI21: =AI19-AI20 -> 624822.42 | ... AM21: =AM19-AM20 -> 499440.45 | AN21: =SUM(AB21:AM21) -> 7999397 | AO21: =AO19-AO20 -> 707704.78 | AP21: =AP19-AP20 -> 707704.78 | AQ21: =AQ19-AQ20 -> 707704.78 | AR21: =AR19-AR20 -> 845100.59 | AS21: =AS19-AS20 -> 845100.59 | AT21: =AT19-AT20 -> 845100.59 | AU21: =AU19-AU20 -> 707704.78 | AV21: =AV19-AV20 -> 707704.78 | ... AZ21: =AZ19-AZ20 -> 570308.97 | BA21: =SUM(AO21:AZ21) -> 9042040.6 | BB21: =BB19-BB20 -> 793202.8 | BC21: =BC19-BC20 -> 793202.8 | BD21: =BD19-BD20 -> 793202.8 | BE21: =BE19-BE20 -> 943022.31 | BF21: =BF19-BF20 -> 943022.31 | BG21: =BG19-BG20 -> 943022.31 | BH21: =BH19-BH20 -> 793202.8 | BI21: =BI19-BI20 -> 793202.8 | ... BM21: =BM19-BM20 -> 643383.29 | BN21: =SUM(BB21:BM21) -> 10117712
A22: Cash Accrual (PAT + Depreciation) | B22: =B21+B15 -> 543817.35 | C22: =C21+C15 -> 543817.35 | D22: =D21+D15 -> 543817.35 | E22: =E21+E15 -> 646417.35 | F22: =F21+F15 -> 646417.35 | G22: =G21+G15 -> 646417.35 | H22: =H21+H15 -> 543817.35 | I22: =I21+I15 -> 543817.35 | ... M22: =M21+M15 -> 441217.35 | N22: =SUM(B22:M22) -> 6936208.2 | O22: =O21+O15 -> 621288.05 | P22: =P21+P15 -> 621288.05 | Q22: =Q21+Q15 -> 621288.05 | R22: =R21+R15 -> 735070.55 | S22: =S21+S15 -> 735070.55 | T22: =T21+T15 -> 735070.55 | U22: =U21+U15 -> 621288.05 | V22: =V21+V15 -> 621288.05 | ... Z22: =Z21+Z15 -> 507505.55 | AA22: =SUM(O22:Z22) -> 7910586.6 | AB22: =AB21+AB15 -> 701489.09 | AC22: =AC21+AC15 -> 701489.09 | AD22: =AD21+AD15 -> 701489.09 | AE22: =AE21+AE15 -> 826871.06 | AF22: =AF21+AF15 -> 826871.06 | AG22: =AG21+AG15 -> 826871.06 | AH22: =AH21+AH15 -> 701489.09 | AI22: =AI21+AI15 -> 701489.09 | ... AM22: =AM21+AM15 -> 576107.12 | AN22: =SUM(AB22:AM22) -> 8919397 | AO22: =AO21+AO15 -> 784371.44 | AP22: =AP21+AP15 -> 784371.44 | AQ22: =AQ21+AQ15 -> 784371.44 | AR22: =AR21+AR15 -> 921767.26 | AS22: =AS21+AS15 -> 921767.26 | AT22: =AT21+AT15 -> 921767.26 | AU22: =AU21+AU15 -> 784371.44 | AV22: =AV21+AV15 -> 784371.44 | ... AZ22: =AZ21+AZ15 -> 646975.63 | BA22: =SUM(AO22:AZ22) -> 9962040.6 | BB22: =BB21+BB15 -> 869869.47 | BC22: =BC21+BC15 -> 869869.47 | BD22: =BD21+BD15 -> 869869.47 | BE22: =BE21+BE15 -> 1019689 | BF22: =BF21+BF15 -> 1019689 | BG22: =BG21+BG15 -> 1019689 | BH22: =BH21+BH15 -> 869869.47 | BI22: =BI21+BI15 -> 869869.47 | ... BM22: =BM21+BM15 -> 720049.96 | BN22: =SUM(BB22:BM22) -> 11037712

Sheet Annual_Summary
A1: ANNUAL SUMMARY — CONSOLIDATED 5-YEAR VIEW
A2: Roll-up of the 60-month projections. Feeds every CMA form below.
B4: Particulars | C4: Year 1 | D4: Year 2 | E4: Year 3 | F4: Year 4 | G4: Year 5
B5: PRODUCTION & SALES
B6: =IFERROR(VLOOKUP(Assumptions!$J$5,Assumptions!$S$5:$Z$21,3,FALSE()),"Production (units)") -> Production (units) | C6: =Production!N6 -> 7200000 | D6: =Production!AA6 -> 7800000 | E6: =Production!AN6 -> 8400000 | F6: =Production!BA6 -> 9000000 | G6: =Production!BN6 -> 9600000
B7: Capacity utilisation (%) | C7: =Assumptions!$C$18 -> 0.6 | D7: =Assumptions!$D$18 -> 0.65 | E7: =Assumptions!$E$18 -> 0.7 | F7: =Assumptions!$F$18 -> 0.75 | G7: =Assumptions!$G$18 -> 0.8
B8: Net Sales / Revenue (₹) | C8: =Sales!N7 -> 36000000 | D8: =Sales!AA7 -> 40560000 | E8: =Sales!AN7 -> 45427200 | F8: =Sales!BA7 -> 50618880 | G8: =Sales!BN7 -> 56153211
B9: COST STRUCTURE (₹)
B10: =IFERROR(VLOOKUP(Assumptions!$J$5,Assumptions!$S$5:$Z$21,5,FALSE()),"Raw materials") -> Raw materials | C10: =Expenses!N5 -> 18000000 | D10: =Expenses!AA5 -> 20475000 | E10: =Expenses!AN5 -> 23152500 | F10: =Expenses!BA5 -> 26046563 | G10: =Expenses!BN5 -> 29172150
B11: =IFERROR(VLOOKUP(Assumptions!$J$5,Assumptions!$S$5:$Z$21,7,FALSE()),"Power & fuel") -> Power & fuel | C11: =Expenses!N6 -> 2160000 | D11: =Expenses!AA6 -> 2480400 | E11: =Expenses!AN6 -> 2831472 | F11: =Expenses!BA6 -> 3215743.2 | G11: =Expenses!BN6 -> 3635933.6
B12: Direct wages & salaries | C12: =Expenses!N7 -> 1800000 | D12: =Expenses!AA7 -> 1890000 | E12: =Expenses!AN7 -> 1984500 | F12: =Expenses!BA7 -> 2083725 | G12: =Expenses!BN7 -> 2187911.2
B13: Other variable cost | C13: =Expenses!N8 -> 1440000 | D13: =Expenses!AA8 -> 1622400 | E13: =Expenses!AN8 -> 1817088 | F13: =Expenses!BA8 -> 2024755.2 | G13: =Expenses!BN8 -> 2246128.4
B14: =IFERROR(VLOOKUP(Assumptions!$J$5,Assumptions!$S$5:$Z$21,8,FALSE()),"Factory overheads") -> Factory overheads | C14: =Expenses!N9 -> 1200000 | D14: =Expenses!AA9 -> 1260000 | E14: =Expenses!AN9 -> 1323000 | F14: =Expenses!BA9 -> 1389150 | G14: =Expenses!BN9 -> 1458607.5
B15: Repairs & maintenance | C15: =Expenses!N10 -> 360000 | D15: =Expenses!AA10 -> 374400 | E15: =Expenses!AN10 -> 389376 | F15: =Expenses!BA10 -> 404951.04 | G15: =Expenses!BN10 -> 421149.08
B16: Administrative expenses | C16: =Expenses!N11 -> 600000 | D16: =Expenses!AA11 -> 624000 | E16: =Expenses!AN11 -> 648960 | F16: =Expenses!BA11 -> 674918.4 | G16: =Expenses!BN11 -> 701915.14
B17: Selling & distribution | C17: =Expenses!N12 -> 720000 | D17: =Expenses!AA12 -> 811200 | E17: =Expenses!AN12 -> 908544 | F17: =Expenses!BA12 -> 1012377.6 | G17: =Expenses!BN12 -> 1123064.2
B18: Depreciation | C18: =Expenses!N13 -> 920000 | D18: =Expenses!AA13 -> 920000 | E18: =Expenses!AN13 -> 920000 | F18: =Expenses!BA13 -> 920000 | G18: =Expenses!BN13 -> 920000
B19: Interest — Term Loan | C19: =Expenses!N14 -> 630000 | D19: =Expenses!AA14 -> 619411.76 | E19: =Expenses!AN14 -> 608823.53 | F19: =Expenses!BA14 -> 598235.29 | G19: =Expenses!BN14 -> 587647.06
B20: Interest — Working Capital | C20: =Expenses!N15 -> 148389.04 | D20: =Expenses!AA15 -> 162406.11 | E20: =Expenses!AN15 -> 177073.86 | F20: =Expenses!BA15 -> 192407.66 | G20: =Expenses!BN15 -> 208422.34
B21: PROFITABILITY (₹)
B22: EBITDA | C22: =Profit!N14 -> 9720000 | D22: =Profit!AA14 -> 11022600 | E22: =Profit!AN14 -> 12371760 | F22: =Profit!BA14 -> 13766697 | G22: =Profit!BN14 -> 15206352
B23: EBIT (Operating Profit) | C23: =Profit!N16 -> 8800000 | D23: =Profit!AA16 -> 10102600 | E23: =Profit!AN16 -> 11451760 | F23: =Profit!BA16 -> 12846697 | G23: =Profit!BN16 -> 14286352
B24: Profit Before Tax | C24: =Profit!N19 -> 8021611 | D24: =Profit!AA19 -> 9320782.1 | E24: =Profit!AN19 -> 10665863 | F24: =Profit!BA19 -> 12056054 | G24: =Profit!BN19 -> 13490282
B25: Income Tax | C25: =Profit!N20 -> 2005402.7 | D25: =Profit!AA20 -> 2330195.5 | E25: =Profit!AN20 -> 2666465.7 | F25: =Profit!BA20 -> 3014013.5 | G25: =Profit!BN20 -> 3372570.6
B26: Profit After Tax (PAT) | C26: =Profit!N21 -> 6016208.2 | D26: =Profit!AA21 -> 6990586.6 | E26: =Profit!AN21 -> 7999397 | F26: =Profit!BA21 -> 9042040.6 | G26: =Profit!BN21 -> 10117712
B27: Cash Accrual (PAT + Depreciation) | C27: =Profit!N22 -> 6936208.2 | D27: =Profit!AA22 -> 7910586.6 | E27: =Profit!AN22 -> 8919397 | F27: =Profit!BA22 -> 9962040.6 | G27: =Profit!BN22 -> 11037712

Sheet Form_II_Operating
A1: FORM II — OPERATING STATEMENT
A2: Projected profitability in the format required for credit appraisal (₹).
B4: Particulars | C4: Year 1 | D4: Year 2 | E4: Year 3 | F4: Year 4 | G4: Year 5
B5: Net Sales | C5: =Annual_Summary!C8 -> 36000000 | D5: =Annual_Summary!D8 -> 40560000 | E5: =Annual_Summary!E8 -> 45427200 | F5: =Annual_Summary!F8 -> 50618880 | G5: =Annual_Summary!G8 -> 56153211
B6: Cost of Production
B7: =IFERROR(VLOOKUP(Assumptions!$J$5,Assumptions!$S$5:$Z$21,5,FALSE()),"Raw materials") -> Raw materials | C7: =Annual_Summary!C10 -> 18000000 | D7: =Annual_Summary!D10 -> 20475000 | E7: =Annual_Summary!E10 -> 23152500 | F7: =Annual_Summary!F10 -> 26046563 | G7: =Annual_Summary!G10 -> 29172150
B8: =IFERROR(VLOOKUP(Assumptions!$J$5,Assumptions!$S$5:$Z$21,7,FALSE()),"Power & fuel") -> Power & fuel | C8: =Annual_Summary!C11 -> 2160000 | D8: =Annual_Summary!D11 -> 2480400 | E8: =Annual_Summary!E11 -> 2831472 | F8: =Annual_Summary!F11 -> 3215743.2 | G8: =Annual_Summary!G11 -> 3635933.6
B9: Direct wages & salaries | C9: =Annual_Summary!C12 -> 1800000 | D9: =Annual_Summary!D12 -> 1890000 | E9: =Annual_Summary!E12 -> 1984500 | F9: =Annual_Summary!F12 -> 2083725 | G9: =Annual_Summary!G12 -> 2187911.2
B10: Other variable cost | C10: =Annual_Summary!C13 -> 1440000 | D10: =Annual_Summary!D13 -> 1622400 | E10: =Annual_Summary!E13 -> 1817088 | F10: =Annual_Summary!F13 -> 2024755.2 | G10: =Annual_Summary!G13 -> 2246128.4
B11: =IFERROR(VLOOKUP(Assumptions!$J$5,Assumptions!$S$5:$Z$21,8,FALSE()),"Factory overheads") -> Factory overheads | C11: =Annual_Summary!C14 -> 1200000 | D11: =Annual_Summary!D14 -> 1260000 | E11: =Annual_Summary!E14 -> 1323000 | F11: =Annual_Summary!F14 -> 1389150 | G11: =Annual_Summary!G14 -> 1458607.5
B12: Repairs & maintenance | C12: =Annual_Summary!C15 -> 360000 | D12: =Annual_Summary!D15 -> 374400 | E12: =Annual_Summary!E15 -> 389376 | F12: =Annual_Summary!F15 -> 404951.04 | G12: =Annual_Summary!G15 -> 421149.08
B13: Depreciation | C13: =Annual_Summary!C18 -> 920000 | D13: =Annual_Summary!D18 -> 920000 | E13: =Annual_Summary!E18 -> 920000 | F13: =Annual_Summary!F18 -> 920000 | G13: =Annual_Summary!G18 -> 920000
B14: Cost of Production | C14: =Annual_Summary!C10+Annual_Summary!C11+Annual_Summary!C12+Annual_Summary!C13+Annual_Summary!C14+Annual_Summary!C15+Annual_Summary!C18 -> 25880000 | D14: =Annual_Summary!D10+Annual_Summary!D11+Annual_Summary!D12+Annual_Summary!D13+Annual_Summary!D14+Annual_Summary!D15+Annual_Summary!D18 -> 29022200 | E14: =Annual_Summary!E10+Annual_Summary!E11+Annual_Summary!E12+Annual_Summary!E13+Annual_Summary!E14+Annual_Summary!E15+Annual_Summary!E18 -> 32417936 | F14: =Annual_Summary!F10+Annual_Summary!F11+Annual_Summary!F12+Annual_Summary!F13+Annual_Summary!F14+Annual_Summary!F15+Annual_Summary!F18 -> 36084887 | G14: =Annual_Summary!G10+Annual_Summary!G11+Annual_Summary!G12+Annual_Summary!G13+Annual_Summary!G14+Annual_Summary!G15+Annual_Summary!G18 -> 40041880
B15: Gross Profit | C15: =Annual_Summary!C8-C14 -> 10120000 | D15: =Annual_Summary!D8-D14 -> 11537800 | E15: =Annual_Summary!E8-E14 -> 13009264 | F15: =Annual_Summary!F8-F14 -> 14533993 | G15: =Annual_Summary!G8-G14 -> 16111331
B16: (-) Administrative expenses | C16: =Annual_Summary!C16 -> 600000 | D16: =Annual_Summary!D16 -> 624000 | E16: =Annual_Summary!E16 -> 648960 | F16: =Annual_Summary!F16 -> 674918.4 | G16: =Annual_Summary!G16 -> 701915.14
B17: (-) Selling & distribution | C17: =Annual_Summary!C17 -> 720000 | D17: =Annual_Summary!D17 -> 811200 | E17: =Annual_Summary!E17 -> 908544 | F17: =Annual_Summary!F17 -> 1012377.6 | G17: =Annual_Summary!G17 -> 1123064.2
B18: Operating Profit (EBIT) | C18: =C15-Annual_Summary!C16-Annual_Summary!C17 -> 8800000 | D18: =D15-Annual_Summary!D16-Annual_Summary!D17 -> 10102600 | E18: =E15-Annual_Summary!E16-Annual_Summary!E17 -> 11451760 | F18: =F15-Annual_Summary!F16-Annual_Summary!F17 -> 12846697 | G18: =G15-Annual_Summary!G16-Annual_Summary!G17 -> 14286352
B19: (-) Interest — Term Loan | C19: =Annual_Summary!C19 -> 630000 | D19: =Annual_Summary!D19 -> 619411.76 | E19: =Annual_Summary!E19 -> 608823.53 | F19: =Annual_Summary!F19 -> 598235.29 | G19: =Annual_Summary!G19 -> 587647.06
B20: (-) Interest — Working Capital | C20: =Annual_Summary!C20 -> 148389.04 | D20: =Annual_Summary!D20 -> 162406.11 | E20: =Annual_Summary!E20 -> 177073.86 | F20: =Annual_Summary!F20 -> 192407.66 | G20: =Annual_Summary!G20 -> 208422.34
B21: Profit Before Tax | C21: =C18-Annual_Summary!C19-Annual_Summary!C20 -> 8021611 | D21: =D18-Annual_Summary!D19-Annual_Summary!D20 -> 9320782.1 | E21: =E18-Annual_Summary!E19-Annual_Summary!E20 -> 10665863 | F21: =F18-Annual_Summary!F19-Annual_Summary!F20 -> 12056054 | G21: =G18-Annual_Summary!G19-Annual_Summary!G20 -> 13490282
B22: (-) Provision for Tax | C22: =Annual_Summary!C25 -> 2005402.7 | D22: =Annual_Summary!D25 -> 2330195.5 | E22: =Annual_Summary!E25 -> 2666465.7 | F22: =Annual_Summary!F25 -> 3014013.5 | G22: =Annual_Summary!G25 -> 3372570.6
B23: Profit After Tax | C23: =C21-Annual_Summary!C25 -> 6016208.2 | D23: =D21-Annual_Summary!D25 -> 6990586.6 | E23: =E21-Annual_Summary!E25 -> 7999397 | F23: =F21-Annual_Summary!F25 -> 9042040.6 | G23: =G21-Annual_Summary!G25 -> 10117712

Sheet Form_III_BalanceSheet
A1: FORM III — PROJECTED BALANCE SHEET
A2: Sources & application of funds; cash is the balancing figure (₹).
B4: Particulars | C4: Year 1 | D4: Year 2 | E4: Year 3 | F4: Year 4 | G4: Year 5
B5: LIABILITIES (₹)
B6: Capital / Promoters' equity | C6: =Assumptions!$C$9 -> 1500000 | D6: =Assumptions!$C$9 -> 1500000 | E6: =Assumptions!$C$9 -> 1500000 | F6: =Assumptions!$C$9 -> 1500000 | G6: =Assumptions!$C$9 -> 1500000
B7: Reserves & surplus (accumulated PAT) | C7: =Annual_Summary!C26 -> 6016208.2 | D7: =C7+Annual_Summary!D26 -> 13006795 | E7: =D7+Annual_Summary!E26 -> 21006192 | F7: =E7+Annual_Summary!F26 -> 30048232 | G7: =F7+Annual_Summary!G26 -> 40165944
B8: Net Worth | C8: =C6+C7 -> 7516208.2 | D8: =D6+D7 -> 14506795 | E8: =E6+E7 -> 22506192 | F8: =F6+F7 -> 31548232 | G8: =G6+G7 -> 41665944
B9: Term loan (closing balance) | C9: =Repayment!C8 -> 5899159.7 | D9: =Repayment!D8 -> 5798319.3 | E9: =Repayment!E8 -> 5697479 | F9: =Repayment!F8 -> 5596638.7 | G9: =Repayment!G8 -> 5495798.3
B10: Bank borrowing — working capital | C10: =Form_V_MPBF!C11 -> 1236575.3 | D10: =Form_V_MPBF!D11 -> 1353384.2 | E10: =Form_V_MPBF!E11 -> 1475615.5 | F10: =Form_V_MPBF!F11 -> 1603397.2 | G10: =Form_V_MPBF!G11 -> 1736852.8
B11: Sundry creditors | C11: =Form_IV_CA_CL!C16 -> 2219178.1 | D11: =Form_IV_CA_CL!D16 -> 2524315.1 | E11: =Form_IV_CA_CL!E16 -> 2854417.8 | F11: =Form_IV_CA_CL!F16 -> 3211220 | G11: =Form_IV_CA_CL!G16 -> 3596566.4
B12: Other current liabilities / provisions | C12: =Form_IV_CA_CL!C17 -> 0 | D12: =Form_IV_CA_CL!D17 -> 0 | E12: =Form_IV_CA_CL!E17 -> 0 | F12: =Form_IV_CA_CL!F17 -> 0 | G12: =Form_IV_CA_CL!G17 -> 0
B13: TOTAL LIABILITIES | C13: =SUM(C8:C12) -> 16871121 | D13: =SUM(D8:D12) -> 24182813 | E13: =SUM(E8:E12) -> 32533704 | F13: =SUM(F8:F12) -> 41959488 | G13: =SUM(G8:G12) -> 52495162
B14: ASSETS (₹)
B15: Gross fixed assets | C15: =Assumptions!$C$42+Assumptions!$C$43+Assumptions!$C$45+Assumptions!$C$47 -> 6200000 | D15: =Assumptions!$C$42+Assumptions!$C$43+Assumptions!$C$45+Assumptions!$C$47 -> 6200000 | E15: =Assumptions!$C$42+Assumptions!$C$43+Assumptions!$C$45+Assumptions!$C$47 -> 6200000 | F15: =Assumptions!$C$42+Assumptions!$C$43+Assumptions!$C$45+Assumptions!$C$47 -> 6200000 | G15: =Assumptions!$C$42+Assumptions!$C$43+Assumptions!$C$45+Assumptions!$C$47 -> 6200000
B16: (-) Accumulated depreciation | C16: =Annual_Summary!C18 -> 920000 | D16: =C16+Annual_Summary!D18 -> 1840000 | E16: =D16+Annual_Summary!E18 -> 2760000 | F16: =E16+Annual_Summary!F18 -> 3680000 | G16: =F16+Annual_Summary!G18 -> 4600000
B17: Net fixed assets | C17: =C15-C16 -> 5280000 | D17: =D15-D16 -> 4360000 | E17: =E15-E16 -> 3440000 | F17: =F15-F16 -> 2520000 | G17: =G15-G16 -> 1600000
B18: Inventory | C18: =Form_IV_CA_CL!C10+Form_IV_CA_CL!C11 -> 1448767.1 | D18: =Form_IV_CA_CL!D10+Form_IV_CA_CL!D11 -> 1636567.1 | E18: =Form_IV_CA_CL!E10+Form_IV_CA_CL!E11 -> 1839635.2 | F18: =Form_IV_CA_CL!F10+Form_IV_CA_CL!F11 -> 2059033.7 | G18: =Form_IV_CA_CL!G10+Form_IV_CA_CL!G11 -> 2295893.3
B19: Sundry debtors / receivables | C19: =Form_IV_CA_CL!C12 -> 2958904.1 | D19: =Form_IV_CA_CL!D12 -> 3333698.6 | E19: =Form_IV_CA_CL!E12 -> 3733742.5 | F19: =Form_IV_CA_CL!F12 -> 4160455.9 | G19: =Form_IV_CA_CL!G12 -> 4615332.4
B20: Cash & bank (balancing figure) | C20: =C13-(C17+C18+C19) -> 7183450.1 | D20: =D13-(D17+D18+D19) -> 14852548 | E20: =E13-(E17+E18+E19) -> 23520326 | F20: =F13-(F17+F18+F19) -> 33219999 | G20: =G13-(G17+G18+G19) -> 43983936
B21: TOTAL ASSETS | C21: =C17+C18+C19+C20 -> 16871121 | D21: =D17+D18+D19+D20 -> 24182813 | E21: =E17+E18+E19+E20 -> 32533704 | F21: =F17+F18+F19+F20 -> 41959488 | G21: =G17+G18+G19+G20 -> 52495162
B22: Check (Liabilities − Assets = 0) | C22: =C13-C21 -> 0 | D22: =D13-D21 -> 0 | E22: =E13-E21 -> 0 | F22: =F13-F21 -> 0 | G22: =G13-G21 -> 0

Sheet Form_IV_CA_CL
A1: FORM IV — CURRENT ASSETS & CURRENT LIABILITIES
A2: Build-up of working-capital requirement from holding-period assumptions (₹).
B4: Particulars | C4: Year 1 | D4: Year 2 | E4: Year 3 | F4: Year 4 | G4: Year 5
B5: OPERATING BASIS
B6: Cost of Production | C6: =Annual_Summary!C10+Annual_Summary!C11+Annual_Summary!C12+Annual_Summary!C13+Annual_Summary!C14+Annual_Summary!C15+Annual_Summary!C18 -> 25880000 | D6: =Annual_Summary!D10+Annual_Summary!D11+Annual_Summary!D12+Annual_Summary!D13+Annual_Summary!D14+Annual_Summary!D15+Annual_Summary!D18 -> 29022200 | E6: =Annual_Summary!E10+Annual_Summary!E11+Annual_Summary!E12+Annual_Summary!E13+Annual_Summary!E14+Annual_Summary!E15+Annual_Summary!E18 -> 32417936 | F6: =Annual_Summary!F10+Annual_Summary!F11+Annual_Summary!F12+Annual_Summary!F13+Annual_Summary!F14+Annual_Summary!F15+Annual_Summary!F18 -> 36084887 | G6: =Annual_Summary!G10+Annual_Summary!G11+Annual_Summary!G12+Annual_Summary!G13+Annual_Summary!G14+Annual_Summary!G15+Annual_Summary!G18 -> 40041880
B7: Purchases (raw material) | C7: =Annual_Summary!C10 -> 18000000 | D7: =Annual_Summary!D10 -> 20475000 | E7: =Annual_Summary!E10 -> 23152500 | F7: =Annual_Summary!F10 -> 26046563 | G7: =Annual_Summary!G10 -> 29172150
B8: Net Sales | C8: =Annual_Summary!C8 -> 36000000 | D8: =Annual_Summary!D8 -> 40560000 | E8: =Annual_Summary!E8 -> 45427200 | F8: =Annual_Summary!F8 -> 50618880 | G8: =Annual_Summary!G8 -> 56153211
B9: CURRENT ASSETS (₹)
B10: Inventory — Raw material | C10: =C7*Assumptions!$C$50/365 -> 739726.03 | D10: =D7*Assumptions!$C$50/365 -> 841438.36 | E10: =E7*Assumptions!$C$50/365 -> 951472.6 | F10: =F7*Assumptions!$C$50/365 -> 1070406.7 | G10: =G7*Assumptions!$C$50/365 -> 1198855.5
B11: Inventory — Finished goods | C11: =C6*Assumptions!$C$51/365 -> 709041.1 | D11: =D6*Assumptions!$C$51/365 -> 795128.77 | E11: =E6*Assumptions!$C$51/365 -> 888162.63 | F11: =F6*Assumptions!$C$51/365 -> 988627.04 | G11: =G6*Assumptions!$C$51/365 -> 1097037.8
B12: Sundry debtors / receivables | C12: =C8*Assumptions!$C$52/365 -> 2958904.1 | D12: =D8*Assumptions!$C$52/365 -> 3333698.6 | E12: =E8*Assumptions!$C$52/365 -> 3733742.5 | F12: =F8*Assumptions!$C$52/365 -> 4160455.9 | G12: =G8*Assumptions!$C$52/365 -> 4615332.4
B13: Cash & bank (minimum) | C13: =Assumptions!$C$54 -> 200000 | D13: =Assumptions!$C$54 -> 200000 | E13: =Assumptions!$C$54 -> 200000 | F13: =Assumptions!$C$54 -> 200000 | G13: =Assumptions!$C$54 -> 200000
B14: Total Current Assets | C14: =SUM(C10:C13) -> 4607671.2 | D14: =SUM(D10:D13) -> 5170265.8 | E14: =SUM(E10:E13) -> 5773377.7 | F14: =SUM(F10:F13) -> 6419489.6 | G14: =SUM(G10:G13) -> 7111225.7
B15: CURRENT LIABILITIES (other than bank finance) (₹)
B16: Sundry creditors / payables | C16: =C7*Assumptions!$C$53/365 -> 2219178.1 | D16: =D7*Assumptions!$C$53/365 -> 2524315.1 | E16: =E7*Assumptions!$C$53/365 -> 2854417.8 | F16: =F7*Assumptions!$C$53/365 -> 3211220 | G16: =G7*Assumptions!$C$53/365 -> 3596566.4
B17: Other current liabilities / provisions | C17: =0 -> 0 | D17: =0 -> 0 | E17: =0 -> 0 | F17: =0 -> 0 | G17: =0 -> 0
B18: Total Current Liabilities (excl. bank) | C18: =C16+C17 -> 2219178.1 | D18: =D16+D17 -> 2524315.1 | E18: =E16+E17 -> 2854417.8 | F18: =F16+F17 -> 3211220 | G18: =G16+G17 -> 3596566.4
B19: Working Capital Gap (TCA − TCL) | C19: =C14-C18 -> 2388493.2 | D19: =D14-D18 -> 2645950.7 | E19: =E14-E18 -> 2918959.9 | F19: =F14-F18 -> 3208269.6 | G19: =G14-G18 -> 3514659.2

Sheet Form_V_MPBF
A1: FORM V — MAXIMUM PERMISSIBLE BANK FINANCE
A2: MPBF computed on the Tandon methodology; Method II drives the working-capital limit (₹).
B4: Particulars | C4: Year 1 | D4: Year 2 | E4: Year 3 | F4: Year 4 | G4: Year 5
B5: Total Current Assets | C5: =Form_IV_CA_CL!C14 -> 4607671.2 | D5: =Form_IV_CA_CL!D14 -> 5170265.8 | E5: =Form_IV_CA_CL!E14 -> 5773377.7 | F5: =Form_IV_CA_CL!F14 -> 6419489.6 | G5: =Form_IV_CA_CL!G14 -> 7111225.7
B6: Current Liabilities (other than bank) | C6: =Form_IV_CA_CL!C18 -> 2219178.1 | D6: =Form_IV_CA_CL!D18 -> 2524315.1 | E6: =Form_IV_CA_CL!E18 -> 2854417.8 | F6: =Form_IV_CA_CL!F18 -> 3211220 | G6: =Form_IV_CA_CL!G18 -> 3596566.4
B7: Working Capital Gap (WCG) | C7: =Form_IV_CA_CL!C19 -> 2388493.2 | D7: =Form_IV_CA_CL!D19 -> 2645950.7 | E7: =Form_IV_CA_CL!E19 -> 2918959.9 | F7: =Form_IV_CA_CL!F19 -> 3208269.6 | G7: =Form_IV_CA_CL!G19 -> 3514659.2
B8: Min. stipulated NWC (margin × CA) | C8: =Assumptions!$C$55*Form_IV_CA_CL!C14 -> 1151917.8 | D8: =Assumptions!$C$55*Form_IV_CA_CL!D14 -> 1292566.4 | E8: =Assumptions!$C$55*Form_IV_CA_CL!E14 -> 1443344.4 | F8: =Assumptions!$C$55*Form_IV_CA_CL!F14 -> 1604872.4 | G8: =Assumptions!$C$55*Form_IV_CA_CL!G14 -> 1777806.4
B9: MPBF — Method I (WCG − margin) | C9: =MAX(0,Form_IV_CA_CL!C19*(1-Assumptions!$C$55)) -> 1791369.9 | D9: =MAX(0,Form_IV_CA_CL!D19*(1-Assumptions!$C$55)) -> 1984463 | E9: =MAX(0,Form_IV_CA_CL!E19*(1-Assumptions!$C$55)) -> 2189219.9 | F9: =MAX(0,Form_IV_CA_CL!F19*(1-Assumptions!$C$55)) -> 2406202.2 | G9: =MAX(0,Form_IV_CA_CL!G19*(1-Assumptions!$C$55)) -> 2635994.4
B10: MPBF — Method II (0.75·CA − CL) | C10: =MAX(0,Form_IV_CA_CL!C14*(1-Assumptions!$C$55)-Form_IV_CA_CL!C18) -> 1236575.3 | D10: =MAX(0,Form_IV_CA_CL!D14*(1-Assumptions!$C$55)-Form_IV_CA_CL!D18) -> 1353384.2 | E10: =MAX(0,Form_IV_CA_CL!E14*(1-Assumptions!$C$55)-Form_IV_CA_CL!E18) -> 1475615.5 | F10: =MAX(0,Form_IV_CA_CL!F14*(1-Assumptions!$C$55)-Form_IV_CA_CL!F18) -> 1603397.2 | G10: =MAX(0,Form_IV_CA_CL!G14*(1-Assumptions!$C$55)-Form_IV_CA_CL!G18) -> 1736852.8
B11: Recommended MPBF (Method II) | C11: =C10 -> 1236575.3 | D11: =D10 -> 1353384.2 | E11: =E10 -> 1475615.5 | F11: =F10 -> 1603397.2 | G11: =G10 -> 1736852.8

Sheet Form_VI_FundFlow
A1: FORM VI — FUND FLOW STATEMENT
A2: Year-on-year sources and applications of funds (₹).
B4: Particulars | C4: Year 1 | D4: Year 2 | E4: Year 3 | F4: Year 4 | G4: Year 5
B5: SOURCES OF FUNDS (₹)
B6: Cash accrual (PAT + Depreciation) | C6: =Annual_Summary!C27 -> 6936208.2 | D6: =Annual_Summary!D27 -> 7910586.6 | E6: =Annual_Summary!E27 -> 8919397 | F6: =Annual_Summary!F27 -> 9962040.6 | G6: =Annual_Summary!G27 -> 11037712
B7: Capital introduced | C7: =Assumptions!$C$9 -> 1500000 | D7: =0 -> 0 | E7: =0 -> 0 | F7: =0 -> 0 | G7: =0 -> 0
B8: Term loan raised | C8: =Assumptions!$C$8 -> 6000000 | D8: =0 -> 0 | E8: =0 -> 0 | F8: =0 -> 0 | G8: =0 -> 0
B9: Increase / (decrease) in bank WC finance | C9: =Form_V_MPBF!C11 -> 1236575.3 | D9: =(Form_V_MPBF!D11-Form_V_MPBF!C11) -> 116808.9 | E9: =(Form_V_MPBF!E11-Form_V_MPBF!D11) -> 122231.22 | F9: =(Form_V_MPBF!F11-Form_V_MPBF!E11) -> 127781.71 | G9: =(Form_V_MPBF!G11-Form_V_MPBF!F11) -> 133455.65
B10: Increase / (decrease) in creditors | C10: =Form_IV_CA_CL!C16 -> 2219178.1 | D10: =(Form_IV_CA_CL!D16-Form_IV_CA_CL!C16) -> 305136.99 | E10: =(Form_IV_CA_CL!E16-Form_IV_CA_CL!D16) -> 330102.74 | F10: =(Form_IV_CA_CL!F16-Form_IV_CA_CL!E16) -> 356802.23 | G10: =(Form_IV_CA_CL!G16-Form_IV_CA_CL!F16) -> 385346.4
B11: TOTAL SOURCES (A) | C11: =SUM(C6:C10) -> 17891962 | D11: =SUM(D6:D10) -> 8332532.5 | E11: =SUM(E6:E10) -> 9371730.9 | F11: =SUM(F6:F10) -> 10446625 | G11: =SUM(G6:G10) -> 11556514
B12: APPLICATION OF FUNDS (₹)
B13: Capital expenditure (fixed assets) | C13: =Form_III_BalanceSheet!C15 -> 6200000 | D13: =(Form_III_BalanceSheet!D15-Form_III_BalanceSheet!C15) -> 0 | E13: =(Form_III_BalanceSheet!E15-Form_III_BalanceSheet!D15) -> 0 | F13: =(Form_III_BalanceSheet!F15-Form_III_BalanceSheet!E15) -> 0 | G13: =(Form_III_BalanceSheet!G15-Form_III_BalanceSheet!F15) -> 0
B14: Repayment of term loan | C14: =Repayment!C7 -> 100840.34 | D14: =Repayment!D7 -> 100840.34 | E14: =Repayment!E7 -> 100840.34 | F14: =Repayment!F7 -> 100840.34 | G14: =Repayment!G7 -> 100840.34
B15: Increase / (decrease) in current assets | C15: =(Form_III_BalanceSheet!C18+Form_III_BalanceSheet!C19+Form_III_BalanceSheet!C20) -> 11591121 | D15: =((Form_III_BalanceSheet!D18+Form_III_BalanceSheet!D19+Form_III_BalanceSheet!D20)-(Form_III_BalanceSheet!C18+Form_III_BalanceSheet!C19+Form_III_BalanceSheet!C20)) -> 8231692.1 | E15: =((Form_III_BalanceSheet!E18+Form_III_BalanceSheet!E19+Form_III_BalanceSheet!E20)-(Form_III_BalanceSheet!D18+Form_III_BalanceSheet!D19+Form_III_BalanceSheet!D20)) -> 9270890.6 | F15: =((Form_III_BalanceSheet!F18+Form_III_BalanceSheet!F19+Form_III_BalanceSheet!F20)-(Form_III_BalanceSheet!E18+Form_III_BalanceSheet!E19+Form_III_BalanceSheet!E20)) -> 10345784 | G15: =((Form_III_BalanceSheet!G18+Form_III_BalanceSheet!G19+Form_III_BalanceSheet!G20)-(Form_III_BalanceSheet!F18+Form_III_BalanceSheet!F19+Form_III_BalanceSheet!F20)) -> 11455673
B16: TOTAL APPLICATIONS (B) | C16: =SUM(C13:C15) -> 17891962 | D16: =SUM(D13:D15) -> 8332532.5 | E16: =SUM(E13:E15) -> 9371730.9 | F16: =SUM(F13:F15) -> 10446625 | G16: =SUM(G13:G15) -> 11556514
B17: Net Surplus / (Deficit) (A − B) | C17: =C11-C16 -> 0 | D17: =D11-D16 -> 0 | E17: =E11-E16 -> 0 | F17: =F11-F16 -> 0 | G17: =G11-G16 -> 0

Sheet Repayment
A1: TERM LOAN — REPAYMENT SCHEDULE
A2: Equal annual principal after moratorium; interest on reducing balance (₹).
B4: Particulars | C4: Year 1 | D4: Year 2 | E4: Year 3 | F4: Year 4 | G4: Year 5
B5: Opening balance | C5: =Assumptions!$C$8 -> 6000000 | D5: =C8 -> 5899159.7 | E5: =D8 -> 5798319.3 | F5: =E8 -> 5697479 | G5: =F8 -> 5596638.7
B6: Interest for the year | C6: =C5*Assumptions!$C$10 -> 630000 | D6: =D5*Assumptions!$C$10 -> 619411.76 | E6: =E5*Assumptions!$C$10 -> 608823.53 | F6: =F5*Assumptions!$C$10 -> 598235.29 | G6: =G5*Assumptions!$C$10 -> 587647.06
B7: Principal repayment | C7: =IF(1<=Assumptions!$C$12/12,0,MIN(C5,IFERROR(Assumptions!$C$8/(Assumptions!$C$11-Assumptions!$C$12/12),0))) -> 100840.34 | D7: =IF(2<=Assumptions!$C$12/12,0,MIN(D5,IFERROR(Assumptions!$C$8/(Assumptions!$C$11-Assumptions!$C$12/12),0))) -> 100840.34 | E7: =IF(3<=Assumptions!$C$12/12,0,MIN(E5,IFERROR(Assumptions!$C$8/(Assumptions!$C$11-Assumptions!$C$12/12),0))) -> 100840.34 | F7: =IF(4<=Assumptions!$C$12/12,0,MIN(F5,IFERROR(Assumptions!$C$8/(Assumptions!$C$11-Assumptions!$C$12/12),0))) -> 100840.34 | G7: =IF(5<=Assumptions!$C$12/12,0,MIN(G5,IFERROR(Assumptions!$C$8/(Assumptions!$C$11-Assumptions!$C$12/12),0))) -> 100840.34
B8: Closing balance | C8: =C5-C7 -> 5899159.7 | D8: =D5-D7 -> 5798319.3 | E8: =E5-E7 -> 5697479 | F8: =F5-F7 -> 5596638.7 | G8: =G5-G7 -> 5495798.3
B10: Note: schedule shows the first 5 years of the projection horizon; any balance beyond Year 5 continues per the sanctioned tenure.

Sheet DSCR
A1: DEBT SERVICE COVERAGE (DSCR)
A2: Repayment capacity: cash available for debt service ÷ debt obligation.
B4: Particulars | C4: Year 1 | D4: Year 2 | E4: Year 3 | F4: Year 4 | G4: Year 5 | H4: Average
B5: Cash available for debt service (₹)
B6: Profit After Tax | C6: =Annual_Summary!C26 -> 6016208.2 | D6: =Annual_Summary!D26 -> 6990586.6 | E6: =Annual_Summary!E26 -> 7999397 | F6: =Annual_Summary!F26 -> 9042040.6 | G6: =Annual_Summary!G26 -> 10117712
B7: (+) Depreciation | C7: =Annual_Summary!C18 -> 920000 | D7: =Annual_Summary!D18 -> 920000 | E7: =Annual_Summary!E18 -> 920000 | F7: =Annual_Summary!F18 -> 920000 | G7: =Annual_Summary!G18 -> 920000
B8: (+) Interest on Term Loan | C8: =Repayment!C6 -> 630000 | D8: =Repayment!D6 -> 619411.76 | E8: =Repayment!E6 -> 608823.53 | F8: =Repayment!F6 -> 598235.29 | G8: =Repayment!G6 -> 587647.06
B9: Cash Available for Debt Service (A) | C9: =C6+C7+C8 -> 7566208.2 | D9: =D6+D7+D8 -> 8529998.4 | E9: =E6+E7+E8 -> 9528220.5 | F9: =F6+F7+F8 -> 10560276 | G9: =G6+G7+G8 -> 11625359
B10: Debt obligation (₹)
B11: Principal repayment | C11: =Repayment!C7 -> 100840.34 | D11: =Repayment!D7 -> 100840.34 | E11: =Repayment!E7 -> 100840.34 | F11: =Repayment!F7 -> 100840.34 | G11: =Repayment!G7 -> 100840.34
B12: Interest on Term Loan | C12: =Repayment!C6 -> 630000 | D12: =Repayment!D6 -> 619411.76 | E12: =Repayment!E6 -> 608823.53 | F12: =Repayment!F6 -> 598235.29 | G12: =Repayment!G6 -> 587647.06
B13: Total Debt Obligation (B) | C13: =C11+C12 -> 730840.34 | D13: =D11+D12 -> 720252.1 | E13: =E11+E12 -> 709663.87 | F13: =F11+F12 -> 699075.63 | G13: =G11+G12 -> 688487.39
B14: DSCR (A ÷ B) | C14: =IFERROR(C9/C13,0) -> 10.352751 | D14: =IFERROR(D9/D13,0) -> 11.843073 | E14: =IFERROR(E9/E13,0) -> 13.426385 | F14: =IFERROR(F9/F13,0) -> 15.106056 | G14: =IFERROR(G9/G13,0) -> 16.885362 | H14: =IFERROR(AVERAGE(C14:G14),0) -> 13.522726

Sheet Sheet1

Sheet Ratios
A1: FINANCIAL VIABILITY — KEY RATIOS
A2: Liquidity, leverage, profitability and coverage indicators for appraisal.
B4: Particulars | C4: Year 1 | D4: Year 2 | E4: Year 3 | F4: Year 4 | G4: Year 5
B5: LIQUIDITY & LEVERAGE
B6: Current Ratio | C6: =IFERROR((Form_III_BalanceSheet!C18+Form_III_BalanceSheet!C19+Form_III_BalanceSheet!C20)/(Form_III_BalanceSheet!C11+Form_III_BalanceSheet!C12+Form_III_BalanceSheet!C10),0) -> 3.3541517 | D6: =IFERROR((Form_III_BalanceSheet!D18+Form_III_BalanceSheet!D19+Form_III_BalanceSheet!D20)/(Form_III_BalanceSheet!D11+Form_III_BalanceSheet!D12+Form_III_BalanceSheet!D10),0) -> 5.1120038 | E6: =IFERROR((Form_III_BalanceSheet!E18+Form_III_BalanceSheet!E19+Form_III_BalanceSheet!E20)/(Form_III_BalanceSheet!E11+Form_III_BalanceSheet!E12+Form_III_BalanceSheet!E10),0) -> 6.7190486 | F6: =IFERROR((Form_III_BalanceSheet!F18+Form_III_BalanceSheet!F19+Form_III_BalanceSheet!F20)/(Form_III_BalanceSheet!F11+Form_III_BalanceSheet!F12+Form_III_BalanceSheet!F10),0) -> 8.1916145 | G6: =IFERROR((Form_III_BalanceSheet!G18+Form_III_BalanceSheet!G19+Form_III_BalanceSheet!G20)/(Form_III_BalanceSheet!G11+Form_III_BalanceSheet!G12+Form_III_BalanceSheet!G10),0) -> 9.542689
B7: Debt–Equity Ratio | C7: =IFERROR((Form_III_BalanceSheet!C9+Form_III_BalanceSheet!C10)/Form_III_BalanceSheet!C8,0) -> 0.94937963 | D7: =IFERROR((Form_III_BalanceSheet!D9+Form_III_BalanceSheet!D10)/Form_III_BalanceSheet!D8,0) -> 0.49298992 | E7: =IFERROR((Form_III_BalanceSheet!E9+Form_III_BalanceSheet!E10)/Form_III_BalanceSheet!E8,0) -> 0.31871649 | F7: =IFERROR((Form_III_BalanceSheet!F9+Form_III_BalanceSheet!F10)/Form_III_BalanceSheet!F8,0) -> 0.22822311 | G7: =IFERROR((Form_III_BalanceSheet!G9+Form_III_BalanceSheet!G10)/Form_III_BalanceSheet!G8,0) -> 0.17358664
B8: TOL / TNW | C8: =IFERROR((Form_III_BalanceSheet!C9+Form_III_BalanceSheet!C10+Form_III_BalanceSheet!C11+Form_III_BalanceSheet!C12)/Form_III_BalanceSheet!C8,0) -> 1.244632 | D8: =IFERROR((Form_III_BalanceSheet!D9+Form_III_BalanceSheet!D10+Form_III_BalanceSheet!D11+Form_III_BalanceSheet!D12)/Form_III_BalanceSheet!D8,0) -> 0.66699907 | E8: =IFERROR((Form_III_BalanceSheet!E9+Form_III_BalanceSheet!E10+Form_III_BalanceSheet!E11+Form_III_BalanceSheet!E12)/Form_III_BalanceSheet!E8,0) -> 0.4455446 | F8: =IFERROR((Form_III_BalanceSheet!F9+Form_III_BalanceSheet!F10+Form_III_BalanceSheet!F11+Form_III_BalanceSheet!F12)/Form_III_BalanceSheet!F8,0) -> 0.33001075 | G8: =IFERROR((Form_III_BalanceSheet!G9+Form_III_BalanceSheet!G10+Form_III_BalanceSheet!G11+Form_III_BalanceSheet!G12)/Form_III_BalanceSheet!G8,0) -> 0.25990573
B9: PROFITABILITY
B10: EBITDA Margin | C10: =IFERROR(Annual_Summary!C22/Annual_Summary!C8,0) -> 0.27 | D10: =IFERROR(Annual_Summary!D22/Annual_Summary!D8,0) -> 0.27176036 | E10: =IFERROR(Annual_Summary!E22/Annual_Summary!E8,0) -> 0.27234256 | F10: =IFERROR(Annual_Summary!F22/Annual_Summary!F8,0) -> 0.27196763 | G10: =IFERROR(Annual_Summary!G22/Annual_Summary!G8,0) -> 0.27080111
B11: Net Profit Margin | C11: =IFERROR(Annual_Summary!C26/Annual_Summary!C8,0) -> 0.16711689 | D11: =IFERROR(Annual_Summary!D26/Annual_Summary!D8,0) -> 0.17235174 | E11: =IFERROR(Annual_Summary!E26/Annual_Summary!E8,0) -> 0.17609267 | F11: =IFERROR(Annual_Summary!F26/Annual_Summary!F8,0) -> 0.1786298 | G11: =IFERROR(Annual_Summary!G26/Annual_Summary!G8,0) -> 0.18018047
B12: Return on Capital Employed | C12: =IFERROR(Annual_Summary!C23/(Form_III_BalanceSheet!C8+Form_III_BalanceSheet!C9),0) -> 0.65596412 | D12: =IFERROR(Annual_Summary!D23/(Form_III_BalanceSheet!D8+Form_III_BalanceSheet!D9),0) -> 0.49753968 | E12: =IFERROR(Annual_Summary!E23/(Form_III_BalanceSheet!E8+Form_III_BalanceSheet!E9),0) -> 0.40603793 | F12: =IFERROR(Annual_Summary!F23/(Form_III_BalanceSheet!F8+Form_III_BalanceSheet!F9),0) -> 0.34585386 | G12: =IFERROR(Annual_Summary!G23/(Form_III_BalanceSheet!G8+Form_III_BalanceSheet!G9),0) -> 0.30292247
B13: COVERAGE & RISK
B14: Interest Coverage | C14: =IFERROR(Annual_Summary!C23/(Annual_Summary!C19+Annual_Summary!C20),0) -> 11.305401 | D14: =IFERROR(Annual_Summary!D23/(Annual_Summary!D19+Annual_Summary!D20),0) -> 12.921935 | E14: =IFERROR(Annual_Summary!E23/(Annual_Summary!E19+Annual_Summary!E20),0) -> 14.571572 | F14: =IFERROR(Annual_Summary!F23/(Annual_Summary!F19+Annual_Summary!F20),0) -> 16.248418 | G14: =IFERROR(Annual_Summary!G23/(Annual_Summary!G19+Annual_Summary!G20),0) -> 17.946113
B15: DSCR | C15: =DSCR!C14 -> 10.352751 | D15: =DSCR!D14 -> 11.843073 | E15: =DSCR!E14 -> 13.426385 | F15: =DSCR!F14 -> 15.106056 | G15: =DSCR!G14 -> 16.885362
B16: Break-even (% of sales) | C16: =IFERROR((Annual_Summary!C12+Annual_Summary!C14+Annual_Summary!C15+Annual_Summary!C16+Annual_Summary!C18+Annual_Summary!C19+Annual_Summary!C20)/(Annual_Summary!C8-(Annual_Summary!C10+Annual_Summary!C11+Annual_Summary!C13+Annual_Summary!C17)),0) -> 0.41362493 | D16: =IFERROR((Annual_Summary!D12+Annual_Summary!D14+Annual_Summary!D15+Annual_Summary!D16+Annual_Summary!D18+Annual_Summary!D19+Annual_Summary!D20)/(Annual_Summary!D8-(Annual_Summary!D10+Annual_Summary!D11+Annual_Summary!D13+Annual_Summary!D17)),0) -> 0.38561847 | E16: =IFERROR((Annual_Summary!E12+Annual_Summary!E14+Annual_Summary!E15+Annual_Summary!E16+Annual_Summary!E18+Annual_Summary!E19+Annual_Summary!E20)/(Annual_Summary!E8-(Annual_Summary!E10+Annual_Summary!E11+Annual_Summary!E13+Annual_Summary!E17)),0) -> 0.36199782 | F16: =IFERROR((Annual_Summary!F12+Annual_Summary!F14+Annual_Summary!F15+Annual_Summary!F16+Annual_Summary!F18+Annual_Summary!F19+Annual_Summary!F20)/(Annual_Summary!F8-(Annual_Summary!F10+Annual_Summary!F11+Annual_Summary!F13+Annual_Summary!F17)),0) -> 0.34189838 | G16: =IFERROR((Annual_Summary!G12+Annual_Summary!G14+Annual_Summary!G15+Annual_Summary!G16+Annual_Summary!G18+Annual_Summary!G19+Annual_Summary!G20)/(Annual_Summary!G8-(Annual_Summary!G10+Annual_Summary!G11+Annual_Summary!G13+Annual_Summary!G17)),0) -> 0.32467329
