Workbook

Sheet Cover
B2: FINANCIAL FEASIBILITY STUDY
B3: 5-Year Monthly Financial Model & Projections
B5: =IF(Assumptions!$D$6="","[ Company / Project Name ]",Assumptions!$D$6) -> [ Company / Project Name ]
B6: =IF(Assumptions!$D$7="","[ Plant Location ]",Assumptions!$D$7) -> [ Plant Location ]
B7: =IF(Assumptions!$D$8="","[ Product / Description ]",Assumptions!$D$8) -> [ Product / Description ]
B9: PREPARED FOR ANGEL INVESTORS
B11: PROJECT SNAPSHOT
B12: Total Project Cost | D12: ='Investment & ROI'!D12 -> 0
B13: Angel Investment Sought | D13: =Assumptions!$D$59 -> 0
B14: Equity Stake Offered | D14: =Assumptions!$D$62 -> 0
B15: 5-Year Revenue | D15: ='Annual Summary'!H9 -> 0
B16: 5-Year PAT | D16: ='Annual Summary'!H21 -> 0
B17: Return on Investment | D17: ='Investment & ROI'!D26 -> 0
B18: Project IRR | D18: ='Investment & ROI'!D31 -> 0
B19: Investor MOIC | D19: ='Investment & ROI'!D44 -> 0
B21: CONTENTS
B22: 1. Assumptions | C22: Single control panel — fill the yellow cells
B23: 2. Production | C23: Monthly output from capacity & utilisation
B24: 3. Sales | C24: Units sold and net revenue
B25: 4. Expenses | C25: COGS, SG&A, depreciation, interest, loan schedule
B26: 5. P&L | C26: Monthly profit & loss
B27: 6. Cash Flow | C27: Operating, investing & financing cash flows
B28: 7. Annual Summary | C28: Yearly roll-up of all results
B29: 8. Investment & ROI | C29: Project cost, funding, returns, investor case
B30: 9. Dashboard | C30: KPI snapshot, charts & scalability
B32: Note: This is a blank template. All cells are pre-linked with formulas; enter your figures on the Assumptions tab and every sheet, chart and metric updates automatically. Prepared as a feasibility study for discussion with prospective angel investors; not an offer of securities.

Sheet Assumptions
A1: ASSUMPTIONS — CONTROL PANEL
A2: Fill the yellow cells only. Every other sheet updates automatically. All figures in Indian Rupees (₹).
B4: Parameter | C4: Unit | D4: Year 1 | E4: Year 2 | F4: Year 3 | G4: Year 4 | H4: Year 5 | I4: Notes / Guidance
A5: 1. PROJECT OVERVIEW
B6: Company / Project Name | C6: text
B7: Plant Location | C7: text
B8: Primary Product / Description | C8: text
B9: Projection Start Date | C9: date
A10: 2. PRODUCTION & CAPACITY (scalability drivers)
B11: Installed Capacity | C11: units/month
B12: Capacity Utilisation | C12: %
B13: Rejection / Scrap Rate | C13: %
A14: 3. SALES & PRICING
B15: Sell-through Rate | C15: % of output
B16: Average Selling Price / unit | C16: ₹/unit
B17: Sales Discount / Returns | C17: % of sales
A18: 4. DIRECT (VARIABLE) COSTS — per unit produced
B19: Raw Material Cost / unit | C19: ₹/unit
B20: Packaging & Consumables / unit | C20: ₹/unit
B21: Power & Fuel / unit | C21: ₹/unit
B22: Other Variable Cost / unit | C22: ₹/unit
A23: 5. MANUFACTURING LABOUR & OVERHEAD (₹ / month)
B24: Direct Labour Cost | C24: ₹/month
B25: Factory Rent / Lease | C25: ₹/month
B26: Repairs & Maintenance | C26: ₹/month
B27: Factory Utilities & Misc Overhead | C27: ₹/month
B28: Quality, Testing & Other Mfg OH | C28: ₹/month
A29: 6. OPERATING EXPENSES (SG&A)
B30: Admin & Management Salaries | C30: ₹/month
B31: Marketing & Selling | C31: % of revenue
B32: Distribution & Freight-out | C32: % of revenue
B33: Office Rent & Admin Overhead | C33: ₹/month
B34: Insurance | C34: ₹/month
B35: Other Operating Expenses | C35: ₹/month
B36: Annual Cost Inflation | C36: % p.a.
A37: 7. WORKING CAPITAL
B38: Receivable Days (Debtors) | C38: days
B39: Inventory Days | C39: days
B40: Payable Days (Creditors) | C40: days
A41: 8. FINANCING & TAX
B42: Term Loan Interest Rate | C42: % p.a.
B43: Loan Tenure | C43: years
B44: Corporate Income Tax Rate | C44: %
A45: 9. CAPITAL EXPENDITURE & DEPRECIATION
B46: Land & Building | C46: ₹
B47: Plant & Machinery | C47: ₹
B48: Furniture & Fixtures | C48: ₹
B49: Vehicles | C49: ₹
B50: Preliminary & Pre-operative Expenses | C50: ₹
B51: Contingency | C51: % of assets
B52: Depreciation Rate – Building | C52: % p.a.
B53: Depreciation Rate – Plant & Machinery | C53: % p.a.
B54: Depreciation Rate – Furniture | C54: % p.a.
B55: Depreciation Rate – Vehicles | C55: % p.a.
B56: Preliminary Exp. Amortisation | C56: years
A57: 10. FUNDING STRUCTURE
B58: Promoter's / Founder Equity | C58: ₹
B59: Angel Investor Investment | C59: ₹
B60: Term Loan / Debt | C60: ₹
A61: 11. INVESTOR & VALUATION
B62: Equity Stake Offered to Angels | C62: %
B63: Discount Rate for NPV | C63: % p.a.
B64: Planned Exit Year | C64: 1–5
B65: Exit Valuation Multiple (EV/EBITDA) | C65: x

Sheet Production
A1: PRODUCTION PLAN
A2: Monthly output driven by installed capacity, utilisation and scrap on the Assumptions tab.
B4: YEAR 1 | N4: YEAR 2 | Z4: YEAR 3 | AL4: YEAR 4 | AX4: YEAR 5
A5: Line item / Month | B5: M1 | C5: M2 | D5: M3 | E5: M4 | F5: M5 | G5: M6 | H5: M7 | I5: M8 | J5: M9 | K5: M10 | L5: M11 | M5: M12 | N5: M13 | O5: M14 | P5: M15 | Q5: M16 | R5: M17 | S5: M18 | T5: M19 | U5: M20 | V5: M21 | W5: M22 | X5: M23 | Y5: M24 | Z5: M25 | AA5: M26 | AB5: M27 | AC5: M28 | AD5: M29 | AE5: M30 | AF5: M31 | AG5: M32 | AH5: M33 | AI5: M34 | AJ5: M35 | AK5: M36 | AL5: M37 | AM5: M38 | AN5: M39 | AO5: M40 | AP5: M41 | AQ5: M42 | AR5: M43 | AS5: M44 | AT5: M45 | AU5: M46 | AV5: M47 | AW5: M48 | AX5: M49 | AY5: M50 | AZ5: M51 | BA5: M52 | BB5: M53 | BC5: M54 | BD5: M55 | BE5: M56 | BF5: M57 | BG5: M58 | BH5: M59 | BI5: M60
A6: Calendar month | B6: =IFERROR(EDATE(Assumptions!$D$9,0),"") -> 0 | C6: =IFERROR(EDATE(Assumptions!$D$9,1),"") -> 31 | D6: =IFERROR(EDATE(Assumptions!$D$9,2),"") -> 60 | E6: =IFERROR(EDATE(Assumptions!$D$9,3),"") -> 91 | F6: =IFERROR(EDATE(Assumptions!$D$9,4),"") -> 121 | G6: =IFERROR(EDATE(Assumptions!$D$9,5),"") -> 152 | H6: =IFERROR(EDATE(Assumptions!$D$9,6),"") -> 182 | I6: =IFERROR(EDATE(Assumptions!$D$9,7),"") -> 213 | J6: =IFERROR(EDATE(Assumptions!$D$9,8),"") -> 244 | K6: =IFERROR(EDATE(Assumptions!$D$9,9),"") -> 274 | L6: =IFERROR(EDATE(Assumptions!$D$9,10),"") -> 305 | M6: =IFERROR(EDATE(Assumptions!$D$9,11),"") -> 335 | N6: =IFERROR(EDATE(Assumptions!$D$9,12),"") -> 366 | O6: =IFERROR(EDATE(Assumptions!$D$9,13),"") -> 397 | P6: =IFERROR(EDATE(Assumptions!$D$9,14),"") -> 425 | Q6: =IFERROR(EDATE(Assumptions!$D$9,15),"") -> 456 | R6: =IFERROR(EDATE(Assumptions!$D$9,16),"") -> 486 | S6: =IFERROR(EDATE(Assumptions!$D$9,17),"") -> 517 | T6: =IFERROR(EDATE(Assumptions!$D$9,18),"") -> 547 | U6: =IFERROR(EDATE(Assumptions!$D$9,19),"") -> 578 | V6: =IFERROR(EDATE(Assumptions!$D$9,20),"") -> 609 | W6: =IFERROR(EDATE(Assumptions!$D$9,21),"") -> 639 | X6: =IFERROR(EDATE(Assumptions!$D$9,22),"") -> 670 | Y6: =IFERROR(EDATE(Assumptions!$D$9,23),"") -> 700 | Z6: =IFERROR(EDATE(Assumptions!$D$9,24),"") -> 731 | AA6: =IFERROR(EDATE(Assumptions!$D$9,25),"") -> 762 | AB6: =IFERROR(EDATE(Assumptions!$D$9,26),"") -> 790 | AC6: =IFERROR(EDATE(Assumptions!$D$9,27),"") -> 821 | AD6: =IFERROR(EDATE(Assumptions!$D$9,28),"") -> 851 | AE6: =IFERROR(EDATE(Assumptions!$D$9,29),"") -> 882 | AF6: =IFERROR(EDATE(Assumptions!$D$9,30),"") -> 912 | AG6: =IFERROR(EDATE(Assumptions!$D$9,31),"") -> 943 | AH6: =IFERROR(EDATE(Assumptions!$D$9,32),"") -> 974 | AI6: =IFERROR(EDATE(Assumptions!$D$9,33),"") -> 1004 | AJ6: =IFERROR(EDATE(Assumptions!$D$9,34),"") -> 1035 | AK6: =IFERROR(EDATE(Assumptions!$D$9,35),"") -> 1065 | AL6: =IFERROR(EDATE(Assumptions!$D$9,36),"") -> 1096 | AM6: =IFERROR(EDATE(Assumptions!$D$9,37),"") -> 1127 | AN6: =IFERROR(EDATE(Assumptions!$D$9,38),"") -> 1155 | AO6: =IFERROR(EDATE(Assumptions!$D$9,39),"") -> 1186 | AP6: =IFERROR(EDATE(Assumptions!$D$9,40),"") -> 1216 | AQ6: =IFERROR(EDATE(Assumptions!$D$9,41),"") -> 1247 | AR6: =IFERROR(EDATE(Assumptions!$D$9,42),"") -> 1277 | AS6: =IFERROR(EDATE(Assumptions!$D$9,43),"") -> 1308 | AT6: =IFERROR(EDATE(Assumptions!$D$9,44),"") -> 1339 | AU6: =IFERROR(EDATE(Assumptions!$D$9,45),"") -> 1369 | AV6: =IFERROR(EDATE(Assumptions!$D$9,46),"") -> 1400 | AW6: =IFERROR(EDATE(Assumptions!$D$9,47),"") -> 1430 | AX6: =IFERROR(EDATE(Assumptions!$D$9,48),"") -> 1461 | AY6: =IFERROR(EDATE(Assumptions!$D$9,49),"") -> 1492 | AZ6: =IFERROR(EDATE(Assumptions!$D$9,50),"") -> 1521 | BA6: =IFERROR(EDATE(Assumptions!$D$9,51),"") -> 1552 | BB6: =IFERROR(EDATE(Assumptions!$D$9,52),"") -> 1582 | BC6: =IFERROR(EDATE(Assumptions!$D$9,53),"") -> 1613 | BD6: =IFERROR(EDATE(Assumptions!$D$9,54),"") -> 1643 | BE6: =IFERROR(EDATE(Assumptions!$D$9,55),"") -> 1674 | BF6: =IFERROR(EDATE(Assumptions!$D$9,56),"") -> 1705 | BG6: =IFERROR(EDATE(Assumptions!$D$9,57),"") -> 1735 | BH6: =IFERROR(EDATE(Assumptions!$D$9,58),"") -> 1766 | BI6: =IFERROR(EDATE(Assumptions!$D$9,59),"") -> 1796
A7: PRODUCTION VOLUME
A8: Installed Capacity (units) | B8: =Assumptions!$D$11 -> 0 | C8: =Assumptions!$D$11 -> 0 | D8: =Assumptions!$D$11 -> 0 | E8: =Assumptions!$D$11 -> 0 | F8: =Assumptions!$D$11 -> 0 | G8: =Assumptions!$D$11 -> 0 | H8: =Assumptions!$D$11 -> 0 | I8: =Assumptions!$D$11 -> 0 | ... M8: =Assumptions!$D$11 -> 0 | N8: =Assumptions!$E$11 -> 0 | O8: =Assumptions!$E$11 -> 0 | P8: =Assumptions!$E$11 -> 0 | Q8: =Assumptions!$E$11 -> 0 | R8: =Assumptions!$E$11 -> 0 | S8: =Assumptions!$E$11 -> 0 | T8: =Assumptions!$E$11 -> 0 | U8: =Assumptions!$E$11 -> 0 | ... Y8: =Assumptions!$E$11 -> 0 | Z8: =Assumptions!$F$11 -> 0 | AA8: =Assumptions!$F$11 -> 0 | AB8: =Assumptions!$F$11 -> 0 | AC8: =Assumptions!$F$11 -> 0 | AD8: =Assumptions!$F$11 -> 0 | AE8: =Assumptions!$F$11 -> 0 | AF8: =Assumptions!$F$11 -> 0 | AG8: =Assumptions!$F$11 -> 0 | ... AK8: =Assumptions!$F$11 -> 0 | AL8: =Assumptions!$G$11 -> 0 | AM8: =Assumptions!$G$11 -> 0 | AN8: =Assumptions!$G$11 -> 0 | AO8: =Assumptions!$G$11 -> 0 | AP8: =Assumptions!$G$11 -> 0 | AQ8: =Assumptions!$G$11 -> 0 | AR8: =Assumptions!$G$11 -> 0 | AS8: =Assumptions!$G$11 -> 0 | ... AW8: =Assumptions!$G$11 -> 0 | AX8: =Assumptions!$H$11 -> 0 | AY8: =Assumptions!$H$11 -> 0 | AZ8: =Assumptions!$H$11 -> 0 | BA8: =Assumptions!$H$11 -> 0 | BB8: =Assumptions!$H$11 -> 0 | BC8: =Assumptions!$H$11 -> 0 | BD8: =Assumptions!$H$11 -> 0 | BE8: =Assumptions!$H$11 -> 0 | ... BI8: =Assumptions!$H$11 -> 0
A9: Capacity Utilisation (%) | B9: =Assumptions!$D$12 -> 0 | C9: =Assumptions!$D$12 -> 0 | D9: =Assumptions!$D$12 -> 0 | E9: =Assumptions!$D$12 -> 0 | F9: =Assumptions!$D$12 -> 0 | G9: =Assumptions!$D$12 -> 0 | H9: =Assumptions!$D$12 -> 0 | I9: =Assumptions!$D$12 -> 0 | ... M9: =Assumptions!$D$12 -> 0 | N9: =Assumptions!$E$12 -> 0 | O9: =Assumptions!$E$12 -> 0 | P9: =Assumptions!$E$12 -> 0 | Q9: =Assumptions!$E$12 -> 0 | R9: =Assumptions!$E$12 -> 0 | S9: =Assumptions!$E$12 -> 0 | T9: =Assumptions!$E$12 -> 0 | U9: =Assumptions!$E$12 -> 0 | ... Y9: =Assumptions!$E$12 -> 0 | Z9: =Assumptions!$F$12 -> 0 | AA9: =Assumptions!$F$12 -> 0 | AB9: =Assumptions!$F$12 -> 0 | AC9: =Assumptions!$F$12 -> 0 | AD9: =Assumptions!$F$12 -> 0 | AE9: =Assumptions!$F$12 -> 0 | AF9: =Assumptions!$F$12 -> 0 | AG9: =Assumptions!$F$12 -> 0 | ... AK9: =Assumptions!$F$12 -> 0 | AL9: =Assumptions!$G$12 -> 0 | AM9: =Assumptions!$G$12 -> 0 | AN9: =Assumptions!$G$12 -> 0 | AO9: =Assumptions!$G$12 -> 0 | AP9: =Assumptions!$G$12 -> 0 | AQ9: =Assumptions!$G$12 -> 0 | AR9: =Assumptions!$G$12 -> 0 | AS9: =Assumptions!$G$12 -> 0 | ... AW9: =Assumptions!$G$12 -> 0 | AX9: =Assumptions!$H$12 -> 0 | AY9: =Assumptions!$H$12 -> 0 | AZ9: =Assumptions!$H$12 -> 0 | BA9: =Assumptions!$H$12 -> 0 | BB9: =Assumptions!$H$12 -> 0 | BC9: =Assumptions!$H$12 -> 0 | BD9: =Assumptions!$H$12 -> 0 | BE9: =Assumptions!$H$12 -> 0 | ... BI9: =Assumptions!$H$12 -> 0
A10: Gross Production (units) | B10: =B8*B9 -> 0 | C10: =C8*C9 -> 0 | D10: =D8*D9 -> 0 | E10: =E8*E9 -> 0 | F10: =F8*F9 -> 0 | G10: =G8*G9 -> 0 | H10: =H8*H9 -> 0 | I10: =I8*I9 -> 0 | ... BI10: =BI8*BI9 -> 0
A11: Rejection / Scrap (%) | B11: =Assumptions!$D$13 -> 0 | C11: =Assumptions!$D$13 -> 0 | D11: =Assumptions!$D$13 -> 0 | E11: =Assumptions!$D$13 -> 0 | F11: =Assumptions!$D$13 -> 0 | G11: =Assumptions!$D$13 -> 0 | H11: =Assumptions!$D$13 -> 0 | I11: =Assumptions!$D$13 -> 0 | ... BI11: =Assumptions!$D$13 -> 0
A12: Saleable Production (units) | B12: =B10*(1-B11) -> 0 | C12: =C10*(1-C11) -> 0 | D12: =D10*(1-D11) -> 0 | E12: =E10*(1-E11) -> 0 | F12: =F10*(1-F11) -> 0 | G12: =G10*(1-G11) -> 0 | H12: =H10*(1-H11) -> 0 | I12: =I10*(1-I11) -> 0 | ... BI12: =BI10*(1-BI11) -> 0

Sheet Sales
A1: SALES & REVENUE
A2: Units sold and net revenue, linked from Production and priced on the Assumptions tab.
B4: YEAR 1 | N4: YEAR 2 | Z4: YEAR 3 | AL4: YEAR 4 | AX4: YEAR 5
A5: Line item / Month | B5: M1 | C5: M2 | D5: M3 | E5: M4 | F5: M5 | G5: M6 | H5: M7 | I5: M8 | J5: M9 | K5: M10 | L5: M11 | M5: M12 | N5: M13 | O5: M14 | P5: M15 | Q5: M16 | R5: M17 | S5: M18 | T5: M19 | U5: M20 | V5: M21 | W5: M22 | X5: M23 | Y5: M24 | Z5: M25 | AA5: M26 | AB5: M27 | AC5: M28 | AD5: M29 | AE5: M30 | AF5: M31 | AG5: M32 | AH5: M33 | AI5: M34 | AJ5: M35 | AK5: M36 | AL5: M37 | AM5: M38 | AN5: M39 | AO5: M40 | AP5: M41 | AQ5: M42 | AR5: M43 | AS5: M44 | AT5: M45 | AU5: M46 | AV5: M47 | AW5: M48 | AX5: M49 | AY5: M50 | AZ5: M51 | BA5: M52 | BB5: M53 | BC5: M54 | BD5: M55 | BE5: M56 | BF5: M57 | BG5: M58 | BH5: M59 | BI5: M60
A6: Calendar month | B6: =IFERROR(EDATE(Assumptions!$D$9,0),"") -> 0 | C6: =IFERROR(EDATE(Assumptions!$D$9,1),"") -> 31 | D6: =IFERROR(EDATE(Assumptions!$D$9,2),"") -> 60 | E6: =IFERROR(EDATE(Assumptions!$D$9,3),"") -> 91 | F6: =IFERROR(EDATE(Assumptions!$D$9,4),"") -> 121 | G6: =IFERROR(EDATE(Assumptions!$D$9,5),"") -> 152 | H6: =IFERROR(EDATE(Assumptions!$D$9,6),"") -> 182 | I6: =IFERROR(EDATE(Assumptions!$D$9,7),"") -> 213 | J6: =IFERROR(EDATE(Assumptions!$D$9,8),"") -> 244 | K6: =IFERROR(EDATE(Assumptions!$D$9,9),"") -> 274 | L6: =IFERROR(EDATE(Assumptions!$D$9,10),"") -> 305 | M6: =IFERROR(EDATE(Assumptions!$D$9,11),"") -> 335 | N6: =IFERROR(EDATE(Assumptions!$D$9,12),"") -> 366 | O6: =IFERROR(EDATE(Assumptions!$D$9,13),"") -> 397 | P6: =IFERROR(EDATE(Assumptions!$D$9,14),"") -> 425 | Q6: =IFERROR(EDATE(Assumptions!$D$9,15),"") -> 456 | R6: =IFERROR(EDATE(Assumptions!$D$9,16),"") -> 486 | S6: =IFERROR(EDATE(Assumptions!$D$9,17),"") -> 517 | T6: =IFERROR(EDATE(Assumptions!$D$9,18),"") -> 547 | U6: =IFERROR(EDATE(Assumptions!$D$9,19),"") -> 578 | V6: =IFERROR(EDATE(Assumptions!$D$9,20),"") -> 609 | W6: =IFERROR(EDATE(Assumptions!$D$9,21),"") -> 639 | X6: =IFERROR(EDATE(Assumptions!$D$9,22),"") -> 670 | Y6: =IFERROR(EDATE(Assumptions!$D$9,23),"") -> 700 | Z6: =IFERROR(EDATE(Assumptions!$D$9,24),"") -> 731 | AA6: =IFERROR(EDATE(Assumptions!$D$9,25),"") -> 762 | AB6: =IFERROR(EDATE(Assumptions!$D$9,26),"") -> 790 | AC6: =IFERROR(EDATE(Assumptions!$D$9,27),"") -> 821 | AD6: =IFERROR(EDATE(Assumptions!$D$9,28),"") -> 851 | AE6: =IFERROR(EDATE(Assumptions!$D$9,29),"") -> 882 | AF6: =IFERROR(EDATE(Assumptions!$D$9,30),"") -> 912 | AG6: =IFERROR(EDATE(Assumptions!$D$9,31),"") -> 943 | AH6: =IFERROR(EDATE(Assumptions!$D$9,32),"") -> 974 | AI6: =IFERROR(EDATE(Assumptions!$D$9,33),"") -> 1004 | AJ6: =IFERROR(EDATE(Assumptions!$D$9,34),"") -> 1035 | AK6: =IFERROR(EDATE(Assumptions!$D$9,35),"") -> 1065 | AL6: =IFERROR(EDATE(Assumptions!$D$9,36),"") -> 1096 | AM6: =IFERROR(EDATE(Assumptions!$D$9,37),"") -> 1127 | AN6: =IFERROR(EDATE(Assumptions!$D$9,38),"") -> 1155 | AO6: =IFERROR(EDATE(Assumptions!$D$9,39),"") -> 1186 | AP6: =IFERROR(EDATE(Assumptions!$D$9,40),"") -> 1216 | AQ6: =IFERROR(EDATE(Assumptions!$D$9,41),"") -> 1247 | AR6: =IFERROR(EDATE(Assumptions!$D$9,42),"") -> 1277 | AS6: =IFERROR(EDATE(Assumptions!$D$9,43),"") -> 1308 | AT6: =IFERROR(EDATE(Assumptions!$D$9,44),"") -> 1339 | AU6: =IFERROR(EDATE(Assumptions!$D$9,45),"") -> 1369 | AV6: =IFERROR(EDATE(Assumptions!$D$9,46),"") -> 1400 | AW6: =IFERROR(EDATE(Assumptions!$D$9,47),"") -> 1430 | AX6: =IFERROR(EDATE(Assumptions!$D$9,48),"") -> 1461 | AY6: =IFERROR(EDATE(Assumptions!$D$9,49),"") -> 1492 | AZ6: =IFERROR(EDATE(Assumptions!$D$9,50),"") -> 1521 | BA6: =IFERROR(EDATE(Assumptions!$D$9,51),"") -> 1552 | BB6: =IFERROR(EDATE(Assumptions!$D$9,52),"") -> 1582 | BC6: =IFERROR(EDATE(Assumptions!$D$9,53),"") -> 1613 | BD6: =IFERROR(EDATE(Assumptions!$D$9,54),"") -> 1643 | BE6: =IFERROR(EDATE(Assumptions!$D$9,55),"") -> 1674 | BF6: =IFERROR(EDATE(Assumptions!$D$9,56),"") -> 1705 | BG6: =IFERROR(EDATE(Assumptions!$D$9,57),"") -> 1735 | BH6: =IFERROR(EDATE(Assumptions!$D$9,58),"") -> 1766 | BI6: =IFERROR(EDATE(Assumptions!$D$9,59),"") -> 1796
A7: SALES VOLUME & REVENUE
A8: Saleable Production (units) | B8: =Production!B12 -> 0 | C8: =Production!C12 -> 0 | D8: =Production!D12 -> 0 | E8: =Production!E12 -> 0 | F8: =Production!F12 -> 0 | G8: =Production!G12 -> 0 | H8: =Production!H12 -> 0 | I8: =Production!I12 -> 0 | ... BI8: =Production!BI12 -> 0
A9: Sell-through Rate (%) | B9: =Assumptions!$D$15 -> 0 | C9: =Assumptions!$D$15 -> 0 | D9: =Assumptions!$D$15 -> 0 | E9: =Assumptions!$D$15 -> 0 | F9: =Assumptions!$D$15 -> 0 | G9: =Assumptions!$D$15 -> 0 | H9: =Assumptions!$D$15 -> 0 | I9: =Assumptions!$D$15 -> 0 | ... BI9: =Assumptions!$D$15 -> 0
A10: Units Sold | B10: =B8*B9 -> 0 | C10: =C8*C9 -> 0 | D10: =D8*D9 -> 0 | E10: =E8*E9 -> 0 | F10: =F8*F9 -> 0 | G10: =G8*G9 -> 0 | H10: =H8*H9 -> 0 | I10: =I8*I9 -> 0 | ... BI10: =BI8*BI9 -> 0
A11: Selling Price / unit (₹) | B11: =Assumptions!$D$16 -> 0 | C11: =Assumptions!$D$16 -> 0 | D11: =Assumptions!$D$16 -> 0 | E11: =Assumptions!$D$16 -> 0 | F11: =Assumptions!$D$16 -> 0 | G11: =Assumptions!$D$16 -> 0 | H11: =Assumptions!$D$16 -> 0 | I11: =Assumptions!$D$16 -> 0 | ... M11: =Assumptions!$D$16 -> 0 | N11: =Assumptions!$E$16 -> 0 | O11: =Assumptions!$E$16 -> 0 | P11: =Assumptions!$E$16 -> 0 | Q11: =Assumptions!$E$16 -> 0 | R11: =Assumptions!$E$16 -> 0 | S11: =Assumptions!$E$16 -> 0 | T11: =Assumptions!$E$16 -> 0 | U11: =Assumptions!$E$16 -> 0 | ... Y11: =Assumptions!$E$16 -> 0 | Z11: =Assumptions!$F$16 -> 0 | AA11: =Assumptions!$F$16 -> 0 | AB11: =Assumptions!$F$16 -> 0 | AC11: =Assumptions!$F$16 -> 0 | AD11: =Assumptions!$F$16 -> 0 | AE11: =Assumptions!$F$16 -> 0 | AF11: =Assumptions!$F$16 -> 0 | AG11: =Assumptions!$F$16 -> 0 | ... AK11: =Assumptions!$F$16 -> 0 | AL11: =Assumptions!$G$16 -> 0 | AM11: =Assumptions!$G$16 -> 0 | AN11: =Assumptions!$G$16 -> 0 | AO11: =Assumptions!$G$16 -> 0 | AP11: =Assumptions!$G$16 -> 0 | AQ11: =Assumptions!$G$16 -> 0 | AR11: =Assumptions!$G$16 -> 0 | AS11: =Assumptions!$G$16 -> 0 | ... AW11: =Assumptions!$G$16 -> 0 | AX11: =Assumptions!$H$16 -> 0 | AY11: =Assumptions!$H$16 -> 0 | AZ11: =Assumptions!$H$16 -> 0 | BA11: =Assumptions!$H$16 -> 0 | BB11: =Assumptions!$H$16 -> 0 | BC11: =Assumptions!$H$16 -> 0 | BD11: =Assumptions!$H$16 -> 0 | BE11: =Assumptions!$H$16 -> 0 | ... BI11: =Assumptions!$H$16 -> 0
A12: Gross Sales Value (₹) | B12: =B10*B11 -> 0 | C12: =C10*C11 -> 0 | D12: =D10*D11 -> 0 | E12: =E10*E11 -> 0 | F12: =F10*F11 -> 0 | G12: =G10*G11 -> 0 | H12: =H10*H11 -> 0 | I12: =I10*I11 -> 0 | ... BI12: =BI10*BI11 -> 0
A13: Less: Discount / Returns (₹) | B13: =B12*Assumptions!$D$17 -> 0 | C13: =C12*Assumptions!$D$17 -> 0 | D13: =D12*Assumptions!$D$17 -> 0 | E13: =E12*Assumptions!$D$17 -> 0 | F13: =F12*Assumptions!$D$17 -> 0 | G13: =G12*Assumptions!$D$17 -> 0 | H13: =H12*Assumptions!$D$17 -> 0 | I13: =I12*Assumptions!$D$17 -> 0 | ... BI13: =BI12*Assumptions!$D$17 -> 0
A14: Net Revenue (₹) | B14: =B12-B13 -> 0 | C14: =C12-C13 -> 0 | D14: =D12-D13 -> 0 | E14: =E12-E13 -> 0 | F14: =F12-F13 -> 0 | G14: =G12-G13 -> 0 | H14: =H12-H13 -> 0 | I14: =I12-I13 -> 0 | ... BI14: =BI12-BI13 -> 0

Sheet Expenses
A1: OPERATING EXPENSES
A2: Direct costs, overheads, SG&A, depreciation and interest — all linked to Assumptions, Production and Sales.
B4: YEAR 1 | N4: YEAR 2 | Z4: YEAR 3 | AL4: YEAR 4 | AX4: YEAR 5
A5: Line item / Month | B5: M1 | C5: M2 | D5: M3 | E5: M4 | F5: M5 | G5: M6 | H5: M7 | I5: M8 | J5: M9 | K5: M10 | L5: M11 | M5: M12 | N5: M13 | O5: M14 | P5: M15 | Q5: M16 | R5: M17 | S5: M18 | T5: M19 | U5: M20 | V5: M21 | W5: M22 | X5: M23 | Y5: M24 | Z5: M25 | AA5: M26 | AB5: M27 | AC5: M28 | AD5: M29 | AE5: M30 | AF5: M31 | AG5: M32 | AH5: M33 | AI5: M34 | AJ5: M35 | AK5: M36 | AL5: M37 | AM5: M38 | AN5: M39 | AO5: M40 | AP5: M41 | AQ5: M42 | AR5: M43 | AS5: M44 | AT5: M45 | AU5: M46 | AV5: M47 | AW5: M48 | AX5: M49 | AY5: M50 | AZ5: M51 | BA5: M52 | BB5: M53 | BC5: M54 | BD5: M55 | BE5: M56 | BF5: M57 | BG5: M58 | BH5: M59 | BI5: M60
A6: Calendar month | B6: =IFERROR(EDATE(Assumptions!$D$9,0),"") -> 0 | C6: =IFERROR(EDATE(Assumptions!$D$9,1),"") -> 31 | D6: =IFERROR(EDATE(Assumptions!$D$9,2),"") -> 60 | E6: =IFERROR(EDATE(Assumptions!$D$9,3),"") -> 91 | F6: =IFERROR(EDATE(Assumptions!$D$9,4),"") -> 121 | G6: =IFERROR(EDATE(Assumptions!$D$9,5),"") -> 152 | H6: =IFERROR(EDATE(Assumptions!$D$9,6),"") -> 182 | I6: =IFERROR(EDATE(Assumptions!$D$9,7),"") -> 213 | J6: =IFERROR(EDATE(Assumptions!$D$9,8),"") -> 244 | K6: =IFERROR(EDATE(Assumptions!$D$9,9),"") -> 274 | L6: =IFERROR(EDATE(Assumptions!$D$9,10),"") -> 305 | M6: =IFERROR(EDATE(Assumptions!$D$9,11),"") -> 335 | N6: =IFERROR(EDATE(Assumptions!$D$9,12),"") -> 366 | O6: =IFERROR(EDATE(Assumptions!$D$9,13),"") -> 397 | P6: =IFERROR(EDATE(Assumptions!$D$9,14),"") -> 425 | Q6: =IFERROR(EDATE(Assumptions!$D$9,15),"") -> 456 | R6: =IFERROR(EDATE(Assumptions!$D$9,16),"") -> 486 | S6: =IFERROR(EDATE(Assumptions!$D$9,17),"") -> 517 | T6: =IFERROR(EDATE(Assumptions!$D$9,18),"") -> 547 | U6: =IFERROR(EDATE(Assumptions!$D$9,19),"") -> 578 | V6: =IFERROR(EDATE(Assumptions!$D$9,20),"") -> 609 | W6: =IFERROR(EDATE(Assumptions!$D$9,21),"") -> 639 | X6: =IFERROR(EDATE(Assumptions!$D$9,22),"") -> 670 | Y6: =IFERROR(EDATE(Assumptions!$D$9,23),"") -> 700 | Z6: =IFERROR(EDATE(Assumptions!$D$9,24),"") -> 731 | AA6: =IFERROR(EDATE(Assumptions!$D$9,25),"") -> 762 | AB6: =IFERROR(EDATE(Assumptions!$D$9,26),"") -> 790 | AC6: =IFERROR(EDATE(Assumptions!$D$9,27),"") -> 821 | AD6: =IFERROR(EDATE(Assumptions!$D$9,28),"") -> 851 | AE6: =IFERROR(EDATE(Assumptions!$D$9,29),"") -> 882 | AF6: =IFERROR(EDATE(Assumptions!$D$9,30),"") -> 912 | AG6: =IFERROR(EDATE(Assumptions!$D$9,31),"") -> 943 | AH6: =IFERROR(EDATE(Assumptions!$D$9,32),"") -> 974 | AI6: =IFERROR(EDATE(Assumptions!$D$9,33),"") -> 1004 | AJ6: =IFERROR(EDATE(Assumptions!$D$9,34),"") -> 1035 | AK6: =IFERROR(EDATE(Assumptions!$D$9,35),"") -> 1065 | AL6: =IFERROR(EDATE(Assumptions!$D$9,36),"") -> 1096 | AM6: =IFERROR(EDATE(Assumptions!$D$9,37),"") -> 1127 | AN6: =IFERROR(EDATE(Assumptions!$D$9,38),"") -> 1155 | AO6: =IFERROR(EDATE(Assumptions!$D$9,39),"") -> 1186 | AP6: =IFERROR(EDATE(Assumptions!$D$9,40),"") -> 1216 | AQ6: =IFERROR(EDATE(Assumptions!$D$9,41),"") -> 1247 | AR6: =IFERROR(EDATE(Assumptions!$D$9,42),"") -> 1277 | AS6: =IFERROR(EDATE(Assumptions!$D$9,43),"") -> 1308 | AT6: =IFERROR(EDATE(Assumptions!$D$9,44),"") -> 1339 | AU6: =IFERROR(EDATE(Assumptions!$D$9,45),"") -> 1369 | AV6: =IFERROR(EDATE(Assumptions!$D$9,46),"") -> 1400 | AW6: =IFERROR(EDATE(Assumptions!$D$9,47),"") -> 1430 | AX6: =IFERROR(EDATE(Assumptions!$D$9,48),"") -> 1461 | AY6: =IFERROR(EDATE(Assumptions!$D$9,49),"") -> 1492 | AZ6: =IFERROR(EDATE(Assumptions!$D$9,50),"") -> 1521 | BA6: =IFERROR(EDATE(Assumptions!$D$9,51),"") -> 1552 | BB6: =IFERROR(EDATE(Assumptions!$D$9,52),"") -> 1582 | BC6: =IFERROR(EDATE(Assumptions!$D$9,53),"") -> 1613 | BD6: =IFERROR(EDATE(Assumptions!$D$9,54),"") -> 1643 | BE6: =IFERROR(EDATE(Assumptions!$D$9,55),"") -> 1674 | BF6: =IFERROR(EDATE(Assumptions!$D$9,56),"") -> 1705 | BG6: =IFERROR(EDATE(Assumptions!$D$9,57),"") -> 1735 | BH6: =IFERROR(EDATE(Assumptions!$D$9,58),"") -> 1766 | BI6: =IFERROR(EDATE(Assumptions!$D$9,59),"") -> 1796
A7: A. DIRECT / VARIABLE COSTS (COGS)
A8: Raw Material | B8: =Production!B10*Assumptions!$D$19 -> 0 | C8: =Production!C10*Assumptions!$D$19 -> 0 | D8: =Production!D10*Assumptions!$D$19 -> 0 | E8: =Production!E10*Assumptions!$D$19 -> 0 | F8: =Production!F10*Assumptions!$D$19 -> 0 | G8: =Production!G10*Assumptions!$D$19 -> 0 | H8: =Production!H10*Assumptions!$D$19 -> 0 | I8: =Production!I10*Assumptions!$D$19 -> 0 | ... M8: =Production!M10*Assumptions!$D$19 -> 0 | N8: =Production!N10*Assumptions!$E$19 -> 0 | O8: =Production!O10*Assumptions!$E$19 -> 0 | P8: =Production!P10*Assumptions!$E$19 -> 0 | Q8: =Production!Q10*Assumptions!$E$19 -> 0 | R8: =Production!R10*Assumptions!$E$19 -> 0 | S8: =Production!S10*Assumptions!$E$19 -> 0 | T8: =Production!T10*Assumptions!$E$19 -> 0 | U8: =Production!U10*Assumptions!$E$19 -> 0 | ... Y8: =Production!Y10*Assumptions!$E$19 -> 0 | Z8: =Production!Z10*Assumptions!$F$19 -> 0 | AA8: =Production!AA10*Assumptions!$F$19 -> 0 | AB8: =Production!AB10*Assumptions!$F$19 -> 0 | AC8: =Production!AC10*Assumptions!$F$19 -> 0 | AD8: =Production!AD10*Assumptions!$F$19 -> 0 | AE8: =Production!AE10*Assumptions!$F$19 -> 0 | AF8: =Production!AF10*Assumptions!$F$19 -> 0 | AG8: =Production!AG10*Assumptions!$F$19 -> 0 | ... AK8: =Production!AK10*Assumptions!$F$19 -> 0 | AL8: =Production!AL10*Assumptions!$G$19 -> 0 | AM8: =Production!AM10*Assumptions!$G$19 -> 0 | AN8: =Production!AN10*Assumptions!$G$19 -> 0 | AO8: =Production!AO10*Assumptions!$G$19 -> 0 | AP8: =Production!AP10*Assumptions!$G$19 -> 0 | AQ8: =Production!AQ10*Assumptions!$G$19 -> 0 | AR8: =Production!AR10*Assumptions!$G$19 -> 0 | AS8: =Production!AS10*Assumptions!$G$19 -> 0 | ... AW8: =Production!AW10*Assumptions!$G$19 -> 0 | AX8: =Production!AX10*Assumptions!$H$19 -> 0 | AY8: =Production!AY10*Assumptions!$H$19 -> 0 | AZ8: =Production!AZ10*Assumptions!$H$19 -> 0 | BA8: =Production!BA10*Assumptions!$H$19 -> 0 | BB8: =Production!BB10*Assumptions!$H$19 -> 0 | BC8: =Production!BC10*Assumptions!$H$19 -> 0 | BD8: =Production!BD10*Assumptions!$H$19 -> 0 | BE8: =Production!BE10*Assumptions!$H$19 -> 0 | ... BI8: =Production!BI10*Assumptions!$H$19 -> 0
A9: Packaging & Consumables | B9: =Production!B10*Assumptions!$D$20*(1+Assumptions!$D$36)^0 -> 0 | C9: =Production!C10*Assumptions!$D$20*(1+Assumptions!$D$36)^0 -> 0 | D9: =Production!D10*Assumptions!$D$20*(1+Assumptions!$D$36)^0 -> 0 | E9: =Production!E10*Assumptions!$D$20*(1+Assumptions!$D$36)^0 -> 0 | F9: =Production!F10*Assumptions!$D$20*(1+Assumptions!$D$36)^0 -> 0 | G9: =Production!G10*Assumptions!$D$20*(1+Assumptions!$D$36)^0 -> 0 | H9: =Production!H10*Assumptions!$D$20*(1+Assumptions!$D$36)^0 -> 0 | I9: =Production!I10*Assumptions!$D$20*(1+Assumptions!$D$36)^0 -> 0 | ... M9: =Production!M10*Assumptions!$D$20*(1+Assumptions!$D$36)^0 -> 0 | N9: =Production!N10*Assumptions!$D$20*(1+Assumptions!$D$36)^1 -> 0 | O9: =Production!O10*Assumptions!$D$20*(1+Assumptions!$D$36)^1 -> 0 | P9: =Production!P10*Assumptions!$D$20*(1+Assumptions!$D$36)^1 -> 0 | Q9: =Production!Q10*Assumptions!$D$20*(1+Assumptions!$D$36)^1 -> 0 | R9: =Production!R10*Assumptions!$D$20*(1+Assumptions!$D$36)^1 -> 0 | S9: =Production!S10*Assumptions!$D$20*(1+Assumptions!$D$36)^1 -> 0 | T9: =Production!T10*Assumptions!$D$20*(1+Assumptions!$D$36)^1 -> 0 | U9: =Production!U10*Assumptions!$D$20*(1+Assumptions!$D$36)^1 -> 0 | ... Y9: =Production!Y10*Assumptions!$D$20*(1+Assumptions!$D$36)^1 -> 0 | Z9: =Production!Z10*Assumptions!$D$20*(1+Assumptions!$D$36)^2 -> 0 | AA9: =Production!AA10*Assumptions!$D$20*(1+Assumptions!$D$36)^2 -> 0 | AB9: =Production!AB10*Assumptions!$D$20*(1+Assumptions!$D$36)^2 -> 0 | AC9: =Production!AC10*Assumptions!$D$20*(1+Assumptions!$D$36)^2 -> 0 | AD9: =Production!AD10*Assumptions!$D$20*(1+Assumptions!$D$36)^2 -> 0 | AE9: =Production!AE10*Assumptions!$D$20*(1+Assumptions!$D$36)^2 -> 0 | AF9: =Production!AF10*Assumptions!$D$20*(1+Assumptions!$D$36)^2 -> 0 | AG9: =Production!AG10*Assumptions!$D$20*(1+Assumptions!$D$36)^2 -> 0 | ... AK9: =Production!AK10*Assumptions!$D$20*(1+Assumptions!$D$36)^2 -> 0 | AL9: =Production!AL10*Assumptions!$D$20*(1+Assumptions!$D$36)^3 -> 0 | AM9: =Production!AM10*Assumptions!$D$20*(1+Assumptions!$D$36)^3 -> 0 | AN9: =Production!AN10*Assumptions!$D$20*(1+Assumptions!$D$36)^3 -> 0 | AO9: =Production!AO10*Assumptions!$D$20*(1+Assumptions!$D$36)^3 -> 0 | AP9: =Production!AP10*Assumptions!$D$20*(1+Assumptions!$D$36)^3 -> 0 | AQ9: =Production!AQ10*Assumptions!$D$20*(1+Assumptions!$D$36)^3 -> 0 | AR9: =Production!AR10*Assumptions!$D$20*(1+Assumptions!$D$36)^3 -> 0 | AS9: =Production!AS10*Assumptions!$D$20*(1+Assumptions!$D$36)^3 -> 0 | ... AW9: =Production!AW10*Assumptions!$D$20*(1+Assumptions!$D$36)^3 -> 0 | AX9: =Production!AX10*Assumptions!$D$20*(1+Assumptions!$D$36)^4 -> 0 | AY9: =Production!AY10*Assumptions!$D$20*(1+Assumptions!$D$36)^4 -> 0 | AZ9: =Production!AZ10*Assumptions!$D$20*(1+Assumptions!$D$36)^4 -> 0 | BA9: =Production!BA10*Assumptions!$D$20*(1+Assumptions!$D$36)^4 -> 0 | BB9: =Production!BB10*Assumptions!$D$20*(1+Assumptions!$D$36)^4 -> 0 | BC9: =Production!BC10*Assumptions!$D$20*(1+Assumptions!$D$36)^4 -> 0 | BD9: =Production!BD10*Assumptions!$D$20*(1+Assumptions!$D$36)^4 -> 0 | BE9: =Production!BE10*Assumptions!$D$20*(1+Assumptions!$D$36)^4 -> 0 | ... BI9: =Production!BI10*Assumptions!$D$20*(1+Assumptions!$D$36)^4 -> 0
A10: Power & Fuel | B10: =Production!B10*Assumptions!$D$21*(1+Assumptions!$D$36)^0 -> 0 | C10: =Production!C10*Assumptions!$D$21*(1+Assumptions!$D$36)^0 -> 0 | D10: =Production!D10*Assumptions!$D$21*(1+Assumptions!$D$36)^0 -> 0 | E10: =Production!E10*Assumptions!$D$21*(1+Assumptions!$D$36)^0 -> 0 | F10: =Production!F10*Assumptions!$D$21*(1+Assumptions!$D$36)^0 -> 0 | G10: =Production!G10*Assumptions!$D$21*(1+Assumptions!$D$36)^0 -> 0 | H10: =Production!H10*Assumptions!$D$21*(1+Assumptions!$D$36)^0 -> 0 | I10: =Production!I10*Assumptions!$D$21*(1+Assumptions!$D$36)^0 -> 0 | ... M10: =Production!M10*Assumptions!$D$21*(1+Assumptions!$D$36)^0 -> 0 | N10: =Production!N10*Assumptions!$D$21*(1+Assumptions!$D$36)^1 -> 0 | O10: =Production!O10*Assumptions!$D$21*(1+Assumptions!$D$36)^1 -> 0 | P10: =Production!P10*Assumptions!$D$21*(1+Assumptions!$D$36)^1 -> 0 | Q10: =Production!Q10*Assumptions!$D$21*(1+Assumptions!$D$36)^1 -> 0 | R10: =Production!R10*Assumptions!$D$21*(1+Assumptions!$D$36)^1 -> 0 | S10: =Production!S10*Assumptions!$D$21*(1+Assumptions!$D$36)^1 -> 0 | T10: =Production!T10*Assumptions!$D$21*(1+Assumptions!$D$36)^1 -> 0 | U10: =Production!U10*Assumptions!$D$21*(1+Assumptions!$D$36)^1 -> 0 | ... Y10: =Production!Y10*Assumptions!$D$21*(1+Assumptions!$D$36)^1 -> 0 | Z10: =Production!Z10*Assumptions!$D$21*(1+Assumptions!$D$36)^2 -> 0 | AA10: =Production!AA10*Assumptions!$D$21*(1+Assumptions!$D$36)^2 -> 0 | AB10: =Production!AB10*Assumptions!$D$21*(1+Assumptions!$D$36)^2 -> 0 | AC10: =Production!AC10*Assumptions!$D$21*(1+Assumptions!$D$36)^2 -> 0 | AD10: =Production!AD10*Assumptions!$D$21*(1+Assumptions!$D$36)^2 -> 0 | AE10: =Production!AE10*Assumptions!$D$21*(1+Assumptions!$D$36)^2 -> 0 | AF10: =Production!AF10*Assumptions!$D$21*(1+Assumptions!$D$36)^2 -> 0 | AG10: =Production!AG10*Assumptions!$D$21*(1+Assumptions!$D$36)^2 -> 0 | ... AK10: =Production!AK10*Assumptions!$D$21*(1+Assumptions!$D$36)^2 -> 0 | AL10: =Production!AL10*Assumptions!$D$21*(1+Assumptions!$D$36)^3 -> 0 | AM10: =Production!AM10*Assumptions!$D$21*(1+Assumptions!$D$36)^3 -> 0 | AN10: =Production!AN10*Assumptions!$D$21*(1+Assumptions!$D$36)^3 -> 0 | AO10: =Production!AO10*Assumptions!$D$21*(1+Assumptions!$D$36)^3 -> 0 | AP10: =Production!AP10*Assumptions!$D$21*(1+Assumptions!$D$36)^3 -> 0 | AQ10: =Production!AQ10*Assumptions!$D$21*(1+Assumptions!$D$36)^3 -> 0 | AR10: =Production!AR10*Assumptions!$D$21*(1+Assumptions!$D$36)^3 -> 0 | AS10: =Production!AS10*Assumptions!$D$21*(1+Assumptions!$D$36)^3 -> 0 | ... AW10: =Production!AW10*Assumptions!$D$21*(1+Assumptions!$D$36)^3 -> 0 | AX10: =Production!AX10*Assumptions!$D$21*(1+Assumptions!$D$36)^4 -> 0 | AY10: =Production!AY10*Assumptions!$D$21*(1+Assumptions!$D$36)^4 -> 0 | AZ10: =Production!AZ10*Assumptions!$D$21*(1+Assumptions!$D$36)^4 -> 0 | BA10: =Production!BA10*Assumptions!$D$21*(1+Assumptions!$D$36)^4 -> 0 | BB10: =Production!BB10*Assumptions!$D$21*(1+Assumptions!$D$36)^4 -> 0 | BC10: =Production!BC10*Assumptions!$D$21*(1+Assumptions!$D$36)^4 -> 0 | BD10: =Production!BD10*Assumptions!$D$21*(1+Assumptions!$D$36)^4 -> 0 | BE10: =Production!BE10*Assumptions!$D$21*(1+Assumptions!$D$36)^4 -> 0 | ... BI10: =Production!BI10*Assumptions!$D$21*(1+Assumptions!$D$36)^4 -> 0
A11: Other Variable Cost | B11: =Production!B10*Assumptions!$D$22*(1+Assumptions!$D$36)^0 -> 0 | C11: =Production!C10*Assumptions!$D$22*(1+Assumptions!$D$36)^0 -> 0 | D11: =Production!D10*Assumptions!$D$22*(1+Assumptions!$D$36)^0 -> 0 | E11: =Production!E10*Assumptions!$D$22*(1+Assumptions!$D$36)^0 -> 0 | F11: =Production!F10*Assumptions!$D$22*(1+Assumptions!$D$36)^0 -> 0 | G11: =Production!G10*Assumptions!$D$22*(1+Assumptions!$D$36)^0 -> 0 | H11: =Production!H10*Assumptions!$D$22*(1+Assumptions!$D$36)^0 -> 0 | I11: =Production!I10*Assumptions!$D$22*(1+Assumptions!$D$36)^0 -> 0 | ... M11: =Production!M10*Assumptions!$D$22*(1+Assumptions!$D$36)^0 -> 0 | N11: =Production!N10*Assumptions!$D$22*(1+Assumptions!$D$36)^1 -> 0 | O11: =Production!O10*Assumptions!$D$22*(1+Assumptions!$D$36)^1 -> 0 | P11: =Production!P10*Assumptions!$D$22*(1+Assumptions!$D$36)^1 -> 0 | Q11: =Production!Q10*Assumptions!$D$22*(1+Assumptions!$D$36)^1 -> 0 | R11: =Production!R10*Assumptions!$D$22*(1+Assumptions!$D$36)^1 -> 0 | S11: =Production!S10*Assumptions!$D$22*(1+Assumptions!$D$36)^1 -> 0 | T11: =Production!T10*Assumptions!$D$22*(1+Assumptions!$D$36)^1 -> 0 | U11: =Production!U10*Assumptions!$D$22*(1+Assumptions!$D$36)^1 -> 0 | ... Y11: =Production!Y10*Assumptions!$D$22*(1+Assumptions!$D$36)^1 -> 0 | Z11: =Production!Z10*Assumptions!$D$22*(1+Assumptions!$D$36)^2 -> 0 | AA11: =Production!AA10*Assumptions!$D$22*(1+Assumptions!$D$36)^2 -> 0 | AB11: =Production!AB10*Assumptions!$D$22*(1+Assumptions!$D$36)^2 -> 0 | AC11: =Production!AC10*Assumptions!$D$22*(1+Assumptions!$D$36)^2 -> 0 | AD11: =Production!AD10*Assumptions!$D$22*(1+Assumptions!$D$36)^2 -> 0 | AE11: =Production!AE10*Assumptions!$D$22*(1+Assumptions!$D$36)^2 -> 0 | AF11: =Production!AF10*Assumptions!$D$22*(1+Assumptions!$D$36)^2 -> 0 | AG11: =Production!AG10*Assumptions!$D$22*(1+Assumptions!$D$36)^2 -> 0 | ... AK11: =Production!AK10*Assumptions!$D$22*(1+Assumptions!$D$36)^2 -> 0 | AL11: =Production!AL10*Assumptions!$D$22*(1+Assumptions!$D$36)^3 -> 0 | AM11: =Production!AM10*Assumptions!$D$22*(1+Assumptions!$D$36)^3 -> 0 | AN11: =Production!AN10*Assumptions!$D$22*(1+Assumptions!$D$36)^3 -> 0 | AO11: =Production!AO10*Assumptions!$D$22*(1+Assumptions!$D$36)^3 -> 0 | AP11: =Production!AP10*Assumptions!$D$22*(1+Assumptions!$D$36)^3 -> 0 | AQ11: =Production!AQ10*Assumptions!$D$22*(1+Assumptions!$D$36)^3 -> 0 | AR11: =Production!AR10*Assumptions!$D$22*(1+Assumptions!$D$36)^3 -> 0 | AS11: =Production!AS10*Assumptions!$D$22*(1+Assumptions!$D$36)^3 -> 0 | ... AW11: =Production!AW10*Assumptions!$D$22*(1+Assumptions!$D$36)^3 -> 0 | AX11: =Production!AX10*Assumptions!$D$22*(1+Assumptions!$D$36)^4 -> 0 | AY11: =Production!AY10*Assumptions!$D$22*(1+Assumptions!$D$36)^4 -> 0 | AZ11: =Production!AZ10*Assumptions!$D$22*(1+Assumptions!$D$36)^4 -> 0 | BA11: =Production!BA10*Assumptions!$D$22*(1+Assumptions!$D$36)^4 -> 0 | BB11: =Production!BB10*Assumptions!$D$22*(1+Assumptions!$D$36)^4 -> 0 | BC11: =Production!BC10*Assumptions!$D$22*(1+Assumptions!$D$36)^4 -> 0 | BD11: =Production!BD10*Assumptions!$D$22*(1+Assumptions!$D$36)^4 -> 0 | BE11: =Production!BE10*Assumptions!$D$22*(1+Assumptions!$D$36)^4 -> 0 | ... BI11: =Production!BI10*Assumptions!$D$22*(1+Assumptions!$D$36)^4 -> 0
A12: Direct Labour | B12: =Assumptions!$D$24 -> 0 | C12: =Assumptions!$D$24 -> 0 | D12: =Assumptions!$D$24 -> 0 | E12: =Assumptions!$D$24 -> 0 | F12: =Assumptions!$D$24 -> 0 | G12: =Assumptions!$D$24 -> 0 | H12: =Assumptions!$D$24 -> 0 | I12: =Assumptions!$D$24 -> 0 | ... M12: =Assumptions!$D$24 -> 0 | N12: =Assumptions!$E$24 -> 0 | O12: =Assumptions!$E$24 -> 0 | P12: =Assumptions!$E$24 -> 0 | Q12: =Assumptions!$E$24 -> 0 | R12: =Assumptions!$E$24 -> 0 | S12: =Assumptions!$E$24 -> 0 | T12: =Assumptions!$E$24 -> 0 | U12: =Assumptions!$E$24 -> 0 | ... Y12: =Assumptions!$E$24 -> 0 | Z12: =Assumptions!$F$24 -> 0 | AA12: =Assumptions!$F$24 -> 0 | AB12: =Assumptions!$F$24 -> 0 | AC12: =Assumptions!$F$24 -> 0 | AD12: =Assumptions!$F$24 -> 0 | AE12: =Assumptions!$F$24 -> 0 | AF12: =Assumptions!$F$24 -> 0 | AG12: =Assumptions!$F$24 -> 0 | ... AK12: =Assumptions!$F$24 -> 0 | AL12: =Assumptions!$G$24 -> 0 | AM12: =Assumptions!$G$24 -> 0 | AN12: =Assumptions!$G$24 -> 0 | AO12: =Assumptions!$G$24 -> 0 | AP12: =Assumptions!$G$24 -> 0 | AQ12: =Assumptions!$G$24 -> 0 | AR12: =Assumptions!$G$24 -> 0 | AS12: =Assumptions!$G$24 -> 0 | ... AW12: =Assumptions!$G$24 -> 0 | AX12: =Assumptions!$H$24 -> 0 | AY12: =Assumptions!$H$24 -> 0 | AZ12: =Assumptions!$H$24 -> 0 | BA12: =Assumptions!$H$24 -> 0 | BB12: =Assumptions!$H$24 -> 0 | BC12: =Assumptions!$H$24 -> 0 | BD12: =Assumptions!$H$24 -> 0 | BE12: =Assumptions!$H$24 -> 0 | ... BI12: =Assumptions!$H$24 -> 0
A13: Factory Rent / Lease | B13: =Assumptions!$D$25*(1+Assumptions!$D$36)^0 -> 0 | C13: =Assumptions!$D$25*(1+Assumptions!$D$36)^0 -> 0 | D13: =Assumptions!$D$25*(1+Assumptions!$D$36)^0 -> 0 | E13: =Assumptions!$D$25*(1+Assumptions!$D$36)^0 -> 0 | F13: =Assumptions!$D$25*(1+Assumptions!$D$36)^0 -> 0 | G13: =Assumptions!$D$25*(1+Assumptions!$D$36)^0 -> 0 | H13: =Assumptions!$D$25*(1+Assumptions!$D$36)^0 -> 0 | I13: =Assumptions!$D$25*(1+Assumptions!$D$36)^0 -> 0 | ... M13: =Assumptions!$D$25*(1+Assumptions!$D$36)^0 -> 0 | N13: =Assumptions!$D$25*(1+Assumptions!$D$36)^1 -> 0 | O13: =Assumptions!$D$25*(1+Assumptions!$D$36)^1 -> 0 | P13: =Assumptions!$D$25*(1+Assumptions!$D$36)^1 -> 0 | Q13: =Assumptions!$D$25*(1+Assumptions!$D$36)^1 -> 0 | R13: =Assumptions!$D$25*(1+Assumptions!$D$36)^1 -> 0 | S13: =Assumptions!$D$25*(1+Assumptions!$D$36)^1 -> 0 | T13: =Assumptions!$D$25*(1+Assumptions!$D$36)^1 -> 0 | U13: =Assumptions!$D$25*(1+Assumptions!$D$36)^1 -> 0 | ... Y13: =Assumptions!$D$25*(1+Assumptions!$D$36)^1 -> 0 | Z13: =Assumptions!$D$25*(1+Assumptions!$D$36)^2 -> 0 | AA13: =Assumptions!$D$25*(1+Assumptions!$D$36)^2 -> 0 | AB13: =Assumptions!$D$25*(1+Assumptions!$D$36)^2 -> 0 | AC13: =Assumptions!$D$25*(1+Assumptions!$D$36)^2 -> 0 | AD13: =Assumptions!$D$25*(1+Assumptions!$D$36)^2 -> 0 | AE13: =Assumptions!$D$25*(1+Assumptions!$D$36)^2 -> 0 | AF13: =Assumptions!$D$25*(1+Assumptions!$D$36)^2 -> 0 | AG13: =Assumptions!$D$25*(1+Assumptions!$D$36)^2 -> 0 | ... AK13: =Assumptions!$D$25*(1+Assumptions!$D$36)^2 -> 0 | AL13: =Assumptions!$D$25*(1+Assumptions!$D$36)^3 -> 0 | AM13: =Assumptions!$D$25*(1+Assumptions!$D$36)^3 -> 0 | AN13: =Assumptions!$D$25*(1+Assumptions!$D$36)^3 -> 0 | AO13: =Assumptions!$D$25*(1+Assumptions!$D$36)^3 -> 0 | AP13: =Assumptions!$D$25*(1+Assumptions!$D$36)^3 -> 0 | AQ13: =Assumptions!$D$25*(1+Assumptions!$D$36)^3 -> 0 | AR13: =Assumptions!$D$25*(1+Assumptions!$D$36)^3 -> 0 | AS13: =Assumptions!$D$25*(1+Assumptions!$D$36)^3 -> 0 | ... AW13: =Assumptions!$D$25*(1+Assumptions!$D$36)^3 -> 0 | AX13: =Assumptions!$D$25*(1+Assumptions!$D$36)^4 -> 0 | AY13: =Assumptions!$D$25*(1+Assumptions!$D$36)^4 -> 0 | AZ13: =Assumptions!$D$25*(1+Assumptions!$D$36)^4 -> 0 | BA13: =Assumptions!$D$25*(1+Assumptions!$D$36)^4 -> 0 | BB13: =Assumptions!$D$25*(1+Assumptions!$D$36)^4 -> 0 | BC13: =Assumptions!$D$25*(1+Assumptions!$D$36)^4 -> 0 | BD13: =Assumptions!$D$25*(1+Assumptions!$D$36)^4 -> 0 | BE13: =Assumptions!$D$25*(1+Assumptions!$D$36)^4 -> 0 | ... BI13: =Assumptions!$D$25*(1+Assumptions!$D$36)^4 -> 0
A14: Repairs & Maintenance | B14: =Assumptions!$D$26*(1+Assumptions!$D$36)^0 -> 0 | C14: =Assumptions!$D$26*(1+Assumptions!$D$36)^0 -> 0 | D14: =Assumptions!$D$26*(1+Assumptions!$D$36)^0 -> 0 | E14: =Assumptions!$D$26*(1+Assumptions!$D$36)^0 -> 0 | F14: =Assumptions!$D$26*(1+Assumptions!$D$36)^0 -> 0 | G14: =Assumptions!$D$26*(1+Assumptions!$D$36)^0 -> 0 | H14: =Assumptions!$D$26*(1+Assumptions!$D$36)^0 -> 0 | I14: =Assumptions!$D$26*(1+Assumptions!$D$36)^0 -> 0 | ... M14: =Assumptions!$D$26*(1+Assumptions!$D$36)^0 -> 0 | N14: =Assumptions!$D$26*(1+Assumptions!$D$36)^1 -> 0 | O14: =Assumptions!$D$26*(1+Assumptions!$D$36)^1 -> 0 | P14: =Assumptions!$D$26*(1+Assumptions!$D$36)^1 -> 0 | Q14: =Assumptions!$D$26*(1+Assumptions!$D$36)^1 -> 0 | R14: =Assumptions!$D$26*(1+Assumptions!$D$36)^1 -> 0 | S14: =Assumptions!$D$26*(1+Assumptions!$D$36)^1 -> 0 | T14: =Assumptions!$D$26*(1+Assumptions!$D$36)^1 -> 0 | U14: =Assumptions!$D$26*(1+Assumptions!$D$36)^1 -> 0 | ... Y14: =Assumptions!$D$26*(1+Assumptions!$D$36)^1 -> 0 | Z14: =Assumptions!$D$26*(1+Assumptions!$D$36)^2 -> 0 | AA14: =Assumptions!$D$26*(1+Assumptions!$D$36)^2 -> 0 | AB14: =Assumptions!$D$26*(1+Assumptions!$D$36)^2 -> 0 | AC14: =Assumptions!$D$26*(1+Assumptions!$D$36)^2 -> 0 | AD14: =Assumptions!$D$26*(1+Assumptions!$D$36)^2 -> 0 | AE14: =Assumptions!$D$26*(1+Assumptions!$D$36)^2 -> 0 | AF14: =Assumptions!$D$26*(1+Assumptions!$D$36)^2 -> 0 | AG14: =Assumptions!$D$26*(1+Assumptions!$D$36)^2 -> 0 | ... AK14: =Assumptions!$D$26*(1+Assumptions!$D$36)^2 -> 0 | AL14: =Assumptions!$D$26*(1+Assumptions!$D$36)^3 -> 0 | AM14: =Assumptions!$D$26*(1+Assumptions!$D$36)^3 -> 0 | AN14: =Assumptions!$D$26*(1+Assumptions!$D$36)^3 -> 0 | AO14: =Assumptions!$D$26*(1+Assumptions!$D$36)^3 -> 0 | AP14: =Assumptions!$D$26*(1+Assumptions!$D$36)^3 -> 0 | AQ14: =Assumptions!$D$26*(1+Assumptions!$D$36)^3 -> 0 | AR14: =Assumptions!$D$26*(1+Assumptions!$D$36)^3 -> 0 | AS14: =Assumptions!$D$26*(1+Assumptions!$D$36)^3 -> 0 | ... AW14: =Assumptions!$D$26*(1+Assumptions!$D$36)^3 -> 0 | AX14: =Assumptions!$D$26*(1+Assumptions!$D$36)^4 -> 0 | AY14: =Assumptions!$D$26*(1+Assumptions!$D$36)^4 -> 0 | AZ14: =Assumptions!$D$26*(1+Assumptions!$D$36)^4 -> 0 | BA14: =Assumptions!$D$26*(1+Assumptions!$D$36)^4 -> 0 | BB14: =Assumptions!$D$26*(1+Assumptions!$D$36)^4 -> 0 | BC14: =Assumptions!$D$26*(1+Assumptions!$D$36)^4 -> 0 | BD14: =Assumptions!$D$26*(1+Assumptions!$D$36)^4 -> 0 | BE14: =Assumptions!$D$26*(1+Assumptions!$D$36)^4 -> 0 | ... BI14: =Assumptions!$D$26*(1+Assumptions!$D$36)^4 -> 0
A15: Factory Utilities & Misc OH | B15: =Assumptions!$D$27*(1+Assumptions!$D$36)^0 -> 0 | C15: =Assumptions!$D$27*(1+Assumptions!$D$36)^0 -> 0 | D15: =Assumptions!$D$27*(1+Assumptions!$D$36)^0 -> 0 | E15: =Assumptions!$D$27*(1+Assumptions!$D$36)^0 -> 0 | F15: =Assumptions!$D$27*(1+Assumptions!$D$36)^0 -> 0 | G15: =Assumptions!$D$27*(1+Assumptions!$D$36)^0 -> 0 | H15: =Assumptions!$D$27*(1+Assumptions!$D$36)^0 -> 0 | I15: =Assumptions!$D$27*(1+Assumptions!$D$36)^0 -> 0 | ... M15: =Assumptions!$D$27*(1+Assumptions!$D$36)^0 -> 0 | N15: =Assumptions!$D$27*(1+Assumptions!$D$36)^1 -> 0 | O15: =Assumptions!$D$27*(1+Assumptions!$D$36)^1 -> 0 | P15: =Assumptions!$D$27*(1+Assumptions!$D$36)^1 -> 0 | Q15: =Assumptions!$D$27*(1+Assumptions!$D$36)^1 -> 0 | R15: =Assumptions!$D$27*(1+Assumptions!$D$36)^1 -> 0 | S15: =Assumptions!$D$27*(1+Assumptions!$D$36)^1 -> 0 | T15: =Assumptions!$D$27*(1+Assumptions!$D$36)^1 -> 0 | U15: =Assumptions!$D$27*(1+Assumptions!$D$36)^1 -> 0 | ... Y15: =Assumptions!$D$27*(1+Assumptions!$D$36)^1 -> 0 | Z15: =Assumptions!$D$27*(1+Assumptions!$D$36)^2 -> 0 | AA15: =Assumptions!$D$27*(1+Assumptions!$D$36)^2 -> 0 | AB15: =Assumptions!$D$27*(1+Assumptions!$D$36)^2 -> 0 | AC15: =Assumptions!$D$27*(1+Assumptions!$D$36)^2 -> 0 | AD15: =Assumptions!$D$27*(1+Assumptions!$D$36)^2 -> 0 | AE15: =Assumptions!$D$27*(1+Assumptions!$D$36)^2 -> 0 | AF15: =Assumptions!$D$27*(1+Assumptions!$D$36)^2 -> 0 | AG15: =Assumptions!$D$27*(1+Assumptions!$D$36)^2 -> 0 | ... AK15: =Assumptions!$D$27*(1+Assumptions!$D$36)^2 -> 0 | AL15: =Assumptions!$D$27*(1+Assumptions!$D$36)^3 -> 0 | AM15: =Assumptions!$D$27*(1+Assumptions!$D$36)^3 -> 0 | AN15: =Assumptions!$D$27*(1+Assumptions!$D$36)^3 -> 0 | AO15: =Assumptions!$D$27*(1+Assumptions!$D$36)^3 -> 0 | AP15: =Assumptions!$D$27*(1+Assumptions!$D$36)^3 -> 0 | AQ15: =Assumptions!$D$27*(1+Assumptions!$D$36)^3 -> 0 | AR15: =Assumptions!$D$27*(1+Assumptions!$D$36)^3 -> 0 | AS15: =Assumptions!$D$27*(1+Assumptions!$D$36)^3 -> 0 | ... AW15: =Assumptions!$D$27*(1+Assumptions!$D$36)^3 -> 0 | AX15: =Assumptions!$D$27*(1+Assumptions!$D$36)^4 -> 0 | AY15: =Assumptions!$D$27*(1+Assumptions!$D$36)^4 -> 0 | AZ15: =Assumptions!$D$27*(1+Assumptions!$D$36)^4 -> 0 | BA15: =Assumptions!$D$27*(1+Assumptions!$D$36)^4 -> 0 | BB15: =Assumptions!$D$27*(1+Assumptions!$D$36)^4 -> 0 | BC15: =Assumptions!$D$27*(1+Assumptions!$D$36)^4 -> 0 | BD15: =Assumptions!$D$27*(1+Assumptions!$D$36)^4 -> 0 | BE15: =Assumptions!$D$27*(1+Assumptions!$D$36)^4 -> 0 | ... BI15: =Assumptions!$D$27*(1+Assumptions!$D$36)^4 -> 0
A16: Quality, Testing & Other OH | B16: =Assumptions!$D$28*(1+Assumptions!$D$36)^0 -> 0 | C16: =Assumptions!$D$28*(1+Assumptions!$D$36)^0 -> 0 | D16: =Assumptions!$D$28*(1+Assumptions!$D$36)^0 -> 0 | E16: =Assumptions!$D$28*(1+Assumptions!$D$36)^0 -> 0 | F16: =Assumptions!$D$28*(1+Assumptions!$D$36)^0 -> 0 | G16: =Assumptions!$D$28*(1+Assumptions!$D$36)^0 -> 0 | H16: =Assumptions!$D$28*(1+Assumptions!$D$36)^0 -> 0 | I16: =Assumptions!$D$28*(1+Assumptions!$D$36)^0 -> 0 | ... M16: =Assumptions!$D$28*(1+Assumptions!$D$36)^0 -> 0 | N16: =Assumptions!$D$28*(1+Assumptions!$D$36)^1 -> 0 | O16: =Assumptions!$D$28*(1+Assumptions!$D$36)^1 -> 0 | P16: =Assumptions!$D$28*(1+Assumptions!$D$36)^1 -> 0 | Q16: =Assumptions!$D$28*(1+Assumptions!$D$36)^1 -> 0 | R16: =Assumptions!$D$28*(1+Assumptions!$D$36)^1 -> 0 | S16: =Assumptions!$D$28*(1+Assumptions!$D$36)^1 -> 0 | T16: =Assumptions!$D$28*(1+Assumptions!$D$36)^1 -> 0 | U16: =Assumptions!$D$28*(1+Assumptions!$D$36)^1 -> 0 | ... Y16: =Assumptions!$D$28*(1+Assumptions!$D$36)^1 -> 0 | Z16: =Assumptions!$D$28*(1+Assumptions!$D$36)^2 -> 0 | AA16: =Assumptions!$D$28*(1+Assumptions!$D$36)^2 -> 0 | AB16: =Assumptions!$D$28*(1+Assumptions!$D$36)^2 -> 0 | AC16: =Assumptions!$D$28*(1+Assumptions!$D$36)^2 -> 0 | AD16: =Assumptions!$D$28*(1+Assumptions!$D$36)^2 -> 0 | AE16: =Assumptions!$D$28*(1+Assumptions!$D$36)^2 -> 0 | AF16: =Assumptions!$D$28*(1+Assumptions!$D$36)^2 -> 0 | AG16: =Assumptions!$D$28*(1+Assumptions!$D$36)^2 -> 0 | ... AK16: =Assumptions!$D$28*(1+Assumptions!$D$36)^2 -> 0 | AL16: =Assumptions!$D$28*(1+Assumptions!$D$36)^3 -> 0 | AM16: =Assumptions!$D$28*(1+Assumptions!$D$36)^3 -> 0 | AN16: =Assumptions!$D$28*(1+Assumptions!$D$36)^3 -> 0 | AO16: =Assumptions!$D$28*(1+Assumptions!$D$36)^3 -> 0 | AP16: =Assumptions!$D$28*(1+Assumptions!$D$36)^3 -> 0 | AQ16: =Assumptions!$D$28*(1+Assumptions!$D$36)^3 -> 0 | AR16: =Assumptions!$D$28*(1+Assumptions!$D$36)^3 -> 0 | AS16: =Assumptions!$D$28*(1+Assumptions!$D$36)^3 -> 0 | ... AW16: =Assumptions!$D$28*(1+Assumptions!$D$36)^3 -> 0 | AX16: =Assumptions!$D$28*(1+Assumptions!$D$36)^4 -> 0 | AY16: =Assumptions!$D$28*(1+Assumptions!$D$36)^4 -> 0 | AZ16: =Assumptions!$D$28*(1+Assumptions!$D$36)^4 -> 0 | BA16: =Assumptions!$D$28*(1+Assumptions!$D$36)^4 -> 0 | BB16: =Assumptions!$D$28*(1+Assumptions!$D$36)^4 -> 0 | BC16: =Assumptions!$D$28*(1+Assumptions!$D$36)^4 -> 0 | BD16: =Assumptions!$D$28*(1+Assumptions!$D$36)^4 -> 0 | BE16: =Assumptions!$D$28*(1+Assumptions!$D$36)^4 -> 0 | ... BI16: =Assumptions!$D$28*(1+Assumptions!$D$36)^4 -> 0
A17: Total COGS | B17: =SUM(B8:B16) -> 0 | C17: =SUM(C8:C16) -> 0 | D17: =SUM(D8:D16) -> 0 | E17: =SUM(E8:E16) -> 0 | F17: =SUM(F8:F16) -> 0 | G17: =SUM(G8:G16) -> 0 | H17: =SUM(H8:H16) -> 0 | I17: =SUM(I8:I16) -> 0 | ... BI17: =SUM(BI8:BI16) -> 0
A18: B. OPERATING EXPENSES (SG&A)
A19: Admin & Management Salaries | B19: =Assumptions!$D$30*(1+Assumptions!$D$36)^0 -> 0 | C19: =Assumptions!$D$30*(1+Assumptions!$D$36)^0 -> 0 | D19: =Assumptions!$D$30*(1+Assumptions!$D$36)^0 -> 0 | E19: =Assumptions!$D$30*(1+Assumptions!$D$36)^0 -> 0 | F19: =Assumptions!$D$30*(1+Assumptions!$D$36)^0 -> 0 | G19: =Assumptions!$D$30*(1+Assumptions!$D$36)^0 -> 0 | H19: =Assumptions!$D$30*(1+Assumptions!$D$36)^0 -> 0 | I19: =Assumptions!$D$30*(1+Assumptions!$D$36)^0 -> 0 | ... M19: =Assumptions!$D$30*(1+Assumptions!$D$36)^0 -> 0 | N19: =Assumptions!$D$30*(1+Assumptions!$D$36)^1 -> 0 | O19: =Assumptions!$D$30*(1+Assumptions!$D$36)^1 -> 0 | P19: =Assumptions!$D$30*(1+Assumptions!$D$36)^1 -> 0 | Q19: =Assumptions!$D$30*(1+Assumptions!$D$36)^1 -> 0 | R19: =Assumptions!$D$30*(1+Assumptions!$D$36)^1 -> 0 | S19: =Assumptions!$D$30*(1+Assumptions!$D$36)^1 -> 0 | T19: =Assumptions!$D$30*(1+Assumptions!$D$36)^1 -> 0 | U19: =Assumptions!$D$30*(1+Assumptions!$D$36)^1 -> 0 | ... Y19: =Assumptions!$D$30*(1+Assumptions!$D$36)^1 -> 0 | Z19: =Assumptions!$D$30*(1+Assumptions!$D$36)^2 -> 0 | AA19: =Assumptions!$D$30*(1+Assumptions!$D$36)^2 -> 0 | AB19: =Assumptions!$D$30*(1+Assumptions!$D$36)^2 -> 0 | AC19: =Assumptions!$D$30*(1+Assumptions!$D$36)^2 -> 0 | AD19: =Assumptions!$D$30*(1+Assumptions!$D$36)^2 -> 0 | AE19: =Assumptions!$D$30*(1+Assumptions!$D$36)^2 -> 0 | AF19: =Assumptions!$D$30*(1+Assumptions!$D$36)^2 -> 0 | AG19: =Assumptions!$D$30*(1+Assumptions!$D$36)^2 -> 0 | ... AK19: =Assumptions!$D$30*(1+Assumptions!$D$36)^2 -> 0 | AL19: =Assumptions!$D$30*(1+Assumptions!$D$36)^3 -> 0 | AM19: =Assumptions!$D$30*(1+Assumptions!$D$36)^3 -> 0 | AN19: =Assumptions!$D$30*(1+Assumptions!$D$36)^3 -> 0 | AO19: =Assumptions!$D$30*(1+Assumptions!$D$36)^3 -> 0 | AP19: =Assumptions!$D$30*(1+Assumptions!$D$36)^3 -> 0 | AQ19: =Assumptions!$D$30*(1+Assumptions!$D$36)^3 -> 0 | AR19: =Assumptions!$D$30*(1+Assumptions!$D$36)^3 -> 0 | AS19: =Assumptions!$D$30*(1+Assumptions!$D$36)^3 -> 0 | ... AW19: =Assumptions!$D$30*(1+Assumptions!$D$36)^3 -> 0 | AX19: =Assumptions!$D$30*(1+Assumptions!$D$36)^4 -> 0 | AY19: =Assumptions!$D$30*(1+Assumptions!$D$36)^4 -> 0 | AZ19: =Assumptions!$D$30*(1+Assumptions!$D$36)^4 -> 0 | BA19: =Assumptions!$D$30*(1+Assumptions!$D$36)^4 -> 0 | BB19: =Assumptions!$D$30*(1+Assumptions!$D$36)^4 -> 0 | BC19: =Assumptions!$D$30*(1+Assumptions!$D$36)^4 -> 0 | BD19: =Assumptions!$D$30*(1+Assumptions!$D$36)^4 -> 0 | BE19: =Assumptions!$D$30*(1+Assumptions!$D$36)^4 -> 0 | ... BI19: =Assumptions!$D$30*(1+Assumptions!$D$36)^4 -> 0
A20: Marketing & Selling | B20: =Sales!B14*Assumptions!$D$31 -> 0 | C20: =Sales!C14*Assumptions!$D$31 -> 0 | D20: =Sales!D14*Assumptions!$D$31 -> 0 | E20: =Sales!E14*Assumptions!$D$31 -> 0 | F20: =Sales!F14*Assumptions!$D$31 -> 0 | G20: =Sales!G14*Assumptions!$D$31 -> 0 | H20: =Sales!H14*Assumptions!$D$31 -> 0 | I20: =Sales!I14*Assumptions!$D$31 -> 0 | ... BI20: =Sales!BI14*Assumptions!$D$31 -> 0
A21: Distribution & Freight-out | B21: =Sales!B14*Assumptions!$D$32 -> 0 | C21: =Sales!C14*Assumptions!$D$32 -> 0 | D21: =Sales!D14*Assumptions!$D$32 -> 0 | E21: =Sales!E14*Assumptions!$D$32 -> 0 | F21: =Sales!F14*Assumptions!$D$32 -> 0 | G21: =Sales!G14*Assumptions!$D$32 -> 0 | H21: =Sales!H14*Assumptions!$D$32 -> 0 | I21: =Sales!I14*Assumptions!$D$32 -> 0 | ... BI21: =Sales!BI14*Assumptions!$D$32 -> 0
A22: Office Rent & Admin Overhead | B22: =Assumptions!$D$33*(1+Assumptions!$D$36)^0 -> 0 | C22: =Assumptions!$D$33*(1+Assumptions!$D$36)^0 -> 0 | D22: =Assumptions!$D$33*(1+Assumptions!$D$36)^0 -> 0 | E22: =Assumptions!$D$33*(1+Assumptions!$D$36)^0 -> 0 | F22: =Assumptions!$D$33*(1+Assumptions!$D$36)^0 -> 0 | G22: =Assumptions!$D$33*(1+Assumptions!$D$36)^0 -> 0 | H22: =Assumptions!$D$33*(1+Assumptions!$D$36)^0 -> 0 | I22: =Assumptions!$D$33*(1+Assumptions!$D$36)^0 -> 0 | ... M22: =Assumptions!$D$33*(1+Assumptions!$D$36)^0 -> 0 | N22: =Assumptions!$D$33*(1+Assumptions!$D$36)^1 -> 0 | O22: =Assumptions!$D$33*(1+Assumptions!$D$36)^1 -> 0 | P22: =Assumptions!$D$33*(1+Assumptions!$D$36)^1 -> 0 | Q22: =Assumptions!$D$33*(1+Assumptions!$D$36)^1 -> 0 | R22: =Assumptions!$D$33*(1+Assumptions!$D$36)^1 -> 0 | S22: =Assumptions!$D$33*(1+Assumptions!$D$36)^1 -> 0 | T22: =Assumptions!$D$33*(1+Assumptions!$D$36)^1 -> 0 | U22: =Assumptions!$D$33*(1+Assumptions!$D$36)^1 -> 0 | ... Y22: =Assumptions!$D$33*(1+Assumptions!$D$36)^1 -> 0 | Z22: =Assumptions!$D$33*(1+Assumptions!$D$36)^2 -> 0 | AA22: =Assumptions!$D$33*(1+Assumptions!$D$36)^2 -> 0 | AB22: =Assumptions!$D$33*(1+Assumptions!$D$36)^2 -> 0 | AC22: =Assumptions!$D$33*(1+Assumptions!$D$36)^2 -> 0 | AD22: =Assumptions!$D$33*(1+Assumptions!$D$36)^2 -> 0 | AE22: =Assumptions!$D$33*(1+Assumptions!$D$36)^2 -> 0 | AF22: =Assumptions!$D$33*(1+Assumptions!$D$36)^2 -> 0 | AG22: =Assumptions!$D$33*(1+Assumptions!$D$36)^2 -> 0 | ... AK22: =Assumptions!$D$33*(1+Assumptions!$D$36)^2 -> 0 | AL22: =Assumptions!$D$33*(1+Assumptions!$D$36)^3 -> 0 | AM22: =Assumptions!$D$33*(1+Assumptions!$D$36)^3 -> 0 | AN22: =Assumptions!$D$33*(1+Assumptions!$D$36)^3 -> 0 | AO22: =Assumptions!$D$33*(1+Assumptions!$D$36)^3 -> 0 | AP22: =Assumptions!$D$33*(1+Assumptions!$D$36)^3 -> 0 | AQ22: =Assumptions!$D$33*(1+Assumptions!$D$36)^3 -> 0 | AR22: =Assumptions!$D$33*(1+Assumptions!$D$36)^3 -> 0 | AS22: =Assumptions!$D$33*(1+Assumptions!$D$36)^3 -> 0 | ... AW22: =Assumptions!$D$33*(1+Assumptions!$D$36)^3 -> 0 | AX22: =Assumptions!$D$33*(1+Assumptions!$D$36)^4 -> 0 | AY22: =Assumptions!$D$33*(1+Assumptions!$D$36)^4 -> 0 | AZ22: =Assumptions!$D$33*(1+Assumptions!$D$36)^4 -> 0 | BA22: =Assumptions!$D$33*(1+Assumptions!$D$36)^4 -> 0 | BB22: =Assumptions!$D$33*(1+Assumptions!$D$36)^4 -> 0 | BC22: =Assumptions!$D$33*(1+Assumptions!$D$36)^4 -> 0 | BD22: =Assumptions!$D$33*(1+Assumptions!$D$36)^4 -> 0 | BE22: =Assumptions!$D$33*(1+Assumptions!$D$36)^4 -> 0 | ... BI22: =Assumptions!$D$33*(1+Assumptions!$D$36)^4 -> 0
A23: Insurance | B23: =Assumptions!$D$34*(1+Assumptions!$D$36)^0 -> 0 | C23: =Assumptions!$D$34*(1+Assumptions!$D$36)^0 -> 0 | D23: =Assumptions!$D$34*(1+Assumptions!$D$36)^0 -> 0 | E23: =Assumptions!$D$34*(1+Assumptions!$D$36)^0 -> 0 | F23: =Assumptions!$D$34*(1+Assumptions!$D$36)^0 -> 0 | G23: =Assumptions!$D$34*(1+Assumptions!$D$36)^0 -> 0 | H23: =Assumptions!$D$34*(1+Assumptions!$D$36)^0 -> 0 | I23: =Assumptions!$D$34*(1+Assumptions!$D$36)^0 -> 0 | ... M23: =Assumptions!$D$34*(1+Assumptions!$D$36)^0 -> 0 | N23: =Assumptions!$D$34*(1+Assumptions!$D$36)^1 -> 0 | O23: =Assumptions!$D$34*(1+Assumptions!$D$36)^1 -> 0 | P23: =Assumptions!$D$34*(1+Assumptions!$D$36)^1 -> 0 | Q23: =Assumptions!$D$34*(1+Assumptions!$D$36)^1 -> 0 | R23: =Assumptions!$D$34*(1+Assumptions!$D$36)^1 -> 0 | S23: =Assumptions!$D$34*(1+Assumptions!$D$36)^1 -> 0 | T23: =Assumptions!$D$34*(1+Assumptions!$D$36)^1 -> 0 | U23: =Assumptions!$D$34*(1+Assumptions!$D$36)^1 -> 0 | ... Y23: =Assumptions!$D$34*(1+Assumptions!$D$36)^1 -> 0 | Z23: =Assumptions!$D$34*(1+Assumptions!$D$36)^2 -> 0 | AA23: =Assumptions!$D$34*(1+Assumptions!$D$36)^2 -> 0 | AB23: =Assumptions!$D$34*(1+Assumptions!$D$36)^2 -> 0 | AC23: =Assumptions!$D$34*(1+Assumptions!$D$36)^2 -> 0 | AD23: =Assumptions!$D$34*(1+Assumptions!$D$36)^2 -> 0 | AE23: =Assumptions!$D$34*(1+Assumptions!$D$36)^2 -> 0 | AF23: =Assumptions!$D$34*(1+Assumptions!$D$36)^2 -> 0 | AG23: =Assumptions!$D$34*(1+Assumptions!$D$36)^2 -> 0 | ... AK23: =Assumptions!$D$34*(1+Assumptions!$D$36)^2 -> 0 | AL23: =Assumptions!$D$34*(1+Assumptions!$D$36)^3 -> 0 | AM23: =Assumptions!$D$34*(1+Assumptions!$D$36)^3 -> 0 | AN23: =Assumptions!$D$34*(1+Assumptions!$D$36)^3 -> 0 | AO23: =Assumptions!$D$34*(1+Assumptions!$D$36)^3 -> 0 | AP23: =Assumptions!$D$34*(1+Assumptions!$D$36)^3 -> 0 | AQ23: =Assumptions!$D$34*(1+Assumptions!$D$36)^3 -> 0 | AR23: =Assumptions!$D$34*(1+Assumptions!$D$36)^3 -> 0 | AS23: =Assumptions!$D$34*(1+Assumptions!$D$36)^3 -> 0 | ... AW23: =Assumptions!$D$34*(1+Assumptions!$D$36)^3 -> 0 | AX23: =Assumptions!$D$34*(1+Assumptions!$D$36)^4 -> 0 | AY23: =Assumptions!$D$34*(1+Assumptions!$D$36)^4 -> 0 | AZ23: =Assumptions!$D$34*(1+Assumptions!$D$36)^4 -> 0 | BA23: =Assumptions!$D$34*(1+Assumptions!$D$36)^4 -> 0 | BB23: =Assumptions!$D$34*(1+Assumptions!$D$36)^4 -> 0 | BC23: =Assumptions!$D$34*(1+Assumptions!$D$36)^4 -> 0 | BD23: =Assumptions!$D$34*(1+Assumptions!$D$36)^4 -> 0 | BE23: =Assumptions!$D$34*(1+Assumptions!$D$36)^4 -> 0 | ... BI23: =Assumptions!$D$34*(1+Assumptions!$D$36)^4 -> 0
A24: Other Operating Expenses | B24: =Assumptions!$D$35*(1+Assumptions!$D$36)^0 -> 0 | C24: =Assumptions!$D$35*(1+Assumptions!$D$36)^0 -> 0 | D24: =Assumptions!$D$35*(1+Assumptions!$D$36)^0 -> 0 | E24: =Assumptions!$D$35*(1+Assumptions!$D$36)^0 -> 0 | F24: =Assumptions!$D$35*(1+Assumptions!$D$36)^0 -> 0 | G24: =Assumptions!$D$35*(1+Assumptions!$D$36)^0 -> 0 | H24: =Assumptions!$D$35*(1+Assumptions!$D$36)^0 -> 0 | I24: =Assumptions!$D$35*(1+Assumptions!$D$36)^0 -> 0 | ... M24: =Assumptions!$D$35*(1+Assumptions!$D$36)^0 -> 0 | N24: =Assumptions!$D$35*(1+Assumptions!$D$36)^1 -> 0 | O24: =Assumptions!$D$35*(1+Assumptions!$D$36)^1 -> 0 | P24: =Assumptions!$D$35*(1+Assumptions!$D$36)^1 -> 0 | Q24: =Assumptions!$D$35*(1+Assumptions!$D$36)^1 -> 0 | R24: =Assumptions!$D$35*(1+Assumptions!$D$36)^1 -> 0 | S24: =Assumptions!$D$35*(1+Assumptions!$D$36)^1 -> 0 | T24: =Assumptions!$D$35*(1+Assumptions!$D$36)^1 -> 0 | U24: =Assumptions!$D$35*(1+Assumptions!$D$36)^1 -> 0 | ... Y24: =Assumptions!$D$35*(1+Assumptions!$D$36)^1 -> 0 | Z24: =Assumptions!$D$35*(1+Assumptions!$D$36)^2 -> 0 | AA24: =Assumptions!$D$35*(1+Assumptions!$D$36)^2 -> 0 | AB24: =Assumptions!$D$35*(1+Assumptions!$D$36)^2 -> 0 | AC24: =Assumptions!$D$35*(1+Assumptions!$D$36)^2 -> 0 | AD24: =Assumptions!$D$35*(1+Assumptions!$D$36)^2 -> 0 | AE24: =Assumptions!$D$35*(1+Assumptions!$D$36)^2 -> 0 | AF24: =Assumptions!$D$35*(1+Assumptions!$D$36)^2 -> 0 | AG24: =Assumptions!$D$35*(1+Assumptions!$D$36)^2 -> 0 | ... AK24: =Assumptions!$D$35*(1+Assumptions!$D$36)^2 -> 0 | AL24: =Assumptions!$D$35*(1+Assumptions!$D$36)^3 -> 0 | AM24: =Assumptions!$D$35*(1+Assumptions!$D$36)^3 -> 0 | AN24: =Assumptions!$D$35*(1+Assumptions!$D$36)^3 -> 0 | AO24: =Assumptions!$D$35*(1+Assumptions!$D$36)^3 -> 0 | AP24: =Assumptions!$D$35*(1+Assumptions!$D$36)^3 -> 0 | AQ24: =Assumptions!$D$35*(1+Assumptions!$D$36)^3 -> 0 | AR24: =Assumptions!$D$35*(1+Assumptions!$D$36)^3 -> 0 | AS24: =Assumptions!$D$35*(1+Assumptions!$D$36)^3 -> 0 | ... AW24: =Assumptions!$D$35*(1+Assumptions!$D$36)^3 -> 0 | AX24: =Assumptions!$D$35*(1+Assumptions!$D$36)^4 -> 0 | AY24: =Assumptions!$D$35*(1+Assumptions!$D$36)^4 -> 0 | AZ24: =Assumptions!$D$35*(1+Assumptions!$D$36)^4 -> 0 | BA24: =Assumptions!$D$35*(1+Assumptions!$D$36)^4 -> 0 | BB24: =Assumptions!$D$35*(1+Assumptions!$D$36)^4 -> 0 | BC24: =Assumptions!$D$35*(1+Assumptions!$D$36)^4 -> 0 | BD24: =Assumptions!$D$35*(1+Assumptions!$D$36)^4 -> 0 | BE24: =Assumptions!$D$35*(1+Assumptions!$D$36)^4 -> 0 | ... BI24: =Assumptions!$D$35*(1+Assumptions!$D$36)^4 -> 0
A25: Total Operating Expenses | B25: =SUM(B19:B24) -> 0 | C25: =SUM(C19:C24) -> 0 | D25: =SUM(D19:D24) -> 0 | E25: =SUM(E19:E24) -> 0 | F25: =SUM(F19:F24) -> 0 | G25: =SUM(G19:G24) -> 0 | H25: =SUM(H19:H24) -> 0 | I25: =SUM(I19:I24) -> 0 | ... BI25: =SUM(BI19:BI24) -> 0
A26: C. DEPRECIATION & FINANCE COST
A27: Depreciation | B27: =(Assumptions!$D$46*Assumptions!$D$52+Assumptions!$D$47*Assumptions!$D$53+Assumptions!$D$48*Assumptions!$D$54+Assumptions!$D$49*Assumptions!$D$55)/12+IFERROR(Assumptions!$D$50/(Assumptions!$D$56*12),0) -> 0 | C27: =(Assumptions!$D$46*Assumptions!$D$52+Assumptions!$D$47*Assumptions!$D$53+Assumptions!$D$48*Assumptions!$D$54+Assumptions!$D$49*Assumptions!$D$55)/12+IFERROR(Assumptions!$D$50/(Assumptions!$D$56*12),0) -> 0 | D27: =(Assumptions!$D$46*Assumptions!$D$52+Assumptions!$D$47*Assumptions!$D$53+Assumptions!$D$48*Assumptions!$D$54+Assumptions!$D$49*Assumptions!$D$55)/12+IFERROR(Assumptions!$D$50/(Assumptions!$D$56*12),0) -> 0 | E27: =(Assumptions!$D$46*Assumptions!$D$52+Assumptions!$D$47*Assumptions!$D$53+Assumptions!$D$48*Assumptions!$D$54+Assumptions!$D$49*Assumptions!$D$55)/12+IFERROR(Assumptions!$D$50/(Assumptions!$D$56*12),0) -> 0 | F27: =(Assumptions!$D$46*Assumptions!$D$52+Assumptions!$D$47*Assumptions!$D$53+Assumptions!$D$48*Assumptions!$D$54+Assumptions!$D$49*Assumptions!$D$55)/12+IFERROR(Assumptions!$D$50/(Assumptions!$D$56*12),0) -> 0 | G27: =(Assumptions!$D$46*Assumptions!$D$52+Assumptions!$D$47*Assumptions!$D$53+Assumptions!$D$48*Assumptions!$D$54+Assumptions!$D$49*Assumptions!$D$55)/12+IFERROR(Assumptions!$D$50/(Assumptions!$D$56*12),0) -> 0 | H27: =(Assumptions!$D$46*Assumptions!$D$52+Assumptions!$D$47*Assumptions!$D$53+Assumptions!$D$48*Assumptions!$D$54+Assumptions!$D$49*Assumptions!$D$55)/12+IFERROR(Assumptions!$D$50/(Assumptions!$D$56*12),0) -> 0 | I27: =(Assumptions!$D$46*Assumptions!$D$52+Assumptions!$D$47*Assumptions!$D$53+Assumptions!$D$48*Assumptions!$D$54+Assumptions!$D$49*Assumptions!$D$55)/12+IFERROR(Assumptions!$D$50/(Assumptions!$D$56*12),0) -> 0 | ... BI27: =(Assumptions!$D$46*Assumptions!$D$52+Assumptions!$D$47*Assumptions!$D$53+Assumptions!$D$48*Assumptions!$D$54+Assumptions!$D$49*Assumptions!$D$55)/12+IFERROR(Assumptions!$D$50/(Assumptions!$D$56*12),0) -> 0
A28: Interest on Term Loan | B28: =B32 -> 0 | C28: =C32 -> 0 | D28: =D32 -> 0 | E28: =E32 -> 0 | F28: =F32 -> 0 | G28: =G32 -> 0 | H28: =H32 -> 0 | I28: =I32 -> 0 | ... BI28: =BI32 -> 0
A30: D. TERM-LOAN AMORTISATION SCHEDULE
A31: Opening Loan Balance | B31: =Assumptions!$D$60 -> 0 | C31: =B34 -> 0 | D31: =C34 -> 0 | E31: =D34 -> 0 | F31: =E34 -> 0 | G31: =F34 -> 0 | H31: =G34 -> 0 | I31: =H34 -> 0 | J31: =I34 -> 0 | ... BI31: =BH34 -> 0
A32: Interest | B32: =B31*Assumptions!$D$42/12 -> 0 | C32: =C31*Assumptions!$D$42/12 -> 0 | D32: =D31*Assumptions!$D$42/12 -> 0 | E32: =E31*Assumptions!$D$42/12 -> 0 | F32: =F31*Assumptions!$D$42/12 -> 0 | G32: =G31*Assumptions!$D$42/12 -> 0 | H32: =H31*Assumptions!$D$42/12 -> 0 | I32: =I31*Assumptions!$D$42/12 -> 0 | ... BI32: =BI31*Assumptions!$D$42/12 -> 0
A33: Principal Repayment | B33: =MIN(B31,IFERROR(Assumptions!$D$60/(Assumptions!$D$43*12),0)) -> 0 | C33: =MIN(C31,IFERROR(Assumptions!$D$60/(Assumptions!$D$43*12),0)) -> 0 | D33: =MIN(D31,IFERROR(Assumptions!$D$60/(Assumptions!$D$43*12),0)) -> 0 | E33: =MIN(E31,IFERROR(Assumptions!$D$60/(Assumptions!$D$43*12),0)) -> 0 | F33: =MIN(F31,IFERROR(Assumptions!$D$60/(Assumptions!$D$43*12),0)) -> 0 | G33: =MIN(G31,IFERROR(Assumptions!$D$60/(Assumptions!$D$43*12),0)) -> 0 | H33: =MIN(H31,IFERROR(Assumptions!$D$60/(Assumptions!$D$43*12),0)) -> 0 | I33: =MIN(I31,IFERROR(Assumptions!$D$60/(Assumptions!$D$43*12),0)) -> 0 | ... BI33: =MIN(BI31,IFERROR(Assumptions!$D$60/(Assumptions!$D$43*12),0)) -> 0
A34: Closing Loan Balance | B34: =B31-B33 -> 0 | C34: =C31-C33 -> 0 | D34: =D31-D33 -> 0 | E34: =E31-E33 -> 0 | F34: =F31-F33 -> 0 | G34: =G31-G33 -> 0 | H34: =H31-H33 -> 0 | I34: =I31-I33 -> 0 | ... BI34: =BI31-BI33 -> 0

Sheet P&L
A1: PROFIT & LOSS (Monthly)
A2: Automatically consolidates Sales and Expenses into monthly profitability.
B4: YEAR 1 | N4: YEAR 2 | Z4: YEAR 3 | AL4: YEAR 4 | AX4: YEAR 5
A5: Line item / Month | B5: M1 | C5: M2 | D5: M3 | E5: M4 | F5: M5 | G5: M6 | H5: M7 | I5: M8 | J5: M9 | K5: M10 | L5: M11 | M5: M12 | N5: M13 | O5: M14 | P5: M15 | Q5: M16 | R5: M17 | S5: M18 | T5: M19 | U5: M20 | V5: M21 | W5: M22 | X5: M23 | Y5: M24 | Z5: M25 | AA5: M26 | AB5: M27 | AC5: M28 | AD5: M29 | AE5: M30 | AF5: M31 | AG5: M32 | AH5: M33 | AI5: M34 | AJ5: M35 | AK5: M36 | AL5: M37 | AM5: M38 | AN5: M39 | AO5: M40 | AP5: M41 | AQ5: M42 | AR5: M43 | AS5: M44 | AT5: M45 | AU5: M46 | AV5: M47 | AW5: M48 | AX5: M49 | AY5: M50 | AZ5: M51 | BA5: M52 | BB5: M53 | BC5: M54 | BD5: M55 | BE5: M56 | BF5: M57 | BG5: M58 | BH5: M59 | BI5: M60
A6: Calendar month | B6: =IFERROR(EDATE(Assumptions!$D$9,0),"") -> 0 | C6: =IFERROR(EDATE(Assumptions!$D$9,1),"") -> 31 | D6: =IFERROR(EDATE(Assumptions!$D$9,2),"") -> 60 | E6: =IFERROR(EDATE(Assumptions!$D$9,3),"") -> 91 | F6: =IFERROR(EDATE(Assumptions!$D$9,4),"") -> 121 | G6: =IFERROR(EDATE(Assumptions!$D$9,5),"") -> 152 | H6: =IFERROR(EDATE(Assumptions!$D$9,6),"") -> 182 | I6: =IFERROR(EDATE(Assumptions!$D$9,7),"") -> 213 | J6: =IFERROR(EDATE(Assumptions!$D$9,8),"") -> 244 | K6: =IFERROR(EDATE(Assumptions!$D$9,9),"") -> 274 | L6: =IFERROR(EDATE(Assumptions!$D$9,10),"") -> 305 | M6: =IFERROR(EDATE(Assumptions!$D$9,11),"") -> 335 | N6: =IFERROR(EDATE(Assumptions!$D$9,12),"") -> 366 | O6: =IFERROR(EDATE(Assumptions!$D$9,13),"") -> 397 | P6: =IFERROR(EDATE(Assumptions!$D$9,14),"") -> 425 | Q6: =IFERROR(EDATE(Assumptions!$D$9,15),"") -> 456 | R6: =IFERROR(EDATE(Assumptions!$D$9,16),"") -> 486 | S6: =IFERROR(EDATE(Assumptions!$D$9,17),"") -> 517 | T6: =IFERROR(EDATE(Assumptions!$D$9,18),"") -> 547 | U6: =IFERROR(EDATE(Assumptions!$D$9,19),"") -> 578 | V6: =IFERROR(EDATE(Assumptions!$D$9,20),"") -> 609 | W6: =IFERROR(EDATE(Assumptions!$D$9,21),"") -> 639 | X6: =IFERROR(EDATE(Assumptions!$D$9,22),"") -> 670 | Y6: =IFERROR(EDATE(Assumptions!$D$9,23),"") -> 700 | Z6: =IFERROR(EDATE(Assumptions!$D$9,24),"") -> 731 | AA6: =IFERROR(EDATE(Assumptions!$D$9,25),"") -> 762 | AB6: =IFERROR(EDATE(Assumptions!$D$9,26),"") -> 790 | AC6: =IFERROR(EDATE(Assumptions!$D$9,27),"") -> 821 | AD6: =IFERROR(EDATE(Assumptions!$D$9,28),"") -> 851 | AE6: =IFERROR(EDATE(Assumptions!$D$9,29),"") -> 882 | AF6: =IFERROR(EDATE(Assumptions!$D$9,30),"") -> 912 | AG6: =IFERROR(EDATE(Assumptions!$D$9,31),"") -> 943 | AH6: =IFERROR(EDATE(Assumptions!$D$9,32),"") -> 974 | AI6: =IFERROR(EDATE(Assumptions!$D$9,33),"") -> 1004 | AJ6: =IFERROR(EDATE(Assumptions!$D$9,34),"") -> 1035 | AK6: =IFERROR(EDATE(Assumptions!$D$9,35),"") -> 1065 | AL6: =IFERROR(EDATE(Assumptions!$D$9,36),"") -> 1096 | AM6: =IFERROR(EDATE(Assumptions!$D$9,37),"") -> 1127 | AN6: =IFERROR(EDATE(Assumptions!$D$9,38),"") -> 1155 | AO6: =IFERROR(EDATE(Assumptions!$D$9,39),"") -> 1186 | AP6: =IFERROR(EDATE(Assumptions!$D$9,40),"") -> 1216 | AQ6: =IFERROR(EDATE(Assumptions!$D$9,41),"") -> 1247 | AR6: =IFERROR(EDATE(Assumptions!$D$9,42),"") -> 1277 | AS6: =IFERROR(EDATE(Assumptions!$D$9,43),"") -> 1308 | AT6: =IFERROR(EDATE(Assumptions!$D$9,44),"") -> 1339 | AU6: =IFERROR(EDATE(Assumptions!$D$9,45),"") -> 1369 | AV6: =IFERROR(EDATE(Assumptions!$D$9,46),"") -> 1400 | AW6: =IFERROR(EDATE(Assumptions!$D$9,47),"") -> 1430 | AX6: =IFERROR(EDATE(Assumptions!$D$9,48),"") -> 1461 | AY6: =IFERROR(EDATE(Assumptions!$D$9,49),"") -> 1492 | AZ6: =IFERROR(EDATE(Assumptions!$D$9,50),"") -> 1521 | BA6: =IFERROR(EDATE(Assumptions!$D$9,51),"") -> 1552 | BB6: =IFERROR(EDATE(Assumptions!$D$9,52),"") -> 1582 | BC6: =IFERROR(EDATE(Assumptions!$D$9,53),"") -> 1613 | BD6: =IFERROR(EDATE(Assumptions!$D$9,54),"") -> 1643 | BE6: =IFERROR(EDATE(Assumptions!$D$9,55),"") -> 1674 | BF6: =IFERROR(EDATE(Assumptions!$D$9,56),"") -> 1705 | BG6: =IFERROR(EDATE(Assumptions!$D$9,57),"") -> 1735 | BH6: =IFERROR(EDATE(Assumptions!$D$9,58),"") -> 1766 | BI6: =IFERROR(EDATE(Assumptions!$D$9,59),"") -> 1796
A7: PROFIT & LOSS STATEMENT
A8: Net Revenue | B8: =Sales!B14 -> 0 | C8: =Sales!C14 -> 0 | D8: =Sales!D14 -> 0 | E8: =Sales!E14 -> 0 | F8: =Sales!F14 -> 0 | G8: =Sales!G14 -> 0 | H8: =Sales!H14 -> 0 | I8: =Sales!I14 -> 0 | ... BI8: =Sales!BI14 -> 0
A9: Less: Cost of Goods Sold | B9: =Expenses!B17 -> 0 | C9: =Expenses!C17 -> 0 | D9: =Expenses!D17 -> 0 | E9: =Expenses!E17 -> 0 | F9: =Expenses!F17 -> 0 | G9: =Expenses!G17 -> 0 | H9: =Expenses!H17 -> 0 | I9: =Expenses!I17 -> 0 | ... BI9: =Expenses!BI17 -> 0
A10: Gross Profit | B10: =B8-B9 -> 0 | C10: =C8-C9 -> 0 | D10: =D8-D9 -> 0 | E10: =E8-E9 -> 0 | F10: =F8-F9 -> 0 | G10: =G8-G9 -> 0 | H10: =H8-H9 -> 0 | I10: =I8-I9 -> 0 | ... BI10: =BI8-BI9 -> 0
A11: Gross Margin (%) | B11: =IFERROR(B10/B8,0) -> 0 | C11: =IFERROR(C10/C8,0) -> 0 | D11: =IFERROR(D10/D8,0) -> 0 | E11: =IFERROR(E10/E8,0) -> 0 | F11: =IFERROR(F10/F8,0) -> 0 | G11: =IFERROR(G10/G8,0) -> 0 | H11: =IFERROR(H10/H8,0) -> 0 | I11: =IFERROR(I10/I8,0) -> 0 | ... BI11: =IFERROR(BI10/BI8,0) -> 0
A12: Less: Operating Expenses (SG&A) | B12: =Expenses!B25 -> 0 | C12: =Expenses!C25 -> 0 | D12: =Expenses!D25 -> 0 | E12: =Expenses!E25 -> 0 | F12: =Expenses!F25 -> 0 | G12: =Expenses!G25 -> 0 | H12: =Expenses!H25 -> 0 | I12: =Expenses!I25 -> 0 | ... BI12: =Expenses!BI25 -> 0
A13: EBITDA | B13: =B10-B12 -> 0 | C13: =C10-C12 -> 0 | D13: =D10-D12 -> 0 | E13: =E10-E12 -> 0 | F13: =F10-F12 -> 0 | G13: =G10-G12 -> 0 | H13: =H10-H12 -> 0 | I13: =I10-I12 -> 0 | ... BI13: =BI10-BI12 -> 0
A14: EBITDA Margin (%) | B14: =IFERROR(B13/B8,0) -> 0 | C14: =IFERROR(C13/C8,0) -> 0 | D14: =IFERROR(D13/D8,0) -> 0 | E14: =IFERROR(E13/E8,0) -> 0 | F14: =IFERROR(F13/F8,0) -> 0 | G14: =IFERROR(G13/G8,0) -> 0 | H14: =IFERROR(H13/H8,0) -> 0 | I14: =IFERROR(I13/I8,0) -> 0 | ... BI14: =IFERROR(BI13/BI8,0) -> 0
A15: Less: Depreciation | B15: =Expenses!B27 -> 0 | C15: =Expenses!C27 -> 0 | D15: =Expenses!D27 -> 0 | E15: =Expenses!E27 -> 0 | F15: =Expenses!F27 -> 0 | G15: =Expenses!G27 -> 0 | H15: =Expenses!H27 -> 0 | I15: =Expenses!I27 -> 0 | ... BI15: =Expenses!BI27 -> 0
A16: EBIT | B16: =B13-B15 -> 0 | C16: =C13-C15 -> 0 | D16: =D13-D15 -> 0 | E16: =E13-E15 -> 0 | F16: =F13-F15 -> 0 | G16: =G13-G15 -> 0 | H16: =H13-H15 -> 0 | I16: =I13-I15 -> 0 | ... BI16: =BI13-BI15 -> 0
A17: Less: Interest | B17: =Expenses!B28 -> 0 | C17: =Expenses!C28 -> 0 | D17: =Expenses!D28 -> 0 | E17: =Expenses!E28 -> 0 | F17: =Expenses!F28 -> 0 | G17: =Expenses!G28 -> 0 | H17: =Expenses!H28 -> 0 | I17: =Expenses!I28 -> 0 | ... BI17: =Expenses!BI28 -> 0
A18: Profit Before Tax | B18: =B16-B17 -> 0 | C18: =C16-C17 -> 0 | D18: =D16-D17 -> 0 | E18: =E16-E17 -> 0 | F18: =F16-F17 -> 0 | G18: =G16-G17 -> 0 | H18: =H16-H17 -> 0 | I18: =I16-I17 -> 0 | ... BI18: =BI16-BI17 -> 0
A19: Less: Tax | B19: =MAX(0,B18)*Assumptions!$D$44 -> 0 | C19: =MAX(0,C18)*Assumptions!$D$44 -> 0 | D19: =MAX(0,D18)*Assumptions!$D$44 -> 0 | E19: =MAX(0,E18)*Assumptions!$D$44 -> 0 | F19: =MAX(0,F18)*Assumptions!$D$44 -> 0 | G19: =MAX(0,G18)*Assumptions!$D$44 -> 0 | H19: =MAX(0,H18)*Assumptions!$D$44 -> 0 | I19: =MAX(0,I18)*Assumptions!$D$44 -> 0 | ... BI19: =MAX(0,BI18)*Assumptions!$D$44 -> 0
A20: Profit After Tax (PAT) | B20: =B18-B19 -> 0 | C20: =C18-C19 -> 0 | D20: =D18-D19 -> 0 | E20: =E18-E19 -> 0 | F20: =F18-F19 -> 0 | G20: =G18-G19 -> 0 | H20: =H18-H19 -> 0 | I20: =I18-I19 -> 0 | ... BI20: =BI18-BI19 -> 0
A21: Net Margin (%) | B21: =IFERROR(B20/B8,0) -> 0 | C21: =IFERROR(C20/C8,0) -> 0 | D21: =IFERROR(D20/D8,0) -> 0 | E21: =IFERROR(E20/E8,0) -> 0 | F21: =IFERROR(F20/F8,0) -> 0 | G21: =IFERROR(G20/G8,0) -> 0 | H21: =IFERROR(H20/H8,0) -> 0 | I21: =IFERROR(I20/I8,0) -> 0 | ... BI21: =IFERROR(BI20/BI8,0) -> 0
A22: Cumulative PAT | B22: =B20 -> 0 | C22: =B22+C20 -> 0 | D22: =C22+D20 -> 0 | E22: =D22+E20 -> 0 | F22: =E22+F20 -> 0 | G22: =F22+G20 -> 0 | H22: =G22+H20 -> 0 | I22: =H22+I20 -> 0 | J22: =I22+J20 -> 0 | ... BI22: =BH22+BI20 -> 0

Sheet Cash Flow
A1: CASH FLOW (Monthly)
A2: Operating, investing and financing cash flows with a simple working-capital model.
B4: YEAR 1 | N4: YEAR 2 | Z4: YEAR 3 | AL4: YEAR 4 | AX4: YEAR 5
A5: Line item / Month | B5: M1 | C5: M2 | D5: M3 | E5: M4 | F5: M5 | G5: M6 | H5: M7 | I5: M8 | J5: M9 | K5: M10 | L5: M11 | M5: M12 | N5: M13 | O5: M14 | P5: M15 | Q5: M16 | R5: M17 | S5: M18 | T5: M19 | U5: M20 | V5: M21 | W5: M22 | X5: M23 | Y5: M24 | Z5: M25 | AA5: M26 | AB5: M27 | AC5: M28 | AD5: M29 | AE5: M30 | AF5: M31 | AG5: M32 | AH5: M33 | AI5: M34 | AJ5: M35 | AK5: M36 | AL5: M37 | AM5: M38 | AN5: M39 | AO5: M40 | AP5: M41 | AQ5: M42 | AR5: M43 | AS5: M44 | AT5: M45 | AU5: M46 | AV5: M47 | AW5: M48 | AX5: M49 | AY5: M50 | AZ5: M51 | BA5: M52 | BB5: M53 | BC5: M54 | BD5: M55 | BE5: M56 | BF5: M57 | BG5: M58 | BH5: M59 | BI5: M60
A6: Calendar month | B6: =IFERROR(EDATE(Assumptions!$D$9,0),"") -> 0 | C6: =IFERROR(EDATE(Assumptions!$D$9,1),"") -> 31 | D6: =IFERROR(EDATE(Assumptions!$D$9,2),"") -> 60 | E6: =IFERROR(EDATE(Assumptions!$D$9,3),"") -> 91 | F6: =IFERROR(EDATE(Assumptions!$D$9,4),"") -> 121 | G6: =IFERROR(EDATE(Assumptions!$D$9,5),"") -> 152 | H6: =IFERROR(EDATE(Assumptions!$D$9,6),"") -> 182 | I6: =IFERROR(EDATE(Assumptions!$D$9,7),"") -> 213 | J6: =IFERROR(EDATE(Assumptions!$D$9,8),"") -> 244 | K6: =IFERROR(EDATE(Assumptions!$D$9,9),"") -> 274 | L6: =IFERROR(EDATE(Assumptions!$D$9,10),"") -> 305 | M6: =IFERROR(EDATE(Assumptions!$D$9,11),"") -> 335 | N6: =IFERROR(EDATE(Assumptions!$D$9,12),"") -> 366 | O6: =IFERROR(EDATE(Assumptions!$D$9,13),"") -> 397 | P6: =IFERROR(EDATE(Assumptions!$D$9,14),"") -> 425 | Q6: =IFERROR(EDATE(Assumptions!$D$9,15),"") -> 456 | R6: =IFERROR(EDATE(Assumptions!$D$9,16),"") -> 486 | S6: =IFERROR(EDATE(Assumptions!$D$9,17),"") -> 517 | T6: =IFERROR(EDATE(Assumptions!$D$9,18),"") -> 547 | U6: =IFERROR(EDATE(Assumptions!$D$9,19),"") -> 578 | V6: =IFERROR(EDATE(Assumptions!$D$9,20),"") -> 609 | W6: =IFERROR(EDATE(Assumptions!$D$9,21),"") -> 639 | X6: =IFERROR(EDATE(Assumptions!$D$9,22),"") -> 670 | Y6: =IFERROR(EDATE(Assumptions!$D$9,23),"") -> 700 | Z6: =IFERROR(EDATE(Assumptions!$D$9,24),"") -> 731 | AA6: =IFERROR(EDATE(Assumptions!$D$9,25),"") -> 762 | AB6: =IFERROR(EDATE(Assumptions!$D$9,26),"") -> 790 | AC6: =IFERROR(EDATE(Assumptions!$D$9,27),"") -> 821 | AD6: =IFERROR(EDATE(Assumptions!$D$9,28),"") -> 851 | AE6: =IFERROR(EDATE(Assumptions!$D$9,29),"") -> 882 | AF6: =IFERROR(EDATE(Assumptions!$D$9,30),"") -> 912 | AG6: =IFERROR(EDATE(Assumptions!$D$9,31),"") -> 943 | AH6: =IFERROR(EDATE(Assumptions!$D$9,32),"") -> 974 | AI6: =IFERROR(EDATE(Assumptions!$D$9,33),"") -> 1004 | AJ6: =IFERROR(EDATE(Assumptions!$D$9,34),"") -> 1035 | AK6: =IFERROR(EDATE(Assumptions!$D$9,35),"") -> 1065 | AL6: =IFERROR(EDATE(Assumptions!$D$9,36),"") -> 1096 | AM6: =IFERROR(EDATE(Assumptions!$D$9,37),"") -> 1127 | AN6: =IFERROR(EDATE(Assumptions!$D$9,38),"") -> 1155 | AO6: =IFERROR(EDATE(Assumptions!$D$9,39),"") -> 1186 | AP6: =IFERROR(EDATE(Assumptions!$D$9,40),"") -> 1216 | AQ6: =IFERROR(EDATE(Assumptions!$D$9,41),"") -> 1247 | AR6: =IFERROR(EDATE(Assumptions!$D$9,42),"") -> 1277 | AS6: =IFERROR(EDATE(Assumptions!$D$9,43),"") -> 1308 | AT6: =IFERROR(EDATE(Assumptions!$D$9,44),"") -> 1339 | AU6: =IFERROR(EDATE(Assumptions!$D$9,45),"") -> 1369 | AV6: =IFERROR(EDATE(Assumptions!$D$9,46),"") -> 1400 | AW6: =IFERROR(EDATE(Assumptions!$D$9,47),"") -> 1430 | AX6: =IFERROR(EDATE(Assumptions!$D$9,48),"") -> 1461 | AY6: =IFERROR(EDATE(Assumptions!$D$9,49),"") -> 1492 | AZ6: =IFERROR(EDATE(Assumptions!$D$9,50),"") -> 1521 | BA6: =IFERROR(EDATE(Assumptions!$D$9,51),"") -> 1552 | BB6: =IFERROR(EDATE(Assumptions!$D$9,52),"") -> 1582 | BC6: =IFERROR(EDATE(Assumptions!$D$9,53),"") -> 1613 | BD6: =IFERROR(EDATE(Assumptions!$D$9,54),"") -> 1643 | BE6: =IFERROR(EDATE(Assumptions!$D$9,55),"") -> 1674 | BF6: =IFERROR(EDATE(Assumptions!$D$9,56),"") -> 1705 | BG6: =IFERROR(EDATE(Assumptions!$D$9,57),"") -> 1735 | BH6: =IFERROR(EDATE(Assumptions!$D$9,58),"") -> 1766 | BI6: =IFERROR(EDATE(Assumptions!$D$9,59),"") -> 1796
A7: A. OPERATING CASH FLOW
A8: Profit After Tax | B8: ='P&L'!B20 -> 0 | C8: ='P&L'!C20 -> 0 | D8: ='P&L'!D20 -> 0 | E8: ='P&L'!E20 -> 0 | F8: ='P&L'!F20 -> 0 | G8: ='P&L'!G20 -> 0 | H8: ='P&L'!H20 -> 0 | I8: ='P&L'!I20 -> 0 | ... BI8: ='P&L'!BI20 -> 0
A9: Add: Depreciation | B9: ='P&L'!B15 -> 0 | C9: ='P&L'!C15 -> 0 | D9: ='P&L'!D15 -> 0 | E9: ='P&L'!E15 -> 0 | F9: ='P&L'!F15 -> 0 | G9: ='P&L'!G15 -> 0 | H9: ='P&L'!H15 -> 0 | I9: ='P&L'!I15 -> 0 | ... BI9: ='P&L'!BI15 -> 0
A10: Debtors / Receivables (balance) | B10: =Sales!B14*Assumptions!$D$38/30 -> 0 | C10: =Sales!C14*Assumptions!$D$38/30 -> 0 | D10: =Sales!D14*Assumptions!$D$38/30 -> 0 | E10: =Sales!E14*Assumptions!$D$38/30 -> 0 | F10: =Sales!F14*Assumptions!$D$38/30 -> 0 | G10: =Sales!G14*Assumptions!$D$38/30 -> 0 | H10: =Sales!H14*Assumptions!$D$38/30 -> 0 | I10: =Sales!I14*Assumptions!$D$38/30 -> 0 | ... BI10: =Sales!BI14*Assumptions!$D$38/30 -> 0
A11: Inventory (balance) | B11: =Expenses!B17*Assumptions!$D$39/30 -> 0 | C11: =Expenses!C17*Assumptions!$D$39/30 -> 0 | D11: =Expenses!D17*Assumptions!$D$39/30 -> 0 | E11: =Expenses!E17*Assumptions!$D$39/30 -> 0 | F11: =Expenses!F17*Assumptions!$D$39/30 -> 0 | G11: =Expenses!G17*Assumptions!$D$39/30 -> 0 | H11: =Expenses!H17*Assumptions!$D$39/30 -> 0 | I11: =Expenses!I17*Assumptions!$D$39/30 -> 0 | ... BI11: =Expenses!BI17*Assumptions!$D$39/30 -> 0
A12: Creditors / Payables (balance) | B12: =Expenses!B17*Assumptions!$D$40/30 -> 0 | C12: =Expenses!C17*Assumptions!$D$40/30 -> 0 | D12: =Expenses!D17*Assumptions!$D$40/30 -> 0 | E12: =Expenses!E17*Assumptions!$D$40/30 -> 0 | F12: =Expenses!F17*Assumptions!$D$40/30 -> 0 | G12: =Expenses!G17*Assumptions!$D$40/30 -> 0 | H12: =Expenses!H17*Assumptions!$D$40/30 -> 0 | I12: =Expenses!I17*Assumptions!$D$40/30 -> 0 | ... BI12: =Expenses!BI17*Assumptions!$D$40/30 -> 0
A13: Net Working Capital | B13: =B10+B11-B12 -> 0 | C13: =C10+C11-C12 -> 0 | D13: =D10+D11-D12 -> 0 | E13: =E10+E11-E12 -> 0 | F13: =F10+F11-F12 -> 0 | G13: =G10+G11-G12 -> 0 | H13: =H10+H11-H12 -> 0 | I13: =I10+I11-I12 -> 0 | ... BI13: =BI10+BI11-BI12 -> 0
A14: Less: Increase in Working Capital | B14: =B13 -> 0 | C14: =C13-B13 -> 0 | D14: =D13-C13 -> 0 | E14: =E13-D13 -> 0 | F14: =F13-E13 -> 0 | G14: =G13-F13 -> 0 | H14: =H13-G13 -> 0 | I14: =I13-H13 -> 0 | J14: =J13-I13 -> 0 | ... BI14: =BI13-BH13 -> 0
A15: Cash Flow from Operations | B15: =B8+B9-B14 -> 0 | C15: =C8+C9-C14 -> 0 | D15: =D8+D9-D14 -> 0 | E15: =E8+E9-E14 -> 0 | F15: =F8+F9-F14 -> 0 | G15: =G8+G9-G14 -> 0 | H15: =H8+H9-H14 -> 0 | I15: =I8+I9-I14 -> 0 | ... BI15: =BI8+BI9-BI14 -> 0
A16: B. INVESTING & FINANCING
A17: Capital Expenditure | B17: =-(Assumptions!$D$46+Assumptions!$D$47+Assumptions!$D$48+Assumptions!$D$49)*(1+Assumptions!$D$51)+Assumptions!$D$50 -> 0 | C17: =0 -> 0 | D17: =0 -> 0 | E17: =0 -> 0 | F17: =0 -> 0 | G17: =0 -> 0 | H17: =0 -> 0 | I17: =0 -> 0 | J17: =0 -> 0 | ... BI17: =0 -> 0
A18: Loan Principal Repayment | B18: =-Expenses!B33 -> 0 | C18: =-Expenses!C33 -> 0 | D18: =-Expenses!D33 -> 0 | E18: =-Expenses!E33 -> 0 | F18: =-Expenses!F33 -> 0 | G18: =-Expenses!G33 -> 0 | H18: =-Expenses!H33 -> 0 | I18: =-Expenses!I33 -> 0 | ... BI18: =-Expenses!BI33 -> 0
A19: Equity Inflow | B19: =Assumptions!$D$58+Assumptions!$D$59 -> 0 | C19: =0 -> 0 | D19: =0 -> 0 | E19: =0 -> 0 | F19: =0 -> 0 | G19: =0 -> 0 | H19: =0 -> 0 | I19: =0 -> 0 | J19: =0 -> 0 | ... BI19: =0 -> 0
A20: Debt Inflow | B20: =Assumptions!$D$60 -> 0 | C20: =0 -> 0 | D20: =0 -> 0 | E20: =0 -> 0 | F20: =0 -> 0 | G20: =0 -> 0 | H20: =0 -> 0 | I20: =0 -> 0 | J20: =0 -> 0 | ... BI20: =0 -> 0
A21: Net Cash Flow | B21: =B15+B17+B18+B19+B20 -> 0 | C21: =C15+C17+C18+C19+C20 -> 0 | D21: =D15+D17+D18+D19+D20 -> 0 | E21: =E15+E17+E18+E19+E20 -> 0 | F21: =F15+F17+F18+F19+F20 -> 0 | G21: =G15+G17+G18+G19+G20 -> 0 | H21: =H15+H17+H18+H19+H20 -> 0 | I21: =I15+I17+I18+I19+I20 -> 0 | ... BI21: =BI15+BI17+BI18+BI19+BI20 -> 0
A22: C. CASH POSITION
A23: Opening Cash | B23: =0 -> 0 | C23: =B24 -> 0 | D23: =C24 -> 0 | E23: =D24 -> 0 | F23: =E24 -> 0 | G23: =F24 -> 0 | H23: =G24 -> 0 | I23: =H24 -> 0 | J23: =I24 -> 0 | ... BI23: =BH24 -> 0
A24: Closing Cash | B24: =B23+B21 -> 0 | C24: =C23+C21 -> 0 | D24: =D23+D21 -> 0 | E24: =E23+E21 -> 0 | F24: =F23+F21 -> 0 | G24: =G23+G21 -> 0 | H24: =H23+H21 -> 0 | I24: =I23+I21 -> 0 | ... BI24: =BI23+BI21 -> 0

Sheet Annual Summary
A1: ANNUAL SUMMARY
A2: Monthly results rolled up to the financial year. All figures in ₹.
B4: Particulars | C4: Year 1 | D4: Year 2 | E4: Year 3 | F4: Year 4 | G4: Year 5 | H4: 5-Yr Total
B5: Installed Capacity (units/mo, avg) | C5: =AVERAGE(Production!B8:M8) -> 0 | D5: =AVERAGE(Production!N8:Y8) -> 0 | E5: =AVERAGE(Production!Z8:AK8) -> 0 | F5: =AVERAGE(Production!AL8:AW8) -> 0 | G5: =AVERAGE(Production!AX8:BI8) -> 0 | H5: =AVERAGE(C5:G5) -> 0
B6: Capacity Utilisation (%, avg) | C6: =IFERROR(AVERAGE(Production!B9:M9),0) -> 0 | D6: =IFERROR(AVERAGE(Production!N9:Y9),0) -> 0 | E6: =IFERROR(AVERAGE(Production!Z9:AK9),0) -> 0 | F6: =IFERROR(AVERAGE(Production!AL9:AW9),0) -> 0 | G6: =IFERROR(AVERAGE(Production!AX9:BI9),0) -> 0 | H6: =IFERROR(AVERAGE(C6:G6),0) -> 0
B7: Saleable Production (units) | C7: =SUM(Production!B12:M12) -> 0 | D7: =SUM(Production!N12:Y12) -> 0 | E7: =SUM(Production!Z12:AK12) -> 0 | F7: =SUM(Production!AL12:AW12) -> 0 | G7: =SUM(Production!AX12:BI12) -> 0 | H7: =SUM(C7:G7) -> 0
B8: Units Sold | C8: =SUM(Sales!B10:M10) -> 0 | D8: =SUM(Sales!N10:Y10) -> 0 | E8: =SUM(Sales!Z10:AK10) -> 0 | F8: =SUM(Sales!AL10:AW10) -> 0 | G8: =SUM(Sales!AX10:BI10) -> 0 | H8: =SUM(C8:G8) -> 0
B9: Net Revenue | C9: =SUM(Sales!B14:M14) -> 0 | D9: =SUM(Sales!N14:Y14) -> 0 | E9: =SUM(Sales!Z14:AK14) -> 0 | F9: =SUM(Sales!AL14:AW14) -> 0 | G9: =SUM(Sales!AX14:BI14) -> 0 | H9: =SUM(C9:G9) -> 0
B10: Cost of Goods Sold | C10: =SUM(Expenses!B17:M17) -> 0 | D10: =SUM(Expenses!N17:Y17) -> 0 | E10: =SUM(Expenses!Z17:AK17) -> 0 | F10: =SUM(Expenses!AL17:AW17) -> 0 | G10: =SUM(Expenses!AX17:BI17) -> 0 | H10: =SUM(C10:G10) -> 0
B11: Gross Profit | C11: =SUM('P&L'!B10:M10) -> 0 | D11: =SUM('P&L'!N10:Y10) -> 0 | E11: =SUM('P&L'!Z10:AK10) -> 0 | F11: =SUM('P&L'!AL10:AW10) -> 0 | G11: =SUM('P&L'!AX10:BI10) -> 0 | H11: =SUM(C11:G11) -> 0
B12: Gross Margin (%) | C12: =IFERROR(C11/C9,0) -> 0 | D12: =IFERROR(D11/D9,0) -> 0 | E12: =IFERROR(E11/E9,0) -> 0 | F12: =IFERROR(F11/F9,0) -> 0 | G12: =IFERROR(G11/G9,0) -> 0 | H12: =IFERROR(H11/H9,0) -> 0
B13: Operating Expenses | C13: =SUM(Expenses!B25:M25) -> 0 | D13: =SUM(Expenses!N25:Y25) -> 0 | E13: =SUM(Expenses!Z25:AK25) -> 0 | F13: =SUM(Expenses!AL25:AW25) -> 0 | G13: =SUM(Expenses!AX25:BI25) -> 0 | H13: =SUM(C13:G13) -> 0
B14: EBITDA | C14: =SUM('P&L'!B13:M13) -> 0 | D14: =SUM('P&L'!N13:Y13) -> 0 | E14: =SUM('P&L'!Z13:AK13) -> 0 | F14: =SUM('P&L'!AL13:AW13) -> 0 | G14: =SUM('P&L'!AX13:BI13) -> 0 | H14: =SUM(C14:G14) -> 0
B15: EBITDA Margin (%) | C15: =IFERROR(C14/C9,0) -> 0 | D15: =IFERROR(D14/D9,0) -> 0 | E15: =IFERROR(E14/E9,0) -> 0 | F15: =IFERROR(F14/F9,0) -> 0 | G15: =IFERROR(G14/G9,0) -> 0 | H15: =IFERROR(H14/H9,0) -> 0
B16: Depreciation | C16: =SUM('P&L'!B15:M15) -> 0 | D16: =SUM('P&L'!N15:Y15) -> 0 | E16: =SUM('P&L'!Z15:AK15) -> 0 | F16: =SUM('P&L'!AL15:AW15) -> 0 | G16: =SUM('P&L'!AX15:BI15) -> 0 | H16: =SUM(C16:G16) -> 0
B17: EBIT | C17: =SUM('P&L'!B16:M16) -> 0 | D17: =SUM('P&L'!N16:Y16) -> 0 | E17: =SUM('P&L'!Z16:AK16) -> 0 | F17: =SUM('P&L'!AL16:AW16) -> 0 | G17: =SUM('P&L'!AX16:BI16) -> 0 | H17: =SUM(C17:G17) -> 0
B18: Interest | C18: =SUM('P&L'!B17:M17) -> 0 | D18: =SUM('P&L'!N17:Y17) -> 0 | E18: =SUM('P&L'!Z17:AK17) -> 0 | F18: =SUM('P&L'!AL17:AW17) -> 0 | G18: =SUM('P&L'!AX17:BI17) -> 0 | H18: =SUM(C18:G18) -> 0
B19: Profit Before Tax | C19: =SUM('P&L'!B18:M18) -> 0 | D19: =SUM('P&L'!N18:Y18) -> 0 | E19: =SUM('P&L'!Z18:AK18) -> 0 | F19: =SUM('P&L'!AL18:AW18) -> 0 | G19: =SUM('P&L'!AX18:BI18) -> 0 | H19: =SUM(C19:G19) -> 0
B20: Tax | C20: =SUM('P&L'!B19:M19) -> 0 | D20: =SUM('P&L'!N19:Y19) -> 0 | E20: =SUM('P&L'!Z19:AK19) -> 0 | F20: =SUM('P&L'!AL19:AW19) -> 0 | G20: =SUM('P&L'!AX19:BI19) -> 0 | H20: =SUM(C20:G20) -> 0
B21: Profit After Tax (PAT) | C21: =SUM('P&L'!B20:M20) -> 0 | D21: =SUM('P&L'!N20:Y20) -> 0 | E21: =SUM('P&L'!Z20:AK20) -> 0 | F21: =SUM('P&L'!AL20:AW20) -> 0 | G21: =SUM('P&L'!AX20:BI20) -> 0 | H21: =SUM(C21:G21) -> 0
B22: Net Margin (%) | C22: =IFERROR(C21/C9,0) -> 0 | D22: =IFERROR(D21/D9,0) -> 0 | E22: =IFERROR(E21/E9,0) -> 0 | F22: =IFERROR(F21/F9,0) -> 0 | G22: =IFERROR(G21/G9,0) -> 0 | H22: =IFERROR(H21/H9,0) -> 0
B23: Cumulative PAT | C23: =C21 -> 0 | D23: =C23+D21 -> 0 | E23: =D23+E21 -> 0 | F23: =E23+F21 -> 0 | G23: =F23+G21 -> 0 | H23: =G23 -> 0
B24: Operating Cash Flow | C24: =SUM('Cash Flow'!B15:M15) -> 0 | D24: =SUM('Cash Flow'!N15:Y15) -> 0 | E24: =SUM('Cash Flow'!Z15:AK15) -> 0 | F24: =SUM('Cash Flow'!AL15:AW15) -> 0 | G24: =SUM('Cash Flow'!AX15:BI15) -> 0 | H24: =SUM(C24:G24) -> 0
B25: Net Cash Flow | C25: =SUM('Cash Flow'!B21:M21) -> 0 | D25: =SUM('Cash Flow'!N21:Y21) -> 0 | E25: =SUM('Cash Flow'!Z21:AK21) -> 0 | F25: =SUM('Cash Flow'!AL21:AW21) -> 0 | G25: =SUM('Cash Flow'!AX21:BI21) -> 0 | H25: =SUM(C25:G25) -> 0
B26: Closing Cash | C26: ='Cash Flow'!M24 -> 0 | D26: ='Cash Flow'!Y24 -> 0 | E26: ='Cash Flow'!AK24 -> 0 | F26: ='Cash Flow'!AW24 -> 0 | G26: ='Cash Flow'!BI24 -> 0 | H26: =G26 -> 0

Sheet Investment & ROI
A1: INVESTMENT, RETURNS & INVESTOR CASE
A2: Project cost, funding, ROI and the angel-investor return summary. All figures in ₹.
A4: A. PROJECT COST
B5: Land & Building | D5: =Assumptions!$D$46 -> 0
B6: Plant & Machinery | D6: =Assumptions!$D$47 -> 0
B7: Furniture & Fixtures | D7: =Assumptions!$D$48 -> 0
B8: Vehicles | D8: =Assumptions!$D$49 -> 0
B9: Contingency | D9: =(Assumptions!$D$46+Assumptions!$D$47+Assumptions!$D$48+Assumptions!$D$49)*Assumptions!$D$51 -> 0
B10: Preliminary & Pre-operative | D10: =Assumptions!$D$50 -> 0
B11: Initial Working Capital | D11: =IFERROR('Annual Summary'!C9*Assumptions!$D$38/365,0)+IFERROR('Annual Summary'!C10*Assumptions!$D$39/365,0)-IFERROR('Annual Summary'!C10*Assumptions!$D$40/365,0) -> 0
B12: TOTAL PROJECT COST | D12: =SUM(D5:D11) -> 0
A14: B. MEANS OF FINANCE
B15: Promoter's / Founder Equity | D15: =Assumptions!$D$58 -> 0
B16: Angel Investor Investment | D16: =Assumptions!$D$59 -> 0
B17: Term Loan / Debt | D17: =Assumptions!$D$60 -> 0
B18: TOTAL FUNDING | D18: =SUM(D15:D17) -> 0
B19: Funding Surplus / (Gap) | D19: =D18-D12 -> 0
B20: Debt : Equity Ratio | D20: =IFERROR(D17/(D15+D16),0) -> 0
A22: C. RETURNS & FEASIBILITY METRICS
B23: Total PAT (5 years) | D23: ='Annual Summary'!H21 -> 0
B24: Average Annual PAT | D24: =D23/5 -> 0
B25: Average Annual Cash Inflow (PAT+Dep) | D25: =(D23+'Annual Summary'!H16)/5 -> 0
B26: Return on Investment (avg PAT / cost) | D26: =IFERROR(D24/D12,0) -> 0
B27: Return on Equity (avg PAT / equity) | D27: =IFERROR(D24/(D15+D16),0) -> 0
B28: Simple Payback Period | D28: =IFERROR(D12/D25,0) -> 0
B29: Free Cash Flow (Yr0 = -cost) | C29: =-D12 -> 0 | D29: ='Annual Summary'!C21+'Annual Summary'!C16 -> 0 | E29: ='Annual Summary'!D21+'Annual Summary'!D16 -> 0 | F29: ='Annual Summary'!E21+'Annual Summary'!E16 -> 0 | G29: ='Annual Summary'!F21+'Annual Summary'!F16 -> 0 | H29: ='Annual Summary'!G21+'Annual Summary'!G16 -> 0
B30: Net Present Value (NPV) | D30: =IFERROR(C29+NPV(Assumptions!$D$63,D29:H29),0) -> 0
B31: Internal Rate of Return (IRR) | D31: =IFERROR(IRR(C29:H29),0) -> 0
A33: D. ANGEL-INVESTOR RETURN CASE
B34: Angel Investment | D34: =Assumptions!$D$59 -> 0
B35: Equity Stake Offered | D35: =Assumptions!$D$62 -> 0
B36: Implied Post-money Valuation | D36: =IFERROR(D34/D35,0) -> 0
B37: Implied Pre-money Valuation | D37: =D36-D34 -> 0
B38: Planned Exit Year | D38: =Assumptions!$D$64 -> 0
B39: Exit-year EBITDA | D39: =IFERROR(INDEX('Annual Summary'!C14:G14,Assumptions!$D$64),0) -> 0
B40: Exit Enterprise Value (EBITDA x mult.) | D40: =D39*Assumptions!$D$65 -> 0
B41: Less: Net Debt at Exit | D41: =IFERROR(INDEX(Expenses!M34:BI34,1,Assumptions!$D$64*12-11),0) -> 0
B42: Exit Equity Value | D42: =MAX(0,D40-D41) -> 0
B43: Investor's Share at Exit | D43: =D42*D35 -> 0
B44: Investor Return Multiple (MOIC) | D44: =IFERROR(D43/D34,0) -> 0
B45: Investor IRR (approx.) | D45: =IFERROR((D44)^(1/Assumptions!$D$64)-1,0) -> 0

Sheet Dashboard
A1: =IF(Assumptions!$D$6="","INVESTOR DASHBOARD",Assumptions!$D$6&" — Investor Dashboard") -> INVESTOR DASHBOARD
A2: 5-Year Feasibility Snapshot • figures update from the Assumptions tab • ₹
B4: Total Revenue (5 yr) | E4: Total PAT (5 yr)
B5: ='Annual Summary'!H9 -> 0 | E5: ='Annual Summary'!H21 -> 0
B7: Avg EBITDA Margin | E7: Return on Investment
B8: ='Annual Summary'!H15 -> 0 | E8: ='Investment & ROI'!D26 -> 0
B10: Net Present Value | E10: Project IRR
B11: ='Investment & ROI'!D30 -> 0 | E11: ='Investment & ROI'!D31 -> 0
B13: Simple Payback | E13: Investor MOIC
B14: ='Investment & ROI'!D28 -> 0 | E14: ='Investment & ROI'!D44 -> 0
B16: SCALABILITY
B17: Revenue CAGR (Y1→Y5) | F17: =IFERROR(('Annual Summary'!G9/'Annual Summary'!C9)^(1/4)-1,0) -> 0
B18: Production CAGR (Y1→Y5) | F18: =IFERROR(('Annual Summary'!G7/'Annual Summary'!C7)^(1/4)-1,0) -> 0
B19: Capacity Growth (Y1→Y5) | F19: =IFERROR('Annual Summary'!G5/'Annual Summary'!C5-1,0) -> 0
B20: Investor IRR (to exit) | F20: ='Investment & ROI'!D45 -> 0
B52: WHY THIS FITS ANGEL-INVESTOR EXPECTATIONS
B53: • Capacity, utilisation and pricing are staged year-by-year so the plan shows a clear ramp and scalable, asset-light growth.
B54: • Headline metrics investors screen on — ROI, IRR, NPV, payback and EBITDA margin — are computed live from the model.
B55: • A dedicated investor block converts the raise into ownership, an implied valuation, an exit value and a return multiple (MOIC).
B56: • Every number traces back to one Assumptions tab, so investors can run their own downside / upside scenarios instantly.
B57: • Working-capital, debt-service and tax are modelled, giving a realistic cash view rather than an accounting-profit-only story.
